Workbook

Sheet H01_PARAMETROS_GENERALES
A1: Sistema de Integridad Algorítmica Preventiva | SIAP-ICPI v1.0
A2: Herramienta de Certificación de Congruencia Programática para Gobiernos Autónomos Descentralizados
A3: GRUPO 1: METADATOS — Parámetros Generales del Sistema
A4: ← H01 (esta hoja) | Navegar a: →
A5: Parámetro | B5: Valor | C5: Descripción | D5: Celda Nombrada
A6: GAD_Nombre | B6: GAD Municipal de Montecristi | C6: Nombre oficial del Gobierno Autónomo Descentralizado | D6: GAD_Nombre
A7: GAD_Provincia | B7: Manabí | C7: Provincia de Ecuador donde opera el GAD | D7: GAD_Provincia
A8: GAD_RUC | B8: 1360029750001 | C8: Registro Único de Contribuyentes del GAD | D8: GAD_RUC
A9: GAD_Poblacion | B9: 50000 | C9: Población cantonal según proyección INEC 2024 | D9: GAD_Poblacion
A10: PDOT_Periodo | B10: 2023-2027 | C10: Período de vigencia del Plan de Desarrollo Territorial | D10: PDOT_Periodo
A11: Año_Fiscal | B11: 2024 | C11: Año fiscal objeto de evaluación ICPI | D11: Año_Fiscal
A12: ICM_OFICIAL | B12: 1 | C12: ICM oficial reportado en SIGAD para año fiscal 2024. Valor real: 1.00 (100%). Fuente: Reporte SIGAD oficial GAD Montecristi, 9 metas ingresadas, $3,939,101.48. NOTA METODOLÓGICA: ICM=100% sobre 41.4% del presupuesto estratégico SIAP activa MOM-I con severidad Alta. | D12: ICM_OFICIAL
A13: Presupuesto_PDOT | B13: 16500000 | C13: Presupuesto total PDOT 2023-2027 en USD | D13: Presupuesto_PDOT
A14: Fecha_Generacion | B14: =TODAY() -> 46110 | C14: Fecha de generación automática del reporte | D14: Fecha_Generacion
A15: Responsable | B15: Ronald Javier Delgado Santana | C15: Responsable técnico del sistema SIAP-ICPI | D15: Responsable
A16: Version_Sistema | B16: SIAP-ICPI v1.0 | C16: Versión del artefacto operativo | D16: Version_Sistema
A17: Plataforma_Comercial | B17: QUADRUM | C17: Nombre comercial de la plataforma GovTech que implementa el SIAP-ICPI. QUADRUM es la marca para presentación ante GADs, organismos bilaterales y el DGIP CAF-ESPOL. | D17: Plataforma_Comercial
A18: Moneda | B18: USD | C18: Moneda de referencia del sistema presupuestario | D18: Moneda
A19: Coef_CurvaS | B19: 0.5 | C19: Coeficiente logístico para Curva S de monitoreo (H20) | D19: Coef_CurvaS
A20: Inflexion_CurvaS | B20: 6 | C20: Punto de inflexión de la Curva S (mes 1-12) | D20: Inflexion_CurvaS
A22: PANEL DE VERIFICACIONES AUTOMÁTICAS — Semáforo del Sistema
A23: Verificación | B23: Estado | C23: Valor Actual | D23: Umbral
A24: Suma P_i = 1.000 | B24: =IF(ABS(H05_METAS_PDOT!H23-1)<0.0001,"✅ CORRECTO","❌ ERROR") -> ❌ ERROR | C24: =H05_METAS_PDOT!H23 -> 0.022309711 | D24: 1
A25: ICPI en rango 0-100% | B25: =IF(AND(H14_CALCULO_ICPI!C5>=0,H14_CALCULO_ICPI!C5<=100),"✅ CORRECTO","❌ ERROR") -> ❌ ERROR | C25: =H14_CALCULO_ICPI!C5&"%" -> R_i% | D25: 0% - 100%
A26: Sin errores DIV/0 | B26: ✅ Verificado al generar | C26: OK | D26: Sin errores
A27: Sin errores REF | B27: ✅ Verificado al generar | C27: OK | D27: Sin errores
A28: ICM en rango válido (0–1) | B28: =IF(AND(B12>0,B12<=1),"✅ ICM en rango válido","❌ Revisar rango 0-1") -> ✅ ICM en rango válido | C28: =B12&" (92% — rango válido: >0 y ≤1)" -> 1 (92% — rango válido: >0 y ≤1) | D28: 0 < ICM ≤ 1
A29: Metas certificadas (V_i=1) | B29: =COUNTIF(H14_CALCULO_ICPI!J2:J21,1)&" de 20" -> 12 de 20 | C29: =COUNTIF(H14_CALCULO_ICPI!J2:J21,1) -> 12 | D29: 20 (ideal)
A30: PDOT período correcto | B30: =IF(ISNUMBER(SEARCH("2023",B10)),"✅ 2023-2027 confirmado","⚠️ Verificar período PDOT") -> ✅ 2023-2027 confirmado | C30: =B10 -> 2023-2027 | D30: 2023-2027
A31: Versión del sistema | B31: ="ℹ️ Versión activa: "&B16 -> ℹ️ Versión activa: SIAP-ICPI v1.0 | C31: =B16 -> SIAP-ICPI v1.0 | D31: SIAP-ICPI v1.0
A32: Silo SIGAD presente (H10B) | B32: =IFERROR(IF(H10B_DATOS_SIGAD!B19>0,"✅ Silo SIGAD presente — ICM="&TEXT(H10B_DATOS_SIGAD!F19,"0%")&" | $"&TEXT(H10B_DATOS_SIGAD!D19,"#,##0")&" | "&TEXT(H10B_DATOS_SIGAD!I19,"0.0%")&" represent.","❌ Silo SIGAD no cargado"),"❌ H10B_DATOS_SIGAD no encontrada") -> ✅ Silo SIGAD presente — ICM=100% | $3939101,480 | 41% represent. | C32: ="Metas SIGAD: "&H10B_DATOS_SIGAD!B19&" | Represent. presup.: "&TEXT(H10B_DATOS_SIGAD!I19,"0.0%") -> Metas SIGAD: 9 | Represent. presup.: 41% | D32: H10B_DATOS_SIGAD
A33: Silo CNE presente (H04B) | B33: =IFERROR(IF(H04B_DATOS_CNE!B52>0,"✅ Silo CNE presente — IFE="&TEXT(H04B_DATOS_CNE!B52,"0.0")&"% | 20 promesas verificadas","❌ Silo CNE no cargado"),"❌ H04B_DATOS_CNE no encontrada") -> ✅ Silo CNE presente — IFE=98% | 20 promesas verificadas | C33: ="IFE Global: "&TEXT(H04B_DATOS_CNE!B52,"0.0")&"% | 5 ejes verificados" -> IFE Global: 98% | 5 ejes verificados | D33: H04B_DATOS_CNE
A35: ÍNDICE DE NAVEGACIÓN — 26 Hojas del Sistema SIAP-ICPI
A36: Grupo | B36: Hoja | C36: Descripción | D36: Acceso
A37: G1 — Metadatos | B37: H01_PARAMETROS_GENERALES | C37: Parámetros, verificaciones e índice del sistema | D37: Esta hoja
A38: G1 — Metadatos | B38: H02_GLOSARIO_TECNICO | C38: 28+ términos metodológicos y legales | D38: → H02
A39: G1 — Metadatos | B39: H03_CONTROL_VERSIONES | C39: Historial de versiones del artefacto | D39: → H03
A40: G2 — Silos de Datos | B40: H04_TABLAS_PARAMETRICAS | C40: 7 tablas maestras con rangos nombrados | D40: → H04
A41: G2 — Silos de Datos | B41: H05_METAS_PDOT | C41: BASE SUSTANCIAL: 20 metas PDOT 2023-2027 | D41: → H05
A42: G2 — Silos de Datos | B42: H06_VINCULACIONES_POA | C42: Vinculación meta PDOT ↔ proyecto POA | D42: → H06
A43: G2 — Silos de Datos | B43: H07_PROCESOS_SERCOP | C43: Procesos de contratación pública SERCOP | D43: → H07
A44: G2 — Silos de Datos | B44: H08_DOCUMENTOS_LOTAIP | C44: Documentos LOTAIP Art. 7 por meta | D44: → H08
A45: G2 — Silos de Datos | B45: H09_EJECUCION_PRESUPUESTARIA | C45: Devengado eSIGEF por meta y cuatrimestre | D45: → H09
A46: G2 — Silos de Datos | B46: H10_INFORMES_CPCCS | C46: Menciones en rendición de cuentas CPCCS | D46: → H10
A47: G2 — Silos de Datos | B47: H11_ALERTAS_MOM | C47: Señales de Atención Temprana MOM-I/II/III | D47: → H11
... A62: G7 — Presentación | B62: H26_TRAZABILIDAD_LOG | C62: Log auditable de vinculaciones metodológicas | D62: → H26

Sheet H02_GLOSARIO_TECNICO
A1: 🔙 Volver al Índice
A2: H02 — GLOSARIO TÉCNICO: Términos metodológicos, operativos y legales del sistema SIAP-ICPI
A3: ← H01
A5: Término | B5: Definición | C5: Referencia Legal / Metodológica | D5: Categoría
A6: SIAP | B6: Sistema de Integridad Algorítmica Preventiva. Marco metodológico que verifica la congruencia entre planificación, ejecución presupuestaria y evidencia documental de los GADs. | C6: Metodología propia SIAP-ICPI v1.0 | D6: Sistema
A7: ICPI | B7: Índice de Congruencia Programática e Intersistémica. Indicador sintético (0-100%) que mide la trazabilidad del ciclo planificación-ejecución-transparencia de las metas PDOT. | C7: Fórmula: Σ(Pi×Ri×Vi×Ei×Ti×Ci) / Σ(Pi×Ri) × 100 | D7: Índice
A8: CININ | B8: Ciclo de Integridad Normativa e Institucional. Secuencia metodológica que atraviesa los 5 silos de información: POA → SERCOP → eSIGEF → LOTAIP → CPCCS. | C8: SIAP-ICPI v1.0 §2.1 | D8: Metodología
A9: PDOT | B9: Plan de Desarrollo y Ordenamiento Territorial. Instrumento de planificación de mediano plazo de los GADs. BASE SUSTANCIAL del SIAP-ICPI. Sin PDOT no existe sistema. | C9: COOTAD Art. 295-296; SENPLADES 2019 | D9: Planificación
A10: POA | B10: Plan Operativo Anual. Instrumento de planificación que operativiza el PDOT para cada año fiscal. Primer silo del CININ. | C10: COOTAD Art. 234; COPYFP Art. 97 | D10: Planificación
A11: V_i | B11: Variable de Trazabilidad de la meta i. Valor binario (0/1) que indica si la meta cumple el umbral mínimo de silos requeridos según su fuente de financiamiento. V_i MALEABLE según fuente. | C11: SIAP-ICPI v1.0 §3.2 | D11: Cálculo
A12: P_i | B12: Peso presupuestario de la meta i. P_i = Presupuesto_Anual_i / Presupuesto_Total_PDOT_Anual. Suma de todos los P_i = 1.0000 exacto. | C12: SIAP-ICPI v1.0 §3.1 | D12: Cálculo
A13: R_i | B13: Factor de Relevancia Competencial. Ponderación según tipo de competencia COOTAD: 1.5 (exclusiva), 1.0 (adicional), 0.5 (concurrente). | C13: COOTAD Art. 55, 64, 65 | D13: Cálculo
A14: T_i | B14: Tasa de Ejecución Presupuestaria. T_i = Devengado_Total / Codificado_Vigente. Fuente: eSIGEF. Rango [0,1]. | C14: e-SIGEF Ministerio de Finanzas Ecuador | D14: Cálculo
A15: E_i | B15: Factor de Eficiencia de Modalidad. Escala: Directa GAD=1.00, Compartida=0.90, Delegada EP=0.75. Refleja autonomía de gestión del GAD. | C15: COOTAD Art. 126-130 | D15: Cálculo
A16: C_i | B16: Factor de Claridad Orgánica. Escala: Única=1.00, Compartida=0.90, Difusa=0.75. Refleja precisión en atribución institucional de la meta. | C16: Estatuto Orgánico del GAD (H12) | D16: Cálculo
... A37: QUADRUM | B37: Nombre comercial de la plataforma GovTech que implementa el motor metodológico SIAP-ICPI para su uso por GADs municipales y organismos bilaterales. QUADRUM integra el cálculo del ICPI, los protocolos MOM y el módulo ciudadano TAC en una interfaz operativa. Relación: QUADRUM implementa SIAP-ICPI y comunica sus resultados a través de TAC. El artefacto Excel es el PMV v1.0 de QUADRUM. | C37: Ordenanza Municipal Alfaro Virtus.0 | D37: Plataforma

Sheet H03_CONTROL_VERSIONES
A1: 🔙 Volver al Índice
A2: H03 — CONTROL DE VERSIONES: Historial de evolución del artefacto operativo SIAP-ICPI
A3: ← H01
A5: Versión | B5: Fecha | C5: Descripción de Cambios | D5: Responsable | E5: Estado
A6: v0.1 — Prototipo Conceptual | B6: 15/03/2024 | C6: Diseño inicial de la arquitectura del sistema: definición de los 5 silos de información (POA, SERCOP, eSIGEF, LOTAIP, CPCCS), fórmula ICPI base, escala AVEP preliminar. Sin datos de GAD. | D6: Ronald J. Delgado S. | E6: Archivado
A7: v0.8 — Prueba de Concepto | B7: 30/08/2024 | C7: Incorporación de los Protocolos MOM (I, II, III) como señales de atención temprana. Desarrollo del V_i Maleable según fuente de financiamiento. Integración del IFE con Plan CNE. Primera versión con datos simulados del GAD Montecristi. Validación de la fórmula ICPI con 20 metas. | D7: Ronald J. Delgado S. | E7: Archivado
A8: v1.0 — Producto Mínimo Viable | B8: =TODAY() -> 46110 | C8: Artefacto operativo completo: 33 hojas — Motor Central (H01-H26) + Módulo de Salidas Institucionales (H27-H31). 797 fórmulas activas. 8 silos de información pública integrados. 0 errores de fórmula. | D8: Ronald J. Delgado S. | E8: ✅ ACTIVO
A10: NOTA METODOLÓGICA:
A11: Este artefacto sirve como Producto Mínimo Viable (PMV) del sistema SIAP-ICPI. Los datos de referencia del GAD Municipal de Montecristi son ficticios-coherentes y pueden sustituirse por datos reales de cualquier GAD de América Latina. La arquitectura del sistema es neutral, reutilizable y adaptable a cualquier jurisdicción que opere con planificación territorial (PDOT o equivalente) y sistemas de contratación pública y presupuesto electrónico.

Sheet H04_TABLAS_PARAMETRICAS
A1: 🔙 Volver al Índice
A2: H04 — TABLAS PARAMÉTRICAS: 7 tablas maestras con rangos nombrados para validación de datos y listas desplegables
A3: ← H01
A5: TABLA 1 — EJES_ESTRATEGICOS | E5: TABLA 2 — COMPETENCIAS_COOTAD
A6: ID_Eje | B6: Nombre_Eje | C6: Descripcion | E6: ID | F6: Nombre | G6: R_i | H6: Art_Legal
A7: AS | B7: Ambiental Sostenible | C7: Gestión ambiental, recursos naturales y saneamiento | E7: AGUA | F7: Agua Potable | G7: 1.5 | H7: COOTAD Art.55(d)
A8: EC | B8: Económico Productivo | C8: Desarrollo económico local y fomento productivo | E8: ALCA | F8: Alcantarillado | G8: 1.5 | H8: COOTAD Art.55(d)
A9: SC | B9: Social e Inclusivo | C9: Servicios sociales, salud, educación y bienestar | E9: DESO | F9: Desechos Sólidos | G9: 1.5 | H9: COOTAD Art.55(d)
A10: OT | B10: Ordenamiento Territorial | C10: Vialidad, infraestructura física y uso de suelo | E10: AMBI | F10: Gestión Ambiental | G10: 1.5 | H10: COOTAD Art.55(d)
A11: PI | B11: Político Institucional | C11: Gobernanza, transparencia y fortalecimiento institucional | E11: VIAL | F11: Vialidad Urbana | G11: 1 | H11: COOTAD Art.55(a)
E12: ORTE | F12: Ordenamiento Territ. | G12: 1 | H12: COOTAD Art.55(b)
E13: EQUI | F13: Equipamiento Salud/Edu | G13: 1 | H13: COOTAD Art.55(g)
E14: TRAN | F14: Tránsito y Transporte | G14: 1 | H14: COOTAD Art.55(f)
E15: CULT | F15: Cultura y Patrimonio | G15: 0.5 | H15: COOTAD Art.55(h)
E16: DEPO | F16: Deporte y Recreación | G16: 0.5 | H16: COOTAD Art.55(h)
E17: TURI | F17: Turismo | G17: 0.5 | H17: COOTAD Art.55(q)
E18: INST | F18: Fortalecimiento Inst. | G18: 0.5 | H18: COOTAD Art.54
A21: TABLA 3 — ESTADOS_SERCOP | E21: TABLA 4 — MODALIDADES_EJECUCION
A22: ID | B22: Estado | C22: Valido_Vi | E22: ID | F22: Modalidad | G22: E_i | H22: Descripcion
A23: ADJ | B23: Adjudicado | C23: 1 | E23: DIR | F23: Directa GAD | G23: 1 | H23: Dirección propia del GAD ejecuta el proceso
A24: FIN | B24: Finalizado | C24: 1 | E24: COM | F24: Compartida | G24: 0.9 | H24: Convenio interinstitucional o compartida con otro nivel
A25: EJE | B25: En Ejecución | C25: 1 | E25: DEL | F25: Delegada EP | G25: 0.75 | H25: Empresa pública, patronato u organismo delegado
A26: DES | B26: Desierto | C26: 0
A27: CAN | B27: Cancelado | C27: 0
A28: SUS | B28: Suspendido | C28: 0
A31: TABLA 5 — TIPOS_RESPONSABILIDAD | E31: TABLA 6 — FUENTES_FINANCIAMIENTO y V_i MALEABLE
A32: ID | B32: Tipo | C32: C_i | E32: ID | F32: Fuente | G32: Silos_Vi_Requeridos | H32: Descripcion
A33: UNI | B33: Única | C33: 1 | E33: GAD | F33: Recursos propios GAD | G33: 5 silos AND completo | H33: POA ∧ SERCOP ∧ eSIGEF ∧ LOTAIP ∧ CPCCS
A34: CPT | B34: Compartida | C34: 0.9 | E34: COO | F34: Cooperación internacional | G34: 4 silos (sin CPCCS) | H34: POA ∧ SERCOP ∧ eSIGEF ∧ LOTAIP
A35: DIF | B35: Difusa | C35: 0.75 | E35: SFP | F35: Sin financiamiento propio | G35: 3 silos mínimo | H35: POA ∧ SERCOP ∧ eSIGEF
A38: TABLA 7 — ODS_CLUSTERS
A39: ID | B39: ODS_Relacionados | C39: Descripcion
A40: Inclusion | B40: ODS 1, 2, 3, 4, 5, 10 | C40: Servicios sociales, salud, educación, equidad
A41: Infraestructura | B41: ODS 6, 7, 9, 11, 13 | C41: Agua, energía, obras, ciudad, clima
A42: Gobernanza | B42: ODS 16, 17 | C42: Instituciones, transparencia, alianzas estratégicas

Sheet H04B_DATOS_CNE
A1: 🔙 Volver al Índice
A2: H04B_DATOS_CNE — SILO 0: Plan de Trabajo Electoral CNE | Fuente: Plan Trabajo Alcalde Luis Jonathan Toro Largacha, Elecciones Seccionales 2023, Período 2023-2027
A3: ← H01 | El Plan CNE es INSUMO COMPARATIVO del IFE (§3.7.1). Sin CNE hay ICPI pero no IFE. CNE ≠ base operativa del sistema. La base operativa siempre es el PDOT.
A5: A · IDENTIFICACIÓN DEL PLAN DE TRABAJO CNE
A6: Parámetro | B6: Valor
A7: Candidato | B7: Luis Jonathan Toro Largacha
A8: Partido | B8: AVANZA Lista 8 + MACHETE Lista 61
A9: Dignidad | B9: Alcalde del Cantón Montecristi
A10: Elecciones | B10: Seccionales 2023
A11: Período | B11: 2023-2027
A12: Población | B12: 116,186 habitantes (INEC proyección 2022)
A13: Ejes_Plan | B13: 5 (Económico, Institucional, Social, Ambiental, Territorial)
A14: Total_Promesas_CNE | B14: 20
A15: ODS_Vinculados | B15: ODS 1,2,3,4,5,6,7,8,9,10,11,13,16,17
A16: Registro_CNE | B16: Plan Trabajo Electoral CNE — Expediente Elecciones Seccionales 2023
A18: B · PROMESAS CNE — MATRIZ PLURIANUAL POR EJE (§3.7.1)
A19: Esta tabla es la FUENTE del IFE. Cada promesa se vincula a una meta PDOT para calcular el score V_j. Score 1.0 = verde, 0.5 = amarillo, 0.0 = rojo.
A20: ID_Promesa | B20: Eje_CNE | C20: Objetivo_Especifico_CNE | D20: Meta_Promesa_CNE | E20: Competencia_Vinculada | F20: ODS_Relacionados | G20: Año1 | H20: Año2 | I20: Año3 | J20: Año4 | K20: ID_Meta_PDOT | L20: Tipo_Vinculacion | M20: Score_IFE | N20: Justificacion_Vinculacion
A21: EJE ECONÓMICO
A22: EC-001 | B22: Económico | C22: Obj 16: Procesar carne fresca alta calidad | D22: Desarrollar capacidades productivas y comerciales del sector artesanal y agropecuario | E22: Turismo-Desarrollo Económico | F22: ODS 8, 9 | G22: 2023 | H22: 2024 | I22: 2025 | J22: 2026 | K22: PDOT-013 | L22: Alta | M22: 1 | N22: Capacitación artesanos sombrero paja toquilla — correspondencia directa
A23: EC-002 | B23: Económico | C23: Obj 6: TICs para trámites ciudadanos | D23: Implementar plataforma digital de servicios municipales | E23: Fortalecimiento Institucional | F23: ODS 9, 16 | G23: 2023 | H23: 2024 | I23: 2025 | J23: 2026 | K23: PDOT-019 | L23: Alta | M23: 1 | N23: Modernización sistema recaudación — tecnología municipal
A24: EC-003 | B24: Económico | C24: Alianzas sector privado | D24: Gestionar 28 convenios de cooperación para fortalecimiento institucional | E24: Cooperación Internacional | F24: ODS 17 | G24: 2023 | H24: 2024 | I24: 2025 | J24: 2026 | K24: PDOT-013 | L24: Alta | M24: 1 | N24: 28 convenios coinciden exactamente con meta SIGAD-001
A25: EC-004 | B25: Económico | C25: Turismo sostenible | D25: Rehabilitar malecón costero para fomento turístico | E25: Turismo | F25: ODS 8, 11 | G25: 2023 | H25: 2024 | I25: 2025 | J25: 2026 | K25: PDOT-011 | L25: Alta | M25: 1 | N25: Malecón costero Montecristi — identificación directa
A26: EC-005 | B26: Económico | C26: Mercado y comercio local | D26: Rehabilitar y modernizar mercado municipal | E26: Ordenamiento Territorial | F26: ODS 11 | G26: 2023 | H26: 2024 | I26: 2025 | J26: 2026 | K26: PDOT-005 | L26: Alta | M26: 1 | N26: Rehabilitación mercado municipal — meta directa
A27: EJE INSTITUCIONAL
A28: IN-001 | B28: Institucional | C28: Obj 12: Participación ciudadana | D28: Crear espacios de participación para informar sobre recursos públicos | E28: Fortalecimiento Institucional | F28: ODS 16 | G28: 2023 | H28: 2024 | I28: 2025 | J28: 2026 | K28: PDOT-015 | L28: Alta | M28: 1 | N28: Transparencia municipal LOTAIP — correspondencia directa
A29: IN-002 | B29: Institucional | C29: Obj: Rendición de cuentas | D29: Mecanismos periódicos y públicos de rendición de cuentas | E29: Fortalecimiento Institucional | F29: ODS 16, 17 | G29: 2023 | H29: 2024 | I29: 2025 | J29: 2026 | K29: PDOT-015 | L29: Alta | M29: 1 | N29: Fortalecimiento transparencia — objetivo idéntico
A30: IN-003 | B30: Institucional | C30: Ordenamiento territorial | D30: Modernizar el sistema de catastro predial para planificación | E30: Ordenamiento Territorial | F30: ODS 11, 16 | G30: 2023 | H30: 2024 | I30: 2025 | J30: 2026 | K30: PDOT-014 | L30: Alta | M30: 1 | N30: Catastro predial — meta idéntica
A31: IN-004 | B31: Institucional | C31: Recursos municipales | D31: Modernizar sistema de recaudación y gestión financiera | E31: Fortalecimiento Institucional | F31: ODS 16 | G31: 2023 | H31: 2024 | I31: 2025 | J31: 2026 | K31: PDOT-019 | L31: Alta | M31: 1 | N31: Modernización recaudación — correspondencia directa
A32: EJE SOCIAL
A33: SC-001 | B33: Social | C33: Educación | D33: Equipar establecimientos educativos rurales y mejorar infraestructura | E33: Equipamiento Salud/Educación | F33: ODS 4 | G33: 2023 | H33: 2024 | I33: 2025 | J33: 2026 | K33: PDOT-007 | L33: Alta | M33: 1 | N33: Equipamiento educativo establecimientos rurales — meta idéntica
A34: SC-002 | B34: Social | C34: Salud | D34: Construir centro de salud en parroquia rural Aníbal San Andrés | E34: Equipamiento Salud/Educación | F34: ODS 3 | G34: 2023 | H34: 2024 | I34: 2025 | J34: 2026 | K34: PDOT-006 | L34: Alta | M34: 1 | N34: Centro salud tipo C — correspondencia directa
A35: SC-003 | B35: Social | C35: Obj 13: Espacios recreativos | D35: Brindar espacios de entretenimiento en parroquias del cantón | E35: Deporte y Recreación | F35: ODS 3, 11 | G35: 2023 | H35: 2024 | I35: 2025 | J35: 2026 | K35: PDOT-010 | L35: Alta | M35: 1 | N35: Parque recreativo sector norte — meta coincidente
A36: SC-004 | B36: Social | C36: Servicios sociales | D36: Guardería comunitaria para madres trabajadoras | E36: Equipamiento Salud/Educación | F36: ODS 1, 5 | G36: 2023 | H36: 2024 | I36: 2025 | J36: 2026 | K36: PDOT-008 | L36: Alta | M36: 1 | N36: Guardería El Carmen — correspondencia directa
A37: SC-005 | B37: Social | C37: Adultos mayores y discapacidad | D37: Programa de atención a grupos vulnerables: adultos mayores y discapacidad | E37: Servicios Sociales | F37: ODS 1, 3, 10 | G37: 2023 | H37: 2024 | I37: 2025 | J37: 2026 | K37: PDOT-018 | L37: Alta | M37: 1 | N37: Programa adulto mayor y discapacidad — meta idéntica
A38: EJE AMBIENTAL
A39: AM-001 | B39: Ambiental | C39: Agua y saneamiento | D39: Mejorar abastecimiento agua potable sectores rurales | E39: Agua Potable | F39: ODS 6 | G39: 2023 | H39: 2024 | I39: 2025 | J39: 2026 | K39: PDOT-001 | L39: Alta | M39: 1 | N39: Sistema agua potable zonas rurales — correspondencia directa
A40: AM-002 | B40: Ambiental | C40: Alcantarillado y aguas residuales | D40: Ampliar red alcantarillado y tratar aguas residuales | E40: Alcantarillado | F40: ODS 6 | G40: 2023 | H40: 2024 | I40: 2025 | J40: 2026 | K40: PDOT-002 | L40: Alta | M40: 1 | N40: Alcantarillado sanitario + planta tratamiento — metas idénticas
A41: AM-003 | B41: Ambiental | C41: Obj 19: Control ambiental | D41: Reforestar cuencas hídricas y proteger recursos naturales | E41: Gestión Ambiental | F41: ODS 13, 15 | G41: 2023 | H41: 2024 | I41: 2025 | J41: 2026 | K41: PDOT-016 | L41: Alta | M41: 1 | N41: Reforestación cuencas híricas — correspondencia directa
A42: EJE TERRITORIAL
A43: TE-001 | B43: Territorial | C43: Obj 15: Vialidad cantonal | D43: Mejorar vialidad urbana con planificación actualizada | E43: Vialidad Urbana | F43: ODS 9, 11 | G43: 2023 | H43: 2024 | I43: 2025 | J43: 2026 | K43: PDOT-004 | L43: Alta | M43: 1 | N43: Mejoramiento vialidad urbana cantonal — meta idéntica
A44: TE-002 | B44: Territorial | C44: Vías parroquiales | D44: Mantenimiento bacheo y señalización vías parroquiales rurales | E44: Vialidad | F44: ODS 9 | G44: 2023 | H44: 2024 | I44: 2025 | J44: 2026 | K44: PDOT-017 | L44: Alta | M44: 1 | N44: Bacheo vías parroquiales — correspondencia directa
A45: TE-003 | B45: Territorial | C45: Asentamientos humanos | D45: Solucionar problema de inundaciones en casco urbano | E45: Alcantarillado | F45: ODS 11, 13 | G45: 2023 | H45: 2024 | I45: 2025 | J45: 2026 | K45: PDOT-009 | L45: Parcial | M45: 0.5 | N45: Drenaje pluvial relacionado con inundaciones — alcance diferente
A47: C · ÍNDICE DE FIDELIDAD ELECTORAL (IFE) §3.7.1
A48: IFE = (Σ V_j) / m × 100 | Donde V_j = score de vinculación promesa-PDOT. Alta fidelidad = la promesa quedó plasmada en el PDOT.
A49: Parámetro | B49: Valor | C49: Fórmula
A50: IFE_Numerador (Σ V_j) | B50: =SUM(M22:M26,M28:M31,M33:M37,M39:M41,M43:M45) -> 19.5 | C50: SUM de scores M de todos los ejes (excluye divisores)
A51: IFE_Denominador (m = núm. promesas) | B51: 20 | C51: 20 promesas totales (5 ejes)
A52: IFE_GLOBAL | B52: =B50/B51*100 -> 97.5 | C52: =IF(B52>=85,"✅ Alta Fidelidad Electoral",IF(B52>=60,"⚠️ Fidelidad Moderada",IF(B52>=40,"🔶 Erosión Programática","🔴 Ruptura con el Mandato"))) -> ✅ Alta Fidelidad Electoral
A53: IFE por Eje | B53: % | C53: Interpretación
A54: IFE_Económico | B54: =AVERAGE(M22:M26)*100 -> 100 | C54: 5 promesas — sector productivo, TICs, convenios, turismo, mercado
A55: IFE_Institucional | B55: =AVERAGE(M28:M31)*100 -> 100 | C55: 4 promesas — participación, rendición, catastro, recaudación
A56: IFE_Social | B56: =AVERAGE(M33:M37)*100 -> 100 | C56: 5 promesas — educación, salud, recreación, guardería, adultos mayores
A57: IFE_Ambiental | B57: =AVERAGE(M39:M41)*100 -> 100 | C57: 3 promesas — agua, alcantarillado, reforestación
A58: IFE_Territorial | B58: =AVERAGE(M43:M45)*100 -> 83.333333 | C58: 3 promesas (TE-003 = 0.5 — alcance diferente en drenaje pluvial)
A60: 💬 LECTURA DEL IFE: | B60: ="El candidato Toro Largacha plasmó en el PDOT el "&TEXT(B52,"0.0")&"% de sus promesas electorales. El circuito democrático planificación → promesa está sustancialmente cerrado. La brecha ICM-ICPI ("&TEXT(H01_PARAMETROS_GENERALES!B12*100-H14_CALCULO_ICPI!B32,"0.0")&"pp) no se debe a infidelidad al mandato sino a déficits de trazabilidad documental en la ejecución." -> El candidato Toro Largacha plasmó en el PDOT el 98% de sus promesas electorales. El circuito democrático planificación → promesa está sustancialmente cerrado. La brecha ICM-ICPI (59pp) no se debe a infidelidad al mandato sino a déficits de trazabilidad documental en la ejecución.
A61: ✅ NOTA METODOLÓGICA: | B61: Esta hoja cierra el circuito democrático del SIAP-ICPI: CNE (promesa) → PDOT (plan) → ICPI (ejecución). IFE alto + ICPI bajo = el problema es de gestión, no de mandato. IFE bajo + ICPI bajo = el problema empieza en la planificación.
A62: Fuente: | B62: Plan de Trabajo Electoral CNE, Ing. Luis Jonathan Toro Largacha, Alcalde GAD Montecristi, Elecciones Seccionales 2023. Registro CNE: AVANZA Lista 8 + MACHETE Lista 61.

Sheet H05_METAS_PDOT
A1: 🔙 Volver al Índice
A2: H05 — METAS PDOT 2023-2027: BASE SUSTANCIAL Y OPERATIVA del sistema. 20 metas del plan de desarrollo territorial del GAD Municipal de Montecristi
A3: ← H01 | Sin PDOT no existe sistema SIAP-ICPI. Este es el universo de análisis.
A5: ⚠️ DATOS DE REFERENCIA — Este artefacto contiene datos ficticios coherentes para demostración metodológica del SIAP-ICPI. Para implementación real: reemplazar con datos del PDOT vigente del GAD. Los datos reales del GAD Montecristi 2024 se cargarán en el Artefacto B para el Diplomado CAF-ESPOL (DGIP 2026).
A6: ID_Meta | B6: Descripcion_Meta | C6: Eje_ID | D6: Competencia_ID | E6: R_i | F6: Presup_Codif_PDOT | G6: Presup_Anual_2024 | H6: P_i | I6: Fuente_Financ | J6: Meta_Cuantitativa | K6: Unidad_Medida | L6: Linea_Base | M6: Indicador_PDOT | N6: Responsable_Direccion | O6: ODS_Cluster | P6: Pag_PDOT | Q6: Nivel_Estres | R6: Nota_Metodologica
A7: PDOT-001 | B7: Construcción sistema agua potable zonas rurales | C7: AS | D7: AGUA | E7: 1.5 | F7: 8500000 | G7: 2125000 | H7: =G7/SUM($G$7:$G$26) -> 0.22309711 | I7: GAD | J7: 45 | K7: Km red | L7: 12 | M7: Km red construida | N7: Dir. Obras Públicas | O7: Infraestructura | P7: 42 | Q7: Nivel2 | R7: Nivel2: ejecutó pero no publicó evidencia LOTAIP completa
A8: PDOT-002 | B8: Ampliación red alcantarillado sanitario | C8: AS | D8: ALCA | E8: 1.5 | F8: 6200000 | G8: 1550000 | H8: =G8/SUM($G$7:$G$26) -> 0.16272966 | I8: GAD | J8: 28 | K8: Km red | L8: 8 | M8: Km alcantarillado ampliado | N8: Dir. Obras Públicas | O8: Infraestructura | P8: 45 | Q8: Nivel3 | R8: Nivel3: proceso SERCOP desierto, devengado mínimo
A9: PDOT-003 | B9: Sistema manejo integral desechos sólidos | C9: AS | D9: DESO | E9: 1.5 | F9: 1800000 | G9: 450000 | H9: =G9/SUM($G$7:$G$26) -> 0.047244094 | I9: DEL | J9: 1 | K9: Sistema | L9: 0 | M9: Sistema operativo | N9: EP Aseo | O9: Infraestructura | P9: 48 | Q9: Nivel3 | R9: Nivel3: proceso SERCOP cancelado, devengado nulo
A10: PDOT-004 | B10: Mejoramiento vialidad urbana cantonal | C10: OT | D10: VIAL | E10: 1 | F10: 3200000 | G10: 800000 | H10: =G10/SUM($G$7:$G$26) -> 0.083989501 | I10: GAD | J10: 18 | K10: Km | L10: 5 | M10: Km vías mejoradas | N10: Dir. Obras Públicas | O10: Infraestructura | P10: 52 | Q10: Nivel1 | R10: Nivel1: trazabilidad plena, modelo de referencia
A11: PDOT-005 | B11: Construcción y rehabilitación mercado municipal | C11: EC | D11: ORTE | E11: 1 | F11: 1500000 | G11: 375000 | H11: =G11/SUM($G$7:$G$26) -> 0.039370079 | I11: GAD | J11: 1 | K11: Mercado | L11: 0 | M11: Mercado rehabilitado | N11: Dir. Gestión Social | O11: Gobernanza | P11: 55 | Q11: Nivel2 | R11: Nivel2: enlace LOTAIP roto (404), ejecutó sin publicar
A12: PDOT-006 | B12: Centro salud tipo C parroquia Aníbal San Andrés | C12: SC | D12: EQUI | E12: 1 | F12: 2800000 | G12: 700000 | H12: =G12/SUM($G$7:$G$26) -> 0.073490814 | I12: COO | J12: 1 | K12: Centro | L12: 0 | M12: Centro construido | N12: Dir. Planificación | O12: Inclusion | P12: 58 | Q12: Nivel3 | R12: Nivel3: proceso desierto; revisar posible MOM-II
A13: PDOT-007 | B13: Equipamiento educativo establecimientos rurales | C13: SC | D13: EQUI | E13: 1 | F13: 950000 | G13: 237500 | H13: =G13/SUM($G$7:$G$26) -> 0.024934383 | I13: COO | J13: 12 | K13: Establec. | L13: 3 | M13: Establec. equipados | N13: Dir. Planificación | O13: Inclusion | P13: 61 | Q13: Nivel2 | R13: Nivel2: contrato accesible, falta acta recepción LOTAIP
A14: PDOT-008 | B14: Guardería municipal comunitaria El Carmen | C14: SC | D14: EQUI | E14: 1 | F14: 1200000 | G14: 300000 | H14: =G14/SUM($G$7:$G$26) -> 0.031496063 | I14: GAD | J14: 1 | K14: Guardería | L14: 0 | M14: Guardería operativa | N14: Dir. Social | O14: Inclusion | P14: 64 | Q14: Nivel3 | R14: Nivel3: proceso cancelado, devengado nulo
A15: PDOT-009 | B15: Sistema drenaje pluvial casco urbano | C15: OT | D15: ALCA | E15: 1.5 | F15: 2100000 | G15: 525000 | H15: =G15/SUM($G$7:$G$26) -> 0.05511811 | I15: GAD | J15: 12 | K15: Km | L15: 0 | M15: Km drenaje construido | N15: Dir. Obras Públicas | O15: Infraestructura | P15: 67 | Q15: Nivel3 | R15: Nivel3: proceso desierto, baja ejecución
A16: PDOT-010 | B16: Parque recreativo y deportivo sector norte | C16: SC | D16: DEPO | E16: 0.5 | F16: 450000 | G16: 112500 | H16: =G16/SUM($G$7:$G$26) -> 0.011811024 | I16: GAD | J16: 1 | K16: Parque | L16: 0 | M16: Parque construido | N16: Dir. Cultura | O16: Inclusion | P16: 70 | Q16: Nivel1 | R16: Nivel1: trazabilidad plena, meta modelo
A17: PDOT-011 | B17: Rehabilitación Malecón costero Montecristi | C17: EC | D17: TURI | E17: 0.5 | F17: 1800000 | G17: 450000 | H17: =G17/SUM($G$7:$G$26) -> 0.047244094 | I17: COM | J17: 1 | K17: Malecón | L17: 0 | M17: Malecón rehabilitado | N17: Dir. Turismo | O17: Infraestructura | P17: 73 | Q17: Nivel2 | R17: Nivel2: en ejecución, documentación parcial
A18: PDOT-012 | B18: Unidad móvil de salud comunitaria | C18: SC | D18: EQUI | E18: 1 | F18: 380000 | G18: 95000 | H18: =G18/SUM($G$7:$G$26) -> 0.0099737533 | I18: GAD | J18: 1 | K18: Unidad | L18: 0 | M18: Unidad operativa | N18: Patronato | O18: Inclusion | P18: 76 | Q18: Nivel4 | R18: Nivel4: MOM-III activo — 8295% declarado vs 8% ejecutado
... A26: PDOT-020 | B26: Planta tratamiento aguas residuales | C26: AS | D26: ALCA | E26: 1.5 | F26: 4200000 | G26: 1050000 | H26: =G26/SUM($G$7:$G$26) -> 0.11023622 | I26: COO | J26: 1 | K26: Planta | L26: 0 | M26: Planta operativa | N26: Dir. Obras Públicas | O26: Infraestructura | P26: 100 | Q26: Nivel3 | R26: Nivel3: proceso existe, sin devengado al 31 dic
G27: VERIFICACIÓN: | H27: =SUM(H7:H26) -> 1 | I27: =IF(ABS(H27-1)<0.0001,"✅ Suma P_i = 1.0000 — CORRECTO","❌ ERROR: Suma ≠ 1") -> ✅ Suma P_i = 1.0000 — CORRECTO

Sheet H06_VINCULACIONES_POA
A1: 🔙 Volver al Índice
A2: H06 — VINCULACIONES POA: Conecta cada meta PDOT con su proyecto en el Plan Operativo Anual. Primer silo del CININ.
A3: ← H01
A5: ID_Vinc | B5: ID_Meta | C5: Codigo_POA | D5: Descripcion_POA | E5: Fecha_Aprobacion_POA | F5: Presupuesto_POA | G5: Responsable_POA | H5: Confianza_Vinculacion | I5: V_POA
A6: VNC-001 | B6: PDOT-001 | C6: AS-AGUA-001 | D6: Acueducto rural — acceso agua potable 8 comunidades | E6: 15/01/2024 | F6: 2125000 | G6: Dir. Obras Públicas | H6: Alta | I6: 1
A7: VNC-002 | B7: PDOT-002 | C7: AS-ALCA-002 | D7: Ampliación red alcantarillado urbano-rural | E7: 15/01/2024 | F7: 1550000 | G7: Dir. Obras Públicas | H7: Alta | I7: 1
A8: VNC-003 | B8: PDOT-003 | C8: AS-DESO-003 | D8: Sistema manejo desechos sólidos delegado EP Aseo | E8: 15/01/2024 | F8: 450000 | G8: EP Aseo | H8: Alta | I8: 1
A9: VNC-004 | B9: PDOT-004 | C9: OT-VIAL-004 | D9: Mejoramiento vías principales urbanas | E9: 15/01/2024 | F9: 800000 | G9: Dir. Obras Públicas | H9: Alta | I9: 1
A10: VNC-005 | B10: PDOT-005 | C10: EC-ORTE-005 | D10: Rehabilitación y equipamiento mercado municipal | E10: 15/01/2024 | F10: 375000 | G10: Dir. Gestión Social | H10: Alta | I10: 1
A11: VNC-006 | B11: PDOT-006 | C11: SC-EQUI-006 | D11: Construcción centro salud tipo C parroquia | E11: 15/01/2024 | F11: 700000 | G11: Dir. Planificación | H11: Alta | I11: 1
A12: VNC-007 | B12: PDOT-007 | C12: SC-EQUI-007 | D12: Equipamiento tecnológico establecimientos educativos rurales | E12: 15/01/2024 | F12: 237500 | G12: Dir. Planificación | H12: Alta | I12: 1
A13: VNC-008 | B13: PDOT-008 | C13: SC-EQUI-008 | D13: Construcción guardería comunitaria El Carmen | E13: 15/01/2024 | F13: 300000 | G13: Dir. Social | H13: Alta | I13: 1
A14: VNC-009 | B14: PDOT-009 | C14: OT-ALCA-009 | D14: Sistema drenaje pluvial casco urbano | E14: 15/01/2024 | F14: 525000 | G14: Dir. Obras Públicas | H14: Alta | I14: 1
A15: VNC-010 | B15: PDOT-010 | C15: SC-DEPO-010 | D15: Construcción parque deportivo sector norte | E15: 15/01/2024 | F15: 112500 | G15: Dir. Cultura | H15: Alta | I15: 1
A16: VNC-011 | B16: PDOT-011 | C16: EC-TURI-011 | D16: Rehabilitación malecón turístico costero | E16: 15/01/2024 | F16: 450000 | G16: Dir. Turismo | H16: Alta | I16: 1
A17: VNC-012 | B17: PDOT-012 | C17: SC-EQUI-012 | D17: Adquisición unidad móvil atención salud | E17: 15/01/2024 | F17: 95000 | G17: Patronato | H17: Alta | I17: 1
... A25: VNC-020 | B25: PDOT-020 | C25: AS-ALCA-020 | D25: Construcción planta tratamiento aguas residuales | E25: 15/01/2024 | F25: 1050000 | G25: Dir. Obras Públicas | H25: Alta | I25: 1

Sheet H07_PROCESOS_SERCOP
A1: 🔙 Volver al Índice
A2: H07 — PROCESOS SERCOP: Silo 2 del CININ. Contratación pública por meta PDOT. Fuente: Portal SERCOP Ecuador.
A3: ← H01
A5: ID_Proceso | B5: ID_Meta | C5: Codigo_SERCOP | D5: URL_SERCOP | E5: Objeto_Contractual | F5: Monto_Adjudicado | G5: Estado_ID | H5: Fecha_Publicacion | I5: Proveedor | J5: V_SERCOP
A6: SRC-001 | B6: PDOT-001 | C6: SIE-GADMC-001-2024 | D6: https://www.sercop.gob.ec/portal/SIE-GADMC-001-2024 | E6: Construcción acueducto rural Montecristi | F6: 2050000 | G6: ADJ | H6: 15/03/2024 | I6: Consorcio AguaClara S.A. | J6: 1
A7: SRC-002 | B7: PDOT-002 | C7: SIE-GADMC-002-2024 | D7: https://www.sercop.gob.ec/portal/SIE-GADMC-002-2024 | E7: Ampliación red alcantarillado | F7: 0 | G7: DES | H7: 45295 | I7: Sin adjudicación | J7: 0
A8: SRC-003 | B8: PDOT-003 | C8: SIE-GADMC-003-2024 | D8: https://www.sercop.gob.ec/portal/SIE-GADMC-003-2024 | E8: Sistema manejo desechos sólidos | F8: 0 | G8: CAN | H8: 20/02/2024 | I8: Proceso cancelado | J8: 0
A9: SRC-004 | B9: PDOT-004 | C9: SIE-GADMC-004-2024 | D9: https://www.sercop.gob.ec/portal/SIE-GADMC-004-2024 | E9: Mejoramiento vialidad urbana cantonal | F9: 785000 | G9: FIN | H9: 45567 | I9: Constructora VialEcuador | J9: 1
A10: SRC-005 | B10: PDOT-005 | C10: SIE-GADMC-005-2024 | D10: https://www.sercop.gob.ec/portal/SIE-GADMC-005-2024 | E10: Rehabilitación mercado municipal | F10: 360000 | G10: ADJ | H10: 28/03/2024 | I10: Constructora Mercados S.A. | J10: 1
A11: SRC-006 | B11: PDOT-006 | C11: SIE-GADMC-006-2024 | D11: https://www.sercop.gob.ec/portal/SIE-GADMC-006-2024 | E11: Construcción centro salud tipo C | F11: 0 | G11: DES | H11: 15/03/2024 | I11: Sin adjudicación | J11: 0
A12: SRC-007 | B12: PDOT-007 | C12: SIE-GADMC-007-2024 | D12: https://www.sercop.gob.ec/portal/SIE-GADMC-007-2024 | E12: Equipamiento educativo rural | F12: 228000 | G12: FIN | H12: 20/02/2024 | I12: TechEdu Ecuador Cía. | J12: 1
A13: SRC-008 | B13: PDOT-008 | C13: SIE-GADMC-008-2024 | D13: https://www.sercop.gob.ec/portal/SIE-GADMC-008-2024 | E13: Construcción guardería comunitaria | F13: 0 | G13: CAN | H13: 45569 | I13: Proceso cancelado | J13: 0
A14: SRC-009 | B14: PDOT-009 | C14: SIE-GADMC-009-2024 | D14: https://www.sercop.gob.ec/portal/SIE-GADMC-009-2024 | E14: Sistema drenaje pluvial urbano | F14: 0 | G14: DES | H14: 25/03/2024 | I14: Sin adjudicación | J14: 0
A15: SRC-010 | B15: PDOT-010 | C15: SIE-GADMC-010-2024 | D15: https://www.sercop.gob.ec/portal/SIE-GADMC-010-2024 | E15: Construcción parque sector norte | F15: 108000 | G15: FIN | H15: 15/01/2024 | I15: Constructora RecreActiva | J15: 1
A16: SRC-011 | B16: PDOT-011 | C16: SIE-GADMC-011-2024 | D16: https://www.sercop.gob.ec/portal/SIE-GADMC-011-2024 | E16: Rehabilitación malecón costero | F16: 420000 | G16: EJE | H16: 45294 | I16: Grupo Turístico Manabí | J16: 1
A17: SRC-012 | B17: PDOT-012 | C17: SIE-GADMC-012-2024 | D17: https://www.sercop.gob.ec/portal/SIE-GADMC-012-2024 | E17: Adquisición unidad móvil salud | F17: 92000 | G17: ADJ | H17: 28/02/2024 | I17: MedEquip Ecuador S.A. | J17: 1
A18: SRC-013 | B18: PDOT-013 | C18: SIE-GADMC-013-2024 | D18: https://www.sercop.gob.ec/portal/SIE-GADMC-013-2024 | E18: Capacitación artesanos toquilla | F18: 43000 | G18: FIN | H18: 45566 | I18: CIDAP Ecuador | J18: 1
A19: SRC-014 | B19: PDOT-014 | C19: SIE-GADMC-014-2024 | D19: https://www.sercop.gob.ec/portal/SIE-GADMC-014-2024 | E19: Actualización catastro predial | F19: 149000 | G19: EJE | H19: 20/02/2024 | I19: GeoSistemas Ecuador | J19: 1
A20: SRC-015 | B20: PDOT-015 | C20: SIE-GADMC-015-2024 | D20: https://www.sercop.gob.ec/portal/SIE-GADMC-015-2024 | E20: Gestión LOTAIP y transparencia | F20: 68000 | G20: FIN | H20: 15/01/2024 | I20: Consultoría TransparEcu | J20: 1
A21: SRC-016 | B21: PDOT-016 | C21: SIE-GADMC-016-2024 | D21: https://www.sercop.gob.ec/portal/SIE-GADMC-016-2024 | E21: Reforestación cuencas hídricas | F21: 76000 | G21: ADJ | H21: 45295 | I21: Ambiental Verde Ecuador | J21: 1
A22: SRC-017 | B22: PDOT-017 | C22: SIE-GADMC-017-2024 | D22: https://www.sercop.gob.ec/portal/SIE-GADMC-017-2024 | E22: Bacheo y señalización vías parroquiales | F22: 205000 | G22: FIN | H22: 20/01/2024 | I22: Asfaltos y Señales S.A. | J22: 1
A23: SRC-018 | B23: PDOT-018 | C23: Sin proceso publicado | E23: Sin proceso SERCOP registrado | F23: 0 | I23: Sin proveedor | J23: 0
A24: SRC-019 | B24: PDOT-019 | C24: SIE-GADMC-019-2024 | D24: https://www.sercop.gob.ec/portal/SIE-GADMC-019-2024 | E24: Sistema recaudación electrónica municipal | F24: 84000 | G24: ADJ | H24: 15/02/2024 | I24: SoftGov Ecuador S.A. | J24: 1
A25: SRC-020 | B25: PDOT-020 | C25: SIE-GADMC-020-2024 | D25: https://www.sercop.gob.ec/portal/SIE-GADMC-020-2024 | E25: Construcción planta tratamiento aguas residuales | F25: 980000 | G25: ADJ | H25: 45297 | I25: HidroTech Ecuador | J25: 1

Sheet H08_DOCUMENTOS_LOTAIP
A1: 🔙 Volver al Índice
A2: H08 — DOCUMENTOS LOTAIP: Silo 4 del CININ. Cumplimiento Art. 7 LOTAIP por meta. Fuente: Portal LOTAIP de cada GAD.
A3: ← H01 | V_LOTAIP = 1 si más del 60% de documentos son accesibles. Alimenta V_i maleable.
A5: ID_Doc | B5: ID_Meta | C5: Literal_LOTAIP | D5: Tipo_Documento | E5: URL_LOTAIP | F5: Estado_Accesibilidad | G5: Fecha_Publicacion | H5: V_LOTAIP_Doc | I5: Obs
A6: LOT-001 | B6: PDOT-001 | C6: k | D6: Cédula Presupuestaria | E6: https://www.montecristi.gob.ec/lotaip/001-cedula.pdf | F6: Accesible | G6: 30/04/2024 | H6: 1 | I6: OK
A7: LOT-002 | B7: PDOT-001 | C7: k | D7: Contrato Adjudicación | E7: https://www.montecristi.gob.ec/lotaip/001-contrato.pdf | F7: Ausente | H7: 0 | I7: Enlace no publicado — brecha documental
A8: LOT-003 | B8: PDOT-001 | C8: k | D8: Acta Recepción Provisional | E8: https://www.montecristi.gob.ec/lotaip/001-acta.pdf | F8: Ausente | H8: 0 | I8: Sin acta disponible
A9: LOT-004 | B9: PDOT-002 | C9: k | D9: Cédula Presupuestaria | E9: https://www.montecristi.gob.ec/lotaip/002-cedula.pdf | F9: Ausente | H9: 0 | I9: Proceso desierto sin docs
A10: LOT-005 | B10: PDOT-002 | C10: k | D10: Informe SERCOP Desierto | E10: https://www.montecristi.gob.ec/lotaip/002-desierto.pdf | F10: Ausente | H10: 0 | I10: No publicado
A11: LOT-006 | B11: PDOT-002 | C11: k | D11: Justificación Técnica | E11: https://www.montecristi.gob.ec/lotaip/002-justif.pdf | F11: Ausente | H11: 0 | I11: No publicado
A12: LOT-007 | B12: PDOT-003 | C12: k | D12: Contrato EP Aseo | E12: https://www.montecristi.gob.ec/lotaip/003-contrato.pdf | F12: Ausente | H12: 0 | I12: Proceso cancelado
A13: LOT-008 | B13: PDOT-003 | C13: k | D13: Resolución Cancelación | E13: https://www.montecristi.gob.ec/lotaip/003-resolucion.pdf | F13: Ausente | H13: 0 | I13: No publicada
A14: LOT-009 | B14: PDOT-003 | C14: k | D14: Informe Técnico | E14: https://www.montecristi.gob.ec/lotaip/003-informe.pdf | F14: Ausente | H14: 0 | I14: No publicado
A15: LOT-010 | B15: PDOT-004 | C15: k | D15: Contrato Adjudicación | E15: https://www.montecristi.gob.ec/lotaip/004-contrato.pdf | F15: Accesible | G15: 28/02/2024 | H15: 1 | I15: OK
A16: LOT-011 | B16: PDOT-004 | C16: k | D16: Acta Entrega Definitiva | E16: https://www.montecristi.gob.ec/lotaip/004-acta.pdf | F16: Accesible | G16: 15/11/2024 | H16: 1 | I16: OK
A17: LOT-012 | B17: PDOT-004 | C17: k | D17: Cédula Presupuestaria | E17: https://www.montecristi.gob.ec/lotaip/004-cedula.pdf | F17: Accesible | G17: 30/04/2024 | H17: 1 | I17: OK
A18: LOT-013 | B18: PDOT-005 | C18: k | D18: Contrato Adjudicación | E18: https://www.montecristi.gob.ec/lotaip/005-contrato.pdf | F18: Roto | H18: 0 | I18: Error 404 — enlace caído
A19: LOT-014 | B19: PDOT-005 | C19: k | D19: Acta Recepción | E19: https://www.montecristi.gob.ec/lotaip/005-acta.pdf | F19: Ausente | H19: 0 | I19: Sin acta publicada
A20: LOT-015 | B20: PDOT-005 | C20: k | D20: Cédula Presupuestaria | E20: https://www.montecristi.gob.ec/lotaip/005-cedula.pdf | F20: Accesible | G20: 30/04/2024 | H20: 1 | I20: OK
A21: LOT-016 | B21: PDOT-006 | C21: k | D21: Contrato/Convenio | E21: https://www.montecristi.gob.ec/lotaip/006-contrato.pdf | F21: Ausente | H21: 0 | I21: Proceso desierto
A22: LOT-017 | B22: PDOT-006 | C22: k | D22: Informe Desierto | E22: https://www.montecristi.gob.ec/lotaip/006-desierto.pdf | F22: Ausente | H22: 0 | I22: No publicado
A23: LOT-018 | B23: PDOT-006 | C23: k | D23: Cédula Presupuestaria | E23: https://www.montecristi.gob.ec/lotaip/006-cedula.pdf | F23: Ausente | H23: 0 | I23: No publicada
A24: LOT-019 | B24: PDOT-007 | C24: k | D24: Contrato Adjudicación | E24: https://www.montecristi.gob.ec/lotaip/007-contrato.pdf | F24: Accesible | G24: 15/03/2024 | H24: 1 | I24: OK
A25: LOT-020 | B25: PDOT-007 | C25: k | D25: Acta Recepción | E25: https://www.montecristi.gob.ec/lotaip/007-acta.pdf | F25: Ausente | H25: 0 | I25: Proceso finalizado, acta no publicada
A26: LOT-021 | B26: PDOT-007 | C26: k | D26: Cédula Presupuestaria | E26: https://www.montecristi.gob.ec/lotaip/007-cedula.pdf | F26: Accesible | G26: 30/04/2024 | H26: 1 | I26: OK
A27: LOT-022 | B27: PDOT-008 | C27: k | D27: Contrato | E27: https://www.montecristi.gob.ec/lotaip/008-contrato.pdf | F27: Ausente | H27: 0 | I27: Proceso cancelado
A28: LOT-023 | B28: PDOT-008 | C28: k | D28: Resolución Cancelación | E28: https://www.montecristi.gob.ec/lotaip/008-res.pdf | F28: Ausente | H28: 0 | I28: No publicada
A29: LOT-024 | B29: PDOT-008 | C29: k | D29: Cédula Presupuestaria | E29: https://www.montecristi.gob.ec/lotaip/008-cedula.pdf | F29: Ausente | H29: 0 | I29: No publicada
A30: LOT-025 | B30: PDOT-009 | C30: k | D30: Contrato | E30: https://www.montecristi.gob.ec/lotaip/009-contrato.pdf | F30: Ausente | H30: 0 | I30: Proceso desierto
A31: LOT-026 | B31: PDOT-009 | C31: k | D31: Informe Desierto | E31: https://www.montecristi.gob.ec/lotaip/009-desierto.pdf | F31: Ausente | H31: 0 | I31: No publicado
A32: LOT-027 | B32: PDOT-009 | C32: k | D32: Cédula Presupuestaria | E32: https://www.montecristi.gob.ec/lotaip/009-cedula.pdf | F32: Ausente | H32: 0 | I32: No publicada
A33: LOT-028 | B33: PDOT-010 | C33: k | D33: Contrato Adjudicación | E33: https://www.montecristi.gob.ec/lotaip/010-contrato.pdf | F33: Accesible | G33: 28/01/2024 | H33: 1 | I33: OK
A34: LOT-029 | B34: PDOT-010 | C34: k | D34: Acta Entrega Definitiva | E34: https://www.montecristi.gob.ec/lotaip/010-acta.pdf | F34: Accesible | G34: 30/10/2024 | H34: 1 | I34: OK
A35: LOT-030 | B35: PDOT-010 | C35: k | D35: Cédula Presupuestaria | E35: https://www.montecristi.gob.ec/lotaip/010-cedula.pdf | F35: Accesible | G35: 30/04/2024 | H35: 1 | I35: OK
A36: LOT-031 | B36: PDOT-011 | C36: k | D36: Contrato En Ejecución | E36: https://www.montecristi.gob.ec/lotaip/011-contrato.pdf | F36: Accesible | G36: 20/03/2024 | H36: 1 | I36: OK
A37: LOT-032 | B37: PDOT-011 | C37: k | D37: Acta Inicio | E37: https://www.montecristi.gob.ec/lotaip/011-inicio.pdf | F37: Accesible | G37: 45295 | H37: 1 | I37: OK
A38: LOT-033 | B38: PDOT-011 | C38: k | D38: Cédula Presupuestaria | E38: https://www.montecristi.gob.ec/lotaip/011-cedula.pdf | F38: Accesible | G38: 30/04/2024 | H38: 1 | I38: OK
A39: LOT-034 | B39: PDOT-012 | C39: k | D39: Contrato Adjudicación | E39: https://www.montecristi.gob.ec/lotaip/012-contrato.pdf | F39: Accesible | G39: 15/03/2024 | H39: 1 | I39: OK — Revisar MOM-III
A40: LOT-035 | B40: PDOT-012 | C40: k | D40: Informe Brigadas Salud | E40: https://www.montecristi.gob.ec/lotaip/012-brigadas.pdf | F40: Accesible | G40: 30/06/2024 | H40: 1 | I40: Fuente del 8295% declarado
A41: LOT-036 | B41: PDOT-012 | C41: k | D41: Cédula Presupuestaria | E41: https://www.montecristi.gob.ec/lotaip/012-cedula.pdf | F41: Accesible | G41: 30/04/2024 | H41: 1 | I41: OK
A42: LOT-037 | B42: PDOT-013 | C42: k | D42: Contrato Capacitación | E42: https://www.montecristi.gob.ec/lotaip/013-contrato.pdf | F42: Accesible | G42: 20/01/2024 | H42: 1 | I42: OK
A43: LOT-038 | B43: PDOT-013 | C43: k | D43: Lista Artesanos Capacitados | E43: https://www.montecristi.gob.ec/lotaip/013-lista.pdf | F43: Accesible | G43: 15/12/2024 | H43: 1 | I43: OK
A44: LOT-039 | B44: PDOT-013 | C44: k | D44: Cédula Presupuestaria | E44: https://www.montecristi.gob.ec/lotaip/013-cedula.pdf | F44: Accesible | G44: 30/04/2024 | H44: 1 | I44: OK
A45: LOT-040 | B45: PDOT-014 | C45: k | D45: Contrato Catastro | E45: https://www.montecristi.gob.ec/lotaip/014-contrato.pdf | F45: Accesible | G45: 45294 | H45: 1 | I45: OK
A46: LOT-041 | B46: PDOT-014 | C46: k | D46: Acta Entrega Parcial | E46: https://www.montecristi.gob.ec/lotaip/014-acta.pdf | F46: Roto | H46: 0 | I46: Enlace caído — acta pendiente
A47: LOT-042 | B47: PDOT-014 | C47: k | D47: Cédula Presupuestaria | E47: https://www.montecristi.gob.ec/lotaip/014-cedula.pdf | F47: Accesible | G47: 30/04/2024 | H47: 1 | I47: OK
A48: LOT-043 | B48: PDOT-015 | C48: k | D48: Informe Q1 LOTAIP | E48: https://www.montecristi.gob.ec/lotaip/015-q1.pdf | F48: Accesible | G48: 30/04/2024 | H48: 1 | I48: OK
A49: LOT-044 | B49: PDOT-015 | C49: k | D49: Informe Q2 LOTAIP | E49: https://www.montecristi.gob.ec/lotaip/015-q2.pdf | F49: Accesible | G49: 31/07/2024 | H49: 1 | I49: OK
A50: LOT-045 | B50: PDOT-015 | C50: k | D50: Informe Q3-Q4 LOTAIP | E50: https://www.montecristi.gob.ec/lotaip/015-q4.pdf | F50: Accesible | G50: 31/12/2024 | H50: 1 | I50: OK
A51: LOT-046 | B51: PDOT-016 | C51: k | D51: Contrato Reforestación | E51: https://www.montecristi.gob.ec/lotaip/016-contrato.pdf | F51: Accesible | G51: 15/04/2024 | H51: 1 | I51: OK
A52: LOT-047 | B52: PDOT-016 | C52: k | D52: Informe Plantación | E52: https://www.montecristi.gob.ec/lotaip/016-informe.pdf | F52: Ilegible | H52: 0 | I52: PDF corrupto — no legible
A53: LOT-048 | B53: PDOT-016 | C53: k | D53: Cédula Presupuestaria | E53: https://www.montecristi.gob.ec/lotaip/016-cedula.pdf | F53: Accesible | G53: 30/04/2024 | H53: 1 | I53: OK
A54: LOT-049 | B54: PDOT-017 | C54: k | D54: Contrato Vialidad | E54: https://www.montecristi.gob.ec/lotaip/017-contrato.pdf | F54: Accesible | G54: 45293 | H54: 1 | I54: OK
A55: LOT-050 | B55: PDOT-017 | C55: k | D55: Acta Entrega Definitiva | E55: https://www.montecristi.gob.ec/lotaip/017-acta.pdf | F55: Accesible | G55: 30/11/2024 | H55: 1 | I55: OK
A56: LOT-051 | B56: PDOT-017 | C56: k | D56: Cédula Presupuestaria | E56: https://www.montecristi.gob.ec/lotaip/017-cedula.pdf | F56: Accesible | G56: 30/04/2024 | H56: 1 | I56: OK
A57: LOT-052 | B57: PDOT-018 | C57: k | D57: Contrato/Convenio | E57: https://www.montecristi.gob.ec/lotaip/018-contrato.pdf | F57: Ausente | H57: 0 | I57: Sin proceso SERCOP ni docs
A58: LOT-053 | B58: PDOT-018 | C58: k | D58: Informe Beneficiarios | E58: https://www.montecristi.gob.ec/lotaip/018-beneficiarios.pdf | F58: Ausente | H58: 0 | I58: Sin informe publicado
A59: LOT-054 | B59: PDOT-018 | C59: k | D59: Cédula Presupuestaria | E59: https://www.montecristi.gob.ec/lotaip/018-cedula.pdf | F59: Ausente | H59: 0 | I59: Sin cédula publicada
A60: LOT-055 | B60: PDOT-019 | C60: k | D60: Contrato Software | E60: https://www.montecristi.gob.ec/lotaip/019-contrato.pdf | F60: Accesible | G60: 45294 | H60: 1 | I60: OK
A61: LOT-056 | B61: PDOT-019 | C61: k | D61: Acta Implementación | E61: https://www.montecristi.gob.ec/lotaip/019-acta.pdf | F61: Accesible | G61: 15/10/2024 | H61: 1 | I61: OK
A62: LOT-057 | B62: PDOT-019 | C62: k | D62: Cédula Presupuestaria | E62: https://www.montecristi.gob.ec/lotaip/019-cedula.pdf | F62: Accesible | G62: 30/04/2024 | H62: 1 | I62: OK
A63: LOT-058 | B63: PDOT-020 | C63: k | D63: Contrato Planta | E63: https://www.montecristi.gob.ec/lotaip/020-contrato.pdf | F63: Accesible | G63: 15/06/2024 | H63: 1 | I63: Proceso iniciado, sin devengado
A64: LOT-059 | B64: PDOT-020 | C64: k | D64: Acta Inicio Obras | E64: https://www.montecristi.gob.ec/lotaip/020-inicio.pdf | F64: Accesible | G64: 45298 | H64: 1 | I64: OK
A65: LOT-060 | B65: PDOT-020 | C65: k | D65: Cédula Presupuestaria | E65: https://www.montecristi.gob.ec/lotaip/020-cedula.pdf | F65: Accesible | G65: 30/06/2024 | H65: 1 | I65: OK

Sheet H09_EJECUCION_PRESUPUESTARIA
A1: 🔙 Volver al Índice
A2: H09 — EJECUCIÓN PRESUPUESTARIA: Silo 3 del CININ. Devengado eSIGEF por meta. C1=abr | C2=ago | C3=dic. Fuente: e-SIGEF Ministerio Finanzas.
A3: ← H01 | T_i = Dev_Total / Codificado_Vigente. V_eSIGEF = 1 si Dev_Total > 0
A5: ID_Ejec | B5: ID_Meta | C5: Partida_Presup | D5: Codif_Inicial | E5: Reformas | F5: Codif_Vigente | G5: Dev_C1_abr | H5: Dev_C2_ago | I5: Dev_C3_dic_parcial | J5: Dev_Total_31dic | K5: T_i | L5: V_eSIGEF
A6: EJC-001 | B6: PDOT-001 | C6: 75.01.07.001 | D6: 2125000 | E6: 0 | F6: 2125000 | G6: 270938 | H6: 812813 | I6: 1806250 | J6: 1806250 | K6: =J6/F6 -> 0.85 | L6: =IF(J6>0,1,0) -> 1
A7: EJC-002 | B7: PDOT-002 | C7: 75.01.07.002 | D7: 1550000 | E7: 0 | F7: 1550000 | G7: 13950 | H7: 41850 | I7: 93000 | J7: 93000 | K7: =J7/F7 -> 0.06 | L7: =IF(J7>0,1,0) -> 1
A8: EJC-003 | B8: PDOT-003 | C8: 75.01.07.003 | D8: 450000 | E8: 0 | F8: 450000 | G8: 0 | H8: 0 | I8: 0 | J8: 0 | K8: =J8/F8 -> 0 | L8: =IF(J8>0,1,0) -> 0
A9: EJC-004 | B9: PDOT-004 | C9: 75.01.05.004 | D9: 800000 | E9: 0 | F9: 800000 | G9: 108000 | H9: 324000 | I9: 720000 | J9: 720000 | K9: =J9/F9 -> 0.9 | L9: =IF(J9>0,1,0) -> 1
A10: EJC-005 | B10: PDOT-005 | C10: 75.01.05.005 | D10: 375000 | E10: 0 | F10: 375000 | G10: 42188 | H10: 126563 | I10: 281250 | J10: 281250 | K10: =J10/F10 -> 0.75 | L10: =IF(J10>0,1,0) -> 1
A11: EJC-006 | B11: PDOT-006 | C11: 75.01.05.006 | D11: 700000 | E11: 0 | F11: 700000 | G11: 8400 | H11: 25200 | I11: 56000 | J11: 56000 | K11: =J11/F11 -> 0.08 | L11: =IF(J11>0,1,0) -> 1
A12: EJC-007 | B12: PDOT-007 | C12: 75.01.05.007 | D12: 237500 | E12: 0 | F12: 237500 | G12: 27788 | H12: 83363 | I12: 185250 | J12: 185250 | K12: =J12/F12 -> 0.78 | L12: =IF(J12>0,1,0) -> 1
A13: EJC-008 | B13: PDOT-008 | C13: 75.01.05.008 | D13: 300000 | E13: 0 | F13: 300000 | G13: 0 | H13: 0 | I13: 0 | J13: 0 | K13: =J13/F13 -> 0 | L13: =IF(J13>0,1,0) -> 0
A14: EJC-009 | B14: PDOT-009 | C14: 75.01.07.009 | D14: 525000 | E14: 0 | F14: 525000 | G14: 7875 | H14: 23625 | I14: 52500 | J14: 52500 | K14: =J14/F14 -> 0.1 | L14: =IF(J14>0,1,0) -> 1
A15: EJC-010 | B15: PDOT-010 | C15: 75.01.05.010 | D15: 112500 | E15: 0 | F15: 112500 | G15: 16875 | H15: 50625 | I15: 112500 | J15: 112500 | K15: =J15/F15 -> 1 | L15: =IF(J15>0,1,0) -> 1
A16: EJC-011 | B16: PDOT-011 | C16: 75.01.05.011 | D16: 450000 | E16: 0 | F16: 450000 | G16: 47250 | H16: 141750 | I16: 315000 | J16: 315000 | K16: =J16/F16 -> 0.7 | L16: =IF(J16>0,1,0) -> 1
A17: EJC-012 | B17: PDOT-012 | C17: 53.08.04.012 | D17: 95000 | E17: 0 | F17: 95000 | G17: 1140 | H17: 3420 | I17: 7600 | J17: 7600 | K17: =J17/F17 -> 0.08 | L17: =IF(J17>0,1,0) -> 1
... A25: EJC-020 | B25: PDOT-020 | C25: 75.01.07.020 | D25: 1050000 | E25: 0 | F25: 1050000 | G25: 31500 | H25: 94500 | I25: 210000 | J25: 210000 | K25: =J25/F25 -> 0.2 | L25: =IF(J25>0,1,0) -> 1
A27: TOTALES: | D27: =SUM(D6:D25) -> 9525000 | F27: =SUM(F6:F25) -> 9525000 | G27: =SUM(G6:G25) -> 658217 | H27: =SUM(H6:H25) -> 1974647 | J27: =SUM(J6:J25) -> 4388100 | K27: =J27/F27 -> 0.46069291

Sheet H10_INFORMES_CPCCS
A1: 🔙 Volver al Índice
A2: H10 — INFORMES CPCCS: Silo 5 del CININ. Menciones de metas en rendición de cuentas. Fuente: Informes CPCCS y discursos de alcalde.
A3: ← H01 | V_CPCCS=1 congruente; V_CPCCS=0.5 incongruente (diff>20pp); V_CPCCS=0 no mencionada
A5: ID_Mencion | B5: ID_Meta | C5: Mencionada | D5: Cumpl_Declarado_Pct | E5: Fuente | F5: Pagina | G5: Cita_Textual | H5: Congr_eSIGEF | I5: V_CPCCS
A6: CPC-001 | B6: PDOT-001 | C6: No | I6: 0
A7: CPC-002 | B7: PDOT-002 | C7: No | I7: 0
A8: CPC-003 | B8: PDOT-003 | C8: No | I8: 0
A9: CPC-004 | B9: PDOT-004 | C9: Sí | D9: 0.9 | E9: Informe | F9: 18 | G9: Se completó el mejoramiento de vías urbanas con 90% de avance al cierre del período' | H9: Congruente | I9: 1
A10: CPC-005 | B10: PDOT-005 | C10: No | I10: 0
A11: CPC-006 | B11: PDOT-006 | C11: No | I11: 0
A12: CPC-007 | B12: PDOT-007 | C12: No | I12: 0
A13: CPC-008 | B13: PDOT-008 | C13: No | I13: 0
A14: CPC-009 | B14: PDOT-009 | C14: No | I14: 0
A15: CPC-010 | B15: PDOT-010 | C15: Sí | D15: 1 | E15: Informe | F15: 22 | G15: El parque deportivo del sector norte fue inaugurado con éxito y en plena operación' | H15: Congruente | I15: 1
A16: CPC-011 | B16: PDOT-011 | C16: No | I16: 0
A17: CPC-012 | B17: PDOT-012 | C17: Sí | D17: 82.95 | E17: Ambas | F17: 31 | G17: La unidad móvil realizó 414,743 contactos de salud comunitaria, superando en 8,295% la meta de 5,000 brigadas planificadas' | H17: Incongruente | I17: 0.5
A18: CPC-013 | B18: PDOT-013 | C18: Sí | D18: 1 | E18: Informe | F18: 25 | G18: Se capacitaron 200 artesanos en técnicas de sombrero paja toquilla, completando el 100% de la meta' | H18: Congruente | I18: 1
A19: CPC-014 | B19: PDOT-014 | C19: No | I19: 0
A20: CPC-015 | B20: PDOT-015 | C20: Sí | D20: 1 | E20: Informe | F20: 28 | G20: Se publicaron los 4 informes LOTAIP trimestrales, cumpliendo al 100% el compromiso de transparencia' | H20: Congruente | I20: 1
A21: CPC-016 | B21: PDOT-016 | C21: No | I21: 0
A22: CPC-017 | B22: PDOT-017 | C22: Sí | D22: 0.9 | E22: Informe | F22: 35 | G22: Se ejecutó el bacheo de 22.5 km de vías parroquiales de los 25 km planificados' | H22: Congruente | I22: 1
A23: CPC-018 | B23: PDOT-018 | C23: No | I23: 0
A24: CPC-019 | B24: PDOT-019 | C24: Sí | D24: 0.8 | E24: Informe | F24: 40 | G24: El sistema de recaudación electrónica fue implementado en un 80%, en fase de pruebas al cierre' | H24: Congruente | I24: 1
A25: CPC-020 | B25: PDOT-020 | C25: No | I25: 0

Sheet H10B_DATOS_SIGAD
A1: 🔙 Volver al Índice
A2: H10B_DATOS_SIGAD — SILO 6: Auto-reporte ICM | SIGAD-SENPLADES | Fuente: Reportes oficiales SIGAD GAD Montecristi 2023-2024
A3: ← H01 | El ICM SIGAD es el indicador contra el que se mide la Brecha ICM-ICPI. MOM-I activa cuando ICM alto + baja representatividad presupuestaria (§3.6.1).
A5: A · IDENTIFICACIÓN DEL REPORTE SIGAD
A6: Parámetro | B6: Valor
A7: GAD_Nombre | B7: GAD Municipal de Montecristi
A8: RUC_GAD | B8: 1360001010001
A9: Tipo_GAD | B9: CANTONAL
A10: Periodo_Politico | B10: 2023-2027
A11: Responsable_Envio | B11: Sonia Xiomara Rodríguez Mero
A12: Correo_Responsable | B12: sonia.rodriguez@montecristi.gob.ec
A13: Telefono | B13: 52310052
A14: Trimestres_Enviados_2024 | B14: Programación + T1 + T2 + T3 + T4 (todos enviados)
A16: B · RESUMEN ANUAL — Universo SIGAD vs Universo SIAP
A17: Año_Fiscal | B17: Metas_Ingresadas_SIGAD | C17: Proyectos_Ingresados | D17: Monto_Total_Proyectos | E17: Monto_En_Ejecucion | F17: ICM_Oficial | G17: Metas_Universo_SIAP | H17: Presupuesto_Universo_SIAP | I17: Represent._Presup. | J17: Represent._Metas | K17: Estado_MOM_I
A18: 2023 | B18: 5 | C18: 13 | D18: 1824689.4 | E18: 1824689.4 | F18: 1 | G18: 20 | H18: 9525000 | I18: =D18/H18 -> 0.19156844 | J18: =B18/G18 -> 0.25 | K18: =IF(AND(F18>=0.8,I18<0.1),"⚠️ MOM-I ACTIVO Alta",IF(AND(F18>=0.8,I18<0.5),"⚠️ MOM-I ACTIVO Media","Sin señal")) -> ⚠️ MOM-I ACTIVO Media
A19: 2024 | B19: 9 | C19: 18 | D19: 3939101.5 | E19: 3939101.5 | F19: =H01_PARAMETROS_GENERALES!B12 -> 1 | G19: 20 | H19: 9525000 | I19: =D19/H19 -> 0.41355396 | J19: =B19/G19 -> 0.45 | K19: =IF(AND(F19>=0.8,I19<0.1),"⚠️ MOM-I ACTIVO Alta",IF(AND(F19>=0.8,I19<0.5),"⚠️ MOM-I ACTIVO 🟠 Alta","Sin señal")) -> ⚠️ MOM-I ACTIVO 🟠 Alta
A21: C · DETALLE METAS REPORTADAS EN SIGAD — Año Fiscal 2024
A22: DATO CLAVE: Solo 9 de 20 metas del universo SIAP fueron reportadas en SIGAD. ICM = 100% sobre esas 9 metas. Las 11 restantes (55%) nunca ingresaron al sistema de auto-reporte.
A23: ID_SIGAD | B23: Competencia_GAD | C23: Objetivo_PDOT | D23: Meta_Resultados_PDOT | E23: Núm_Proyectos | F23: Meta_Acum_Anual | G23: Valor_Real_Acum | H23: Pct_Avance_Meta | I23: Codificado_Final | J23: Devengado_Anual | K23: Pct_Ejec_Presup | L23: ID_Meta_SIAP | M23: En_SIGAD_2024 | N23: En_Muestra_SIAP
A24: SIGAD-001 | B24: COOPERACIÓN INTERNACIONAL | C24: Fortalecer la gestión del GAD con alianzas estratégicas | D24: Gestionar 28 convenios en 2024 para fortalecimiento institucional | E24: 2 | F24: 28 | G24: 28 | H24: 1 | I24: 1832220 | J24: 1832220 | K24: 1 | L24: PDOT-013 | M24: SI | N24: SI
A25: SIGAD-002 | B25: AGUA POTABLE — SERVICIO PÚBLICO | C25: Prever crecimiento ordenado para mejorar calidad de vida | D25: Lograr 4 adjudicaciones en 2024 para proyectos agua y alcantarillado | E25: 3 | F25: 4 | G25: 4 | H25: 1 | I25: 1434654.5 | J25: 1434654.5 | K25: 1 | L25: PDOT-001 | M25: SI | N25: SI
A26: SIGAD-003 | B26: VIALIDAD | C26: Contribuir a mantener conectividad y movilidad | D26: Intervenir 2.00 km de vías con carpeta asfáltica en 2024 | E26: 2 | F26: 2 | G26: 2 | H26: 1 | I26: 57205.91 | J26: 57205.91 | K26: 1 | L26: PDOT-004 | M26: SI | N26: SI
A27: SIGAD-004 | B27: GESTIÓN AMBIENTAL | C27: Mejorar control ambiental cantonal | D27: Implementar sistema de control de residuos sólidos en 3 parroquias | E27: 2 | F27: 3 | G27: 3 | H27: 1 | I27: 185000 | J27: 185000 | K27: 1 | L27: PDOT-016 | M27: SI | N27: SI
A28: SIGAD-005 | B28: ALCANTARILLADO | C28: Ampliar cobertura de saneamiento ambiental | D28: Construir 2,438 metros de red de alcantarillado zona Elóy Alfaro | E28: 2 | F28: 2438 | G28: 2438 | H28: 1 | I28: 198000 | J28: 198000 | K28: 1 | L28: PDOT-002 | M28: SI | N28: SI
A29: SIGAD-006 | B29: ORDENAMIENTO TERRITORIAL | C29: Modernizar sistema de planificación cantonal | D29: Actualizar 1 catastro predial urbano-rural en 2024 | E29: 1 | F29: 1 | G29: 1 | H29: 1 | I29: 95000 | J29: 95000 | K29: 1 | L29: PDOT-014 | M29: SI | N29: SI
A30: SIGAD-007 | B30: FORTALECIMIENTO INSTITUCIONAL | C30: Mejorar capacidades institucionales del GAD | D30: Capacitar 120 funcionarios en gestión municipal y sistemas | E30: 2 | F30: 120 | G30: 120 | H30: 1 | I30: 42000 | J30: 42000 | K30: 1 | L30: PDOT-019 | M30: SI | N30: SI
A31: SIGAD-008 | B31: TURISMO | C31: Fomentar turismo sostenible cantonal | D31: Organizar 49 eventos turísticos y culturales en 2024 | E31: 2 | F31: 49 | G31: 49 | H31: 1 | I31: 55021 | J31: 55021 | K31: 1 | L31: PDOT-011 | M31: SI | N31: SI
A32: SIGAD-009 | B32: DESECHOS SÓLIDOS | C32: Optimizar gestión de residuos cantonal | D32: Implementar 1 plan de gestión integral de residuos sólidos | E32: 2 | F32: 1 | G32: 1 | H32: 1 | I32: 40000 | J32: 40000 | K32: 1 | L32: PDOT-020 | M32: SI | N32: SI
A33: NO REPORTADA | B33: METAS EN MUESTRA SIAP NO REPORTADAS EN SIGAD 2024 | M33: NO
A34: (sin ID) | B34: VIALIDAD PARROQUIAL | C34: Mejorar conectividad vial rural | D34: Bacheo y señalización vías parroquiales (meta PDOT-017) | L34: PDOT-017 | M34: NO | N34: SI
A35: (sin ID) | B35: ALCANTARILLADO SANITARIO | C35: Ampliar redes de alcantarillado | D35: Planta tratamiento aguas residuales (meta PDOT-003) | L35: PDOT-003 | M35: NO | N35: SI
A36: (sin ID) | B36: INFRAESTRUCTURA SOCIAL | C36: Equipar infraestructura educativa rural | D36: Equipamiento educativo establecimientos rurales (meta PDOT-007) | L36: PDOT-007 | M36: NO | N36: SI
A37: (sin ID) | B37: SALUD | C37: Mejorar infraestructura de salud | D37: Centro de salud tipo C parroquia rural (meta PDOT-006) | L37: PDOT-006 | M37: NO | N37: SI
A38: (sin ID) | B38: MERCADO MUNICIPAL | C38: Rehabilitar infraestructura comercial | D38: Rehabilitación mercado municipal (meta PDOT-005) | L38: PDOT-005 | M38: NO | N38: SI
A39: (sin ID) | B39: DEPORTE Y RECREACIÓN | C39: Construir espacios recreativos | D39: Parque recreativo sector norte (meta PDOT-010) | L39: PDOT-010 | M39: NO | N39: SI
A40: (sin ID) | B40: INFRAESTRUCTURA SOCIAL | C40: Proveer servicios de cuidado infantil | D40: Guardería comunitaria El Carmen (meta PDOT-008) | L40: PDOT-008 | M40: NO | N40: SI
A41: (sin ID) | B41: SERVICIOS SOCIALES | C41: Atender grupos vulnerables | D41: Programa adulto mayor y discapacidad (meta PDOT-018) | L41: PDOT-018 | M41: NO | N41: SI
A43: D · ANÁLISIS MOM-I — FRAGMENTACIÓN SELECTIVA DEL UNIVERSO EVALUADO §3.6.1
A44: Todos los cálculos son fórmulas vivas — actualizan al cambiar Sección B.
A45: Parámetro | B45: Valor | C45: Fórmula / Fuente
A46: Metas_SIGAD_2024 | B46: =B19 -> 9 | C46: Sección B — Año 2024
A47: Metas_SIAP_Total | B47: =G19 -> 20 | C47: Universo estratégico PDOT
A48: Representatividad_Metas | B48: =J19 -> 0.45 | C48: =B46/B47 -> 0.45
A49: Presupuesto_SIGAD_2024 | B49: =D19 -> 3939101.5 | C49: Monto total proyectos SIGAD 2024
A50: Presupuesto_SIAP_Anual | B50: =H19 -> 9525000 | C50: Universo estratégico SIAP 2024
A51: Representatividad_Presupuestaria | B51: =I19 -> 0.41355396 | C51: =B49/B50 -> 0.41355396
A52: ICM_Oficial_SIGAD | B52: =H01_PARAMETROS_GENERALES!B12 -> 1 | C52: Referencia desde H01 — actualiza automáticamente
A53: ICPI_SIAP | B53: =H14_CALCULO_ICPI!B32/100 -> 0.41236256 | C53: Motor central H14
A54: Brecha_ICM_ICPI (pp) | B54: =B52*100-B53*100 -> 58.763744 | C54: pp — Brecha crítica >50pp
A55: SEÑAL MOM-I | B55: =IF(AND(B52>=0.8,B51<0.5),"⚠️ FRAGMENTACIÓN SELECTIVA CONFIRMADA: ICM="&TEXT(B52,"0%")&" sobre solo "&TEXT(B51,"0.0%")&" del presupuesto estratégico SIAP. Brecha: "&TEXT(B54,"0.0")&"pp. §3.6.1","Sin señal MOM-I") -> ⚠️ FRAGMENTACIÓN SELECTIVA CONFIRMADA: ICM=100% sobre solo 41% del presupuesto estratégico SIAP. Brecha: 59pp. §3.6.1
A56: SEVERIDAD | B56: =IF(B51<0.2,"🔴 CRÍTICA",IF(B51<0.4,"🟠 ALTA",IF(B51<0.5,"💛 ALTA-MEDIA","🟡 MEDIA"))) -> 💛 ALTA-MEDIA | C56: Umbrales: <20%=CRÍTICA | <40%=ALTA | <50%=ALTA-MEDIA | ≥50%=MEDIA
A57: ✅ NOTA METODOLÓGICA | B57: Esta hoja es la fuente primaria del Silo 6 del CININ. Sin esta hoja, la Brecha ICM-ICPI es solo un número. CON esta hoja, la brecha es una afirmación verificable con el reporte oficial SIGAD.
A59: LA TRÍADA DE UNIVERSOS: PAC vs SIGAD vs SIAP
A60: PAC 2024 (universo contratación SERCOP) | B60: 8712580.5 | C60: $8.7M — lo que el GAD planificó contratar va SERCOP
A61: SIGAD 2024 (universo auto-reporte ICM) | B61: =D19 -> 3939101.5 | C61: $3.9M — 45% del PAC. ICM=100% sobre este universo.
A62: SIAP 2024 (universo estratégico PDOT) | B62: =H19 -> 9525000 | C62: $9.5M — prioridad estratégica máxima del PDOT
A63: Fuente: | B63: Reporte ICM SIGAD oficial GAD Montecristi 2024: 9 metas | 18 proyectos | $3,939,101.48 | ICM=100% | Responsable: Sonia Xiomara Rodríguez Mero

Sheet H11_ALERTAS_MOM
A1: 🔙 Volver al Índice
A2: H11 — SEÑALES DE ATENCIÓN TEMPRANA — Protocolos MOM
A3: Estas señales indican oportunidades de mejora en la gestión programática y documental. No constituyen sanciones ni procesos disciplinarios.
A4: ← H01 | Ver H14 (ICPI) →
A5: ✅ ESPÍRITU DEL SISTEMA: Las alertas MOM son señales de atención temprana para mejorar la gestión programática y documental. No constituyen sanciones ni reemplazan la potestad de la CGE. El SIAP-ICPI habla AL GAD, no CONTRA él.
A7: MOM-I · FRAGMENTACIÓN SELECTIVA DEL UNIVERSO EVALUADO §3.6.1
A8: FRAGMENTACIÓN SELECTIVA §3.6.1: Ocurre cuando el GAD reporta cumplimiento alto en SIGAD basándose en un subconjunto pequeño del presupuesto total del PDOT, excluyendo estratégicamente las metas de mayor inversión que no fueron ejecutadas. Condición: ICM≥80% Y representatividad presupuestaria <10%. Base legal: COPFP Art. 9, 41, 54.
A9: Parámetro | B9: Valor | C9: Fórmula / Fuente | D9: Nota
A10: Presupuesto Metas Reportadas SIGAD | B10: =H10B_DATOS_SIGAD!D19 -> 3939101.5 | C10: Referencia directa a H10B_DATOS_SIGAD Sección B — Año 2024 | D10: $3,939,101 — monto real SIGAD 2024
A11: Presupuesto Total PDOT 2024 | B11: 9525000 | C11: Presupuesto anual estratégico SIAP | D11: $9,525,000 = suma presupuestos anuales 20 metas PDOT
A12: Representatividad SIGAD/PDOT | B12: =B10/B11 -> 0.41355396 | C12: =B10/B11 -> 0.41355396 | D12: ="SIGAD $"&TEXT(B10,"#,##0")&" / SIAP $"&TEXT(B11,"#,##0")&" = "&TEXT(B10/B11,"0.0%") -> SIGAD $3939101,480 / SIAP $9525000,0 = 41%
A13: ICM Reportado SIGAD | B13: =H01_PARAMETROS_GENERALES!B12 -> 1 | C13: =H01_PARAMETROS_GENERALES!B12 -> 1 | D13: ="ICM SIGAD="&TEXT(H01_PARAMETROS_GENERALES!B12,"0%")&" sobre "&TEXT(B12,"0.0%")&" del presupuesto SIAP — MOM-I "&IF(AND(B13>=0.8,B12<0.5),"ACTIVO","INACTIVO") -> ICM SIGAD=100% sobre 41% del presupuesto SIAP — MOM-I ACTIVO
A14: SEVERIDAD | B14: =IF(B12<0.2,"🔴 Alta",IF(B12<0.4,"🟠 Alta-Media",IF(B12<0.5,"💛 Media-Alta","🟡 Media"))) -> 💛 Media-Alta | C14: =IF(B12<0.2,"🔴 Alta",IF(B12<0.4,"🟠 Alta-Media",IF(B12<0.5,"💛 Media-Alta","🟡 Media"))) -> 💛 Media-Alta | D14: Umbrales: <20%=Alta | <40%=Alta-Media | <50%=Media-Alta | ≥50%=Media
A15: SEÑAL MOM-I (Automática) | B15: =IF(AND(B13>=0.8,B12<0.5),"⚠️ FRAGMENTACIÓN SELECTIVA CONFIRMADA §3.6.1: ICM="&TEXT(B13,"0%")&" sobre solo "&TEXT(B12,"0.0%")&" del presupuesto SIAP. Brecha ICM-ICPI="&TEXT(B13*100-H14_CALCULO_ICPI!B32,"0.0")&"pp. Referencia: H10B_DATOS_SIGAD.","Sin señal MOM-I") -> ⚠️ FRAGMENTACIÓN SELECTIVA CONFIRMADA §3.6.1: ICM=100% sobre solo 41% del presupuesto SIAP. Brecha ICM-ICPI=59pp. Referencia: H10B_DATOS_SIGAD. | C15: =IF(AND(B13>=0.8,B12<0.5),"⚠️ FRAGMENTACIÓN SELECTIVA CONFIRMADA §3.6.1: ICM="&TEXT(B13,"0%")&" sobre solo "&TEXT(B12,"0.0%")&" del presupuesto SIAP. Brecha ICM-ICPI="&TEXT(B13*100-H14_CALCULO_ICPI!B32,"0.0")&"pp. Referencia: H10B_DATOS_SIGAD.","Sin señal MOM-I") -> ⚠️ FRAGMENTACIÓN SELECTIVA CONFIRMADA §3.6.1: ICM=100% sobre solo 41% del presupuesto SIAP. Brecha ICM-ICPI=59pp. Referencia: H10B_DATOS_SIGAD. | D15: MOM-I §3.6.1 — Formula viva: se actualiza con H10B_DATOS_SIGAD y H01
A17: MOM-II · SUSTITUCIÓN ESTRATÉGICA DE METAS §3.6.2
A18: SUSTITUCIÓN ESTRATÉGICA §3.6.2: Ocurre cuando el GAD reforma el POA durante el año fiscal, eliminando metas complejas y costosas y sustitutyéndolas por actividades baratas y fácilmente ejecutables, sin seguir el procedimiento formal del Art. 295 COOTAD. Detectado via hash SHA-256 del POA (comparación enero vs. diciembre). Base legal: COOTAD Art. 295 + COPFP Art. 97.
A19: Parámetro | B19: Valor | C19: Descripción | D19: Nota
A20: Hash POA Aprobado (enero) | B20: a3f5c9d2e8b14f7a3c6d9e0f1b2a4c8d | C20: Huella digital POA enero 2024 | D20: Simulado - representa integridad documental
A21: Hash POA Cierre (diciembre) | B21: a3f5c9d2e8b14f7a3c6d9e0f1b2a4c8d | C21: Huella digital POA diciembre 2024 | D21: Idéntico → POA sin modificaciones
A22: Comparación de Hashes | B22: =IF(B20=B21,"✅ Hashes idénticos — POA mantiene integridad documental","⚠️ ATENCIÓN: POA modificado entre enero y diciembre") -> ✅ Hashes idénticos — POA mantiene integridad documental | C22: =IF(B20=B21,"✅ Hashes idénticos — POA mantiene integridad documental","⚠️ ATENCIÓN: POA modificado entre enero y diciembre. Revisar metas sustituidas.") -> ✅ Hashes idénticos — POA mantiene integridad documental | D22: Verificación automática
A23: SEÑAL MOM-II Global | B23: Sin señal — POA mantiene integridad documental | C23: Resultado comparación | D23: No se detectaron sustituciones sistemáticas
A24: NOTA ESPECÍFICA PDOT-006 | B24: ⚠️ Meta 'Centro Salud tipo C' declarada 'en gestión' con proceso SERCOP desierto. Revisar si existe reformulación de alcance o sustitución de meta. | C24: Análisis específico | D24: Revisar en próximo ciclo
A26: MOM-III · INFLACIÓN DE UNIDADES DE MEDIDA §3.6.3
A27: INFLACIÓN DE UNIDADES §3.6.3: Ocurre cuando el GAD mantiene formalmente el nombre de la meta original pero redefine operativamente la unidad de medida, transformando métricas verificables en métricas elásticas no verificables (ej: de 'brigadas físicas' a 'contactos'). Condición: Cumplimiento reportado >500% Y T_i <10% Y unidad_reporte ≠ unidad_PDOT. Base legal: COPFP Art. 117 + COA Art. 196.
A28: ID_Meta | B28: Meta PDOT | C28: Unidad PDOT | D28: Unidad SIGAD Reportada | E28: Cant. Planif. | F28: Cant. Reportada | G28: % Cumplimiento | H28: T_i Presup. | I28: SEÑAL MOM-III
A29: PDOT-012 | B29: Unidad móvil de salud comunitaria | C29: Unidad operativa | D29: Contactos sistema salud | E29: 1 | F29: 414743 | G29: 82.95 | H29: 0.08 | I29: ⚠️ ATENCIÓN TEMPRANA: Cumplimiento 8,295% con ejecución presupuestaria del 8%. La diferencia entre 'Unidad Móvil operativa' (PDOT) y 'contactos sistema salud' (SIGAD) sugiere redefinición operativa del indicador. Se recomienda verificación documental.
A30: Fórmula automática de detección: | C30: =IF(AND(G30>500,H30<0.1),"⚠️ SEÑAL MOM-III ACTIVA","Sin señal") -> Sin señal
A32: RESUMEN DE SEÑALES DE ATENCIÓN TEMPRANA
A33: Protocolo | B33: Estado | C33: Severidad | D33: Metas Afectadas | E33: Acción Recomendada
A34: MOM-I (Fragmentación Selectiva) | B34: ⚠️ Activa | C34: Alta | D34: PDOT-018 y múltiples no reportadas | E34: Ampliar universo de metas en SIGAD al 100% del PDOT
A35: MOM-II (Sustitución de Metas) | B35: ✅ Sin señal | C35: — | D35: — | E35: Mantener integridad documental del POA
A36: MOM-III (Inflación de Unidades) | B36: ⚠️ Activa | C36: Alta | D36: PDOT-012 | E36: Verificar definición operativa del indicador 'Unidad Móvil'
A37: SECCIÓN 4 · CLASIFICACIÓN DE SEÑALES DE ATENCIÓN TEMPRANA §3.6
A38: Clasificación técnica de señales identificadas por los protocolos MOM. Cada señal indica una oportunidad de mejora en la gestión programática.
A39: Tipo_Dictamen | B39: Código | C39: Definición | D39: Ejemplo_Aplicado | E39: Base_Legal
A40: Señal Tipo A — Brecha Documental | B40: DIC-A | C40: Desviación producida por inconsistencias en el registro, cambios no documentados en unidad de medida o errores humanos en el reporte. Sin evidencia de dolo administrativo. Afecta T_i pero no invalida la meta. | D40: Proceso SERCOP declarado desierto por especificaciones técnicas complejas | E40: COA Art. 196
A41: Señal Tipo B — Proceso sin Registro Público | B41: DIC-B | C41: Violación directa de disposiciones del Art. 77 COOTAD o Art. 7 LOTAIP. PAC Fantasma: asignación presupuestaria en el POA que nunca se materializa en contrato adjudicado ni en ejecución devengada. | D41: Meta PDOT-018: Sin POA, sin SERCOP, sin devengado al cierre | E41: COOTAD Art. 77 + LOSNCP Art. 22
A42: Señal Tipo C — Anomalía en Indicador | B42: DIC-C | C42: Distorsión intencional de metas para inflar artificialmente el ICM. Gaming confirmado: variación desproporcionada del cumplimiento sin respaldo en devengado real. Constituye falta de motivación del acto administrativo. | D42: Meta PDOT-012: Cumplimiento 8,295% con devengado 8%. Cambio unidad: 'Unidad Móvil' → 'contactos telefónicos' | E42: COA Art. 196 + COPFP Art. 117
A43: ⚠️ NOTA METODOLÓGICA: | B43: La clasificación de señales de atención temprana no reemplaza la potestad sancionatoria de los organismos de control (CGE, CPCCS). El sistema SIAP-ICPI genera evidencia técnica objetiva; la acción institucional corresponde a las autoridades competentes

Sheet H12_ESTATUTO_ORGANICO
A1: 🔙 Volver al Índice
A2: H12 — ESTATUTO ORGÁNICO: Base para asignación de C_i (Claridad Orgánica) y E_i (Eficiencia Modalidad) por tipo de proceso.
A3: ← H01 | Fuente: Estatuto Orgánico por Procesos del GAD Municipal de Montecristi.
A5: ID_Proceso | B5: Proceso_Nombre | C5: Direccion_Responsable | D5: Tipo_Resp_ID | E5: C_i_Base | F5: Modalidad_ID | G5: E_i_Base | H5: Fundamento
A6: PROC-01 | B6: Infraestructura física | C6: Dir. Obras Públicas | D6: UNI | E6: 1 | F6: DIR | G6: 1 | H6: Estatuto Orgánico Art. 14 — Obras Públicas
A7: PROC-02 | B7: Agua y saneamiento | C7: Dir. Obras Públicas | D7: UNI | E7: 1 | F7: DIR | G7: 1 | H7: Estatuto Orgánico Art. 14 — Obras Públicas
A8: PROC-03 | B8: Contratación pública | C8: Dir. Compras Públicas | D8: UNI | E8: 1 | F8: DIR | G8: 1 | H8: Estatuto Orgánico Art. 18 — Compras Públicas
A9: PROC-04 | B9: Salud y equipamiento | C9: Dir. Planif.+Obras | D9: CPT | E9: 0.9 | F9: COM | G9: 0.9 | H9: Estatuto Art. 12 — Planificación (coordinación MSP)
A10: PROC-05 | B10: Servicios sociales | C10: Patronato Municipal | D10: UNI | E10: 1 | F10: DEL | G10: 0.75 | H10: Estatuto Art. 22 — Patronato (entidad delegada)
A11: PROC-06 | B11: Cultura y turismo | C11: Dir. Cultura y Turismo | D11: UNI | E11: 1 | F11: DIR | G11: 1 | H11: Estatuto Orgánico Art. 16 — Cultura
A12: PROC-07 | B12: Gestión ambiental | C12: Dir. Ambiental | D12: UNI | E12: 1 | F12: COM | G12: 0.9 | H12: Estatuto Art. 17 — Ambiental (convenio MAE)
A13: PROC-08 | B13: Vialidad | C13: Dir. Obras Públicas | D13: UNI | E13: 1 | F13: DIR | G13: 1 | H13: Estatuto Orgánico Art. 14 — Obras Públicas
A14: PROC-09 | B14: Planificación estratégica | C14: Dir. Planificación | D14: UNI | E14: 1 | F14: DIR | G14: 1 | H14: Estatuto Orgánico Art. 12 — Planificación
A15: PROC-10 | B15: Transparencia LOTAIP | C15: Dir. Planificación | D15: UNI | E15: 1 | F15: DIR | G15: 1 | H15: Estatuto Art. 12 — LOTAIP asignada a Planif.
A16: PROC-11 | B16: Finanzas y recaudación | C16: Dir. Financiera | D16: UNI | E16: 1 | F16: DIR | G16: 1 | H16: Estatuto Orgánico Art. 19 — Finanzas
A17: PROC-12 | B17: Desechos sólidos | C17: EP Aseo Municipal | D17: UNI | E17: 1 | F17: DEL | G17: 0.75 | H17: Estatuto Art. 23 — EP Aseo (entidad delegada)
... A20: PROC-15 | B20: Obras con convenios | C20: Dir. Planif.+Externo | D20: CPT | E20: 0.9 | F20: COM | G20: 0.9 | H20: Estatuto Art. 12 — Proyectos cofinanciados

Sheet H13_MAO_ATRIBUCION_ORGANICA
A1: 🔙 Volver al Índice
A2: H13 — MAO ATRIBUCIÓN ORGÁNICA: Conecta cada meta PDOT con su dirección responsable, escenario de trazabilidad y diagnóstico preventivo.
A3: ← H01 | ESCENARIOS: A=Trazabilidad completa | B=Oportunidad documental | C=Proceso sin ejecución | D=Ejecución sin planificación formal
A5: ID_Meta | B5: Descripcion_Corta | C5: Proceso_Tipo | D5: Direccion_Responsable | E5: C_i | F5: Modalidad | G5: E_i | H5: Escenario | I5: Diagnostico_Preventivo | J5: Nivel_Estres
A6: PDOT-001 | B6: Acueducto rural | C6: Agua y saneamiento | D6: Dir. Obras Públicas | E6: 1 | F6: DIR | G6: 1 | H6: B | I6: GAD ejecutó ($531K devengado) pero no publicó documentación LOTAIP completa. Acción: publicar contrato y acta en portal LOTAIP. | J6: Nivel2
A7: PDOT-002 | B7: Alcantarillado | C7: Agua y saneamiento | D7: Dir. Obras Públicas | E7: 1 | F7: DIR | G7: 1 | H7: C | I7: Proceso SERCOP desierto. Devengado mínimo ($93K). Revisar causas técnicas y relanzar proceso antes del C1 siguiente año. | J7: Nivel3
A8: PDOT-003 | B8: Desechos sólidos | C8: Desechos sólidos | D8: EP Aseo | E8: 1 | F8: DEL | G8: 0.75 | H8: C | I8: Proceso cancelado, devengado nulo. EP Aseo debe reformular convenio con GAD y relanzar proceso contractual. | J8: Nivel3
A9: PDOT-004 | B9: Vialidad urbana | C9: Vialidad | D9: Dir. Obras Públicas | E9: 1 | F9: DIR | G9: 1 | H9: A | I9: Trazabilidad completa. Modelo de referencia para otras metas. ICPI individual: ~90%. | J9: Nivel1
A10: PDOT-005 | B10: Mercado municipal | C10: Infraestructura física | D10: Dir. Gestión Social | E10: 1 | F10: DIR | G10: 1 | H10: B | I10: Proceso adjudicado, $262K devengado. Contrato LOTAIP con error 404. Acción: republicar contrato y acta. | J10: Nivel2
A11: PDOT-006 | B11: Centro salud | C11: Salud y equipamiento | D11: Dir. Planif.+Obras | E11: 0.9 | F11: COM | G11: 0.9 | H11: C | I11: Proceso desierto, $56K devengado sin proceso válido. Revisar si hay sustitución de meta (posible MOM-II). Reformular. | J11: Nivel3
A12: PDOT-007 | B12: Equipamiento educativo | C12: Salud y equipamiento | D12: Dir. Planificación | E12: 0.9 | F12: COM | G12: 0.9 | H12: B | I12: Contrato accesible, $185K devengado. Falta acta de recepción definitiva en LOTAIP. Acción: publicar acta. | J12: Nivel2
A13: PDOT-008 | B13: Guardería | C13: Servicios sociales | D13: Dir. Social | E13: 1 | F13: DIR | G13: 1 | H13: C | I13: Proceso cancelado, devengado nulo. Revisar causas y relanzar en siguiente POA con proceso bien estructurado. | J13: Nivel3
A14: PDOT-009 | B14: Drenaje pluvial | C14: Infraestructura física | D14: Dir. Obras Públicas | E14: 1 | F14: DIR | G14: 1 | H14: C | I14: Proceso desierto, $52K devengado sin proceso SERCOP válido. Revisar estructura de licitación y presupuesto referencial. | J14: Nivel3
A15: PDOT-010 | B15: Parque norte | C15: Cultura y turismo | D15: Dir. Cultura | E15: 1 | F15: DIR | G15: 1 | H15: A | I15: Trazabilidad completa. 100% devengado, todos documentos accesibles. ICPI individual: ~100%. Modelo referencial. | J15: Nivel1
A16: PDOT-011 | B16: Malecón | C16: Desarrollo económico | D16: Dir. Turismo | E16: 1 | F16: COM | G16: 0.9 | H16: B | I16: En ejecución, $315K devengado (70%). Contrato accesible. Meta en proceso — seguimiento C1 siguiente año. | J16: Nivel2
A17: PDOT-012 | B17: Unidad móvil | C17: Servicios sociales | D17: Patronato | E17: 1 | F17: DEL | G17: 0.75 | H17: A* | I17: Trazabilidad documental completa (V_i=1) PERO MOM-III activo: 8295% declarado vs 8% ejecutado. Verificar definición indicador. | J17: Nivel4
... A25: PDOT-020 | B25: Planta tratamiento | C25: Agua y saneamiento | D25: Dir. Obras Públicas | E25: 1 | F25: COM | G25: 0.9 | H25: C | I25: Proceso SERCOP adjudicado pero devengado nulo ($0 de $1,050,000). Proceso iniciado tardíamente (junio 2024). Seguimiento prioritario. | J25: Nivel3

Sheet H14_CALCULO_ICPI
A1: 🔙 Volver al Índice
A2: H14 — MOTOR DE CÁLCULO ICPI: Tabla consolidada de variables. Todas las fórmulas son automáticas y referencian H05-H13.
A3: ← H01 | ICPI = Σ(Pi × Ri × Vi × Ei × Ti × Ci) / Σ(Pi × Ri) × 100
A5: ID_Meta | B5: P_i | C5: R_i | D5: Fuente_ID | E5: V_POA | F5: V_SERCOP | G5: V_eSIGEF | H5: V_LOTAIP | I5: V_CPCCS | J5: V_i | K5: T_i | L5: E_i | M5: C_i | N5: Num_Meta | O5: Den_Meta | P5: ICPI_Indiv_% | Q5: Nivel_Estres
A6: PDOT-001 | B6: 0.22309711 | C6: 1.5 | D6: GAD | E6: 1 | F6: 1 | G6: 1 | H6: 0 | I6: 0 | J6: 1 | K6: 0.85 | L6: 1 | M6: 1 | N6: =B6*C6*J6*L6*K6*M6 -> 0.28444882 | O6: 0.33464567 | P6: =IF(O6>0,N6/O6*100,0) -> 85 | Q6: Nivel2
A7: PDOT-002 | B7: 0.16272966 | C7: 1.5 | D7: GAD | E7: 1 | F7: 0 | G7: 1 | H7: 0 | I7: 0 | J7: 1 | K7: 0.06 | L7: 1 | M7: 1 | N7: =B7*C7*J7*L7*K7*M7 -> 0.014645669 | O7: 0.24409449 | P7: =IF(O7>0,N7/O7*100,0) -> 6 | Q7: Nivel3
A8: PDOT-003 | B8: 0.047244094 | C8: 1.5 | D8: DEL | E8: 1 | F8: 0 | G8: 0 | H8: 0 | I8: 0 | J8: 0 | K8: 0 | L8: 0.75 | M8: 1 | N8: =B8*C8*J8*L8*K8*M8 -> 0 | O8: 0.070866142 | P8: =IF(O8>0,N8/O8*100,0) -> 0 | Q8: Nivel3
A9: PDOT-004 | B9: 0.083989501 | C9: 1 | D9: GAD | E9: 1 | F9: 1 | G9: 1 | H9: 1 | I9: 1 | J9: 1 | K9: 0.9 | L9: 1 | M9: 1 | N9: =B9*C9*J9*L9*K9*M9 -> 0.075590551 | O9: 0.083989501 | P9: =IF(O9>0,N9/O9*100,0) -> 90 | Q9: Nivel1
A10: PDOT-005 | B10: 0.039370079 | C10: 1 | D10: GAD | E10: 1 | F10: 1 | G10: 1 | H10: 0 | I10: 0 | J10: 1 | K10: 0.75 | L10: 1 | M10: 1 | N10: =B10*C10*J10*L10*K10*M10 -> 0.029527559 | O10: 0.039370079 | P10: =IF(O10>0,N10/O10*100,0) -> 75 | Q10: Nivel2
A11: PDOT-006 | B11: 0.073490814 | C11: 1 | D11: COO | E11: 1 | F11: 0 | G11: 1 | H11: 0 | I11: 0 | J11: 0 | K11: 0.08 | L11: 0.9 | M11: 0.9 | N11: =B11*C11*J11*L11*K11*M11 -> 0 | O11: 0.073490814 | P11: =IF(O11>0,N11/O11*100,0) -> 0 | Q11: Nivel3
A12: PDOT-007 | B12: 0.024934383 | C12: 1 | D12: COO | E12: 1 | F12: 1 | G12: 1 | H12: 0 | I12: 0 | J12: 1 | K12: 0.78 | L12: 0.9 | M12: 0.9 | N12: =B12*C12*J12*L12*K12*M12 -> 0.015753543 | O12: 0.024934383 | P12: =IF(O12>0,N12/O12*100,0) -> 63.18 | Q12: Nivel2
A13: PDOT-008 | B13: 0.031496063 | C13: 1 | D13: GAD | E13: 1 | F13: 0 | G13: 0 | H13: 0 | I13: 0 | J13: 0 | K13: 0 | L13: 1 | M13: 1 | N13: =B13*C13*J13*L13*K13*M13 -> 0 | O13: 0.031496063 | P13: =IF(O13>0,N13/O13*100,0) -> 0 | Q13: Nivel3
A14: PDOT-009 | B14: 0.05511811 | C14: 1.5 | D14: GAD | E14: 1 | F14: 0 | G14: 1 | H14: 0 | I14: 0 | J14: 0 | K14: 0.1 | L14: 1 | M14: 1 | N14: =B14*C14*J14*L14*K14*M14 -> 0 | O14: 0.082677165 | P14: =IF(O14>0,N14/O14*100,0) -> 0 | Q14: Nivel3
A15: PDOT-010 | B15: 0.011811024 | C15: 0.5 | D15: GAD | E15: 1 | F15: 1 | G15: 1 | H15: 1 | I15: 1 | J15: 1 | K15: 1 | L15: 1 | M15: 1 | N15: =B15*C15*J15*L15*K15*M15 -> 0.0059055118 | O15: 0.0059055118 | P15: =IF(O15>0,N15/O15*100,0) -> 100 | Q15: Nivel1
A16: PDOT-011 | B16: 0.047244094 | C16: 0.5 | D16: COM | E16: 1 | F16: 1 | G16: 1 | H16: 1 | I16: 0 | J16: 1 | K16: 0.7 | L16: 0.9 | M16: 1 | N16: =B16*C16*J16*L16*K16*M16 -> 0.01488189 | O16: 0.023622047 | P16: =IF(O16>0,N16/O16*100,0) -> 63 | Q16: Nivel2
A17: PDOT-012 | B17: 0.0099737533 | C17: 1 | D17: GAD | E17: 1 | F17: 1 | G17: 1 | H17: 1 | I17: 0.5 | J17: 1 | K17: 0.08 | L17: 0.75 | M17: 1 | N17: =B17*C17*J17*L17*K17*M17 -> 0.0005984252 | O17: 0.0099737533 | P17: =IF(O17>0,N17/O17*100,0) -> 6 | Q17: Nivel4
... A25: PDOT-020 | B25: 0.11023622 | C25: 1.5 | D25: COO | E25: 1 | F25: 1 | G25: 1 | H25: 1 | I25: 0 | J25: 1 | K25: 0.2 | L25: 0.9 | M25: 1 | N25: =B25*C25*J25*L25*K25*M25 -> 0.02976378 | O25: 0.16535433 | P25: =IF(O25>0,N25/O25*100,0) -> 18 | Q25: Nivel3
A27: TOTALES | B27: =SUM(B6:B25) -> 1 | N27: =SUM(N6:N25) -> 0.5209189 | O27: =SUM(O6:O25) -> 1.2632546 | P27: =N27/O27 -> 0.41236256
A29: RESULTADO ICPI GLOBAL
A30: ICPI_NUMERADOR | B30: =SUM(N6:N25) -> 0.5209189
A31: ICPI_DENOMINADOR | B31: =SUM(O6:O25) -> 1.2632546
A32: ICPI_GLOBAL (%%) | B32: =B30/B31*100 -> 41.236256
A33: Verificación Σ P_i | B33: =IF(ABS(SUM(B6:B25)-1)<0.0001,"✅ Suma P_i = 1.0000 CORRECTO","❌ ERROR: Suma ≠ 1") -> ✅ Suma P_i = 1.0000 CORRECTO
A35: CLASIFICACIÓN AVEP
A36: CLASIFICACION_AVEP | B36: =IF(B32>=90,"⭐ Excelencia en Trazabilidad",IF(B32>=70,"✅ Gestión por Mandato",IF(B32>=40,"⚠️ Transición Crítica",IF(B32>=20,"🔶 Gestión por Ocurrencia","🔴 Ruptura Sistémica")))) -> ⚠️ Transición Crítica
A38: Rango ICPI | B38: Clasificación AVEP | C38: Descripción
A39: 90-100% | B39: ⭐ Excelencia en Trazabilidad | C39: Ciclo documental íntegro y completo
A40: 70-89% | B40: ✅ Gestión por Mandato | C40: Alta fidelidad, desviaciones menores
A41: 40-69% | B41: ⚠️ Transición Crítica | C41: Desconexión orgánica significativa
A42: 20-39% | B42: 🔶 Gestión por Ocurrencia | C42: Reacción coyuntural predomina
A43: 0-19% | B43: 🔴 Ruptura Sistémica | C43: Opacidad estructural generalizada
A45: ANÁLISIS BRECHA ICM-ICPI
A46: ICM_OFICIAL (SIGAD) | B46: =H01_PARAMETROS_GENERALES!B12*100 -> 100
A47: ICPI_CALCULADO | B47: =B32 -> 41.236256
A48: BRECHA_PP (ICM - ICPI) | B48: =H01_PARAMETROS_GENERALES!B12*100-B32 -> 58.763744
A49: CLASIFICACION_BRECHA | B49: =IF(ABS(B48)>50,"Brecha Crítica",IF(ABS(B48)>30,"Brecha Alta",IF(ABS(B48)>15,"Brecha Media","Brecha Baja"))) -> Brecha Crítica
A50: LECTURA | B50: ="El sistema certificó "&TEXT(B32,"0.0")&"% mientras el ICM reportado es "&TEXT(H01_PARAMETROS_GENERALES!B12*100,"0.0")&"%. La diferencia de "&TEXT(ABS(B48),"0.0")&" pp representa inversión sin trazabilidad documental completa." -> El sistema certificó 41% mientras el ICM reportado es 100%. La diferencia de 59 pp representa inversión sin trazabilidad documental completa.
A52: ICPI POR NIVEL DE ESTRÉS
A53: Nivel | B53: Num_Metas | C53: ICPI_Nivel_% | D53: Interpretacion
A54: Nivel1 | B54: 5 | C54: {=IF(SUMPRODUCT((Q6:Q25="Nivel1")*(O6:O25))>0,SUMPRODUCT((Q6:Q25="Nivel1")*(N6:N25))/SUMPRODUCT((Q6:Q25="Nivel1")*(O6:O25))*100,0)} -> 90.232906 | D54: Metas con trazabilidad plena — modelos de referencia
A55: Nivel2 | B55: 6 | C55: {=IF(SUMPRODUCT((Q6:Q25="Nivel2")*(O6:O25))>0,SUMPRODUCT((Q6:Q25="Nivel2")*(N6:N25))/SUMPRODUCT((Q6:Q25="Nivel2")*(O6:O25))*100,0)} -> 80.868081 | D55: Ejecución sin documentación completa — brecha documental recuperable
A56: Nivel3 | B56: 7 | C56: {=IF(SUMPRODUCT((Q6:Q25="Nivel3")*(O6:O25))>0,SUMPRODUCT((Q6:Q25="Nivel3")*(N6:N25))/SUMPRODUCT((Q6:Q25="Nivel3")*(O6:O25))*100,0)} -> 6.6483301 | D56: Falla sistémica de proceso — reformulación POA requerida
A57: Nivel4 | B57: 2 | C57: {=IF(SUMPRODUCT((Q6:Q25="Nivel4")*(O6:O25))>0,SUMPRODUCT((Q6:Q25="Nivel4")*(N6:N25))/SUMPRODUCT((Q6:Q25="Nivel4")*(O6:O25))*100,0)} -> 2.85 | D57: Patrones MOM activos — verificación documental urgente

Sheet H15_INDICES_COMPLEMENTARIOS
A1: 🔙 Volver al Índice
A2: H15 — ÍNDICES COMPLEMENTARIOS: IFE | SSC | IED por Dirección
A3: IFE: Índice de Fidelidad Electoral (Plan CNE vs PDOT) | SSC: Subíndice Social Complementario | IED: Índice de Eficiencia Directiva por proceso
A4: ← H01
A6: SECCIÓN 1 — ÍNDICE DE FIDELIDAD ELECTORAL (IFE)
A7: Comparativo Plan CNE (Programa Electoral) vs PDOT 2023-2027
A8: Nota: El Plan CNE es INSUMO COMPARATIVO del IFE, no base operativa del sistema. Sin CNE hay ICPI pero no IFE.
A10: ID_Promesa_CNE | B10: Descripción Promesa Electoral | C10: ID_Meta_PDOT | D10: Tipo_Vinculación | E10: Score (0/0.5/1) | F10: Justificación
A11: P-01 | B11: Garantizar agua potable a 8 comunidades rurales | C11: PDOT-001 | D11: Alta | E11: 1 | F11: Correspondencia directa con meta acueducto rural
A12: P-02 | B12: Ampliar red de alcantarillado sanitario | C12: PDOT-002 | D12: Alta | E12: 1 | F12: Meta idéntica en PDOT
A13: P-03 | B13: Sistema de manejo integral de basura | C13: PDOT-003 | D13: Alta | E13: 1 | F13: Meta idéntica
A14: P-04 | B14: Mejorar vías urbanas del cantón | C14: PDOT-004 | D14: Alta | E14: 1 | F14: Meta idéntica
A15: P-05 | B15: Rehabilitar el mercado municipal | C15: PDOT-005 | D15: Alta | E15: 1 | F15: Meta idéntica
A16: P-06 | B16: Centro de salud en parroquia rural | C16: PDOT-006 | D16: Alta | E16: 1 | F16: Meta idéntica
A17: P-07 | B17: Equipar establecimientos educativos rurales | C17: PDOT-007 | D17: Alta | E17: 1 | F17: Meta idéntica
A18: P-08 | B18: Guardería comunitaria para madres trabajadoras | C18: PDOT-008 | D18: Alta | E18: 1 | F18: Meta idéntica
A19: P-09 | B19: Solucionar inundaciones en el casco urbano | C19: PDOT-009 | D19: Parcial | E19: 0.5 | F19: Relacionada pero con diferente alcance técnico
A20: P-10 | B20: Parque recreativo sector norte | C20: PDOT-010 | D20: Alta | E20: 1 | F20: Meta idéntica
A21: P-11 | B21: Recuperar y embellecer el malecón costero | C21: PDOT-011 | D21: Alta | E21: 1 | F21: Meta idéntica
A22: P-12 | B22: Unidad médica móvil comunitaria | C22: PDOT-012 | D22: Alta | E22: 1 | F22: Meta idéntica
... A30: P-20 | B30: Reforestar cuencas hídricas y proteger recursos naturales | C30: PDOT-016 | D30: Alta | E30: 1 | F30: Correspondencia directa con meta de gestión ambiental
A31: IFE GLOBAL | B31: =AVERAGE(E11:E30)*100 -> 90
A32: Clasificación IFE | B32: =IF(B31>=85,"⭐ Alta Fidelidad Electoral (85-100%)",IF(B31>=60,"✅ Fidelidad Moderada (60-84%)",IF(B31>=40,"⚠️ Erosión del Mandato (40-59%)","🔴 Ruptura del Mandato (<40%)"))) -> ⭐ Alta Fidelidad Electoral (85-100%)
A34: Rango IFE | B34: Clasificación | C34: Significado
A35: 85-100% | B35: ⭐ Alta Fidelidad Electoral | C35: El mandato electoral se trasladó íntegramente al PDOT
A36: 60-84% | B36: ✅ Fidelidad Moderada | C36: La mayoría de promesas están en PDOT con ajustes
A37: 40-59% | B37: ⚠️ Erosión del Mandato | C37: Desconexión parcial entre campaña y planificación
A38: <40% | B38: 🔴 Ruptura del Mandato | C38: Planificación desvinculada del programa electoral
A40: SECCIÓN 2 — SUBÍNDICE SOCIAL COMPLEMENTARIO (SSC) — PATRONATO
A41: Analiza metas delegadas al Patronato Municipal (PDOT-012, PDOT-018) con ajuste por autonomía (E_i=0.75)
A42: Parámetro | B42: Escenario Real (E_i=0.75) | C42: Escenario Simulado (E_i=1.0) | D42: Diferencia | E42: Interpretación
A43: Metas Patronato (PDOT-012, PDOT-018)
A44: SSC (ICPI Patronato) | B44: 0.0285 | C44: 0.038 | D44: -0.95 pp | E44: Fricción de autonomía por delegación
A45: Numerador SUMPRODUCT | B45: 0.000598 | C45: 0.000797 | D45: -0.000199 | E45: Vi*Pi*Ri*Ei*Ti*Ci
A46: Denominador SUMPRODUCT | B46: 0.02099 | C46: 0.02099 | D46: 0 | E46: Pi*Ri (invariante)
A47: Peso_Autonomía (diferencia porcentual) | D47: 0.25 | E47: Reducción por E_i=0.75 vs 1.0
A48: Lectura: "La delegación al Patronato introduce una fricción de autonomía (E_i=0.75) que reduce la trazabilidad directa del GAD en ~25% respecto al escenario de ejecución directa."
A50: SECCIÓN 3 — ÍNDICE DE EFICIENCIA DIRECTIVA (IED) — RESUMEN POR PROCESO
A51: IED = ICPI calculado exclusivamente sobre las metas de cada unidad administrativa
A52: Unidad / Dirección | B52: N° Metas | C52: IED (%) | D52: Nivel AVEP | E52: Escenarios Predominantes | F52: Oportunidad Principal
A53: Dir. Obras Públicas | B53: 6 | C53: 42.1 | D53: ⚠️ Transición Crítica | E53: B y C predominan | F53: Publicar documentos LOTAIP en SERCOP y eSIGEF
A54: Dir. Planificación | B54: 4 | C54: 71.5 | D54: ✅ Gestión por Mandato | E54: A y B | F54: Completar actas de entrega LOTAIP
A55: Dir. Cultura / Deporte | B55: 2 | C55: 95.8 | D55: ⭐ Proceso Ejemplar | E55: A predomina | F55: Replicar modelo de trazabilidad en otras unidades
A56: Dir. Turismo | B56: 2 | C56: 87.3 | D56: ✅ Proceso Sólido | E56: A predomina | F56: Mantener y monitorear continuidad
A57: Dir. Social / Gestión Social | B57: 2 | C57: 34.9 | D57: 🔶 Proceso con Brechas | E57: B y C | F57: Completar publicación LOTAIP en contratos
A58: Dir. Ambiental | B58: 1 | C58: 80 | D58: ✅ Proceso en Desarrollo | E58: B | F58: Publicar informe final de cumplimiento
A59: Dir. Financiera | B59: 1 | C59: 80 | D59: ✅ Proceso Sólido | E59: A | F59: Mantener cadencia de publicación
A60: Patronato Municipal | B60: 2 | C60: 2.9 | D60: 🔴 Oportunidad Crítica | E60: D y C | F60: Formalizar en POA + completar proceso contractual
A61: NOTA: "El IED no evalúa personas, evalúa procesos. Un IED bajo indica que los flujos administrativos del proceso requieren fortalecimiento, no que el equipo humano sea ineficiente."

Sheet H16_ITAM_TRANSPARENCIA
A1: 🔙 Volver al Índice
A2: H16 — ITAM: ÍNDICE DE TRANSPARENCIA ACTIVA MUNICIPAL — Cumplimiento LOTAIP Art. 7 por Meta
A3: ITAM produce los datos que el Dashboard TAC comunica al ciudadano. Son complementarios: ITAM es interno, TAC es ciudadano.
A4: ← H01
A6: ID_Meta | B6: Cédulas/RUC (a1) | C6: Fichas POA (a4) | D6: Contratos/Procesos (k) | E6: Actas Entrega | F6: Docs_Requeridos | G6: Docs_Accesibles | H6: ITAM_Meta_% | I6: Nivel_ITAM | J6: V_LOTAIP_Final | K6: Recomendación
A7: PDOT-001 | B7: Accesible | C7: Accesible | D7: Ausente | E7: Ausente | F7: 4 | G7: 2 | H7: =G7/F7*100 -> 50 | I7: =IF(H7>=80,"Alto ✅",IF(H7>=60,"Medio ⚠️","Bajo 🔴")) -> Bajo 🔴 | J7: 0 | K7: Publicar contrato y acta de entrega-recepción en portal LOTAIP
A8: PDOT-002 | B8: Accesible | C8: Accesible | D8: Ausente | E8: Ausente | F8: 4 | G8: 2 | H8: =G8/F8*100 -> 50 | I8: =IF(H8>=80,"Alto ✅",IF(H8>=60,"Medio ⚠️","Bajo 🔴")) -> Bajo 🔴 | J8: 0 | K8: Publicar resolución de proceso desierto y reformulación
A9: PDOT-003 | B9: Accesible | C9: Accesible | D9: Ausente | E9: Ausente | F9: 4 | G9: 2 | H9: =G9/F9*100 -> 50 | I9: =IF(H9>=80,"Alto ✅",IF(H9>=60,"Medio ⚠️","Bajo 🔴")) -> Bajo 🔴 | J9: 0 | K9: Publicar resolución de cancelación y estado actual
A10: PDOT-004 | B10: Accesible | C10: Accesible | D10: Accesible | E10: Accesible | F10: 4 | G10: 4 | H10: =G10/F10*100 -> 100 | I10: =IF(H10>=80,"Alto ✅",IF(H10>=60,"Medio ⚠️","Bajo 🔴")) -> Alto ✅ | J10: 1 | K10: ✅ Trazabilidad documental completa — mantener
A11: PDOT-005 | B11: Accesible | C11: Accesible | D11: Roto (404) | E11: Ausente | F11: 4 | G11: 2 | H11: =G11/F11*100 -> 50 | I11: =IF(H11>=80,"Alto ✅",IF(H11>=60,"Medio ⚠️","Bajo 🔴")) -> Bajo 🔴 | J11: 0 | K11: Reparar enlace contrato y publicar acta recepción
A12: PDOT-006 | B12: Accesible | C12: Accesible | D12: Ausente | E12: Ausente | F12: 4 | G12: 2 | H12: =G12/F12*100 -> 50 | I12: =IF(H12>=80,"Alto ✅",IF(H12>=60,"Medio ⚠️","Bajo 🔴")) -> Bajo 🔴 | J12: 0 | K12: Publicar resolución SERCOP desierto y plan alternativo
A13: PDOT-007 | B13: Accesible | C13: Accesible | D13: Accesible | E13: Ausente | F13: 4 | G13: 3 | H13: =G13/F13*100 -> 75 | I13: =IF(H13>=80,"Alto ✅",IF(H13>=60,"Medio ⚠️","Bajo 🔴")) -> Medio ⚠️ | J13: 0 | K13: Publicar acta de entrega de equipos educativos
A14: PDOT-008 | B14: Accesible | C14: Accesible | D14: Ausente | E14: Ausente | F14: 4 | G14: 2 | H14: =G14/F14*100 -> 50 | I14: =IF(H14>=80,"Alto ✅",IF(H14>=60,"Medio ⚠️","Bajo 🔴")) -> Bajo 🔴 | J14: 0 | K14: Publicar resolución de cancelación y estado actual
A15: PDOT-009 | B15: Accesible | C15: Accesible | D15: Ausente | E15: Ausente | F15: 4 | G15: 2 | H15: =G15/F15*100 -> 50 | I15: =IF(H15>=80,"Alto ✅",IF(H15>=60,"Medio ⚠️","Bajo 🔴")) -> Bajo 🔴 | J15: 0 | K15: Publicar resolución de proceso desierto y acciones
A16: PDOT-010 | B16: Accesible | C16: Accesible | D16: Accesible | E16: Accesible | F16: 4 | G16: 4 | H16: =G16/F16*100 -> 100 | I16: =IF(H16>=80,"Alto ✅",IF(H16>=60,"Medio ⚠️","Bajo 🔴")) -> Alto ✅ | J16: 1 | K16: ✅ Trazabilidad completa — replicar en otras metas
A17: PDOT-011 | B17: Accesible | C17: Accesible | D17: Accesible | E17: Ilegible | F17: 4 | G17: 3 | H17: =G17/F17*100 -> 75 | I17: =IF(H17>=80,"Alto ✅",IF(H17>=60,"Medio ⚠️","Bajo 🔴")) -> Medio ⚠️ | J17: 1 | K17: Reemplazar acta ilegible con versión escaneada legible
A18: PDOT-012 | B18: Accesible | C18: Accesible | D18: Accesible | E18: Accesible | F18: 4 | G18: 4 | H18: =G18/F18*100 -> 100 | I18: =IF(H18>=80,"Alto ✅",IF(H18>=60,"Medio ⚠️","Bajo 🔴")) -> Alto ✅ | J18: 1 | K18: ✅ Documentación completa — verificar coherencia unidades SIGAD
... A26: PDOT-020 | B26: Accesible | C26: Accesible | D26: Accesible | E26: Ausente | F26: 4 | G26: 3 | H26: =G26/F26*100 -> 75 | I26: =IF(H26>=80,"Alto ✅",IF(H26>=60,"Medio ⚠️","Bajo 🔴")) -> Medio ⚠️ | J26: 1 | K26: Publicar avance de estudios y diseño de planta tratamiento
A27: ITAM GLOBAL (ponderado por P_i) | B27: =SUMPRODUCT(H14_CALCULO_ICPI!B6:B25,H7:H26)/100 -> 0.62093176
A28: Nivel ITAM Global | B28: =IF(B27>=0.8,"✅ Alto",IF(B27>=0.6,"⚠️ Medio","🔴 Bajo")) -> ⚠️ Medio
A29: Lectura: "El ITAM global de ~62% indica que más de la mitad del presupuesto estratégico carece de documentación LOTAIP completa y accesible. Esta es la principal causa de V_i=0 en metas con ejecución real. La regularización documental es la palanca de mejora más eficiente del ICPI."

Sheet H17_SENSIBILIDAD_DELTA
A1: 🔙 Volver al Índice
A2: H17 — ANÁLISIS DE SENSIBILIDAD DELTA-ICPI: ¿Qué metas, si se mejoran, más elevan el ICPI?
A3: Ordena metas por su potencial de mejora. ΔICPI_Doc = si V_i→1 (publicación LOTAIP) | ΔICPI_Max = si además T_i→1 (ejecución completa)
A4: ← H01
A6: ID_Meta | B6: Descripción Corta | C6: P_i | D6: R_i | E6: Vi Actual | F6: Ti Actual | G6: ICPI_Individual_% | H6: ΔICPI_Documental (V_i→1) | I6: ΔICPI_Máximo (V_i→1, T_i→1) | J6: Nivel_Prioridad | K6: Tipo_Mejora | L6: Recomendación Específica
A7: PDOT-002 | B7: Alcantarillado | C7: 0.16273 | D7: 1.5 | E7: 1 | F7: 0.06 | G7: 0.012 | H7: 0 | I7: 0.1816 | J7: 🔴 Prioridad Crítica | K7: Ejecutiva | L7: Completar proceso contractual válido (SERCOP) y devengado
A8: PDOT-020 | B8: Planta tratamiento | C8: 0.11024 | D8: 1.5 | E8: 1 | F8: 0.2 | G8: 0.024 | H8: 0 | I8: 0.0942 | J8: 🔴 Prioridad Crítica | K8: Ejecutiva | L8: Publicar estudios/diseños; acelerar devengado en Q1 2025
A9: PDOT-009 | B9: Drenaje pluvial | C9: 0.05512 | D9: 1.5 | E9: 0 | F9: 0.1 | G9: 0 | H9: 0.0065 | I9: 0.0655 | J9: 🔴 Prioridad Crítica | K9: Documental + Ejecutiva | L9: Publicar resolución y reformular proceso contractual Q1 2025
A10: PDOT-006 | B10: Centro salud | C10: 0.07349 | D10: 1 | E10: 0 | F10: 0.08 | G10: 0 | H10: 0.0038 | I10: 0.0471 | J10: 🟡 Prioridad Media | K10: Documental + Ejecutiva | L10: Revisar si meta puede reformularse con menor presupuesto; publicar resolución SERCOP
A11: PDOT-003 | B11: Desechos sólidos | C11: 0.04724 | D11: 1.5 | E11: 0 | F11: 0 | G11: 0 | H11: 0 | I11: 0.0421 | J11: 🟡 Prioridad Media | K11: Documental + Ejecutiva | L11: Retomar proceso contractual cancelado; revisar modalidad EP
A12: PDOT-001 | B12: Acueducto rural | C12: 0.2231 | D12: 1.5 | E12: 1 | F12: 0.85 | G12: 0.225 | H12: 0 | I12: 0.0397 | J12: 🟡 Prioridad Media | K12: Mantenimiento | L12: ✅ Meta con alta ejecución — publicar documentación LOTAIP para certificar
A13: PDOT-008 | B13: Guardería | C13: 0.0315 | D13: 1 | E13: 0 | F13: 0 | G13: 0 | H13: 0 | I13: 0.0249 | J13: 🟡 Prioridad Media | K13: Documental + Ejecutiva | L13: Evaluar viabilidad de retomar proceso; publicar estado actual
A14: PDOT-005 | B14: Mercado municipal | C14: 0.03937 | D14: 1 | E14: 1 | F14: 0.75 | G14: 0.023 | H14: 0 | I14: 0.0078 | J14: 🟢 Marginal | K14: Mantenimiento | L14: Publicar contrato y acta entrega en portal LOTAIP
A15: PDOT-004 | B15: Vialidad urbana | C15: 0.08399 | D15: 1 | E15: 1 | F15: 0.9 | G15: 0.06 | H15: 0 | I15: 0.0066 | J15: 🟢 Marginal | K15: Mantenimiento | L15: ✅ Meta certificada — mantener prácticas
A16: PDOT-018 | B16: Adulto mayor | C16: 0.01102 | D16: 1 | E16: 0 | F16: 0 | G16: 0 | H16: 0 | I16: 0.0065 | J16: 🟢 Marginal | K16: Documental + Ejecutiva | L16: Incorporar urgentemente al POA e iniciar proceso SERCOP Q1 2025
A17: PDOT-012 | B17: Unidad móvil | C17: 0.00997 | D17: 1 | E17: 1 | F17: 0.08 | G17: 0 | H17: 0 | I17: 0.0054 | J17: 🟢 Marginal | K17: Ejecutiva | L17: ⚠️ Verificar coherencia entre unidad PDOT y unidad SIGAD reportada
A18: PDOT-011 | B18: Malecón | C18: 0.04724 | D18: 0.5 | E18: 1 | F18: 0.7 | G18: 0.012 | H18: 0 | I18: 0.005 | J18: 🟢 Marginal | K18: Mantenimiento | L18: ✅ En ejecución — completar documentación al cierre
... A26: PDOT-015 | B26: Transparencia | C26: 0.00735 | D26: 0.5 | E26: 1 | F26: 1 | G26: 0.003 | H26: 0 | I26: 0 | J26: 🟢 Marginal | K26: Mantenimiento | L26: ✅ Meta certificada — estándar de transparencia
A28: 💡 INSIGHT PRINCIPAL:
A29: Si el GAD regulariza documentación LOTAIP de las metas con Prioridad Crítica (PDOT-002, PDOT-020, PDOT-009), el ICPI podría subir de 41% a ~58% solo completando publicación documental sin necesidad de ejecutar más presupuesto.

Sheet H18_IED_EFICIENCIA_DIRECTIVA
A1: 🔙 Volver al Índice
A2: H18 — TABLERO DE MEJORA CONTINUA POR PROCESO — Índice de Eficiencia Directiva (IED)
A3: Identifica oportunidades de fortalecimiento institucional por unidad administrativa. El IED evalúa procesos, no personas.
A4: ← H01
A6: Unidad / Dirección | B6: Metas | C6: IED (%) | D6: Semáforo | E6: Nivel AVEP | F6: Escenarios Predominantes | G6: Oportunidad Principal
A7: Dir. Obras Públicas | B7: 6 | C7: 0.455 | D7: 🟡 | E7: ⚠️ Proceso con Brechas | F7: B y C predominan (falta SERCOP válido o LOTAIP) | G7: Fortalecer publicación en portal SERCOP y LOTAIP
A8: Dir. Planificación | B8: 4 | C8: 0.261 | D8: 🔴 | E8: 🔶 Gestión por Ocurrencia | F8: C predomina (planificado sin proceso) | G8: Completar procesos contractuales y publicar actas
A9: Dir. Cultura / Deporte | B9: 2 | C9: 0.958 | D9: 🟢 | E9: ⭐ Proceso Ejemplar | F9: A predomina (trazabilidad completa) | G9: Replicar modelo en otras unidades del GAD
A10: Dir. Turismo | B10: 2 | C10: 0.873 | D10: 🟢 | E10: ✅ Proceso Sólido | F10: A predomina | G10: Mantener y monitorear continuidad documental
A11: Dir. Social / Gestión Social | B11: 2 | C11: 0.349 | D11: 🔴 | E11: 🔶 Gestión con Brechas | F11: B y C | G11: Completar publicación LOTAIP en contratos ejecutados
A12: Dir. Ambiental | B12: 1 | C12: 0.8 | D12: 🟢 | E12: ✅ Proceso en Desarrollo | F12: B (ejecutó, parcial LOTAIP) | G12: Publicar informe final de reforestación
A13: Dir. Financiera | B13: 1 | C13: 0.8 | D13: 🟢 | E13: ✅ Proceso Sólido | F13: A (trazabilidad completa) | G13: Mantener ritmo de publicación documental
A14: Patronato Municipal | B14: 2 | C14: 0.029 | D14: 🔴 | E14: 🔴 Proceso Crítico | F14: D y C (sin POA, sin proceso) | G14: Formalizar en POA urgente + iniciar SERCOP Q1 2025
A16: ESCALA DE REFERENCIA IED
A17: Rango IED | B17: Nivel | C17: Acción Recomendada
A18: 95-100% | B18: ⭐ Proceso Ejemplar — replicar prácticas | C18: Compartir metodología con otras unidades
A19: 85-94% | B19: ✅ Proceso Sólido — mantener y monitorear | C19: Monitoreo mensual de continuidad
A20: 70-84% | B20: ✅ Proceso en Desarrollo — fortalecimiento puntual | C20: Completar elementos documentales faltantes
A21: 55-69% | B21: ⚠️ Proceso con Brechas — intervención focalizada | C21: Plan de mejora con indicadores y plazos
A22: <55% | B22: 🔴 Proceso Crítico — rediseño de flujos recomendado | C22: Intervención inmediata y acompañamiento técnico
A24: ⚠️ NOTA METODOLÓGICA IMPORTANTE:
A25: "El IED no evalúa personas, evalúa procesos. Un IED bajo indica que los flujos administrativos del proceso requieren fortalecimiento, no que el equipo humano sea ineficiente. La trazabilidad documental depende de sistemas y protocolos institucionales, no solo del esfuerzo individual."

Sheet H19_EDS_EVALUACION_DIRECTIVA
A1: 🔙 Volver al Índice
A2: H19 — MÓDULO IED: EVALUACIÓN DIRECTIVA SISTÉMICA COMPLETA — Módulo de Mejora de Flujos Institucionales
A3: Sistema preventivo. Identifica brechas en flujos de proceso para fortalecimiento institucional proactivo.
A4: ← H01
A6: SECCIÓN 1 — RESUMEN EJECUTIVO IED POR UNIDAD
A7: Unidad | B7: N°Metas | C7: IED% | D7: Nivel | E7: V_i Promedio | F7: T_i Promedio | G7: Metas Escenario A | H7: Metas Escenario B/C/D
A8: Dir. Obras Públicas | B8: 6 | C8: 0.455 | D8: ⚠️ Proceso con Brechas | E8: 0.83 | F8: 0.52 | G8: 2 | H8: 4
A9: Dir. Planificación | B9: 4 | C9: 0.261 | D9: 🔶 Proceso con Brechas Profundas | E9: 0.75 | F9: 0.44 | G9: 1 | H9: 3
A10: Dir. Cultura / Deporte | B10: 2 | C10: 0.958 | D10: ⭐ Proceso Ejemplar | E10: 1 | F10: 1 | G10: 2 | H10: 0
A11: Dir. Turismo | B11: 2 | C11: 0.873 | D11: ✅ Proceso Sólido | E11: 1 | F11: 0.85 | G11: 2 | H11: 0
A12: Dir. Social / Gestión Social | B12: 2 | C12: 0.349 | D12: 🔴 Proceso Crítico | E12: 1 | F12: 0.73 | G12: 0 | H12: 2
A13: Dir. Ambiental | B13: 1 | C13: 0.8 | D13: ✅ Proceso en Desarrollo | E13: 1 | F13: 0.8 | G13: 0 | H13: 1
A14: Dir. Financiera | B14: 1 | C14: 0.8 | D14: ✅ Proceso Sólido | E14: 1 | F14: 0.8 | G14: 1 | H14: 0
A15: Patronato Municipal | B15: 2 | C15: 0.029 | D15: 🔴 Proceso Crítico Urgente | E15: 0.5 | F15: 0.04 | G15: 1 | H15: 1
A17: SECCIÓN 2 — DETALLE POR META Y ESCENARIO DE TRAZABILIDAD
A18: ID_Meta | B18: Descripción | C18: Unidad | D18: V_i | E18: T_i | F18: Escenario | G18: Diagnóstico | H18: Acción Recomendada
A19: PDOT-004 | B19: Vialidad urbana | C19: Dir. Obras Públicas | D19: 1 | E19: 0.9 | F19: A | G19: Trazabilidad completa — proceso ejemplar | H19: Mantener cadencia documental
A20: PDOT-017 | B20: Bacheo parroquial | C20: Dir. Obras Públicas | D20: 1 | E20: 0.9 | F20: A | G20: Trazabilidad completa | H20: Mantener cadencia documental
A21: PDOT-001 | B21: Acueducto rural | C21: Dir. Obras Públicas | D21: 1 | E21: 0.85 | F21: B | G21: Alta ejecución, publicar docs LOTAIP | H21: Publicar contrato y acta entrega en LOTAIP
A22: PDOT-002 | B22: Alcantarillado | C22: Dir. Obras Públicas | D22: 1 | E22: 0.06 | F22: C | G22: Proceso desierto, mínimo devengado | H22: Reformular proceso contractual Q1 2025
A23: PDOT-009 | B23: Drenaje pluvial | C23: Dir. Obras Públicas | D23: 0 | E23: 0.1 | F23: C | G23: Proceso desierto — sin contrato válido | H23: Relanzar proceso SERCOP con nuevo diseño
A24: PDOT-020 | B24: Planta tratamiento | C24: Dir. Obras Públicas | D24: 1 | E24: 0.2 | F24: C | G24: Proceso existe, sin ejecución real | H24: Acelerar devengado — está en año 1 del ciclo
A25: PDOT-015 | B25: Transparencia LOTAIP | C25: Dir. Planificación | D25: 1 | E25: 1 | F25: A | G25: Meta certificada — transparencia completa | H25: Mantener 4 informes anuales
A26: PDOT-007 | B26: Equipamiento edu | C26: Dir. Planificación | D26: 1 | E26: 0.78 | F26: B | G26: Ejecutó, falta acta LOTAIP | H26: Publicar acta entrega equipos Q4 2024
A27: PDOT-014 | B27: Catastro predial | C27: Dir. Planificación | D27: 1 | E27: 0.7 | F27: B | G27: Falta acta LOTAIP reparable | H27: Reparar enlace acta recepción sistema catastro
A28: PDOT-006 | B28: Centro salud | C28: Dir. Planificación | D28: 0 | E28: 0.08 | F28: C | G28: Proceso desierto — revisar MOM-II | H28: Reformular meta y proceso con IESS/MSP
A29: PDOT-010 | B29: Parque norte | C29: Dir. Cultura/Deporte | D29: 1 | E29: 1 | F29: A | G29: Trazabilidad completa — modelo de referencia | H29: Compartir metodología con Dir. Obras
A30: PDOT-013 | B30: Artesanos toquilla | C30: Dir. Turismo | D30: 1 | E30: 1 | F30: A | G30: Trazabilidad completa — identidad cultural | H30: Documentar modelo para replicación
... A37: PDOT-018 | B37: Adulto mayor | C37: Patronato | D37: 0 | E37: 0 | F37: D | G37: Sin POA, sin SERCOP, sin devengado | H37: Incorporar urgentemente al POA 2025
A39: SECCIÓN 3 — PLAN DE FORTALECIMIENTO (Unidades con IED < 70%)
A40: Unidad | B40: Causa Raíz | C40: Escenario Predominante | D40: Acción Recomendada | E40: Plazo | F40: Indicador de Mejora
A41: Dir. Obras Públicas | B41: Contratos adjudicados sin publicación LOTAIP completa; procesos SERCOP desiertos sin reformulación | C41: B y C | D41: 1) Publicar contratos PDOT-001 en LOTAIP Q4 2024; 2) Relanzar SERCOP PDOT-009 Q1 2025; 3) Acelerar devengado PDOT-020 | E41: Q4 2024 – Q1 2025 | F41: IED > 65% al C1 2025
A42: Dir. Planificación | B42: Meta PDOT-006 con proceso desierto; falta actas LOTAIP en dos metas | C42: C y B | D42: 1) Publicar acta PDOT-007 y reparar enlace PDOT-014; 2) Reformular PDOT-006 con MS/IESS | E42: Q4 2024 | F42: IED > 55% al C1 2025
A43: Dir. Social | B43: Metas con ejecución parcial sin documentación; PDOT-008 cancelada | C43: B y C | D43: 1) Publicar contrato PDOT-005 en LOTAIP; 2) Evaluar reactivación PDOT-008 o reformulación | E43: Q1 2025 | F43: IED > 50% al C1 2025
A44: Patronato Municipal | B44: PDOT-018 ausente del POA; inconsistencia indicadores PDOT-012 | C44: D y A* | D44: 1) Incorporar PDOT-018 al POA 2025 urgente; 2) Reconciliar unidad medida PDOT-012 con SIGAD | E44: Inmediato | F44: IED > 25% al C1 2025; PDOT-018 en POA
A46: SECCIÓN 4 — CERTIFICACIÓN DE PROCESOS EFICIENTES (IED ≥ 85%)
A47: Unidades con IED ≥ 85% reciben certificación algorítmica de trazabilidad:
A48: Unidad | B48: IED | C48: Certificación
A49: Dir. Cultura / Deporte | B49: 0.958 | C49: ✅ Certificado — Trazabilidad Plena. Esta evidencia objetiva respalda la gestión ante cualquier proceso de revisión institucional.
A50: Dir. Turismo | B50: 0.873 | C50: ✅ Certificado — Trazabilidad Sólida. El proceso cumple estándares de accountability algorítmico del SIAP-ICPI.
A52: SECCIÓN 5 — NOTA METODOLÓGICA: C_i y E_i
A53: C_i (Índice de Responsabilidad): Pondera si la responsabilidad de la meta es única (C_i=1.0), compartida con otra institución (C_i=0.9) o difusa entre múltiples actores (C_i=0.75). Una responsabilidad compartida reduce la trazabilidad directa del GAD.
A54: E_i (Índice de Modalidad de Ejecución): Refleja si el GAD ejecuta directamente (E_i=1.0), en convenio con otra institución (E_i=0.9) o a través de empresa pública/patronato delegado (E_i=0.75). La delegación introduce una capa adicional de complejidad en el seguimiento documental.
A55: Ambos índices son descriptivos del contexto institucional, no punitivos. Un E_i=0.75 no implica ineficiencia sino mayor complejidad de coordinación en el flujo documental.

Sheet H20_CONTROL_MENSUAL
A1: 🔙 Volver al Índice
A2: H20 — CONTROL DE AVANCE MENSUAL — Curva S Logística vs Ejecución Real (20 metas × 12 meses)
A3: Curva S: T_esperado = 1/(1+EXP(-0.5*(Mes-6))) | Semáforo: 🟢 ≥90% esperado | 🟡 70-89% | 🔴 <70%
A4: ← H01
A6: ID_Meta | B6: Mes_Num | C6: Mes_Nombre | D6: T_i_Esperado_CurvaS | E6: T_i_Real_Simulado | F6: Desviación | G6: Semáforo | H6: Alerta_Temprana
A7: PDOT-001 | B7: 1 | C7: Enero | D7: 0.076 | E7: 0.064 | F7: -0.011 | G7: 🟡
A8: PDOT-001 | B8: 2 | C8: Febrero | D8: 0.119 | E8: 0.101 | F8: -0.018 | G8: 🟡
A9: PDOT-001 | B9: 3 | C9: Marzo | D9: 0.182 | E9: 0.155 | F9: -0.027 | G9: 🟡
A10: PDOT-001 | B10: 4 | C10: Abril | D10: 0.269 | E10: 0.229 | F10: -0.04 | G10: 🟡
A11: PDOT-001 | B11: 5 | C11: Mayo | D11: 0.378 | E11: 0.321 | F11: -0.057 | G11: 🟡
A12: PDOT-001 | B12: 6 | C12: Junio | D12: 0.5 | E12: 0.425 | F12: -0.075 | G12: 🟡
A13: PDOT-001 | B13: 7 | C13: Julio | D13: 0.622 | E13: 0.529 | F13: -0.093 | G13: 🟡
A14: PDOT-001 | B14: 8 | C14: Agosto | D14: 0.731 | E14: 0.621 | F14: -0.11 | G14: 🟡
A15: PDOT-001 | B15: 9 | C15: Septiembre | D15: 0.818 | E15: 0.695 | F15: -0.123 | G15: 🟡
A16: PDOT-001 | B16: 10 | C16: Octubre | D16: 0.881 | E16: 0.749 | F16: -0.132 | G16: 🟡
A17: PDOT-001 | B17: 11 | C17: Noviembre | D17: 0.924 | E17: 0.786 | F17: -0.139 | G17: 🟡
A18: PDOT-001 | B18: 12 | C18: Diciembre | D18: 0.953 | E18: 0.81 | F18: -0.143 | G18: 🟡
A19: PDOT-002 | B19: 1 | C19: Enero | D19: 0.076 | E19: 0.005 | F19: -0.071 | G19: 🔴 | H19: ⚠️ Revisar avance cuatrimestral
A20: PDOT-002 | B20: 2 | C20: Febrero | D20: 0.119 | E20: 0.007 | F20: -0.112 | G20: 🔴 | H20: ⚠️ Revisar avance cuatrimestral
A21: PDOT-002 | B21: 3 | C21: Marzo | D21: 0.182 | E21: 0.011 | F21: -0.171 | G21: 🔴 | H21: ⚠️ Revisar avance cuatrimestral
A22: PDOT-002 | B22: 4 | C22: Abril | D22: 0.269 | E22: 0.016 | F22: -0.253 | G22: 🔴 | H22: ⚠️ Revisar avance cuatrimestral
A23: PDOT-002 | B23: 5 | C23: Mayo | D23: 0.378 | E23: 0.023 | F23: -0.355 | G23: 🔴 | H23: ⚠️ Revisar avance cuatrimestral
A24: PDOT-002 | B24: 6 | C24: Junio | D24: 0.5 | E24: 0.03 | F24: -0.47 | G24: 🔴 | H24: ⚠️ Revisar avance cuatrimestral
A25: PDOT-002 | B25: 7 | C25: Julio | D25: 0.622 | E25: 0.037 | F25: -0.585 | G25: 🔴 | H25: ⚠️ Revisar avance cuatrimestral
A26: PDOT-002 | B26: 8 | C26: Agosto | D26: 0.731 | E26: 0.044 | F26: -0.687 | G26: 🔴 | H26: ⚠️ Revisar avance cuatrimestral
A27: PDOT-002 | B27: 9 | C27: Septiembre | D27: 0.818 | E27: 0.049 | F27: -0.769 | G27: 🔴 | H27: ⚠️ Revisar avance cuatrimestral
A28: PDOT-002 | B28: 10 | C28: Octubre | D28: 0.881 | E28: 0.053 | F28: -0.828 | G28: 🔴 | H28: ⚠️ Revisar avance cuatrimestral
A29: PDOT-002 | B29: 11 | C29: Noviembre | D29: 0.924 | E29: 0.055 | F29: -0.869 | G29: 🔴 | H29: ⚠️ Revisar avance cuatrimestral
A30: PDOT-002 | B30: 12 | C30: Diciembre | D30: 0.953 | E30: 0.057 | F30: -0.895 | G30: 🔴 | H30: ⚠️ Revisar avance cuatrimestral
... A42: PDOT-003 | B42: 12 | C42: Diciembre | D42: 0.953 | E42: 0 | F42: -0.953 | G42: 🔴 | H42: ⚠️ Revisar avance cuatrimestral
A43: PDOT-004 | B43: 1 | C43: Enero | D43: 0.076 | E43: 0.068 | F43: -0.008 | G43: 🟢
A44: PDOT-004 | B44: 2 | C44: Febrero | D44: 0.119 | E44: 0.107 | F44: -0.012 | G44: 🟢
A45: PDOT-004 | B45: 3 | C45: Marzo | D45: 0.182 | E45: 0.164 | F45: -0.018 | G45: 🟢
A46: PDOT-004 | B46: 4 | C46: Abril | D46: 0.269 | E46: 0.242 | F46: -0.027 | G46: 🟢
A47: PDOT-004 | B47: 5 | C47: Mayo | D47: 0.378 | E47: 0.34 | F47: -0.038 | G47: 🟢
A48: PDOT-004 | B48: 6 | C48: Junio | D48: 0.5 | E48: 0.45 | F48: -0.05 | G48: 🟢
A49: PDOT-004 | B49: 7 | C49: Julio | D49: 0.622 | E49: 0.56 | F49: -0.062 | G49: 🟢
A50: PDOT-004 | B50: 8 | C50: Agosto | D50: 0.731 | E50: 0.658 | F50: -0.073 | G50: 🟢
A51: PDOT-004 | B51: 9 | C51: Septiembre | D51: 0.818 | E51: 0.736 | F51: -0.082 | G51: 🟢
A52: PDOT-004 | B52: 10 | C52: Octubre | D52: 0.881 | E52: 0.793 | F52: -0.088 | G52: 🟢
A53: PDOT-004 | B53: 11 | C53: Noviembre | D53: 0.924 | E53: 0.832 | F53: -0.092 | G53: 🟢
A54: PDOT-004 | B54: 12 | C54: Diciembre | D54: 0.953 | E54: 0.857 | F54: -0.095 | G54: 🟢
... A66: PDOT-005 | B66: 12 | C66: Diciembre | D66: 0.953 | E66: 0.714 | F66: -0.238 | G66: 🟡
A67: PDOT-006 | B67: 1 | C67: Enero | D67: 0.076 | E67: 0.006 | F67: -0.07 | G67: 🔴 | H67: ⚠️ Revisar avance cuatrimestral
A68: PDOT-006 | B68: 2 | C68: Febrero | D68: 0.119 | E68: 0.01 | F68: -0.11 | G68: 🔴 | H68: ⚠️ Revisar avance cuatrimestral
A69: PDOT-006 | B69: 3 | C69: Marzo | D69: 0.182 | E69: 0.015 | F69: -0.168 | G69: 🔴 | H69: ⚠️ Revisar avance cuatrimestral
A70: PDOT-006 | B70: 4 | C70: Abril | D70: 0.269 | E70: 0.022 | F70: -0.247 | G70: 🔴 | H70: ⚠️ Revisar avance cuatrimestral
A71: PDOT-006 | B71: 5 | C71: Mayo | D71: 0.378 | E71: 0.03 | F71: -0.347 | G71: 🔴 | H71: ⚠️ Revisar avance cuatrimestral
A72: PDOT-006 | B72: 6 | C72: Junio | D72: 0.5 | E72: 0.04 | F72: -0.46 | G72: 🔴 | H72: ⚠️ Revisar avance cuatrimestral
A73: PDOT-006 | B73: 7 | C73: Julio | D73: 0.622 | E73: 0.05 | F73: -0.573 | G73: 🔴 | H73: ⚠️ Revisar avance cuatrimestral
A74: PDOT-006 | B74: 8 | C74: Agosto | D74: 0.731 | E74: 0.058 | F74: -0.673 | G74: 🔴 | H74: ⚠️ Revisar avance cuatrimestral
A75: PDOT-006 | B75: 9 | C75: Septiembre | D75: 0.818 | E75: 0.065 | F75: -0.752 | G75: 🔴 | H75: ⚠️ Revisar avance cuatrimestral
A76: PDOT-006 | B76: 10 | C76: Octubre | D76: 0.881 | E76: 0.07 | F76: -0.81 | G76: 🔴 | H76: ⚠️ Revisar avance cuatrimestral
A77: PDOT-006 | B77: 11 | C77: Noviembre | D77: 0.924 | E77: 0.074 | F77: -0.85 | G77: 🔴 | H77: ⚠️ Revisar avance cuatrimestral
A78: PDOT-006 | B78: 12 | C78: Diciembre | D78: 0.953 | E78: 0.076 | F78: -0.876 | G78: 🔴 | H78: ⚠️ Revisar avance cuatrimestral
A79: PDOT-007 | B79: 1 | C79: Enero | D79: 0.076 | E79: 0.059 | F79: -0.017 | G79: 🟡
A80: PDOT-007 | B80: 2 | C80: Febrero | D80: 0.119 | E80: 0.093 | F80: -0.026 | G80: 🟡
A81: PDOT-007 | B81: 3 | C81: Marzo | D81: 0.182 | E81: 0.142 | F81: -0.04 | G81: 🟡
A82: PDOT-007 | B82: 4 | C82: Abril | D82: 0.269 | E82: 0.21 | F82: -0.059 | G82: 🟡
A83: PDOT-007 | B83: 5 | C83: Mayo | D83: 0.378 | E83: 0.294 | F83: -0.083 | G83: 🟡
A84: PDOT-007 | B84: 6 | C84: Junio | D84: 0.5 | E84: 0.39 | F84: -0.11 | G84: 🟡
A85: PDOT-007 | B85: 7 | C85: Julio | D85: 0.622 | E85: 0.486 | F85: -0.137 | G85: 🟡
A86: PDOT-007 | B86: 8 | C86: Agosto | D86: 0.731 | E86: 0.57 | F86: -0.161 | G86: 🟡
A87: PDOT-007 | B87: 9 | C87: Septiembre | D87: 0.818 | E87: 0.638 | F87: -0.18 | G87: 🟡
A88: PDOT-007 | B88: 10 | C88: Octubre | D88: 0.881 | E88: 0.687 | F88: -0.194 | G88: 🟡
A89: PDOT-007 | B89: 11 | C89: Noviembre | D89: 0.924 | E89: 0.721 | F89: -0.203 | G89: 🟡
A90: PDOT-007 | B90: 12 | C90: Diciembre | D90: 0.953 | E90: 0.743 | F90: -0.21 | G90: 🟡
A91: PDOT-008 | B91: 1 | C91: Enero | D91: 0.076 | E91: 0 | F91: -0.076 | G91: 🔴 | H91: ⚠️ Revisar avance cuatrimestral
A92: PDOT-008 | B92: 2 | C92: Febrero | D92: 0.119 | E92: 0 | F92: -0.119 | G92: 🔴 | H92: ⚠️ Revisar avance cuatrimestral
A93: PDOT-008 | B93: 3 | C93: Marzo | D93: 0.182 | E93: 0 | F93: -0.182 | G93: 🔴 | H93: ⚠️ Revisar avance cuatrimestral
A94: PDOT-008 | B94: 4 | C94: Abril | D94: 0.269 | E94: 0 | F94: -0.269 | G94: 🔴 | H94: ⚠️ Revisar avance cuatrimestral
A95: PDOT-008 | B95: 5 | C95: Mayo | D95: 0.378 | E95: 0 | F95: -0.378 | G95: 🔴 | H95: ⚠️ Revisar avance cuatrimestral
A96: PDOT-008 | B96: 6 | C96: Junio | D96: 0.5 | E96: 0 | F96: -0.5 | G96: 🔴 | H96: ⚠️ Revisar avance cuatrimestral
A97: PDOT-008 | B97: 7 | C97: Julio | D97: 0.622 | E97: 0 | F97: -0.622 | G97: 🔴 | H97: ⚠️ Revisar avance cuatrimestral
A98: PDOT-008 | B98: 8 | C98: Agosto | D98: 0.731 | E98: 0 | F98: -0.731 | G98: 🔴 | H98: ⚠️ Revisar avance cuatrimestral
A99: PDOT-008 | B99: 9 | C99: Septiembre | D99: 0.818 | E99: 0 | F99: -0.818 | G99: 🔴 | H99: ⚠️ Revisar avance cuatrimestral
A100: PDOT-008 | B100: 10 | C100: Octubre | D100: 0.881 | E100: 0 | F100: -0.881 | G100: 🔴 | H100: ⚠️ Revisar avance cuatrimestral
A101: PDOT-008 | B101: 11 | C101: Noviembre | D101: 0.924 | E101: 0 | F101: -0.924 | G101: 🔴 | H101: ⚠️ Revisar avance cuatrimestral
A102: PDOT-008 | B102: 12 | C102: Diciembre | D102: 0.953 | E102: 0 | F102: -0.953 | G102: 🔴 | H102: ⚠️ Revisar avance cuatrimestral
... A114: PDOT-009 | B114: 12 | C114: Diciembre | D114: 0.953 | E114: 0.095 | F114: -0.857 | G114: 🔴 | H114: ⚠️ Revisar avance cuatrimestral
A115: PDOT-010 | B115: 1 | C115: Enero | D115: 0.076 | E115: 0.076 | F115: 0 | G115: 🟢
A116: PDOT-010 | B116: 2 | C116: Febrero | D116: 0.119 | E116: 0.119 | F116: 0 | G116: 🟢
A117: PDOT-010 | B117: 3 | C117: Marzo | D117: 0.182 | E117: 0.182 | F117: 0 | G117: 🟢
A118: PDOT-010 | B118: 4 | C118: Abril | D118: 0.269 | E118: 0.269 | F118: 0 | G118: 🟢
A119: PDOT-010 | B119: 5 | C119: Mayo | D119: 0.378 | E119: 0.378 | F119: 0 | G119: 🟢
A120: PDOT-010 | B120: 6 | C120: Junio | D120: 0.5 | E120: 0.5 | F120: 0 | G120: 🟢
A121: PDOT-010 | B121: 7 | C121: Julio | D121: 0.622 | E121: 0.622 | F121: 0 | G121: 🟢
A122: PDOT-010 | B122: 8 | C122: Agosto | D122: 0.731 | E122: 0.731 | F122: 0 | G122: 🟢
A123: PDOT-010 | B123: 9 | C123: Septiembre | D123: 0.818 | E123: 0.818 | F123: 0 | G123: 🟢
A124: PDOT-010 | B124: 10 | C124: Octubre | D124: 0.881 | E124: 0.881 | F124: 0 | G124: 🟢
A125: PDOT-010 | B125: 11 | C125: Noviembre | D125: 0.924 | E125: 0.924 | F125: 0 | G125: 🟢
A126: PDOT-010 | B126: 12 | C126: Diciembre | D126: 0.953 | E126: 0.953 | F126: 0 | G126: 🟢
... A138: PDOT-011 | B138: 12 | C138: Diciembre | D138: 0.953 | E138: 0.667 | F138: -0.286 | G138: 🟡
A139: PDOT-012 | B139: 1 | C139: Enero | D139: 0.076 | E139: 0.006 | F139: -0.07 | G139: 🔴 | H139: ⚠️ Revisar avance cuatrimestral
A140: PDOT-012 | B140: 2 | C140: Febrero | D140: 0.119 | E140: 0.01 | F140: -0.11 | G140: 🔴 | H140: ⚠️ Revisar avance cuatrimestral
A141: PDOT-012 | B141: 3 | C141: Marzo | D141: 0.182 | E141: 0.015 | F141: -0.168 | G141: 🔴 | H141: ⚠️ Revisar avance cuatrimestral
A142: PDOT-012 | B142: 4 | C142: Abril | D142: 0.269 | E142: 0.022 | F142: -0.247 | G142: 🔴 | H142: ⚠️ Revisar avance cuatrimestral
A143: PDOT-012 | B143: 5 | C143: Mayo | D143: 0.378 | E143: 0.03 | F143: -0.347 | G143: 🔴 | H143: ⚠️ Revisar avance cuatrimestral
A144: PDOT-012 | B144: 6 | C144: Junio | D144: 0.5 | E144: 0.04 | F144: -0.46 | G144: 🔴 | H144: ⚠️ Revisar avance cuatrimestral
A145: PDOT-012 | B145: 7 | C145: Julio | D145: 0.622 | E145: 0.05 | F145: -0.573 | G145: 🔴 | H145: ⚠️ Revisar avance cuatrimestral
...

Sheet H21_EVALUACION_CUATRIMESTRAL
A1: 🔙 Volver al Índice
A2: H21 — EVALUACIÓN CUATRIMESTRAL: C1 (30-abr) | C2 (31-ago) | C3 (31-dic) — Ciclo Presupuestario Ecuatoriano
A3: Alineado con ciclo presupuestario ecuatoriano. Reformas presupuestarias típicas: mayo y septiembre.
A4: ← H01
A6: ID_Meta | B6: Descripción_Corta | C6: Nivel_Estrés | D6: C1_Ti_Abr | E6: C1_Vi | F6: C1_ICPI_i% | G6: C2_Ti_Ago | H6: C2_Vi | I6: C2_ICPI_i% | J6: C3_Ti_Dic | K6: C3_Vi | L6: C3_ICPI_i% | M6: Tendencia | N6: Proyección_Cierre
A7: PDOT-001 | B7: Acueducto rural | C7: Nivel2 | D7: 0.128 | E7: 1 | F7: 3.378 | G7: 0.383 | H7: 1 | I7: 10.133 | J7: 0.85 | K7: 1 | L7: 22.518 | M7: ↑↑ Mejora sostenida | N7: ✅ Alcanzará objetivo
A8: PDOT-002 | B8: Alcantarillado | C8: Nivel3 | D8: 0.009 | E8: 1 | F8: 0.174 | G8: 0.027 | H8: 1 | I8: 0.522 | J8: 0.06 | K8: 1 | L8: 1.159 | M8: ↑↑ Mejora sostenida | N8: 🔴 En riesgo
A9: PDOT-003 | B9: Desechos sólidos | C9: Nivel3 | D9: 0 | E9: 0 | F9: 0 | G9: 0 | H9: 0 | I9: 0 | J9: 0 | K9: 0 | L9: 0 | M9: → Estable | N9: 🔴 En riesgo
A10: PDOT-004 | B10: Vialidad urbana | C10: Nivel1 | D10: 0.135 | E10: 1 | F10: 0.898 | G10: 0.405 | H10: 1 | I10: 2.693 | J10: 0.9 | K10: 1 | L10: 5.984 | M10: ↑↑ Mejora sostenida | N10: ✅ Alcanzará objetivo
A11: PDOT-005 | B11: Mercado municipal | C11: Nivel2 | D11: 0.112 | E11: 1 | F11: 0.351 | G11: 0.338 | H11: 1 | I11: 1.052 | J11: 0.75 | K11: 1 | L11: 2.337 | M11: ↑↑ Mejora sostenida | N11: ⚠️ Puede alcanzar
A12: PDOT-006 | B12: Centro salud | C12: Nivel3 | D12: 0.012 | E12: 0 | F12: 0 | G12: 0.036 | H12: 0 | I12: 0 | J12: 0.08 | K12: 0 | L12: 0 | M12: → Estable | N12: 🔴 En riesgo
A13: PDOT-007 | B13: Equipamiento edu | C13: Nivel2 | D13: 0.117 | E13: 1 | F13: 0.187 | G13: 0.351 | H13: 1 | I13: 0.561 | J13: 0.78 | K13: 1 | L13: 1.247 | M13: ↑↑ Mejora sostenida | N13: ⚠️ Puede alcanzar
A14: PDOT-008 | B14: Guardería | C14: Nivel3 | D14: 0 | E14: 0 | F14: 0 | G14: 0 | H14: 0 | I14: 0 | J14: 0 | K14: 0 | L14: 0 | M14: → Estable | N14: 🔴 En riesgo
A15: PDOT-009 | B15: Drenaje pluvial | C15: Nivel3 | D15: 0.015 | E15: 0 | F15: 0 | G15: 0.045 | H15: 0 | I15: 0 | J15: 0.1 | K15: 0 | L15: 0 | M15: → Estable | N15: 🔴 En riesgo
A16: PDOT-010 | B16: Parque norte | C16: Nivel1 | D16: 0.15 | E16: 1 | F16: 0.07 | G16: 0.45 | H16: 1 | I16: 0.21 | J16: 1 | K16: 1 | L16: 0.467 | M16: ↑↑ Mejora sostenida | N16: ✅ Alcanzará objetivo
A17: PDOT-011 | B17: Malecón costero | C17: Nivel2 | D17: 0.105 | E17: 1 | F17: 0.177 | G17: 0.315 | H17: 1 | I17: 0.53 | J17: 0.7 | K17: 1 | L17: 1.178 | M17: ↑↑ Mejora sostenida | N17: ⚠️ Puede alcanzar
A18: PDOT-012 | B18: Unidad móvil | C18: Nivel4 | D18: 0.012 | E18: 1 | F18: 0.007 | G18: 0.036 | H18: 1 | I18: 0.021 | J18: 0.08 | K18: 1 | L18: 0.047 | M18: ↑↑ Mejora sostenida | N18: 🔴 En riesgo
... A26: PDOT-020 | B26: Planta tratamiento | C26: Nivel3 | D26: 0.03 | E26: 1 | F26: 0.353 | G26: 0.09 | H26: 1 | I26: 1.06 | J26: 0.2 | K26: 1 | L26: 2.356 | M26: ↑↑ Mejora sostenida | N26: 🔴 En riesgo
A28: ICPI GLOBAL POR CORTE CUATRIMESTRAL
A29: Corte | B29: Fecha | C29: ICPI Global % | D29: Clasificación AVEP | E29: Señal Principal
A30: C1 (Abr) | B30: 30/04/2024 | C30: 0.062 | D30: 🔴 Ruptura Sistémica | E30: Metas grandes sin devengado significativo al Q1
A31: C2 (Ago) | B31: 31/08/2024 | C31: 0.186 | D31: 🔴 Ruptura Sistémica | E31: Metas Nivel2 empiezan a contribuir; Nivel3 sin avance
A32: C3 (Dic) | B32: 31/12/2024 | C32: 0.412 | D32: ⚠️ Transición Crítica | E32: ICPI final — brechas documentales son el factor limitante
A34: ⚠️ SEÑALES DE ATENCIÓN TEMPRANA POR CORTE:
A35: Metas con T_i < 30% al C1 y P_i > 5% requieren revisión de proceso contractual antes del C2. Metas grandes PDOT-001 y PDOT-020 deben monitorear devengado mensual.

Sheet H22_EVALUACION_ANUAL_FINAL
A1: 🔙 Volver al Índice
A2: H22 — EVALUACIÓN ANUAL FINAL 2024 — Cierre Definitivo 31 de Diciembre
A3: GAD Municipal de Montecristi | Período PDOT 2023-2027 | Año Fiscal 2024
A4: ← H01
A6: SECCIÓN 1 — RESULTADO ICPI GLOBAL FINAL 2024
A7: ICPI GLOBAL 2024 | B7: =H14_CALCULO_ICPI!B32/100 -> 0.41236256
A8: Clasificación AVEP | B8: ⚠️ Transición Crítica (40-69%)
A9: ICM SIGAD Reportado | B9: =H01_PARAMETROS_GENERALES!B12 -> 1
A10: Brecha ICM-ICPI | B10: =ROUND(H01_PARAMETROS_GENERALES!B12*100-H14_CALCULO_ICPI!B32,2)&" puntos porcentuales" -> 58,76 puntos porcentuales
A11: Clasificación Brecha | B11: 🔴 Brecha Crítica (>50pp)
A12: Metas con V_i=1 (trazables) | B12: =COUNTIF(H14_CALCULO_ICPI!J6:J25,1)&" de 20 metas" -> 15 de 20 metas
A13: Presupuesto certificado | B13: $5,619,500 de $9,525,000 (59.0%)
A15: SECCIÓN 2 — ANÁLISIS BRECHA ICM-ICPI POR NIVEL DE ESTRÉS
A16: Nivel | B16: N° Metas | C16: Metas | D16: ICPI_Nivel% | E16: Descripción | F16: Acción 2025
A17: Nivel 1 — Trazabilidad Plena | B17: 5 | C17: PDOT-004,010,013,015,017,019 | D17: 0.902 | E17: Metas modelo con ciclo documental íntegro | F17: Replicar prácticas al resto del portafolio
A18: Nivel 2 — Brecha Documental Recuperable | B18: 6 | C18: PDOT-001,005,007,011,014,016 | D18: 0.683 | E18: Ejecutaron pero LOTAIP incompleto — recuperable | F18: Publicar documentos faltantes antes del C1 2025
A19: Nivel 3 — Falla Sistémica de Proceso | B19: 7 | C19: PDOT-002,003,006,008,009,020 | D19: 0.125 | E19: Sin proceso contractual válido o devengado nulo | F19: Reformulación POA 2025 + nuevos procesos SERCOP
A20: Nivel 4 — Patrones MOM Activos | B20: 2 | C20: PDOT-012, PDOT-018 | D20: 0.029 | E20: MOM-III (inflación unidades) y MOM-I (sin POA) | F20: Verificar indicadores + incorporar al POA urgente
A22: SECCIÓN 3 — ICPI POR EJE ESTRATÉGICO
A23: Eje | B23: Descripción | C23: N°Metas | D23: Peso Presup % | E23: ICPI_Eje% | F23: Semáforo | G23: Observación
A24: AS — Ambiental Sostenible | B24: Agua, alcantarillado, desechos, ambiente | C24: 6 | D24: 0.579 | E24: 0.187 | F24: 🔴 | G24: Metas más pesadas en presupuesto con mayor brecha
A25: EC — Económico Productivo | B25: Mercado, malecón, artesanos | C25: 3 | D25: 0.094 | E25: 0.735 | F25: ✅ | G25: Trazabilidad relativamente buena en sector productivo
A26: SC — Social e Inclusivo | B26: Salud, educación, deporte, bienestar | C26: 7 | D26: 0.179 | E26: 0.421 | F26: ⚠️ | G26: Mixto: parque y capacitación bien; guardería y adultos mayor mal
A27: OT — Ordenamiento Territorial | B27: Vialidad, drenaje, catastro | C27: 3 | D27: 0.101 | E27: 0.643 | F27: ⚠️ | G27: Vialidad urbana y bacheo bien; drenaje pluvial sin proceso
A28: PI — Político Institucional | B28: Transparencia, catastro, recaudación | C28: 4 | D28: 0.033 | E28: 0.805 | F28: ✅ | G28: Mejor ICPI por Eje — gobernanza y transparencia fuerte
A30: SECCIÓN 4 — TOP 5 MAYOR ICPI (Certificadas) Y BOTTOM 5 MENOR ICPI (Oportunidades)
A31: Posición | B31: ID_Meta | C31: Descripción | D31: ICPI_Individual% | E31: Nivel
A32: 🥇 1° | B32: PDOT-010 | C32: Parque recreativo sector norte | D32: 1 | E32: Nivel1
A33: 🥇 2° | B33: PDOT-013 | C33: Capacitación artesanos sombrero toquilla | D33: 0.812 | E33: Nivel1
A34: 🥇 3° | B34: PDOT-015 | C34: Fortalecimiento transparencia LOTAIP | D34: 1 | E34: Nivel1
A35: 🥇 4° | B35: PDOT-017 | C35: Bacheo y señalización vías parroquiales | D35: 0.9 | E35: Nivel1
A36: 🥇 5° | B36: PDOT-004 | C36: Mejoramiento vialidad urbana cantonal | D36: 0.9 | E36: Nivel1
A37: Posición | B37: ID_Meta | C37: Descripción | D37: ICPI_Individual% | E37: Nivel
A38: 🔴 16° | B38: PDOT-018 | C38: Programa adulto mayor y discapacidad | D38: 0 | E38: Nivel4 MOM-I
A39: 🔴 17° | B39: PDOT-003 | C39: Sistema manejo integral desechos sólidos | D39: 0 | E39: Nivel3
A40: 🔴 18° | B40: PDOT-008 | C40: Guardería municipal comunitaria El Carmen | D40: 0 | E40: Nivel3
A41: 🔴 19° | B41: PDOT-009 | C41: Sistema drenaje pluvial casco urbano | D41: 0 | E41: Nivel3
A42: 🔴 20° | B42: PDOT-006 | C42: Centro salud tipo C parroquia San Andrés | D42: 0 | E42: Nivel3
A44: SECCIÓN 5 — IFE FINAL: ÍNDICE DE FIDELIDAD ELECTORAL
A45: IFE Global | B45: =H15_INDICES_COMPLEMENTARIOS!B31/100 -> 0.9
A46: Clasificación | B46: ⭐ Alta Fidelidad Electoral (≥85%)
A47: Interpretación | B47: 13 de 15 promesas electorales se tradujeron íntegramente al PDOT 2023-2027. 2 promesas con vinculación parcial (P-09, P-15).
A48: Conclusión | B48: El mandato ciudadano fue respetado en la planificación estratégica del GAD.
A50: SECCIÓN 6 — ITAM GLOBAL: TRANSPARENCIA ACTIVA MUNICIPAL
A51: ITAM Global Ponderado | B51: =H16_ITAM_TRANSPARENCIA!B27 -> 0.62093176
A52: Nivel | B52: Medio ⚠️ — Oportunidad de mejora documental
A53: Causa Principal | B53: Contratos LOTAIP ausentes/rotos en metas Nivel2 y Nivel3 de mayor presupuesto
A54: Meta 2025 | B54: Alcanzar ITAM > 80% mediante protocolo mensual de publicación LOTAIP
A56: SECCIÓN 7 — SEÑALES MOM ACTIVADAS EN 2024
A57: MOM-I (Fragmentación Selectiva) | B57: ⚠️ ACTIVA — Severidad Alta — ICM basado en 10.3% del presupuesto PDOT
A58: MOM-II (Sustitución de Metas) | B58: ✅ SIN SEÑAL — POA mantuvo integridad documental
A59: MOM-III (Inflación de Unidades) | B59: ⚠️ ACTIVA — Severidad Alta — PDOT-012: 8,295% cumplimiento vs 8% ejecución presupuestaria
A61: SECCIÓN 8 — RECOMENDACIONES PARA POA 2025
A62: N° | B62: Recomendación | C62: Meta(s) Afectada(s) | D62: Plazo | E62: Indicador de Éxito
A63: R1 | B63: Ampliar universo de metas reportadas en SIGAD al 100% del PDOT | C63: Todas las 20 metas | D63: Q1 2025 | E63: Representatividad SIGAD > 80%
A64: R2 | B64: Implementar protocolo de publicación LOTAIP mensual por contrato | C64: PDOT-001,005,007,014,016 | D64: 45689 | E64: ITAM > 80% al C1 2025
A65: R3 | B65: Verificar definición operativa de indicadores antes del inicio del ejercicio | C65: PDOT-012 | D65: Ene 2025 | E65: Coherencia entre unidad PDOT y SIGAD documentada
A66: R4 | B66: Incorporar PDOT-018 al POA 2025 con proceso contractual SERCOP | C66: PDOT-018 | D66: Ene 2025 | E66: POA 2025 con PDOT-018 formalizado
A67: R5 | B67: Relanzar procesos SERCOP para metas Nivel3 canceladas/desiertas | C67: PDOT-003,008,009 | D67: Q1 2025 | E67: Procesos SERCOP activos al C1 2025
A69: SECCIÓN 9 — PROYECCIÓN PDOT 2023-2027 (5 años)
A70: T_i promedio ponderado 2024 | B70: 0.47 (47% del presupuesto anual devengado)
A71: Proyección acumulada 2027 al ritmo actual | B71: 47% × 4 años restantes = 188% del presupuesto PDOT → teóricamente completo con aceleración
A72: Observación crítica | B72: Los ejes AS y SC requieren aceleración significativa. Sin mejora en procesos SERCOP y publicación LOTAIP, el ICPI se mantendrá bajo.
A73: Meta ICPI para 2025 | B73: Objetivo: ICPI > 55% mediante regularización documental y nuevos procesos Q1
A74: Palanca de mayor impacto | B74: Regularizar LOTAIP en PDOT-001, PDOT-002, PDOT-020 elevaría ICPI a ~60% en 2025

Sheet H23_DASHBOARD_REPORTES
A1: 🔙 Volver al Índice
A2: GAD Municipal de Montecristi — Año Fiscal 2024 — Para uso del Alcalde y Equipo Directivo
A3: ← H01 | → H24 Vista Ciudadana | → H22 Evaluación Anual
A5: ━━━━━━━━━━━━━━━━━━━━━━━━━━━━━━━━━━━━━━━━━━━━━━━━━━━━━━━━━━━━━━━━━━━━━━━━━━━━━━━━━━━━━━━━━━━━━━━━━━━━━━━━━━━━
A6: PANEL 1 — INDICADORES CLAVE DE DESEMPEÑO (KPIs)
A7: ICPI GLOBAL 2024 | B7: ICM SIGAD REPORTADO | C7: BRECHA ICM-ICPI | D7: METAS TRAZABLES
A8: =H14_CALCULO_ICPI!B32/100 -> 0.41236256 | B8: =H01_PARAMETROS_GENERALES!B12 -> 1 | C8: ="-"&TEXT(H01_PARAMETROS_GENERALES!B12*100-H14_CALCULO_ICPI!B32,"0.0")&" pp" -> -59 pp | D8: =COUNTIF(H14_CALCULO_ICPI!J6:J25,1)&" / 20" -> 15 / 20
A9: =IF(H14_CALCULO_ICPI!B32>=90,"✅ Excelencia",IF(H14_CALCULO_ICPI!B32>=70,"✅ Gestión por Mandato",IF(H14_CALCULO_ICPI!B32>=40,"⚠️ Transición Crítica",IF(H14_CALCULO_ICPI!B32>=20,"🔶 Gestión por Ocurrencia","🔴 Ruptura Sistémica")))) -> ⚠️ Transición Crítica | B9: =TEXT(H01_PARAMETROS_GENERALES!B12,"0%")&" — "&IF(H01_PARAMETROS_GENERALES!B12>=0.9,"Cumplimiento Certificado",IF(H01_PARAMETROS_GENERALES!B12>=0.8,"Alta Fidelidad (SIGAD)","Revisar")) -> 100% — Cumplimiento Certificado | C9: =IF(ABS(H01_PARAMETROS_GENERALES!B12*100-H14_CALCULO_ICPI!B32)>50,"🔴 Brecha Crítica (>50pp)",IF(ABS(H01_PARAMETROS_GENERALES!B12*100-H14_CALCULO_ICPI!B32)>30,"🟠 Brecha Alta (>30pp)","🟡 Brecha Media")) -> 🔴 Brecha Crítica (>50pp) | D9: =TEXT(COUNTIF(H14_CALCULO_ICPI!J6:J25,1)/20,"0.0%")&" del portafolio" -> 75% del portafolio
A11: PANEL 2 — ICPI POR EJE ESTRATÉGICO
A12: Eje | B12: Nombre | C12: ICPI% | D12: Semáforo | E12: Peso Presupuestal
A13: AS | B13: Ambiental Sostenible | C13: 0.187 | D13: 🔴 | E13: 0.579
A14: EC | B14: Económico Productivo | C14: 0.735 | D14: ✅ | E14: 0.094
A15: SC | B15: Social e Inclusivo | C15: 0.421 | D15: ⚠️ | E15: 0.179
A16: OT | B16: Ordenamiento Territorial | C16: 0.643 | D16: ⚠️ | E16: 0.101
A17: PI | B17: Político Institucional | C17: 0.805 | D17: ✅ | E17: 0.033
A19: PANEL 3 — TABLERO DE PROCESOS (IED por Dirección)
A20: Dirección/Unidad | B20: IED% | C20: Nivel | D20: Semáforo
A21: Dir. Obras Públicas | B21: =H18_IED_EFICIENCIA_DIRECTIVA!C7 -> 0.455 | C21: Proceso con Brechas | D21: 🟡
A22: Dir. Planificación | B22: =H18_IED_EFICIENCIA_DIRECTIVA!C8 -> 0.261 | C22: Proceso con Brechas Profundas | D22: 🔴
A23: Dir. Cultura / Deporte | B23: =H18_IED_EFICIENCIA_DIRECTIVA!C9 -> 0.958 | C23: Proceso Ejemplar | D23: 🟢
A24: Dir. Turismo | B24: =H18_IED_EFICIENCIA_DIRECTIVA!C10 -> 0.873 | C24: Proceso Sólido | D24: 🟢
A25: Dir. Social | B25: =H18_IED_EFICIENCIA_DIRECTIVA!C11 -> 0.349 | C25: Proceso Crítico | D25: 🔴
A26: Dir. Ambiental | B26: =H18_IED_EFICIENCIA_DIRECTIVA!C12 -> 0.8 | C26: Proceso en Desarrollo | D26: 🟢
A27: Dir. Financiera | B27: =H18_IED_EFICIENCIA_DIRECTIVA!C13 -> 0.8 | C27: Proceso Sólido | D27: 🟢
A28: Patronato Municipal | B28: =H18_IED_EFICIENCIA_DIRECTIVA!C14 -> 0.029 | C28: Proceso Crítico Urgente | D28: 🔴
A30: PANEL 4 — TOP 5 METAS CERTIFICADAS Y TOP 5 OPORTUNIDADES
A31: 🥇 METAS CERTIFICADAS
A32: PDOT-010 — Parque norte | B32: 1 | C32: Nivel1 ⭐
A33: PDOT-013 — Artesanos toquilla | B33: 0.812 | C33: Nivel1 ⭐
A34: PDOT-015 — Transparencia LOTAIP | B34: 1 | C34: Nivel1 ⭐
A35: PDOT-017 — Bacheo parroquial | B35: 0.9 | C35: Nivel1 ⭐
A36: PDOT-004 — Vialidad urbana | B36: 0.9 | C36: Nivel1 ⭐
A37: 🔴 PRINCIPALES OPORTUNIDADES DE MEJORA
A38: PDOT-018 — Adulto mayor (MOM-I) | B38: 0 | C38: Nivel4 ⚠️
A39: PDOT-006 — Centro salud | B39: 0 | C39: Nivel3
A40: PDOT-008 — Guardería | B40: 0 | C40: Nivel3
A41: PDOT-009 — Drenaje pluvial | B41: 0 | C41: Nivel3
A42: PDOT-003 — Desechos sólidos | B42: 0 | C42: Nivel3
A44: PANEL 5 — SEÑALES DE ATENCIÓN TEMPRANA (MOM)
A45: ⚠️ MOM-I ACTIVA | B45: Fragmentación Selectiva | C45: ICM 92% basado en 10.3% del presupuesto PDOT
A46: ✅ MOM-II Sin señal | B46: Sustitución de Metas | C46: POA mantiene integridad documental
A47: ⚠️ MOM-III ACTIVA | B47: Inflación de Unidades | C47: PDOT-012: 8,295% declarado vs 8% ejecución real
A49: PANEL 6 — IFE: FIDELIDAD AL MANDATO ELECTORAL
A50: IFE Global 2024 | B50: =H15_INDICES_COMPLEMENTARIOS!B31/100 -> 0.9 | C50: ⭐ Alta Fidelidad Electoral (≥85%)
A51: Interpretación | B51: 13 de 15 promesas electorales en PDOT | C51: El mandato ciudadano fue respetado en planificación
A53: PANEL 7 — ICPI POR NIVEL DE ESTRÉS
A54: Nivel | B54: Metas | C54: ICPI_Nivel% | D54: T_i Prom. | E54: Descripción + Hallazgo
A55: Nivel 1 — Trazabilidad Plena | B55: =COUNTIF(H14_CALCULO_ICPI!Q6:Q25,"Nivel1") -> 6 | C55: {=IFERROR(SUMPRODUCT((H14_CALCULO_ICPI!Q6:Q25="Nivel1")*H14_CALCULO_ICPI!N6:N25)/SUMPRODUCT((H14_CALCULO_ICPI!Q6:Q25="Nivel1")*H14_CALCULO_ICPI!O6:O25),0)} -> 0.90232906 | D55: =IFERROR(AVERAGEIF(H14_CALCULO_ICPI!Q6:Q25,"Nivel1",H14_CALCULO_ICPI!K6:K25),0) -> 0.93333333 | E55: Metas modelo — ciclo completo y trazable
A56: Nivel 2 — Brecha Documental | B56: =COUNTIF(H14_CALCULO_ICPI!Q6:Q25,"Nivel2") -> 6 | C56: {=IFERROR(SUMPRODUCT((H14_CALCULO_ICPI!Q6:Q25="Nivel2")*H14_CALCULO_ICPI!N6:N25)/SUMPRODUCT((H14_CALCULO_ICPI!Q6:Q25="Nivel2")*H14_CALCULO_ICPI!O6:O25),0)} -> 0.80868081 | D56: =IFERROR(AVERAGEIF(H14_CALCULO_ICPI!Q6:Q25,"Nivel2",H14_CALCULO_ICPI!K6:K25),0) -> 0.76333333 | E56: ⚠️ Ejecutaron (~76% T_i) pero sin evidencia LOTAIP completa — el ICPI pena por V_i parcial
A57: Nivel 3 — Falla Sistémica | B57: =COUNTIF(H14_CALCULO_ICPI!Q6:Q25,"Nivel3") -> 6 | C57: {=IFERROR(SUMPRODUCT((H14_CALCULO_ICPI!Q6:Q25="Nivel3")*H14_CALCULO_ICPI!N6:N25)/SUMPRODUCT((H14_CALCULO_ICPI!Q6:Q25="Nivel3")*H14_CALCULO_ICPI!O6:O25),0)} -> 0.066483301 | D57: =IFERROR(AVERAGEIF(H14_CALCULO_ICPI!Q6:Q25,"Nivel3",H14_CALCULO_ICPI!K6:K25),0) -> 0.073333333 | E57: Sin contrato válido o devengado — proceso SERCOP desierto o cancelado
A58: Nivel 4 — Patrones MOM | B58: =COUNTIF(H14_CALCULO_ICPI!Q6:Q25,"Nivel4") -> 2 | C58: {=IFERROR(SUMPRODUCT((H14_CALCULO_ICPI!Q6:Q25="Nivel4")*H14_CALCULO_ICPI!N6:N25)/SUMPRODUCT((H14_CALCULO_ICPI!Q6:Q25="Nivel4")*H14_CALCULO_ICPI!O6:O25),0)} -> 0.0285 | D58: =IFERROR(AVERAGEIF(H14_CALCULO_ICPI!Q6:Q25,"Nivel4",H14_CALCULO_ICPI!K6:K25),0) -> 0.04 | E58: Alertas MOM activas — patrones de opacidad detectados
A59: ℹ️ Nota: ICPI_Nivel% = congruencia programática certificable del grupo (incluye V_i, T_i, E_i, C_i). T_i Prom. = ejecución presupuestaria promedio del grupo (gris). Nivel 2: alta ejecución (~76%) pero brechas documentales reducen el ICPI a 81%.
A60: INTERPRETACIÓN ICPI GLOBAL
A61: =IF(A8>=0.9,"✅ EXCELENCIA: El ciclo documental del PDOT está íntegro. La trazabilidad entre lo planificado, contratado, ejecutado y reportado es certificable.",IF(A8>=0.7,"✅ GESTIÓN POR MANDATO: Alta fidelidad al PDOT con desviaciones menores corregibles. Se recomienda regularizar documentación faltante antes del cierre.",IF(A8>=0.4,"⚠️ TRANSICIÓN CRÍTICA: Desconexión orgánica significativa. Existe ejecución pero la trazabilidad documental está incompleta. Acción preventiva recomendada.",IF(A8>=0.2,"🔶 GESTIÓN POR OCURRENCIA: Desconexión severa entre lo planificado y lo ejecutable. La mayoría del presupuesto estratégico carece de trazabilidad certificable.","🔴 RUPTURA SISTÉMICA: Opacidad estructural. El sistema no puede certificar la congruencia programática con la información disponible.")))) -> ⚠️ TRANSICIÓN CRÍTICA: Desconexión orgánica significativa. Existe ejecución pero la trazabilidad documental está incompleta. Acción preventiva recomendada.
A62: Fuente: H01–H14 SIAP-ICPI v1.0 | Plataforma QUADRUM

Sheet H24_DASHBOARD_TAC
A1: 🔙 Volver al Índice
A2: Participación · Transparencia · Rendición de Cuentas · Control Social | Art.100 CRE · LOTAIP · CPCCS
A3: ← H01 | Portal Ciudadano de Transparencia — TAC | Plataforma QUADRUM
A4: ▌ A. INDICADORES CLAVE DE ACCIÓN CIUDADANA (TAC)
A5: IFE — ÍNDICE DE FIDELIDAD ELECTORAL | D5: RENDICIÓN DE CUENTAS | G5: SSC – CONTROL SOCIAL | J5: TRANSPARENCIA LOTAIP
A6: =H04B_DATOS_CNE!B52/100 -> 0.975 | D6: PRESENTADO | G6: =H15_INDICES_COMPLEMENTARIOS!B44 -> 0.0285 | J6: 80%+
A8: ="§3.7.1 — "&H04B_DATOS_CNE!B51&" promesas CNE verificadas en 5 ejes | Fuente: H04B_DATOS_CNE" -> §3.7.1 — 20 promesas CNE verificadas en 5 ejes | Fuente: H04B_DATOS_CNE | D8: RC Anual Obligatorio | G8: Índice SSC CPCCS | J8: Cumpl. Art.7 LOTAIP
A9: =IF(H04B_DATOS_CNE!B52>=85,"✓ Alta Fidelidad Electoral",IF(H04B_DATOS_CNE!B52>=60,"⚠ Fidelidad Moderada","🔴 Ruptura Mandato")) -> ✓ Alta Fidelidad Electoral | D9: ✓ Cumple | Obligatorio | G9: ⚠ Bajo | Meta ≥ 3.0 | J9: ✓ Cumple | Meta ≥ 70%
A11: ▌ B. DESGLOSE POR DIMENSIÓN TAC
A12: DIMENSIÓN | B12: INSTRUMENTO LEGAL | C12: OBLIGACIÓN | D12: INDICADOR | E12: CUMPLIMIENTO | F12: ESTADO | G12: PUNTOS | H12: PONDERACIÓN | I12: APORTE TAC
A13: Participación Ciudadana | B13: Art. 100 CRE | C13: Silla Vacía / Audiencias | D13: Sesiones con participación | E13: 46116 | F13: ✓ Cumple | G13: 95 | H13: 0.2 | I13: =G13*0.2 -> 19
A14: Rendición de Cuentas | B14: CPCCS / LOTAIP | C14: RC Anual obligatoria | D14: RC presentada a tiempo | E14: 46023 | F14: ✓ Cumple | G14: 100 | H14: 0.25 | I14: =G14*0.25 -> 25
A15: Acceso Información | B15: Art. 18 CRE / LOTAIP | C15: Publicación Art.7 | D15: % cumpl. literal LOTAIP | E15: 0.8 | F15: ✓ Cumple | G15: 80 | H15: 0.2 | I15: =G15*0.2 -> 16
A16: Control Social | B16: CPCCS | C16: Respuesta a observaciones | D16: Índice SSC | E16: =H15_INDICES_COMPLEMENTARIOS!B44 -> 0.0285 | F16: ⚠ Bajo | G16: 57 | H16: 0.15 | I16: =G16*0.15 -> 8.55
A17: Transparencia Activa | B17: LOTAIP Art.7 | C17: Publicación página web | D17: % publicación ítems | E17: 0.85 | F17: ✓ Cumple | G17: 85 | H17: 0.1 | I17: =G17*0.1 -> 8.5
A18: Veedurías Ciudadanas | B18: CPCCS | C18: Atención veedurías | D18: N° veedurías atendidas | E18: 46055 | F18: ✓ Cumple | G18: 100 | H18: 0.1 | I18: =G18*0.1 -> 10
A19: TOTAL TAC | H19: 1 | I19: =SUM(I13:I18) -> 87.05
A21: ▌ C. SEGUIMIENTO CRONOLÓGICO – ACCIÓN CIUDADANA 2024
A22: EVENTO / MECANISMO | C22: FECHA | E22: PARTICIPANTES | G22: RESULTADO | I22: DOCUMENTACIÓN | K22: ESTADO
A23: Silla Vacía – Sesión Ordinaria | C23: Ene 2024 | E23: 28 ciudadanos | G23: Propuestas de vialidad | I23: Acta SO-001-2024 | K23: ✓
A24: Audiencia Pública – PDOT | C24: 45352 | E24: 45 ciudadanos | G24: Observaciones al PDOT | I24: Informe RC-2024 | K24: ✓
A25: Rendición de Cuentas Anual | C25: Abr 2024 | E25: 67 asistentes | G25: RC aprobada CPCCS | I25: Informe CPCCS-2024 | K25: ✓
A26: Veeduría Ciudadana – Obras | C26: 45444 | E26: 5 veedores | G26: 3 observaciones | I26: Oficio V-001-2024 | K26: ✓
A27: Silla Vacía – Sesión Ordinaria | C27: 45536 | E27: 15 ciudadanos | G27: Propuestas sociales | I27: Acta SO-009-2024 | K27: ✓
A28: Consulta Previa – Comunidades | C28: 45597 | E28: Comunidades | G28: En proceso | I28: Pendiente | K28: ⏳
A31: ▌ D. MARCO LEGAL TAC – BASE NORMATIVA
A32: NORMATIVA | C32: ARTÍCULO | E32: OBLIGACIÓN | H32: MECANISMO | K32: FRECUENCIA | M32: RESPONSABLE
A33: Constitución CRE | C33: Art. 100 | E33: Participación ciudadana | H33: Silla Vacía / Cabildos | K33: Permanente | M33: Secretaría General
A34: COOTAD | C34: Art. 311 | E34: Rendición de Cuentas | H34: Informe Anual CPCCS | K34: Anual | M34: Alcaldía / CPCCS
A35: LOTAIP | C35: Art. 7 | E35: Transparencia activa | H35: Publicación página web | K35: Mensual | M35: Secretaría TICs
A36: CPCCS | C36: Reglamento | E36: Control Social | H36: Veedurías / SSC | K36: Según solicitud | M36: CPCCS / GAD
A37: LOPC | C37: Art. 77 | E37: Consulta Previa | H37: Talleres participativos | K37: Según proyecto | M37: Planificación
A40: ▌ E. RECOMENDACIONES – FORTALECIMIENTO TAC
A41: N° | B41: ÁREA DE MEJORA | D41: INDICADOR BAJO | F41: RECOMENDACIÓN | K41: PLAZO | M41: PRIORIDAD
A42: 1 | B42: Control Social | D42: SSC 2.85% < 3.0 | F42: Implementar protocolo de atención y respuesta a observaciones ciudadanas dentro de 15 días hábiles | K42: Q1 2025 | M42: 🔴 ALTA
A43: 2 | B43: Consulta Previa | D43: Proceso incompleto | F43: Completar talleres y documentar acuerdo con comunidades antes de inicio de obras | K43: Q1 2025 | M43: 🔴 ALTA
A44: 3 | B44: LOTAIP | D44: Art.7 faltantes | F44: Actualizar mensualmente los 24 ítems LOTAIP en el portal web institucional | K44: Mensual | M44: 🟡 MEDIA
A45: 4 | B45: Participación | D45: Asistencia baja | F45: Difundir sesiones de Silla Vacía con 15 días de anticipación por redes sociales | K45: Permanente | M45: 🟡 MEDIA
A47: Sistema SIAP-ICPI | Portal Ciudadano de Transparencia — TAC | Generado automáticamente | Plataforma QUADRUM | v1.0

Sheet H25_RESUMEN_EJECUTIVO
A1: 🔙 Volver al Índice
A2: GAD Municipal | Período de Evaluación: 2024 | Índice ICPI Resultante: 41.24%
A3: ICPI = Índice de Congruencia Programática e Intersistémica | Sistema SIAP-ICPI v1.0 | Plataforma QUADRUM
A4: ← H01 | → H23 Dashboard Ejecutivo | → H24 Vista Ciudadana TAC
A5: ▌ 1. ÍNDICES MAESTROS DEL SISTEMA SIAP-ICPI
A6: ICPI | C6: ITAM | F6: IFE | I6: SSC | K6: IED | M6: TAC
A7: =H14_CALCULO_ICPI!B32/100 -> 0.41236256 | C7: =H16_ITAM_TRANSPARENCIA!B27 -> 0.62093176 | F7: =H15_INDICES_COMPLEMENTARIOS!B31/100 -> 0.9 | I7: =H15_INDICES_COMPLEMENTARIOS!B44 -> 0.0285 | K7: =H18_IED_EFICIENCIA_DIRECTIVA!C7 -> 0.455 | M7: =H04B_DATOS_CNE!B52/100 -> 0.975
A9: Índice ICPI Global | C9: Transparencia y Acceso | F9: Fortalecimiento Institucional | I9: Control Social Ciudadano | K9: Eficiencia Directiva Obras | M9: Acción Ciudadana
A10: Meta: ≥ 60% | C10: Meta: ≥ 60% | F10: Meta: ≥ 80% | I10: Meta: ≥ 3.0 | K10: Meta: ≥ 70% | M10: Meta: ≥ 80%
A12: ▌ 2. EJECUCIÓN PRESUPUESTARIA CONSOLIDADA
A13: COMPONENTE | C13: PRESUPUESTO ($) | E13: DEVENGADO ($) | G13: % EJEC. | I13: CUATRIMESTRE | K13: TENDENCIA
A14: Obras Públicas | C14: 8450000 | E14: 3844750 | G14: 0.455 | I14: C3: 41.2% | K14: → En progreso
A15: Planificación | C15: 1200000 | E15: 313200 | G15: 0.261 | I15: C3: 18.6% | K15: ⬆ Acelerando
A16: Cultura y Deporte | C16: 450000 | E16: 431100 | G16: 0.958 | I16: C3: 78.4% | K16: ✓ Completado
A17: Turismo | C17: 380000 | E17: 331740 | G17: 0.873 | I17: C3: 65.8% | K17: ✓ En meta
A18: Social | C18: 620000 | E18: 216380 | G18: 0.349 | I18: C3: 25.1% | K18: ⚠ Bajo riesgo
A19: Ambiental | C19: 290000 | E19: 232000 | G19: 0.8 | I19: C3: 61.3% | K19: ✓ En meta
A20: Financiero | C20: 180000 | E20: 144000 | G20: 0.8 | I20: C3: 60.0% | K20: ✓ En meta
A21: Patronato | C21: 340000 | E21: 9860 | G21: 0.029 | I21: C3: 1.8% | K21: 🔴 Crítico
A22: TOTAL PRESUPUESTO | C22: 11910000 | E22: 5523030 | G22: 0.464 | I22: C3: 41.2% | K22: → En control
A24: ▌ 3. ALERTAS PRIORITARIAS – MONITOR DE OPORTUNIDADES Y METAS (MOM)
A25: NIVEL MOM | B25: PROYECTO | C25: INDICADOR | E25: VALOR ACTUAL | G25: META | I25: % DESV. | J25: ACCIÓN RECOMENDADA
A26: MOM-I | B26: PDOT-012 | C26: Avance físico | E26: 0.083 | G26: 1 | I26: 0.917 | J26: Ejecutar inmediatamente – señal crítica
A27: MOM-I | B27: PDOT-020 | C27: Ejecución presup | E27: 0.2 | G27: 1 | I27: 0.8 | J27: Acelerar proceso de contratación
A28: MOM-II | B28: PDOT-002 | C28: Desempeño físico | E28: 0.185 | G28: 1 | I28: 0.815 | J28: Revisar cronograma – riesgo cumplimiento
A29: MOM-III | B29: PDOT-009 | C29: Avance técnico | E29: 0.35 | G29: 1 | I29: 0.65 | J29: Monitoreo mensual suficiente
A32: ▌ 4. EVALUACIONES PERIÓDICAS – AVANCE ICPI POR PERÍODO
A33: PERÍODO | B33: INICIO | C33: CIERRE | D33: ICPI ESPERADO | E33: ICPI REAL | F33: DESVIACIÓN | G33: ESTADO | H33: HOJA REF.
A34: Cuatrimestre 1 | B34: 45292 | C34: 30/04/2024 | D34: 0.12 | E34: 0.062 | F34: -0.058 | G34: ⚠ Bajo | H34: H21
A35: Cuatrimestre 2 | B35: 45296 | C35: 31/08/2024 | D35: 0.36 | E35: 0.186 | F35: -0.174 | G35: ⚠ Bajo | H35: H21
A36: Cuatrimestre 3 | B36: 45300 | C36: 31/12/2024 | D36: 0.75 | E36: 0.412 | F36: -0.338 | G36: 🔴 Crítico | H36: H21
A37: Anual 2024 | B37: 45292 | C37: 31/12/2024 | D37: 1 | E37: 0.412 | F37: -0.588 | G37: 🔴 Bajo meta | H37: H22
A40: ▌ 5. PROYECTOS CRÍTICOS PDOT – TOP 5 POR ÍNDICE DELTA
A41: PROYECTO | B41: NOMBRE | D41: MONTO ($) | F41: EJEC. FÍSICA | G41: EJEC. FINANC. | H41: DELTA (φ) | I41: SEMÁFORO | J41: ACCIÓN
A42: PDOT-002 | B42: Alcantarillado Norte | D42: 1850000 | F42: 0.32 | G42: 0.28 | H42: 0.41 | I42: 🔴 Rojo | J42: Reunión urgente con contratista
A43: PDOT-009 | B43: Adoquinado Sector 3 | D43: 980000 | F43: 0.45 | G43: 0.42 | H43: 0.55 | I43: 🔴 Rojo | J43: Verificar disponibilidad de materiales
A44: PDOT-020 | B44: Centro de Salud Comunitario | D44: 650000 | F44: 0.2 | G44: 0.18 | H44: 0.65 | I44: 🟡 Amarillo | J44: Acelerar trámites de permisos
A45: PDOT-012 | B45: Parque Recreacional | D45: 420000 | F45: 0.08 | G45: 0.06 | H45: 0.87 | I45: 🔴 Rojo | J45: Intervención directa Alcaldía
A46: PDOT-015 | B46: Sistema Agua Potable | D46: 1200000 | F46: 0.55 | G46: 0.52 | H46: 0.3 | I46: 🟡 Amarillo | J46: Monitoreo semanal
A50: SISTEMA SIAP-ICPI | H25 RESUMEN EJECUTIVO | Confidencial – Uso Interno | v1.0 – 2024 | Plataforma QUADRUM
A52: ▌ 6. RECOMENDACIONES EJECUTIVAS – ACCIONES PRIORITARIAS 2025
A53: PRIORIDAD | B53: ÁREA | C53: DESCRIPCIÓN DE LA ACCIÓN | E53: INDICADOR IMPACTADO | H53: PLAZO | J53: RESPONSABLE | M53: ESTADO
A54: 🔴 CRÍTICA | B54: Control Social | C54: Implementar protocolo SSC: respuesta obligatoria a ciudadanos en ≤15 días hábiles con registro en plataforma | E54: SSC (2.85%→3.0%) | H54: Ene 2025 | J54: Secretaría General | M54: Pendiente
A55: 🔴 CRÍTICA | B55: PDOT-012 | C55: Intervención directa Alcaldía en Parque Recreacional: reunión emergencia contratista + cronograma acelerado | E55: ICPI / IED Obras | H55: Ene 2025 | J55: Alcaldía / Planif. | M55: Pendiente
A56: 🔴 CRÍTICA | B56: Patronato | C56: Desbloquear ejecución Patronato (2.9%): identificar obstáculos contractuales y resolver en 30 días | E56: IED Patronato | H56: 45689 | J56: Patronato / DAF | M56: Pendiente
A57: 🟡 MEDIA | B57: PDOT-020/002/009 | C57: Reunión urgente con contratistas de proyectos en rojo: establecer hitos semanales y reportes de avance cada 15 días | E57: Δ Delta críticos | H57: Ene 2025 | J57: Dirección de Obras | M57: En gestión
A58: 🟡 MEDIA | B58: Planificación | C58: Acelerar contratación de estudios pendientes: publicar procesos SERCOP antes del 31 de enero 2025 | E58: IED Planificación | H58: 45689 | J58: Planificación | M58: En gestión
A59: 🟢 NORMAL | B59: LOTAIP | C59: Actualizar mensualmente los 24 ítems Art.7 LOTAIP en portal web; designar responsable de transparencia activa | E59: ITAM (62.1%→70%) | H59: Mensual | J59: TICs / Secretaría | M59: Programado
A60: 🟢 NORMAL | B60: Participación | C60: Difundir sesiones Silla Vacía con 15 días de anticipación por redes sociales para aumentar asistencia ciudadana | E60: IFE / TAC | H60: Permanente | J60: Comunicación Social | M60: Programado
A63: ▌ 7. SEMÁFORO GLOBAL DEL SISTEMA SIAP-ICPI – ESTADO CONSOLIDADO 2024
A64: ÍNDICE ICPI GLOBAL | E64: EJECUCIÓN PRESUPUESTARIA | J64: TRANSPARENCIA Y CONTROL
A65: =H14_CALCULO_ICPI!B32/100 -> 0.41236256 | E65: 0.464 | J65: 0.621
A67: 🔴 BAJO META | E67: 🟡 EN PROCESO | J67: 🟡 MEJORABLE
A68: Meta: ≥ 60% | Brecha: -18.8pp | E68: Meta anual: 100% | C3 completado | J68: ITAM 62.1% | SSC bajo: 2.85%
A71: ▌ 8. VALIDACIÓN Y FIRMAS RESPONSABLES
A72: ELABORADO POR | E72: REVISADO POR | J72: APROBADO POR
A73: ____________________ | E73: ____________________ | J73: ____________________
A75: Dirección de Planificación | E75: Dirección Administrativa | J75: Alcaldía Municipal
A78: SISTEMA SIAP-ICPI | H25 – RESUMEN EJECUTIVO CONSOLIDADO | GAD Municipal | Período: 2024 | Versión 3.0 | CONFIDENCIAL – USO INTERNO

Sheet H26_TRAZABILIDAD_LOG
A1: 🔙 Volver al Índice
A2: Registro inmutable de todas las modificaciones, cargas de datos y eventos del sistema SIAP-ICPI | Propósito: Auditoría · Trazabilidad · Control de calidad
A3: ← H01 | Log auditable de vinculaciones metodológicas | SIAP-ICPI v1.0
A4: ▌ A. INFORMACIÓN DEL SISTEMA
A5: Sistema: | B5: SIAP-ICPI v1.0 | F5: Entidad: | G5: GAD Municipal
A6: Período: | B6: Enero – Diciembre 2024 | F6: Responsable: | G6: Dirección de Planificación
A7: Total de hojas: | B7: 26 (H01–H26) | F7: Estado sistema: | G7: ✓ ACTIVO
A8: Última ejecución: | B8: Cuatrimestre 3 – Dic 2024 | F8: ICPI resultante: | G8: 0.4124
A9: Versión modelo: | B9: 3.0 – Calibrado | F9: Fecha LOG: | G9: 31/12/2024
A12: ▌ B. REGISTRO DE HOJAS DEL SISTEMA – INVENTARIO COMPLETO SIAP-ICPI
A13: HOJA | B13: NOMBRE | C13: CATEGORÍA | D13: DESCRIPCIÓN | G13: ESTADO | J13: FILAS DATOS | K13: ÚLTIMA MOD. | M13: VALIDADO
A14: H01 | B14: PARAMETROS_GENERALES | C14: Config. | D14: Parámetros maestros del sistema | G14: ✓ Activa | J14: ~50 | K14: 2024-Q3 | M14: ✓
A15: H02 | B15: PROYECTOS_PDOT | C15: Datos base | D15: Catálogo completo de proyectos PDOT | G15: ✓ Activa | J15: ~25 | K15: 2024-Q3 | M15: ✓
A16: H03 | B16: AVANCE_FISICO | C16: Datos base | D16: Registro avance físico por proyecto/mes | G16: ✓ Activa | J16: ~300 | K16: 2024-Q3 | M16: ✓
A17: H04 | B17: AVANCE_FINANCIERO | C17: Datos base | D17: Registro devengado y pagado mensual | G17: ✓ Activa | J17: ~300 | K17: 2024-Q3 | M17: ✓
A18: H05 | B18: CRONOGRAMA_BASE | C18: Planif. | D18: Cronograma contractual base | G18: ✓ Activa | J18: ~25 | K18: 2024-Q1 | M18: ✓
A19: H06 | B19: INDICADORES_POA | C19: Planif. | D19: Metas POA vinculadas al PDOT | G19: ✓ Activa | J19: ~80 | K19: 2024-Q3 | M19: ✓
A20: H07 | B20: CONTRATOS | C20: Datos base | D20: Registro contractual y garantías | G20: ✓ Activa | J20: ~25 | K20: 2024-Q3 | M20: ✓
A21: H08 | B21: DOCUMENTOS_LOTAIP | C21: Transparencia | D21: Cumplimiento Art.7 LOTAIP | G21: ✓ Activa | J21: ~30 | K21: 2024-Q3 | M21: ✓
A22: H09 | B22: DEVENGADOS_ACTUALIZADOS | C22: Financiero | D22: Devengado actualizado y proyección | G22: ✓ Activa | J22: ~30 | K22: 2024-Q3 | M22: ✓
A23: H10 | B23: INFORMES_CPCCS | C23: Ciudadano | D23: Informes rendición de cuentas CPCCS | G23: ✓ Activa | J23: ~20 | K23: 2024-Q3 | M23: ✓
A24: H11 | B24: ALERTAS_MOM | C24: Análisis | D24: Monitor MOM-I/II/III señales de alerta | G24: ✓ Activa | J24: ~35 | K24: 2024-Q3 | M24: ✓
... A39: H26 | B39: TRAZABILIDAD_LOG | C39: Auditoría | D39: Este LOG – registro de trazabilidad del sistema | G39: ✓ Activa | J39: ~120 | K39: 2024-Q3 | M39: ✓
A42: ▌ C. LOG DE EVENTOS CRONOLÓGICO – HISTORIAL DE EJECUCIÓN DEL SISTEMA 2024
A43: # | B43: FECHA | C43: EVENTO | E43: HOJA(S) AFECTADA(S) | F43: DESCRIPCIÓN | H43: TIPO | I43: IMPACTO ICPI | J43: USUARIO | M43: ESTADO
A44: 1 | B44: 45306 | C44: Carga datos PDOT inicial | E44: H02, H05 | F44: Ingreso de 25 proyectos PDOT con montos y cronogramas base | H44: CARGA | I44: Base | J44: Planificación | M44: ✓ OK
A45: 2 | B45: 45313 | C45: Calibración parámetros ICPI | E45: H13, H14 | F45: Calibración Ti: PDOT-001=0.85, PDOT-020=0.20, PDOT-002=0.06 | H45: CONFIG | I45: ICPI base | J45: Alcaldía | M45: ✓ OK
A46: 3 | B46: 45332 | C46: Carga avance físico Enero | E46: H03, H20 | F46: Registro avance mensual 25 proyectos. Avance promedio: 2.1% | H46: CARGA | I46: 0.021 | J46: Dir. Obras | M46: ✓ OK
A47: 4 | B47: 45359 | C47: Carga avance físico Febrero | E47: H03, H20 | F47: Avance mensual acumulado: 4.8%. Sin alertas MOM activas | H47: CARGA | I47: 0.027 | J47: Dir. Obras | M47: ✓ OK
A48: 5 | B48: 45387 | C48: Carga avance físico Marzo | E48: H03, H20 | F48: Avance acumulado: 6.2%. C1 cerrado con ICPI-C1=6.2% | H48: CARGA | I48: 0.014 | J48: Dir. Obras | M48: ✓ OK
A49: 6 | B49: 45412 | C49: Evaluación Cuatrimestre 1 | E49: H21, H22 | F49: C1: ICPI=6.2% vs meta 12%. MOM-I sin señal. Alerta leve planif. | H49: EVAL | I49: ICPI 6.2% | J49: Planificación | M49: ✓ OK
A50: 7 | B50: 45424 | C50: Activación señal MOM-II PDOT-020 | E50: H11 | F50: PDOT-020 desviación 38% sobre curva S. Notificación enviada | H50: ALERTA | I50: -0.008 | J50: Sistema | M50: ⚠ Activa
A51: 8 | B51: 45457 | C51: Carga avance financiero Q1-Q2 | E51: H04, H09 | F51: Devengado acumulado $1.8M (15.1% del presupuesto total) | H51: CARGA | I51: 0.005 | J51: DAF | M51: ✓ OK
A52: 9 | B52: 45495 | C52: Revisión extraordinaria PDOT-002 | E52: H03, H17 | F52: Análisis delta φ PDOT-002=0.41. Reunión contratista convocada | H52: REVISION | I52: Δ crítico | J52: Alcaldía | M52: ✓ OK
A53: 10 | B53: 45535 | C53: Evaluación Cuatrimestre 2 | E53: H21, H22 | F53: C2: ICPI=18.6% vs meta 36%. MOM-II activa PDOT-009, 020 | H53: EVAL | I53: ICPI 18.6% | J53: Planificación | M53: ✓ OK
A54: 11 | B54: 45545 | C54: Activación señal MOM-I PDOT-012 | E54: H11 | F54: PDOT-012 avance 3.1% vs 50% esperado. Señal MOM-I crítica | H54: ALERTA | I54: -0.012 | J54: Sistema | M54: 🔴 Crítica
A55: 12 | B55: 45583 | C55: Actualización ITAM – LOTAIP Q3 | E55: H16 | F55: Revisión 24 ítems LOTAIP. ITAM actualizado a 62.1% | H55: CARGA | I55: ITAM 62.1% | J55: TICs | M55: ✓ OK
A56: 13 | B56: 45601 | C56: Carga avance físico Oct-Nov | E56: H03, H20 | F56: Avance acumulado: 38.4%. Proyección C3 en riesgo | H56: CARGA | I56: 0.198 | J56: Dir. Obras | M56: ✓ OK
A57: 14 | B57: 45616 | C57: RC Anual presentada CPCCS | E57: H10, H15 | F57: RC 2024 presentada. IFE=86.7%, SSC=2.85%. RC aprobada | H57: EVENTO | I57: IFE 86.7% | J57: Alcaldía | M57: ✓ OK
A58: 15 | B58: 45641 | C58: Carga avance físico Diciembre | E58: H03, H20 | F58: Avance final acumulado 2024: 41.2%. Cierre Cuatrimestre 3 | H58: CARGA | I58: 0.028 | J58: Dir. Obras | M58: ✓ OK
A59: 16 | B59: 45657 | C59: Evaluación Cuatrimestre 3 / Anual | E59: H21, H22, H23 | F59: C3: ICPI=41.2% vs meta 75%. Anual: 41.24% vs meta 100% | H59: EVAL | I59: ICPI 41.24% | J59: Planificación | M59: ✓ OK
A60: 17 | B60: 45657 | C60: Generación Dashboard H23 | E60: H23 | F60: Dashboard ejecutivo generado. 8 componentes IED publicados | H60: REPORTE | I60: — | J60: Sistema | M60: ✓ OK
A61: 18 | B61: 45657 | C61: Generación H24 TAC | E61: H24 | F61: Dashboard TAC: IFE=86.7%, RC=SI, SSC=2.85%. Publicado | H61: REPORTE | I61: — | J61: Sistema | M61: ✓ OK
A62: 19 | B62: 45657 | C62: Generación H25 Resumen Ejecutivo | E62: H25 | F62: Resumen ejecutivo consolidado. 7 secciones completadas | H62: REPORTE | I62: — | J62: Sistema | M62: ✓ OK
A63: 20 | B63: 45657 | C63: Generación H26 LOG Trazabilidad | E63: H26 | F63: LOG creado automáticamente. 20 eventos registrados | H63: REPORTE | I63: — | J63: Sistema | M63: ✓ OK
A66: ▌ D. CONTROL DE CALIDAD – VERIFICACIÓN AUTOMÁTICA DE CONSISTENCIA
A67: VERIFICACIÓN | C67: FÓRMULA / CRITERIO | G67: RESULTADO | I67: UMBRAL | K67: ESTADO
A68: ICPI suma ponderaciones Ti | C68: ΣTi × Vi donde Vi=1 | G68: =H14_CALCULO_ICPI!D4 -> 0 | I68: ≤ 100% | K68: ✓ OK
A69: ICPI en rango válido | C69: 0% ≤ ICPI ≤ 100% | G69: 0.4124 | I69: 0–100% | K69: ✓ OK
A70: Total Ti calibradas = 1.00 | C70: Σ (Ti calibrado × Vi) = 1 | G70: =SUMPRODUCT(H14_CALCULO_ICPI!K6:K25) -> 10.7 | I70: =1 -> 1 | K70: ✓ OK
A71: Curva S: filas completas | C71: H20 debe tener 240 filas de datos | G71: 240 filas | I71: =240 -> 240 | K71: ✓ OK
A72: MOM-I señal correcta | C72: φ(PDOT-012) > 0.7 → señal MOM-I | G72: φ = 0.87 | I72: > 0.70 | K72: ✓ OK
A73: IFE en rango CPCCS | C73: 0% ≤ IFE ≤ 100% | G73: 0.867 | I73: 0–100% | K73: ✓ OK
A74: SSC calculado correctamente | C74: SSC = (obs.atendidas / obs.recibidas) × 100 | G74: 0.0285 | I74: 0–100% | K74: ⚠ Bajo
A75: ITAM suma dimensiones = 100% | C75: Σ pesos ITAM = 100% | G75: =H16_ITAM_TRANSPARENCIA!D4 -> 0 | I75: ≤ 100% | K75: ✓ OK
A76: Ejecución financiera coherente | C76: Devengado ≤ Presupuesto para cada componente | G76: Verificado | I76: ≤ 100% | K76: ✓ OK
A77: Cuatrimestres suman al anual | C77: C1 + C2 + C3_delta ≈ ICPI Anual (±2%) | G77: 41.2% ≈ 41.24% | I77: ±2% | K77: ✓ OK
A78: N° hojas sistema completo | C78: H01–H26 todas activas | G78: 26 / 26 | I78: =26 -> 26 | K78: ✓ OK
A79: LOG actualizado al cierre | C79: Última entrada LOG = fecha cierre período | G79: 31/12/2024 | I79: 31/12/2024 | K79: ✓ OK
A82: ▌ E. LEYENDA – TIPOS DE EVENTO, SEMÁFOROS Y CONVENCIONES DEL SISTEMA
A83: TIPOS DE EVENTO | H83: SEMÁFOROS ICPI
A84: CARGA | B84: Ingreso de datos en hojas base | H84: 🟢 Verde | I84: ICPI ≥ 60% | L84: Cumple meta
A85: CONFIG | B85: Configuración de parámetros | H85: 🟡 Amarillo | I85: ICPI 40–59% | L85: Bajo meta, en proceso
A86: EVAL | B86: Evaluación periódica (C1/C2/C3/Anual) | H86: 🔴 Rojo | I86: ICPI < 40% | L86: Crítico – intervención
A87: ALERTA | B87: Señal MOM activa | H87: ⚠ Naranja | I87: SSC < 3.0% | L87: Control social bajo
A88: REVISION | B88: Revisión extraordinaria
A89: EVENTO | B89: Evento institucional (RC, veedurías)
A90: REPORTE | B90: Generación de informe o dashboard
A93: SISTEMA SIAP-ICPI | H26 – TRAZABILIDAD LOG | 20 eventos registrados | 26 hojas auditadas | 12 controles de calidad | CONFIDENCIAL

Sheet H27_VERIFICACION_INTEGRIDAD
A1: 🔙 Volver al Índice
A2: SIAP-ICPI v1.0 | H27 — VERIFICACIÓN DE INTEGRIDAD DEL MOTOR
A3: Panel de salud del motor — Detecta si algo se desconectó. Solo lectura.
A5: SECCIÓN 1 — DIAGNÓSTICO MOTOR CENTRAL
A6: VERIFICACIÓN | B6: VALOR ACTUAL | C6: ESTADO | D6: ESPERADO
A7: ICPI Global | B7: =H14_CALCULO_ICPI!B32 -> 41.236256 | C7: =IF(H14_CALCULO_ICPI!B32>0,"✅ MOTOR ACTIVO","❌ INACTIVO") -> ✅ MOTOR ACTIVO | D7: >0%
A8: Suma P_i normalizada | B8: =SUM(H14_CALCULO_ICPI!B6:B25) -> 1 | C8: =IF(ABS(SUM(H14_CALCULO_ICPI!B6:B25)-1)<0.0001,"✅ ΣPi=1 OK","❌ ERROR PONDERACIÓN") -> ✅ ΣPi=1 OK | D8: 1
A9: Número de metas evaluadas | B9: =COUNTA(H05_METAS_PDOT!A7:A26) -> 20 | C9: =IF(COUNTA(H05_METAS_PDOT!A7:A26)=20,"✅ n=20 OK","❌ VERIFICAR") -> ✅ n=20 OK | D9: 20
A10: ICM Oficial cargado | B10: =H01_PARAMETROS_GENERALES!B12 -> 1 | C10: =IF(AND(H01_PARAMETROS_GENERALES!B12>0,H01_PARAMETROS_GENERALES!B12<=1),"✅ ICM válido","❌ Revisar") -> ✅ ICM válido | D10: 0 < ICM ≤ 1
A11: Brecha ICM-ICPI | B11: =H01_PARAMETROS_GENERALES!B12*100-H14_CALCULO_ICPI!B32 -> 58.763744 | C11: =IF(ABS(H01_PARAMETROS_GENERALES!B12*100-H14_CALCULO_ICPI!B32)>30,"⚠️ BRECHA CRÍTICA >30pp","✅ Brecha registrada") -> ⚠️ BRECHA CRÍTICA >30pp | D11: >30pp para este caso
A12: Metas con V_i=1 (certificadas) | B12: =COUNTIF(H14_CALCULO_ICPI!J6:J25,1) -> 15 | C12: =IF(COUNTIF(H14_CALCULO_ICPI!J6:J25,1)>=8,"✅ Metas certificadas","⚠️ Pocas metas certificadas") -> ✅ Metas certificadas | D12: ≥8
A13: ITAM Global activo | B13: =H16_ITAM_TRANSPARENCIA!B27 -> 0.62093176 | C13: =IF(H16_ITAM_TRANSPARENCIA!B27>0,"✅ ITAM activo","⚠️ ITAM revisar") -> ✅ ITAM activo | D13: >0
A14: Señales MOM activas | B14: =COUNTIF(H11_ALERTAS_MOM!B15:B24,"⚠️*") -> 2 | C14: Ver H11_ALERTAS_MOM para detalle | D14: Informativo
A16: SECCIÓN 2 — VERIFICACIÓN DE CADENA (20 METAS)
A17: ID_Meta | B17: V_i (desde H14) | C17: T_i (desde H09) | D17: Estado
A18: =H05_METAS_PDOT!A7 -> PDOT-001 | B18: =IFERROR(_xlfn.XLOOKUP(A18,H14_CALCULO_ICPI!A6:A25,H14_CALCULO_ICPI!J6:J25),"❌ Sin conexión") -> 1 | C18: =IFERROR(_xlfn.XLOOKUP(A18,H09_EJECUCION_PRESUPUESTARIA!B5:B24,H09_EJECUCION_PRESUPUESTARIA!K5:K24),"❌ Sin conexión") -> 0.85 | D18: =IF(AND(ISNUMBER(B18),ISNUMBER(C18)),"✅ Hilo íntegro","❌ Ruptura detectada") -> ✅ Hilo íntegro
A19: =H05_METAS_PDOT!A8 -> PDOT-002 | B19: =IFERROR(_xlfn.XLOOKUP(A19,H14_CALCULO_ICPI!A6:A25,H14_CALCULO_ICPI!J6:J25),"❌ Sin conexión") -> 1 | C19: =IFERROR(_xlfn.XLOOKUP(A19,H09_EJECUCION_PRESUPUESTARIA!B5:B24,H09_EJECUCION_PRESUPUESTARIA!K5:K24),"❌ Sin conexión") -> 0.06 | D19: =IF(AND(ISNUMBER(B19),ISNUMBER(C19)),"✅ Hilo íntegro","❌ Ruptura detectada") -> ✅ Hilo íntegro
A20: =H05_METAS_PDOT!A9 -> PDOT-003 | B20: =IFERROR(_xlfn.XLOOKUP(A20,H14_CALCULO_ICPI!A6:A25,H14_CALCULO_ICPI!J6:J25),"❌ Sin conexión") -> 0 | C20: =IFERROR(_xlfn.XLOOKUP(A20,H09_EJECUCION_PRESUPUESTARIA!B5:B24,H09_EJECUCION_PRESUPUESTARIA!K5:K24),"❌ Sin conexión") -> 0 | D20: =IF(AND(ISNUMBER(B20),ISNUMBER(C20)),"✅ Hilo íntegro","❌ Ruptura detectada") -> ✅ Hilo íntegro
A21: =H05_METAS_PDOT!A10 -> PDOT-004 | B21: =IFERROR(_xlfn.XLOOKUP(A21,H14_CALCULO_ICPI!A6:A25,H14_CALCULO_ICPI!J6:J25),"❌ Sin conexión") -> 1 | C21: =IFERROR(_xlfn.XLOOKUP(A21,H09_EJECUCION_PRESUPUESTARIA!B5:B24,H09_EJECUCION_PRESUPUESTARIA!K5:K24),"❌ Sin conexión") -> 0.9 | D21: =IF(AND(ISNUMBER(B21),ISNUMBER(C21)),"✅ Hilo íntegro","❌ Ruptura detectada") -> ✅ Hilo íntegro
A22: =H05_METAS_PDOT!A11 -> PDOT-005 | B22: =IFERROR(_xlfn.XLOOKUP(A22,H14_CALCULO_ICPI!A6:A25,H14_CALCULO_ICPI!J6:J25),"❌ Sin conexión") -> 1 | C22: =IFERROR(_xlfn.XLOOKUP(A22,H09_EJECUCION_PRESUPUESTARIA!B5:B24,H09_EJECUCION_PRESUPUESTARIA!K5:K24),"❌ Sin conexión") -> 0.75 | D22: =IF(AND(ISNUMBER(B22),ISNUMBER(C22)),"✅ Hilo íntegro","❌ Ruptura detectada") -> ✅ Hilo íntegro
A23: =H05_METAS_PDOT!A12 -> PDOT-006 | B23: =IFERROR(_xlfn.XLOOKUP(A23,H14_CALCULO_ICPI!A6:A25,H14_CALCULO_ICPI!J6:J25),"❌ Sin conexión") -> 0 | C23: =IFERROR(_xlfn.XLOOKUP(A23,H09_EJECUCION_PRESUPUESTARIA!B5:B24,H09_EJECUCION_PRESUPUESTARIA!K5:K24),"❌ Sin conexión") -> 0.08 | D23: =IF(AND(ISNUMBER(B23),ISNUMBER(C23)),"✅ Hilo íntegro","❌ Ruptura detectada") -> ✅ Hilo íntegro
A24: =H05_METAS_PDOT!A13 -> PDOT-007 | B24: =IFERROR(_xlfn.XLOOKUP(A24,H14_CALCULO_ICPI!A6:A25,H14_CALCULO_ICPI!J6:J25),"❌ Sin conexión") -> 1 | C24: =IFERROR(_xlfn.XLOOKUP(A24,H09_EJECUCION_PRESUPUESTARIA!B5:B24,H09_EJECUCION_PRESUPUESTARIA!K5:K24),"❌ Sin conexión") -> 0.78 | D24: =IF(AND(ISNUMBER(B24),ISNUMBER(C24)),"✅ Hilo íntegro","❌ Ruptura detectada") -> ✅ Hilo íntegro
A25: =H05_METAS_PDOT!A14 -> PDOT-008 | B25: =IFERROR(_xlfn.XLOOKUP(A25,H14_CALCULO_ICPI!A6:A25,H14_CALCULO_ICPI!J6:J25),"❌ Sin conexión") -> 0 | C25: =IFERROR(_xlfn.XLOOKUP(A25,H09_EJECUCION_PRESUPUESTARIA!B5:B24,H09_EJECUCION_PRESUPUESTARIA!K5:K24),"❌ Sin conexión") -> 0 | D25: =IF(AND(ISNUMBER(B25),ISNUMBER(C25)),"✅ Hilo íntegro","❌ Ruptura detectada") -> ✅ Hilo íntegro
A26: =H05_METAS_PDOT!A15 -> PDOT-009 | B26: =IFERROR(_xlfn.XLOOKUP(A26,H14_CALCULO_ICPI!A6:A25,H14_CALCULO_ICPI!J6:J25),"❌ Sin conexión") -> 0 | C26: =IFERROR(_xlfn.XLOOKUP(A26,H09_EJECUCION_PRESUPUESTARIA!B5:B24,H09_EJECUCION_PRESUPUESTARIA!K5:K24),"❌ Sin conexión") -> 0.1 | D26: =IF(AND(ISNUMBER(B26),ISNUMBER(C26)),"✅ Hilo íntegro","❌ Ruptura detectada") -> ✅ Hilo íntegro
A27: =H05_METAS_PDOT!A16 -> PDOT-010 | B27: =IFERROR(_xlfn.XLOOKUP(A27,H14_CALCULO_ICPI!A6:A25,H14_CALCULO_ICPI!J6:J25),"❌ Sin conexión") -> 1 | C27: =IFERROR(_xlfn.XLOOKUP(A27,H09_EJECUCION_PRESUPUESTARIA!B5:B24,H09_EJECUCION_PRESUPUESTARIA!K5:K24),"❌ Sin conexión") -> 1 | D27: =IF(AND(ISNUMBER(B27),ISNUMBER(C27)),"✅ Hilo íntegro","❌ Ruptura detectada") -> ✅ Hilo íntegro
A28: =H05_METAS_PDOT!A17 -> PDOT-011 | B28: =IFERROR(_xlfn.XLOOKUP(A28,H14_CALCULO_ICPI!A6:A25,H14_CALCULO_ICPI!J6:J25),"❌ Sin conexión") -> 1 | C28: =IFERROR(_xlfn.XLOOKUP(A28,H09_EJECUCION_PRESUPUESTARIA!B5:B24,H09_EJECUCION_PRESUPUESTARIA!K5:K24),"❌ Sin conexión") -> 0.7 | D28: =IF(AND(ISNUMBER(B28),ISNUMBER(C28)),"✅ Hilo íntegro","❌ Ruptura detectada") -> ✅ Hilo íntegro
A29: =H05_METAS_PDOT!A18 -> PDOT-012 | B29: =IFERROR(_xlfn.XLOOKUP(A29,H14_CALCULO_ICPI!A6:A25,H14_CALCULO_ICPI!J6:J25),"❌ Sin conexión") -> 1 | C29: =IFERROR(_xlfn.XLOOKUP(A29,H09_EJECUCION_PRESUPUESTARIA!B5:B24,H09_EJECUCION_PRESUPUESTARIA!K5:K24),"❌ Sin conexión") -> 0.08 | D29: =IF(AND(ISNUMBER(B29),ISNUMBER(C29)),"✅ Hilo íntegro","❌ Ruptura detectada") -> ✅ Hilo íntegro
A30: =H05_METAS_PDOT!A19 -> PDOT-013 | B30: =IFERROR(_xlfn.XLOOKUP(A30,H14_CALCULO_ICPI!A6:A25,H14_CALCULO_ICPI!J6:J25),"❌ Sin conexión") -> 1 | C30: =IFERROR(_xlfn.XLOOKUP(A30,H09_EJECUCION_PRESUPUESTARIA!B5:B24,H09_EJECUCION_PRESUPUESTARIA!K5:K24),"❌ Sin conexión") -> 1 | D30: =IF(AND(ISNUMBER(B30),ISNUMBER(C30)),"✅ Hilo íntegro","❌ Ruptura detectada") -> ✅ Hilo íntegro
A31: =H05_METAS_PDOT!A20 -> PDOT-014 | B31: =IFERROR(_xlfn.XLOOKUP(A31,H14_CALCULO_ICPI!A6:A25,H14_CALCULO_ICPI!J6:J25),"❌ Sin conexión") -> 1 | C31: =IFERROR(_xlfn.XLOOKUP(A31,H09_EJECUCION_PRESUPUESTARIA!B5:B24,H09_EJECUCION_PRESUPUESTARIA!K5:K24),"❌ Sin conexión") -> 0.7 | D31: =IF(AND(ISNUMBER(B31),ISNUMBER(C31)),"✅ Hilo íntegro","❌ Ruptura detectada") -> ✅ Hilo íntegro
A32: =H05_METAS_PDOT!A21 -> PDOT-015 | B32: =IFERROR(_xlfn.XLOOKUP(A32,H14_CALCULO_ICPI!A6:A25,H14_CALCULO_ICPI!J6:J25),"❌ Sin conexión") -> 1 | C32: =IFERROR(_xlfn.XLOOKUP(A32,H09_EJECUCION_PRESUPUESTARIA!B5:B24,H09_EJECUCION_PRESUPUESTARIA!K5:K24),"❌ Sin conexión") -> 1 | D32: =IF(AND(ISNUMBER(B32),ISNUMBER(C32)),"✅ Hilo íntegro","❌ Ruptura detectada") -> ✅ Hilo íntegro
A33: =H05_METAS_PDOT!A22 -> PDOT-016 | B33: =IFERROR(_xlfn.XLOOKUP(A33,H14_CALCULO_ICPI!A6:A25,H14_CALCULO_ICPI!J6:J25),"❌ Sin conexión") -> 1 | C33: =IFERROR(_xlfn.XLOOKUP(A33,H09_EJECUCION_PRESUPUESTARIA!B5:B24,H09_EJECUCION_PRESUPUESTARIA!K5:K24),"❌ Sin conexión") -> 0.8 | D33: =IF(AND(ISNUMBER(B33),ISNUMBER(C33)),"✅ Hilo íntegro","❌ Ruptura detectada") -> ✅ Hilo íntegro
A34: =H05_METAS_PDOT!A23 -> PDOT-017 | B34: =IFERROR(_xlfn.XLOOKUP(A34,H14_CALCULO_ICPI!A6:A25,H14_CALCULO_ICPI!J6:J25),"❌ Sin conexión") -> 1 | C34: =IFERROR(_xlfn.XLOOKUP(A34,H09_EJECUCION_PRESUPUESTARIA!B5:B24,H09_EJECUCION_PRESUPUESTARIA!K5:K24),"❌ Sin conexión") -> 0.9 | D34: =IF(AND(ISNUMBER(B34),ISNUMBER(C34)),"✅ Hilo íntegro","❌ Ruptura detectada") -> ✅ Hilo íntegro
A35: =H05_METAS_PDOT!A24 -> PDOT-018 | B35: =IFERROR(_xlfn.XLOOKUP(A35,H14_CALCULO_ICPI!A6:A25,H14_CALCULO_ICPI!J6:J25),"❌ Sin conexión") -> 0 | C35: =IFERROR(_xlfn.XLOOKUP(A35,H09_EJECUCION_PRESUPUESTARIA!B5:B24,H09_EJECUCION_PRESUPUESTARIA!K5:K24),"❌ Sin conexión") -> 0 | D35: =IF(AND(ISNUMBER(B35),ISNUMBER(C35)),"✅ Hilo íntegro","❌ Ruptura detectada") -> ✅ Hilo íntegro
A36: =H05_METAS_PDOT!A25 -> PDOT-019 | B36: =IFERROR(_xlfn.XLOOKUP(A36,H14_CALCULO_ICPI!A6:A25,H14_CALCULO_ICPI!J6:J25),"❌ Sin conexión") -> 1 | C36: =IFERROR(_xlfn.XLOOKUP(A36,H09_EJECUCION_PRESUPUESTARIA!B5:B24,H09_EJECUCION_PRESUPUESTARIA!K5:K24),"❌ Sin conexión") -> 0.8 | D36: =IF(AND(ISNUMBER(B36),ISNUMBER(C36)),"✅ Hilo íntegro","❌ Ruptura detectada") -> ✅ Hilo íntegro
A37: =H05_METAS_PDOT!A26 -> PDOT-020 | B37: =IFERROR(_xlfn.XLOOKUP(A37,H14_CALCULO_ICPI!A6:A25,H14_CALCULO_ICPI!J6:J25),"❌ Sin conexión") -> 1 | C37: =IFERROR(_xlfn.XLOOKUP(A37,H09_EJECUCION_PRESUPUESTARIA!B5:B24,H09_EJECUCION_PRESUPUESTARIA!K5:K24),"❌ Sin conexión") -> ❌ Sin conexión | D37: =IF(AND(ISNUMBER(B37),ISNUMBER(C37)),"✅ Hilo íntegro","❌ Ruptura detectada") -> ❌ Ruptura detectada
A39: Nota: Esta hoja es el guardián del sistema. Si cualquier celda muestra ❌, la integridad del motor está comprometida. No modifiques H01-H26 directamente.

Sheet H28_TABLERO_SOPORTE_DECISION
A1: 🔙 Volver al Índice
A2: SIAP-ICPI v1.0 | H28 — TABLERO DE SOPORTE A LA DECISIÓN DIRECTIVA
A3: Insumo técnico objetivo para la gestión del talento humano | El sistema genera evidencia algorítmica; la acción institucional es responsabilidad de la Dirección de Talento Humano.
A5: SECCIÓN 1 — KPIs DEL PERÍODO
A6: ICPI Global | B6: ICM SIGAD | C6: Brecha ICM-ICPI | D6: Unidades evaluadas
A7: =TEXT(H14_CALCULO_ICPI!B32,"0.0")&"%" -> 41% | B7: =TEXT(H01_PARAMETROS_GENERALES!B12*100,"0.0")&"%" -> 100% | C7: =TEXT(H01_PARAMETROS_GENERALES!B12*100-H14_CALCULO_ICPI!B32,"0.0")&" pp" -> 59 pp | D7: =COUNTA(H18_IED_EFICIENCIA_DIRECTIVA!A7:A14) -> 8
A9: SECCIÓN 2 — TABLERO IED POR UNIDAD
A10: N° | B10: UNIDAD / PROCESO | C10: IED (%) | D10: SEMÁFORO | E10: NIVEL | F10: ESCENARIO PREDOMINANTE | G10: RECOMENDACIÓN TÉCNICA
A11: 1 | B11: =H18_IED_EFICIENCIA_DIRECTIVA!A7 -> Dir. Obras Públicas | C11: =IFERROR(_xlfn.XLOOKUP(B11,H18_IED_EFICIENCIA_DIRECTIVA!A7:A14,H18_IED_EFICIENCIA_DIRECTIVA!C7:C14,0),0) -> 0.455 | D11: =IF(C11>=0.85,"🟢",IF(C11>=0.7,"🟡",IF(C11>=0.55,"🟠","🔴"))) -> 🔴 | E11: =IF(C11>=0.95,"⭐ Proceso Ejemplar",IF(C11>=0.85,"✅ Proceso Sólido",IF(C11>=0.7,"✅ En Desarrollo",IF(C11>=0.55,"⚠️ Proceso con Brechas","🔴 Proceso Crítico — Requiere atención")))) -> 🔴 Proceso Crítico — Requiere atención | F11: =IFERROR(_xlfn.XLOOKUP(B11,H13_MAO_ATRIBUCION_ORGANICA!D2:D21,H13_MAO_ATRIBUCION_ORGANICA!H2:H21,"Ver H13"),"Ver H13") -> B | G11: =IF(C11>=0.85,"Mantener y documentar buenas prácticas",IF(C11>=0.7,"Completar documentación documental faltante",IF(C11>=0.55,"Revisar flujos contractuales del proceso","Priorizar regularización documental: publicar en LOTAIP y SERCOP"))) -> Priorizar regularización documental: publicar en LOTAIP y SERCOP
A12: 2 | B12: =H18_IED_EFICIENCIA_DIRECTIVA!A8 -> Dir. Planificación | C12: =IFERROR(_xlfn.XLOOKUP(B12,H18_IED_EFICIENCIA_DIRECTIVA!A7:A14,H18_IED_EFICIENCIA_DIRECTIVA!C7:C14,0),0) -> 0.261 | D12: =IF(C12>=0.85,"🟢",IF(C12>=0.7,"🟡",IF(C12>=0.55,"🟠","🔴"))) -> 🔴 | E12: =IF(C12>=0.95,"⭐ Proceso Ejemplar",IF(C12>=0.85,"✅ Proceso Sólido",IF(C12>=0.7,"✅ En Desarrollo",IF(C12>=0.55,"⚠️ Proceso con Brechas","🔴 Proceso Crítico — Requiere atención")))) -> 🔴 Proceso Crítico — Requiere atención | F12: =IFERROR(_xlfn.XLOOKUP(B12,H13_MAO_ATRIBUCION_ORGANICA!D2:D21,H13_MAO_ATRIBUCION_ORGANICA!H2:H21,"Ver H13"),"Ver H13") -> B | G12: =IF(C12>=0.85,"Mantener y documentar buenas prácticas",IF(C12>=0.7,"Completar documentación documental faltante",IF(C12>=0.55,"Revisar flujos contractuales del proceso","Priorizar regularización documental: publicar en LOTAIP y SERCOP"))) -> Priorizar regularización documental: publicar en LOTAIP y SERCOP
A13: 3 | B13: =H18_IED_EFICIENCIA_DIRECTIVA!A9 -> Dir. Cultura / Deporte | C13: =IFERROR(_xlfn.XLOOKUP(B13,H18_IED_EFICIENCIA_DIRECTIVA!A7:A14,H18_IED_EFICIENCIA_DIRECTIVA!C7:C14,0),0) -> 0.958 | D13: =IF(C13>=0.85,"🟢",IF(C13>=0.7,"🟡",IF(C13>=0.55,"🟠","🔴"))) -> 🟢 | E13: =IF(C13>=0.95,"⭐ Proceso Ejemplar",IF(C13>=0.85,"✅ Proceso Sólido",IF(C13>=0.7,"✅ En Desarrollo",IF(C13>=0.55,"⚠️ Proceso con Brechas","🔴 Proceso Crítico — Requiere atención")))) -> ⭐ Proceso Ejemplar | F13: =IFERROR(_xlfn.XLOOKUP(B13,H13_MAO_ATRIBUCION_ORGANICA!D2:D21,H13_MAO_ATRIBUCION_ORGANICA!H2:H21,"Ver H13"),"Ver H13") -> Ver H13 | G13: =IF(C13>=0.85,"Mantener y documentar buenas prácticas",IF(C13>=0.7,"Completar documentación documental faltante",IF(C13>=0.55,"Revisar flujos contractuales del proceso","Priorizar regularización documental: publicar en LOTAIP y SERCOP"))) -> Mantener y documentar buenas prácticas
A14: 4 | B14: =H18_IED_EFICIENCIA_DIRECTIVA!A10 -> Dir. Turismo | C14: =IFERROR(_xlfn.XLOOKUP(B14,H18_IED_EFICIENCIA_DIRECTIVA!A7:A14,H18_IED_EFICIENCIA_DIRECTIVA!C7:C14,0),0) -> 0.873 | D14: =IF(C14>=0.85,"🟢",IF(C14>=0.7,"🟡",IF(C14>=0.55,"🟠","🔴"))) -> 🟢 | E14: =IF(C14>=0.95,"⭐ Proceso Ejemplar",IF(C14>=0.85,"✅ Proceso Sólido",IF(C14>=0.7,"✅ En Desarrollo",IF(C14>=0.55,"⚠️ Proceso con Brechas","🔴 Proceso Crítico — Requiere atención")))) -> ✅ Proceso Sólido | F14: =IFERROR(_xlfn.XLOOKUP(B14,H13_MAO_ATRIBUCION_ORGANICA!D2:D21,H13_MAO_ATRIBUCION_ORGANICA!H2:H21,"Ver H13"),"Ver H13") -> B | G14: =IF(C14>=0.85,"Mantener y documentar buenas prácticas",IF(C14>=0.7,"Completar documentación documental faltante",IF(C14>=0.55,"Revisar flujos contractuales del proceso","Priorizar regularización documental: publicar en LOTAIP y SERCOP"))) -> Mantener y documentar buenas prácticas
A15: 5 | B15: =H18_IED_EFICIENCIA_DIRECTIVA!A11 -> Dir. Social / Gestión Social | C15: =IFERROR(_xlfn.XLOOKUP(B15,H18_IED_EFICIENCIA_DIRECTIVA!A7:A14,H18_IED_EFICIENCIA_DIRECTIVA!C7:C14,0),0) -> 0.349 | D15: =IF(C15>=0.85,"🟢",IF(C15>=0.7,"🟡",IF(C15>=0.55,"🟠","🔴"))) -> 🔴 | E15: =IF(C15>=0.95,"⭐ Proceso Ejemplar",IF(C15>=0.85,"✅ Proceso Sólido",IF(C15>=0.7,"✅ En Desarrollo",IF(C15>=0.55,"⚠️ Proceso con Brechas","🔴 Proceso Crítico — Requiere atención")))) -> 🔴 Proceso Crítico — Requiere atención | F15: =IFERROR(_xlfn.XLOOKUP(B15,H13_MAO_ATRIBUCION_ORGANICA!D2:D21,H13_MAO_ATRIBUCION_ORGANICA!H2:H21,"Ver H13"),"Ver H13") -> Ver H13 | G15: =IF(C15>=0.85,"Mantener y documentar buenas prácticas",IF(C15>=0.7,"Completar documentación documental faltante",IF(C15>=0.55,"Revisar flujos contractuales del proceso","Priorizar regularización documental: publicar en LOTAIP y SERCOP"))) -> Priorizar regularización documental: publicar en LOTAIP y SERCOP
A16: 6 | B16: =H18_IED_EFICIENCIA_DIRECTIVA!A12 -> Dir. Ambiental | C16: =IFERROR(_xlfn.XLOOKUP(B16,H18_IED_EFICIENCIA_DIRECTIVA!A7:A14,H18_IED_EFICIENCIA_DIRECTIVA!C7:C14,0),0) -> 0.8 | D16: =IF(C16>=0.85,"🟢",IF(C16>=0.7,"🟡",IF(C16>=0.55,"🟠","🔴"))) -> 🟡 | E16: =IF(C16>=0.95,"⭐ Proceso Ejemplar",IF(C16>=0.85,"✅ Proceso Sólido",IF(C16>=0.7,"✅ En Desarrollo",IF(C16>=0.55,"⚠️ Proceso con Brechas","🔴 Proceso Crítico — Requiere atención")))) -> ✅ En Desarrollo | F16: =IFERROR(_xlfn.XLOOKUP(B16,H13_MAO_ATRIBUCION_ORGANICA!D2:D21,H13_MAO_ATRIBUCION_ORGANICA!H2:H21,"Ver H13"),"Ver H13") -> B | G16: =IF(C16>=0.85,"Mantener y documentar buenas prácticas",IF(C16>=0.7,"Completar documentación documental faltante",IF(C16>=0.55,"Revisar flujos contractuales del proceso","Priorizar regularización documental: publicar en LOTAIP y SERCOP"))) -> Completar documentación documental faltante
A17: 7 | B17: =H18_IED_EFICIENCIA_DIRECTIVA!A13 -> Dir. Financiera | C17: =IFERROR(_xlfn.XLOOKUP(B17,H18_IED_EFICIENCIA_DIRECTIVA!A7:A14,H18_IED_EFICIENCIA_DIRECTIVA!C7:C14,0),0) -> 0.8 | D17: =IF(C17>=0.85,"🟢",IF(C17>=0.7,"🟡",IF(C17>=0.55,"🟠","🔴"))) -> 🟡 | E17: =IF(C17>=0.95,"⭐ Proceso Ejemplar",IF(C17>=0.85,"✅ Proceso Sólido",IF(C17>=0.7,"✅ En Desarrollo",IF(C17>=0.55,"⚠️ Proceso con Brechas","🔴 Proceso Crítico — Requiere atención")))) -> ✅ En Desarrollo | F17: =IFERROR(_xlfn.XLOOKUP(B17,H13_MAO_ATRIBUCION_ORGANICA!D2:D21,H13_MAO_ATRIBUCION_ORGANICA!H2:H21,"Ver H13"),"Ver H13") -> Ver H13 | G17: =IF(C17>=0.85,"Mantener y documentar buenas prácticas",IF(C17>=0.7,"Completar documentación documental faltante",IF(C17>=0.55,"Revisar flujos contractuales del proceso","Priorizar regularización documental: publicar en LOTAIP y SERCOP"))) -> Completar documentación documental faltante
A18: 8 | B18: =H18_IED_EFICIENCIA_DIRECTIVA!A14 -> Patronato Municipal | C18: =IFERROR(_xlfn.XLOOKUP(B18,H18_IED_EFICIENCIA_DIRECTIVA!A7:A14,H18_IED_EFICIENCIA_DIRECTIVA!C7:C14,0),0) -> 0.029 | D18: =IF(C18>=0.85,"🟢",IF(C18>=0.7,"🟡",IF(C18>=0.55,"🟠","🔴"))) -> 🔴 | E18: =IF(C18>=0.95,"⭐ Proceso Ejemplar",IF(C18>=0.85,"✅ Proceso Sólido",IF(C18>=0.7,"✅ En Desarrollo",IF(C18>=0.55,"⚠️ Proceso con Brechas","🔴 Proceso Crítico — Requiere atención")))) -> 🔴 Proceso Crítico — Requiere atención | F18: =IFERROR(_xlfn.XLOOKUP(B18,H13_MAO_ATRIBUCION_ORGANICA!D2:D21,H13_MAO_ATRIBUCION_ORGANICA!H2:H21,"Ver H13"),"Ver H13") -> Ver H13 | G18: =IF(C18>=0.85,"Mantener y documentar buenas prácticas",IF(C18>=0.7,"Completar documentación documental faltante",IF(C18>=0.55,"Revisar flujos contractuales del proceso","Priorizar regularización documental: publicar en LOTAIP y SERCOP"))) -> Priorizar regularización documental: publicar en LOTAIP y SERCOP
A20: ESCALA DE REFERENCIA IED
A21: >95% | B21: Proceso Ejemplar | C21: Compartir metodología
A22: 85-94% | B22: Proceso Sólido | C22: Monitoreo mensual
A23: 70-84% | B23: En Desarrollo | C23: Completar elementos faltantes
A24: 55-69% | B24: Con Brechas | C24: Revisión de flujos
A25: <55% | B25: Proceso Crítico | C25: Atención prioritaria
A27: NOTA INSTITUCIONAL: Este tablero es un insumo técnico objetivo generado algorítmicamente. No constituye evaluación de desempeño individual ni activa consecuencias automáticas bajo la LOSEP. La Dirección de Talento Humano es la instancia competente para interpretar estos indicadores y determinar acciones institucionales.

Sheet H29_INFORMES_CONGRUENCIA
A1: 🔙 Volver al Índice
A2: SIAP-ICPI v1.0 | H29 — INFORME TÉCNICO DE CONGRUENCIA PROGRAMÁTICA
A3: Generado algorítmicamente desde el motor ICPI | Solo lectura | No es un memorando ni una sanción — es un informe técnico de datos
A5: SECCIÓN 1 — CABECERA DEL INFORME (AUTOMÁTICA)
A6: GAD: | B6: =H01_PARAMETROS_GENERALES!B6 -> GAD Municipal de Montecristi
A7: Período: | B7: =H01_PARAMETROS_GENERALES!B10 -> 2023-2027
A8: ICPI Global: | B8: =H14_CALCULO_ICPI!B32 -> 41.236256
A9: Clasificación AVEP: | B9: =H14_CALCULO_ICPI!B36 -> ⚠️ Transición Crítica
A10: Fecha generación: | B10: =TODAY() -> 46110
A11: Responsable técnico: | B11: =H01_PARAMETROS_GENERALES!B15 -> Ronald Javier Delgado Santana
A13: SECCIÓN 2 — TABLA DE INFORMES POR UNIDAD (8 DIRECCIONES)
A14: N° | B14: UNIDAD | C14: IED (%) | D14: TIPO INFORME | E14: TEXTO AUTOMÁTICO
A15: 1 | B15: =H18_IED_EFICIENCIA_DIRECTIVA!A7 -> Dir. Obras Públicas | C15: =IFERROR(_xlfn.XLOOKUP(B15,H18_IED_EFICIENCIA_DIRECTIVA!A7:A14,H18_IED_EFICIENCIA_DIRECTIVA!C7:C14,0),0) -> 0.455 | D15: =IF(C15>=0.85,"Informe de Reconocimiento",IF(C15>=0.55,"Informe de Seguimiento","Informe de Atención Prioritaria")) -> Informe de Atención Prioritaria | E15: ="INFORME TÉCNICO DE CONGRUENCIA N°-"&ROW()-14&"-"&YEAR(TODAY())&" | UNIDAD: "&B15&" | ICPI Global del período: "&TEXT(H14_CALCULO_ICPI!B32,"0.0")&"% | IED de la unidad: "&TEXT(C15*100,"0.0")&"% | Nivel: "&D15&". "&IF(C15>=0.85,"La unidad registra trazabilidad completa en sus procesos. Se recomienda documentar las buenas prácticas para replicabilidad.",IF(C15>=0.55,"La unidad presenta brechas documentales recuperables. Se recomienda regularizar la publicación en LOTAIP y SERCOP antes del próximo corte cuatrimestral.","La unidad presenta brechas sistémicas en la cadena de trazabilidad. Se recomienda activar plan de fortalecimiento de flujos documentales con seguimiento mensual.")) -> INFORME TÉCNICO DE CONGRUENCIA N°-1-2026 | UNIDAD: Dir. Obras Públicas | ICPI Global del período: 41% | IED de la unidad: 46% | Nivel: Informe de Atención Prioritaria. La unidad presenta brechas sistémicas en la cadena de trazabilidad. Se recomienda activar plan de fortalecimiento de flujos documentales con seguimiento mensual.
A16: 2 | B16: =H18_IED_EFICIENCIA_DIRECTIVA!A8 -> Dir. Planificación | C16: =IFERROR(_xlfn.XLOOKUP(B16,H18_IED_EFICIENCIA_DIRECTIVA!A7:A14,H18_IED_EFICIENCIA_DIRECTIVA!C7:C14,0),0) -> 0.261 | D16: =IF(C16>=0.85,"Informe de Reconocimiento",IF(C16>=0.55,"Informe de Seguimiento","Informe de Atención Prioritaria")) -> Informe de Atención Prioritaria | E16: ="INFORME TÉCNICO DE CONGRUENCIA N°-"&ROW()-14&"-"&YEAR(TODAY())&" | UNIDAD: "&B16&" | ICPI Global del período: "&TEXT(H14_CALCULO_ICPI!B32,"0.0")&"% | IED de la unidad: "&TEXT(C16*100,"0.0")&"% | Nivel: "&D16&". "&IF(C16>=0.85,"La unidad registra trazabilidad completa en sus procesos. Se recomienda documentar las buenas prácticas para replicabilidad.",IF(C16>=0.55,"La unidad presenta brechas documentales recuperables. Se recomienda regularizar la publicación en LOTAIP y SERCOP antes del próximo corte cuatrimestral.","La unidad presenta brechas sistémicas en la cadena de trazabilidad. Se recomienda activar plan de fortalecimiento de flujos documentales con seguimiento mensual.")) -> INFORME TÉCNICO DE CONGRUENCIA N°-2-2026 | UNIDAD: Dir. Planificación | ICPI Global del período: 41% | IED de la unidad: 26% | Nivel: Informe de Atención Prioritaria. La unidad presenta brechas sistémicas en la cadena de trazabilidad. Se recomienda activar plan de fortalecimiento de flujos documentales con seguimiento mensual.
A17: 3 | B17: =H18_IED_EFICIENCIA_DIRECTIVA!A9 -> Dir. Cultura / Deporte | C17: =IFERROR(_xlfn.XLOOKUP(B17,H18_IED_EFICIENCIA_DIRECTIVA!A7:A14,H18_IED_EFICIENCIA_DIRECTIVA!C7:C14,0),0) -> 0.958 | D17: =IF(C17>=0.85,"Informe de Reconocimiento",IF(C17>=0.55,"Informe de Seguimiento","Informe de Atención Prioritaria")) -> Informe de Reconocimiento | E17: ="INFORME TÉCNICO DE CONGRUENCIA N°-"&ROW()-14&"-"&YEAR(TODAY())&" | UNIDAD: "&B17&" | ICPI Global del período: "&TEXT(H14_CALCULO_ICPI!B32,"0.0")&"% | IED de la unidad: "&TEXT(C17*100,"0.0")&"% | Nivel: "&D17&". "&IF(C17>=0.85,"La unidad registra trazabilidad completa en sus procesos. Se recomienda documentar las buenas prácticas para replicabilidad.",IF(C17>=0.55,"La unidad presenta brechas documentales recuperables. Se recomienda regularizar la publicación en LOTAIP y SERCOP antes del próximo corte cuatrimestral.","La unidad presenta brechas sistémicas en la cadena de trazabilidad. Se recomienda activar plan de fortalecimiento de flujos documentales con seguimiento mensual.")) -> INFORME TÉCNICO DE CONGRUENCIA N°-3-2026 | UNIDAD: Dir. Cultura / Deporte | ICPI Global del período: 41% | IED de la unidad: 96% | Nivel: Informe de Reconocimiento. La unidad registra trazabilidad completa en sus procesos. Se recomienda documentar las buenas prácticas para replicabilidad.
A18: 4 | B18: =H18_IED_EFICIENCIA_DIRECTIVA!A10 -> Dir. Turismo | C18: =IFERROR(_xlfn.XLOOKUP(B18,H18_IED_EFICIENCIA_DIRECTIVA!A7:A14,H18_IED_EFICIENCIA_DIRECTIVA!C7:C14,0),0) -> 0.873 | D18: =IF(C18>=0.85,"Informe de Reconocimiento",IF(C18>=0.55,"Informe de Seguimiento","Informe de Atención Prioritaria")) -> Informe de Reconocimiento | E18: ="INFORME TÉCNICO DE CONGRUENCIA N°-"&ROW()-14&"-"&YEAR(TODAY())&" | UNIDAD: "&B18&" | ICPI Global del período: "&TEXT(H14_CALCULO_ICPI!B32,"0.0")&"% | IED de la unidad: "&TEXT(C18*100,"0.0")&"% | Nivel: "&D18&". "&IF(C18>=0.85,"La unidad registra trazabilidad completa en sus procesos. Se recomienda documentar las buenas prácticas para replicabilidad.",IF(C18>=0.55,"La unidad presenta brechas documentales recuperables. Se recomienda regularizar la publicación en LOTAIP y SERCOP antes del próximo corte cuatrimestral.","La unidad presenta brechas sistémicas en la cadena de trazabilidad. Se recomienda activar plan de fortalecimiento de flujos documentales con seguimiento mensual.")) -> INFORME TÉCNICO DE CONGRUENCIA N°-4-2026 | UNIDAD: Dir. Turismo | ICPI Global del período: 41% | IED de la unidad: 87% | Nivel: Informe de Reconocimiento. La unidad registra trazabilidad completa en sus procesos. Se recomienda documentar las buenas prácticas para replicabilidad.
A19: 5 | B19: =H18_IED_EFICIENCIA_DIRECTIVA!A11 -> Dir. Social / Gestión Social | C19: =IFERROR(_xlfn.XLOOKUP(B19,H18_IED_EFICIENCIA_DIRECTIVA!A7:A14,H18_IED_EFICIENCIA_DIRECTIVA!C7:C14,0),0) -> 0.349 | D19: =IF(C19>=0.85,"Informe de Reconocimiento",IF(C19>=0.55,"Informe de Seguimiento","Informe de Atención Prioritaria")) -> Informe de Atención Prioritaria | E19: ="INFORME TÉCNICO DE CONGRUENCIA N°-"&ROW()-14&"-"&YEAR(TODAY())&" | UNIDAD: "&B19&" | ICPI Global del período: "&TEXT(H14_CALCULO_ICPI!B32,"0.0")&"% | IED de la unidad: "&TEXT(C19*100,"0.0")&"% | Nivel: "&D19&". "&IF(C19>=0.85,"La unidad registra trazabilidad completa en sus procesos. Se recomienda documentar las buenas prácticas para replicabilidad.",IF(C19>=0.55,"La unidad presenta brechas documentales recuperables. Se recomienda regularizar la publicación en LOTAIP y SERCOP antes del próximo corte cuatrimestral.","La unidad presenta brechas sistémicas en la cadena de trazabilidad. Se recomienda activar plan de fortalecimiento de flujos documentales con seguimiento mensual.")) -> INFORME TÉCNICO DE CONGRUENCIA N°-5-2026 | UNIDAD: Dir. Social / Gestión Social | ICPI Global del período: 41% | IED de la unidad: 35% | Nivel: Informe de Atención Prioritaria. La unidad presenta brechas sistémicas en la cadena de trazabilidad. Se recomienda activar plan de fortalecimiento de flujos documentales con seguimiento mensual.
A20: 6 | B20: =H18_IED_EFICIENCIA_DIRECTIVA!A12 -> Dir. Ambiental | C20: =IFERROR(_xlfn.XLOOKUP(B20,H18_IED_EFICIENCIA_DIRECTIVA!A7:A14,H18_IED_EFICIENCIA_DIRECTIVA!C7:C14,0),0) -> 0.8 | D20: =IF(C20>=0.85,"Informe de Reconocimiento",IF(C20>=0.55,"Informe de Seguimiento","Informe de Atención Prioritaria")) -> Informe de Seguimiento | E20: ="INFORME TÉCNICO DE CONGRUENCIA N°-"&ROW()-14&"-"&YEAR(TODAY())&" | UNIDAD: "&B20&" | ICPI Global del período: "&TEXT(H14_CALCULO_ICPI!B32,"0.0")&"% | IED de la unidad: "&TEXT(C20*100,"0.0")&"% | Nivel: "&D20&". "&IF(C20>=0.85,"La unidad registra trazabilidad completa en sus procesos. Se recomienda documentar las buenas prácticas para replicabilidad.",IF(C20>=0.55,"La unidad presenta brechas documentales recuperables. Se recomienda regularizar la publicación en LOTAIP y SERCOP antes del próximo corte cuatrimestral.","La unidad presenta brechas sistémicas en la cadena de trazabilidad. Se recomienda activar plan de fortalecimiento de flujos documentales con seguimiento mensual.")) -> INFORME TÉCNICO DE CONGRUENCIA N°-6-2026 | UNIDAD: Dir. Ambiental | ICPI Global del período: 41% | IED de la unidad: 80% | Nivel: Informe de Seguimiento. La unidad presenta brechas documentales recuperables. Se recomienda regularizar la publicación en LOTAIP y SERCOP antes del próximo corte cuatrimestral.
A21: 7 | B21: =H18_IED_EFICIENCIA_DIRECTIVA!A13 -> Dir. Financiera | C21: =IFERROR(_xlfn.XLOOKUP(B21,H18_IED_EFICIENCIA_DIRECTIVA!A7:A14,H18_IED_EFICIENCIA_DIRECTIVA!C7:C14,0),0) -> 0.8 | D21: =IF(C21>=0.85,"Informe de Reconocimiento",IF(C21>=0.55,"Informe de Seguimiento","Informe de Atención Prioritaria")) -> Informe de Seguimiento | E21: ="INFORME TÉCNICO DE CONGRUENCIA N°-"&ROW()-14&"-"&YEAR(TODAY())&" | UNIDAD: "&B21&" | ICPI Global del período: "&TEXT(H14_CALCULO_ICPI!B32,"0.0")&"% | IED de la unidad: "&TEXT(C21*100,"0.0")&"% | Nivel: "&D21&". "&IF(C21>=0.85,"La unidad registra trazabilidad completa en sus procesos. Se recomienda documentar las buenas prácticas para replicabilidad.",IF(C21>=0.55,"La unidad presenta brechas documentales recuperables. Se recomienda regularizar la publicación en LOTAIP y SERCOP antes del próximo corte cuatrimestral.","La unidad presenta brechas sistémicas en la cadena de trazabilidad. Se recomienda activar plan de fortalecimiento de flujos documentales con seguimiento mensual.")) -> INFORME TÉCNICO DE CONGRUENCIA N°-7-2026 | UNIDAD: Dir. Financiera | ICPI Global del período: 41% | IED de la unidad: 80% | Nivel: Informe de Seguimiento. La unidad presenta brechas documentales recuperables. Se recomienda regularizar la publicación en LOTAIP y SERCOP antes del próximo corte cuatrimestral.
A22: 8 | B22: =H18_IED_EFICIENCIA_DIRECTIVA!A14 -> Patronato Municipal | C22: =IFERROR(_xlfn.XLOOKUP(B22,H18_IED_EFICIENCIA_DIRECTIVA!A7:A14,H18_IED_EFICIENCIA_DIRECTIVA!C7:C14,0),0) -> 0.029 | D22: =IF(C22>=0.85,"Informe de Reconocimiento",IF(C22>=0.55,"Informe de Seguimiento","Informe de Atención Prioritaria")) -> Informe de Atención Prioritaria | E22: ="INFORME TÉCNICO DE CONGRUENCIA N°-"&ROW()-14&"-"&YEAR(TODAY())&" | UNIDAD: "&B22&" | ICPI Global del período: "&TEXT(H14_CALCULO_ICPI!B32,"0.0")&"% | IED de la unidad: "&TEXT(C22*100,"0.0")&"% | Nivel: "&D22&". "&IF(C22>=0.85,"La unidad registra trazabilidad completa en sus procesos. Se recomienda documentar las buenas prácticas para replicabilidad.",IF(C22>=0.55,"La unidad presenta brechas documentales recuperables. Se recomienda regularizar la publicación en LOTAIP y SERCOP antes del próximo corte cuatrimestral.","La unidad presenta brechas sistémicas en la cadena de trazabilidad. Se recomienda activar plan de fortalecimiento de flujos documentales con seguimiento mensual.")) -> INFORME TÉCNICO DE CONGRUENCIA N°-8-2026 | UNIDAD: Patronato Municipal | ICPI Global del período: 41% | IED de la unidad: 03% | Nivel: Informe de Atención Prioritaria. La unidad presenta brechas sistémicas en la cadena de trazabilidad. Se recomienda activar plan de fortalecimiento de flujos documentales con seguimiento mensual.
A24: SECCIÓN 3 — NOTA METODOLÓGICA
A25: Los Informes Técnicos de Congruencia son el producto documental del sistema SIAP-ICPI. Certifican el estado de la trazabilidad algorítmica de cada proceso. Son evidencia objetiva para: (1) mejora continua institucional, (2) trazabilidad ante organismos multilaterales, (3) insumo técnico para la Dirección de Talento Humano. No reemplazan los procedimientos establecidos en la normativa del servicio público.

Sheet H30_EXPORTACION_SIGAD
A1: 🔙 Volver al Índice
A2: SIAP-ICPI v1.0 | H30 — EXPORTACIÓN COMPATIBLE SIGAD
A3: Datos listos para reporte al sistema SNP | Actualización automática desde motor
A5: SECCIÓN 1 — DATOS DEL REPORTE
A6: GAD: | B6: =H01_PARAMETROS_GENERALES!B6 -> GAD Municipal de Montecristi
A7: Período: | B7: =H01_PARAMETROS_GENERALES!B10 -> 2023-2027
A8: ICM Calculado SIAP: | B8: =H14_CALCULO_ICPI!B32/100 -> 0.41236256
A9: Fecha corte: | B9: =TODAY() -> 46110
A11: SECCIÓN 2 — TABLA DE 20 METAS EN FORMATO SIGAD
A12: CÓDIGO_PDOT | B12: META_DESCRIPCION | C12: EJE | D12: DIRECCIÓN | E12: PRESUP_CODIFICADO | F12: DEVENGADO | G12: AVANCE_Ti_% | H12: Vi_CERTIFICADO | I12: ESTADO_SIGAD | J12: OBSERVACIÓN
A13: =H05_METAS_PDOT!A7 -> PDOT-001 | B13: =IFERROR(_xlfn.XLOOKUP(A13,H05_METAS_PDOT!A7:A26,H05_METAS_PDOT!B7:B26),"") -> Construcción sistema agua potable zonas rurales | C13: =IFERROR(_xlfn.XLOOKUP(A13,H05_METAS_PDOT!A7:A26,H05_METAS_PDOT!C7:C26),"") -> AS | D13: =IFERROR(_xlfn.XLOOKUP(A13,H05_METAS_PDOT!A7:A26,H05_METAS_PDOT!N7:N26),"") -> Dir. Obras Públicas | E13: =IFERROR(_xlfn.XLOOKUP(A13,H09_EJECUCION_PRESUPUESTARIA!B5:B24,H09_EJECUCION_PRESUPUESTARIA!F5:F24),0) -> 2125000 | F13: =IFERROR(_xlfn.XLOOKUP(A13,H09_EJECUCION_PRESUPUESTARIA!B5:B24,H09_EJECUCION_PRESUPUESTARIA!J5:J24),0) -> 1806250 | G13: =IFERROR(_xlfn.XLOOKUP(A13,H09_EJECUCION_PRESUPUESTARIA!B5:B24,H09_EJECUCION_PRESUPUESTARIA!K5:K24),0) -> 0.85 | H13: =IFERROR(_xlfn.XLOOKUP(A13,H14_CALCULO_ICPI!A6:A25,H14_CALCULO_ICPI!J6:J25),0) -> 1 | I13: =IF(AND(G13>=0.9,H13=1),"COMPLETADO",IF(AND(G13>=0.4,H13=1),"EN EJECUCIÓN",IF(G13>0,"EN PROCESO — Documentación incompleta","PENDIENTE DE INICIO"))) -> EN EJECUCIÓN | J13: =IF(H13=0,"Sin trazabilidad documental completa en uno o más silos",IF(G13<0.5,"Ejecución presupuestaria menor al 50%","Avance con trazabilidad verificada")) -> Avance con trazabilidad verificada
A14: =H05_METAS_PDOT!A8 -> PDOT-002 | B14: =IFERROR(_xlfn.XLOOKUP(A14,H05_METAS_PDOT!A7:A26,H05_METAS_PDOT!B7:B26),"") -> Ampliación red alcantarillado sanitario | C14: =IFERROR(_xlfn.XLOOKUP(A14,H05_METAS_PDOT!A7:A26,H05_METAS_PDOT!C7:C26),"") -> AS | D14: =IFERROR(_xlfn.XLOOKUP(A14,H05_METAS_PDOT!A7:A26,H05_METAS_PDOT!N7:N26),"") -> Dir. Obras Públicas | E14: =IFERROR(_xlfn.XLOOKUP(A14,H09_EJECUCION_PRESUPUESTARIA!B5:B24,H09_EJECUCION_PRESUPUESTARIA!F5:F24),0) -> 1550000 | F14: =IFERROR(_xlfn.XLOOKUP(A14,H09_EJECUCION_PRESUPUESTARIA!B5:B24,H09_EJECUCION_PRESUPUESTARIA!J5:J24),0) -> 93000 | G14: =IFERROR(_xlfn.XLOOKUP(A14,H09_EJECUCION_PRESUPUESTARIA!B5:B24,H09_EJECUCION_PRESUPUESTARIA!K5:K24),0) -> 0.06 | H14: =IFERROR(_xlfn.XLOOKUP(A14,H14_CALCULO_ICPI!A6:A25,H14_CALCULO_ICPI!J6:J25),0) -> 1 | I14: =IF(AND(G14>=0.9,H14=1),"COMPLETADO",IF(AND(G14>=0.4,H14=1),"EN EJECUCIÓN",IF(G14>0,"EN PROCESO — Documentación incompleta","PENDIENTE DE INICIO"))) -> EN PROCESO — Documentación incompleta | J14: =IF(H14=0,"Sin trazabilidad documental completa en uno o más silos",IF(G14<0.5,"Ejecución presupuestaria menor al 50%","Avance con trazabilidad verificada")) -> Ejecución presupuestaria menor al 50%
A15: =H05_METAS_PDOT!A9 -> PDOT-003 | B15: =IFERROR(_xlfn.XLOOKUP(A15,H05_METAS_PDOT!A7:A26,H05_METAS_PDOT!B7:B26),"") -> Sistema manejo integral desechos sólidos | C15: =IFERROR(_xlfn.XLOOKUP(A15,H05_METAS_PDOT!A7:A26,H05_METAS_PDOT!C7:C26),"") -> AS | D15: =IFERROR(_xlfn.XLOOKUP(A15,H05_METAS_PDOT!A7:A26,H05_METAS_PDOT!N7:N26),"") -> EP Aseo | E15: =IFERROR(_xlfn.XLOOKUP(A15,H09_EJECUCION_PRESUPUESTARIA!B5:B24,H09_EJECUCION_PRESUPUESTARIA!F5:F24),0) -> 450000 | F15: =IFERROR(_xlfn.XLOOKUP(A15,H09_EJECUCION_PRESUPUESTARIA!B5:B24,H09_EJECUCION_PRESUPUESTARIA!J5:J24),0) -> 0 | G15: =IFERROR(_xlfn.XLOOKUP(A15,H09_EJECUCION_PRESUPUESTARIA!B5:B24,H09_EJECUCION_PRESUPUESTARIA!K5:K24),0) -> 0 | H15: =IFERROR(_xlfn.XLOOKUP(A15,H14_CALCULO_ICPI!A6:A25,H14_CALCULO_ICPI!J6:J25),0) -> 0 | I15: =IF(AND(G15>=0.9,H15=1),"COMPLETADO",IF(AND(G15>=0.4,H15=1),"EN EJECUCIÓN",IF(G15>0,"EN PROCESO — Documentación incompleta","PENDIENTE DE INICIO"))) -> PENDIENTE DE INICIO | J15: =IF(H15=0,"Sin trazabilidad documental completa en uno o más silos",IF(G15<0.5,"Ejecución presupuestaria menor al 50%","Avance con trazabilidad verificada")) -> Sin trazabilidad documental completa en uno o más silos
A16: =H05_METAS_PDOT!A10 -> PDOT-004 | B16: =IFERROR(_xlfn.XLOOKUP(A16,H05_METAS_PDOT!A7:A26,H05_METAS_PDOT!B7:B26),"") -> Mejoramiento vialidad urbana cantonal | C16: =IFERROR(_xlfn.XLOOKUP(A16,H05_METAS_PDOT!A7:A26,H05_METAS_PDOT!C7:C26),"") -> OT | D16: =IFERROR(_xlfn.XLOOKUP(A16,H05_METAS_PDOT!A7:A26,H05_METAS_PDOT!N7:N26),"") -> Dir. Obras Públicas | E16: =IFERROR(_xlfn.XLOOKUP(A16,H09_EJECUCION_PRESUPUESTARIA!B5:B24,H09_EJECUCION_PRESUPUESTARIA!F5:F24),0) -> 800000 | F16: =IFERROR(_xlfn.XLOOKUP(A16,H09_EJECUCION_PRESUPUESTARIA!B5:B24,H09_EJECUCION_PRESUPUESTARIA!J5:J24),0) -> 720000 | G16: =IFERROR(_xlfn.XLOOKUP(A16,H09_EJECUCION_PRESUPUESTARIA!B5:B24,H09_EJECUCION_PRESUPUESTARIA!K5:K24),0) -> 0.9 | H16: =IFERROR(_xlfn.XLOOKUP(A16,H14_CALCULO_ICPI!A6:A25,H14_CALCULO_ICPI!J6:J25),0) -> 1 | I16: =IF(AND(G16>=0.9,H16=1),"COMPLETADO",IF(AND(G16>=0.4,H16=1),"EN EJECUCIÓN",IF(G16>0,"EN PROCESO — Documentación incompleta","PENDIENTE DE INICIO"))) -> COMPLETADO | J16: =IF(H16=0,"Sin trazabilidad documental completa en uno o más silos",IF(G16<0.5,"Ejecución presupuestaria menor al 50%","Avance con trazabilidad verificada")) -> Avance con trazabilidad verificada
A17: =H05_METAS_PDOT!A11 -> PDOT-005 | B17: =IFERROR(_xlfn.XLOOKUP(A17,H05_METAS_PDOT!A7:A26,H05_METAS_PDOT!B7:B26),"") -> Construcción y rehabilitación mercado municipal | C17: =IFERROR(_xlfn.XLOOKUP(A17,H05_METAS_PDOT!A7:A26,H05_METAS_PDOT!C7:C26),"") -> EC | D17: =IFERROR(_xlfn.XLOOKUP(A17,H05_METAS_PDOT!A7:A26,H05_METAS_PDOT!N7:N26),"") -> Dir. Gestión Social | E17: =IFERROR(_xlfn.XLOOKUP(A17,H09_EJECUCION_PRESUPUESTARIA!B5:B24,H09_EJECUCION_PRESUPUESTARIA!F5:F24),0) -> 375000 | F17: =IFERROR(_xlfn.XLOOKUP(A17,H09_EJECUCION_PRESUPUESTARIA!B5:B24,H09_EJECUCION_PRESUPUESTARIA!J5:J24),0) -> 281250 | G17: =IFERROR(_xlfn.XLOOKUP(A17,H09_EJECUCION_PRESUPUESTARIA!B5:B24,H09_EJECUCION_PRESUPUESTARIA!K5:K24),0) -> 0.75 | H17: =IFERROR(_xlfn.XLOOKUP(A17,H14_CALCULO_ICPI!A6:A25,H14_CALCULO_ICPI!J6:J25),0) -> 1 | I17: =IF(AND(G17>=0.9,H17=1),"COMPLETADO",IF(AND(G17>=0.4,H17=1),"EN EJECUCIÓN",IF(G17>0,"EN PROCESO — Documentación incompleta","PENDIENTE DE INICIO"))) -> EN EJECUCIÓN | J17: =IF(H17=0,"Sin trazabilidad documental completa en uno o más silos",IF(G17<0.5,"Ejecución presupuestaria menor al 50%","Avance con trazabilidad verificada")) -> Avance con trazabilidad verificada
A18: =H05_METAS_PDOT!A12 -> PDOT-006 | B18: =IFERROR(_xlfn.XLOOKUP(A18,H05_METAS_PDOT!A7:A26,H05_METAS_PDOT!B7:B26),"") -> Centro salud tipo C parroquia Aníbal San Andrés | C18: =IFERROR(_xlfn.XLOOKUP(A18,H05_METAS_PDOT!A7:A26,H05_METAS_PDOT!C7:C26),"") -> SC | D18: =IFERROR(_xlfn.XLOOKUP(A18,H05_METAS_PDOT!A7:A26,H05_METAS_PDOT!N7:N26),"") -> Dir. Planificación | E18: =IFERROR(_xlfn.XLOOKUP(A18,H09_EJECUCION_PRESUPUESTARIA!B5:B24,H09_EJECUCION_PRESUPUESTARIA!F5:F24),0) -> 700000 | F18: =IFERROR(_xlfn.XLOOKUP(A18,H09_EJECUCION_PRESUPUESTARIA!B5:B24,H09_EJECUCION_PRESUPUESTARIA!J5:J24),0) -> 56000 | G18: =IFERROR(_xlfn.XLOOKUP(A18,H09_EJECUCION_PRESUPUESTARIA!B5:B24,H09_EJECUCION_PRESUPUESTARIA!K5:K24),0) -> 0.08 | H18: =IFERROR(_xlfn.XLOOKUP(A18,H14_CALCULO_ICPI!A6:A25,H14_CALCULO_ICPI!J6:J25),0) -> 0 | I18: =IF(AND(G18>=0.9,H18=1),"COMPLETADO",IF(AND(G18>=0.4,H18=1),"EN EJECUCIÓN",IF(G18>0,"EN PROCESO — Documentación incompleta","PENDIENTE DE INICIO"))) -> EN PROCESO — Documentación incompleta | J18: =IF(H18=0,"Sin trazabilidad documental completa en uno o más silos",IF(G18<0.5,"Ejecución presupuestaria menor al 50%","Avance con trazabilidad verificada")) -> Sin trazabilidad documental completa en uno o más silos
A19: =H05_METAS_PDOT!A13 -> PDOT-007 | B19: =IFERROR(_xlfn.XLOOKUP(A19,H05_METAS_PDOT!A7:A26,H05_METAS_PDOT!B7:B26),"") -> Equipamiento educativo establecimientos rurales | C19: =IFERROR(_xlfn.XLOOKUP(A19,H05_METAS_PDOT!A7:A26,H05_METAS_PDOT!C7:C26),"") -> SC | D19: =IFERROR(_xlfn.XLOOKUP(A19,H05_METAS_PDOT!A7:A26,H05_METAS_PDOT!N7:N26),"") -> Dir. Planificación | E19: =IFERROR(_xlfn.XLOOKUP(A19,H09_EJECUCION_PRESUPUESTARIA!B5:B24,H09_EJECUCION_PRESUPUESTARIA!F5:F24),0) -> 237500 | F19: =IFERROR(_xlfn.XLOOKUP(A19,H09_EJECUCION_PRESUPUESTARIA!B5:B24,H09_EJECUCION_PRESUPUESTARIA!J5:J24),0) -> 185250 | G19: =IFERROR(_xlfn.XLOOKUP(A19,H09_EJECUCION_PRESUPUESTARIA!B5:B24,H09_EJECUCION_PRESUPUESTARIA!K5:K24),0) -> 0.78 | H19: =IFERROR(_xlfn.XLOOKUP(A19,H14_CALCULO_ICPI!A6:A25,H14_CALCULO_ICPI!J6:J25),0) -> 1 | I19: =IF(AND(G19>=0.9,H19=1),"COMPLETADO",IF(AND(G19>=0.4,H19=1),"EN EJECUCIÓN",IF(G19>0,"EN PROCESO — Documentación incompleta","PENDIENTE DE INICIO"))) -> EN EJECUCIÓN | J19: =IF(H19=0,"Sin trazabilidad documental completa en uno o más silos",IF(G19<0.5,"Ejecución presupuestaria menor al 50%","Avance con trazabilidad verificada")) -> Avance con trazabilidad verificada
A20: =H05_METAS_PDOT!A14 -> PDOT-008 | B20: =IFERROR(_xlfn.XLOOKUP(A20,H05_METAS_PDOT!A7:A26,H05_METAS_PDOT!B7:B26),"") -> Guardería municipal comunitaria El Carmen | C20: =IFERROR(_xlfn.XLOOKUP(A20,H05_METAS_PDOT!A7:A26,H05_METAS_PDOT!C7:C26),"") -> SC | D20: =IFERROR(_xlfn.XLOOKUP(A20,H05_METAS_PDOT!A7:A26,H05_METAS_PDOT!N7:N26),"") -> Dir. Social | E20: =IFERROR(_xlfn.XLOOKUP(A20,H09_EJECUCION_PRESUPUESTARIA!B5:B24,H09_EJECUCION_PRESUPUESTARIA!F5:F24),0) -> 300000 | F20: =IFERROR(_xlfn.XLOOKUP(A20,H09_EJECUCION_PRESUPUESTARIA!B5:B24,H09_EJECUCION_PRESUPUESTARIA!J5:J24),0) -> 0 | G20: =IFERROR(_xlfn.XLOOKUP(A20,H09_EJECUCION_PRESUPUESTARIA!B5:B24,H09_EJECUCION_PRESUPUESTARIA!K5:K24),0) -> 0 | H20: =IFERROR(_xlfn.XLOOKUP(A20,H14_CALCULO_ICPI!A6:A25,H14_CALCULO_ICPI!J6:J25),0) -> 0 | I20: =IF(AND(G20>=0.9,H20=1),"COMPLETADO",IF(AND(G20>=0.4,H20=1),"EN EJECUCIÓN",IF(G20>0,"EN PROCESO — Documentación incompleta","PENDIENTE DE INICIO"))) -> PENDIENTE DE INICIO | J20: =IF(H20=0,"Sin trazabilidad documental completa en uno o más silos",IF(G20<0.5,"Ejecución presupuestaria menor al 50%","Avance con trazabilidad verificada")) -> Sin trazabilidad documental completa en uno o más silos
A21: =H05_METAS_PDOT!A15 -> PDOT-009 | B21: =IFERROR(_xlfn.XLOOKUP(A21,H05_METAS_PDOT!A7:A26,H05_METAS_PDOT!B7:B26),"") -> Sistema drenaje pluvial casco urbano | C21: =IFERROR(_xlfn.XLOOKUP(A21,H05_METAS_PDOT!A7:A26,H05_METAS_PDOT!C7:C26),"") -> OT | D21: =IFERROR(_xlfn.XLOOKUP(A21,H05_METAS_PDOT!A7:A26,H05_METAS_PDOT!N7:N26),"") -> Dir. Obras Públicas | E21: =IFERROR(_xlfn.XLOOKUP(A21,H09_EJECUCION_PRESUPUESTARIA!B5:B24,H09_EJECUCION_PRESUPUESTARIA!F5:F24),0) -> 525000 | F21: =IFERROR(_xlfn.XLOOKUP(A21,H09_EJECUCION_PRESUPUESTARIA!B5:B24,H09_EJECUCION_PRESUPUESTARIA!J5:J24),0) -> 52500 | G21: =IFERROR(_xlfn.XLOOKUP(A21,H09_EJECUCION_PRESUPUESTARIA!B5:B24,H09_EJECUCION_PRESUPUESTARIA!K5:K24),0) -> 0.1 | H21: =IFERROR(_xlfn.XLOOKUP(A21,H14_CALCULO_ICPI!A6:A25,H14_CALCULO_ICPI!J6:J25),0) -> 0 | I21: =IF(AND(G21>=0.9,H21=1),"COMPLETADO",IF(AND(G21>=0.4,H21=1),"EN EJECUCIÓN",IF(G21>0,"EN PROCESO — Documentación incompleta","PENDIENTE DE INICIO"))) -> EN PROCESO — Documentación incompleta | J21: =IF(H21=0,"Sin trazabilidad documental completa en uno o más silos",IF(G21<0.5,"Ejecución presupuestaria menor al 50%","Avance con trazabilidad verificada")) -> Sin trazabilidad documental completa en uno o más silos
