Workbook

Sheet H00_ÍNDICE
A1: 🏛️ TERRA SIAP-ICPI v2.0 | QUADRUM | B1: ⬅️ ÍNDICE GENERAL | C1: ="ICPI: "&TEXT(H12_MOTOR_ICPI_CANÓNICO!B28,"0,0")&"%" -> ICPI: 72,9% | D1: H00 — ÍNDICE
A2: 🏛️ TERRA SIAP-ICPI v2.0 — ÍNDICE GENERAL DEL ECOSISTEMA
A3: 37 hojas · 7 bloques funcionales · GAD Municipal de Montecristi | QUADRUM GovTech | NIVEL 0 — Navegación
A4: Hoja | B4: Bloque | C4: Descripción | D4: Tab_Color | E4: Estado_Sistema
A5: H00_ÍNDICE | B5: 0 — Navegación | C5: Índice navegable con ICPI en tiempo real | D5: #718096 | E5: ✅ Activa
A6: H01_PARÁMETROS | B6: 1 — Configuración | C6: Parámetros únicos del sistema TERRA | D6: #003087 | E6: ✅ Activa
A7: H02_GLOSARIO_TERRA | B7: 1 — Configuración | C7: Glosario de 15 términos técnicos TERRA | D7: #003087 | E7: ✅ Activa
A8: H03_S1_ELECTORAL_CNE | B8: 2 — Silo S1 | C8: Promesas electorales → IFE (82,5%) | D8: #3182CE | E8: ✅ Activa
A9: H04_S2_PLANIFICACIÓN_PDOT | B9: 2 — Silo S2 | C9: 20 metas PDOT — Base absoluta del sistema | D9: #3182CE | E9: ✅ Activa
A10: H05_S3_OPERATIVO_POA | B10: 2 — Silo S3 | C10: Plan Operativo Anual — ejecución mensual | D10: #3182CE | E10: ✅ Activa
A11: H06_S4_CONTRATACIÓN_SERCOP | B11: 2 — Silo S4 | C11: Contratos SERCOP — V_SERCOP verificador | D11: #3182CE | E11: ✅ Activa
A12: H07_S5_FINANCIERO_eSIGEF | B12: 2 — Silo S5 | C12: Devengado eSIGEF — T_i por meta | D12: #3182CE | E12: ✅ Activa
A13: H08_S6_AUTOREPORTE_SIGAD | B13: 2 — Silo S6 | C13: ICM auto-reportado 100% vs ICPI 72,7% | D13: #3182CE | E13: ✅ Activa
A14: H09_S7_TRANSPARENCIA_LOTAIP | B14: 2 — Silo S7 | C14: ITAM transparencia activa 90% | D14: #3182CE | E14: ✅ Activa
A15: H10_S8_PARTICIPACIÓN_CPCCS | B15: 2 — Silo S8 | C15: Rendición de cuentas CPCCS | D15: #3182CE | E15: ✅ Activa
... A41: H36_TERRA_BRIDGE | B41: 7 — Salidas | C41: Puente Web JSON — SIAP Web + TERRA Ciudadana | D41: #718096 | E41: ✅ Activa
A44: ▌ ESTADÍSTICAS DEL SISTEMA
A45: Total hojas TERRA: | B45: 37
A46: Total silos verificadores: | B46: 9
A47: Total señales SAT: | B47: 4
A48: Total índices derivados: | B48: 6
A49: ="ICPI Global en tiempo real: "&INT(H12_MOTOR_ICPI_CANÓNICO!B28)&","&TEXT(MOD(H12_MOTOR_ICPI_CANÓNICO!B28,1)*10,"0")&"% — "&H12_MOTOR_ICPI_CANÓNICO!B29 -> ICPI Global en tiempo real: 72,9% — 🟢 Gestión por Mandato

Sheet H01_PARÁMETROS
A1: 🏛️ TERRA SIAP-ICPI v2.0 | QUADRUM | B1: ⬅️ ÍNDICE GENERAL | C1: ="ICPI: "&TEXT(H12_MOTOR_ICPI_CANÓNICO!B28,"0,0")&"%" -> ICPI: 72,9% | D1: H01 — PARÁMETROS | E1: =TEXT(TODAY(),"DD/MM/YYYY") -> 05/04/2026
A2: H01 — PARÁMETROS GENERALES TERRA SIAP-ICPI v2.0
A3: FUENTE Única de toda configuración. TODAS las hojas leen de aquí. NADIE más tiene valores de configuración hardcodeados.
A5: ▌ SECCIÓN A — IDENTIFICACIÓN DEL GAD
A6: GAD_Nombre | B6: GAD Municipal de Montecristi
A7: GAD_Codigo | B7: 130801
A8: GAD_RUC | B8: 1360000430001
A9: GAD_Provincia | B9: Manabí
A10: GAD_Período | B10: 2024-2027
A11: GAD_Alcalde | B11: Ing. Jonathan Toro Largacha
A12: ICM_SIGAD_Oficial | B12: 1
A13: Fecha_Corte | B13: 2024-12-31T05:00:00.000Z
A14: Año_Fiscal | B14: 2024
A15: Total_Metas_PDOT | B15: 20
A16: Total_Promesas_CNE | B16: 25
A18: ▌ SECCIÓN B — ESCALA AVEP (5 NIVELES)
A19: Nivel | B19: Min_% | C19: Max_% | D19: Etiqueta | E19: Color_Hex | F19: Emoji
A20: 5 | B20: 90 | C20: 100 | D20: Excelencia en Gobernanza | E20: #003087 | F20: 🔵
A21: 4 | B21: 70 | C21: 89 | D21: Gestión por Mandato | E21: #38a169 | F21: 🟢
A22: 3 | B22: 40 | C22: 69 | D22: Transición Crítica | E22: #d69e2e | F22: 🟡
A23: 2 | B23: 20 | C23: 39 | D23: Gestión por Ocurrencia | E23: #e67e22 | F23: 🟠
A24: 1 | B24: 0 | C24: 19 | D24: Ruptura Sistémica | E24: #e53e3e | F24: 🔴
A25: Función AVEP estándar (referencia):
A26: =SI(valor>=90,"🔵 Excelencia en Gobernanza",SI(valor>=70,"🟢 Gestión por Mandato",SI(valor>=40,"🟡 Transición Crítica",SI(valor>=20,"🟠 Gestión por Ocurrencia","🔴 Ruptura Sistémica"))))
A27: ▌ SECCIÓN C — PARÁMETROS FISCALES Y DISCRIMINACIÓN POSITIVA
A28: Presupuesto_Total_GAD | B28: 26689147
A29: Presupuesto_Patronato (Art.249 COOTAD — 10%) | B29: =B28*0.1 -> 2668914.7
A30: Fecha_Reforma_COOTAD | B30: 2026-02-23T05:00:00.000Z
A31: Fecha_Vigencia_Regla_Fiscal | B31: 2026-06-01T05:00:00.000Z
A32: Pct_Inversion_Minimo | B32: 0.65
A33: Pct_Corriente_Maximo | B33: 0.35
A34: SAT_IV_Activa [MALEABLE: actualizar B31 si reforma COOTAD derogada] | B34: =IF(B13>=B31,"SÍ","NO") -> NO
A35: --- DISCRIMINACIÓN POSITIVA — Módulo TERRA Ciudadano ---
A36: Multiplicador_Clima [Bono 15% para metas ODS 13 — Resiliencia] | B36: 1.15
A37: Multiplicador_Genero [Bono 15% para metas ODS 5 — Igualdad] | B37: 1.15
A38: Nota discriminación positiva: | B38: Estos multiplicadores elevan el R_i de metas de género y clima en H04, haciendo que su incumplimiento penalice más el IED. La fórmula canónica del motor NO cambia.
A40: ▌ SECCIÓN D — UMBRALES SEÑALES SAT
A41: SAT_I_Umbral_ICM | B41: 0.8
A42: SAT_I_Umbral_Universo | B42: 0.1
A43: SAT_II_Umbral_Reforma | B43: 0.05
A44: SAT_III_Umbral_Cumpl | B44: 5
A45: SAT_III_Umbral_Deveng | B45: 0.1
A46: MMP_Umbral_Brecha [Si devengado < 30% al Q3, meta elegible financiamiento externo] | B46: 0.3
A49: ▌ SECCIÓN E — PLAN NACIONAL VIGENTE
A50: PND_Nombre | B50: Ecuador No Se Detiene 2025-2029
A51: PND_Resolución | B51: CNP 0012-2025
A52: PND_Metas_ODS [de 98 metas totales vinculadas a Agenda 2030] | B52: 96
A53: SNP_Nombre [NUNCA usar SENPLADES — fue suprimida en 2019] | B53: Secretaría Nacional de Planificación

Sheet H02_GLOSARIO_TERRA
A1: 🏛️ TERRA SIAP-ICPI v2.0 | QUADRUM | B1: ⬅️ ÍNDICE GENERAL | C1: ="ICPI: "&TEXT(H12_MOTOR_ICPI_CANÓNICO!B28,"0,0")&"%" -> ICPI: 72,9% | D1: H02 — GLOSARIO | E1: =TEXT(TODAY(),"DD/MM/YYYY") -> 05/04/2026
A2: H02 — GLOSARIO TERRA — 15 TÉRMINOS CANÓNICOS
A3: Los únicos términos propios del ecosistema. NO se inventan otros.
A5: # | B5: Sigla | C5: Término Completo | D5: Definición | E5: Ref. Legal
A6: 1 | B6: TERRA | C6: Ecosistema de Integridad Algorítmica Preventiva | D6: Plataforma GovTech de QUADRUM para gobernanza preventiva municipal | E6: COOTAD Art.295
A7: 2 | B7: SIAP | C7: Sistema de Integridad Algorítmica Preventiva | D7: Arquitectura metodológica de verificación cruzada intersistémica para GADs | E7: COOTAD Art.295 + COPFP Art.9
A8: 3 | B8: ICPI | C8: Índice de Congruencia Programática e Intersistémica | D8: Métrica nuclear que certifica alineación verificable entre PDOT y ejecución en 9 silos | E8: COPFP Art.54
A9: 4 | B9: IFE | C9: Índice de Fidelidad Electoral | D9: Verificador complementario. Mide si las promesas del Plan CNE fueron incorporadas al PDOT. NO es motor de cálculo. | E9: Código Democracia
A10: 5 | B10: IED | C10: Índice de Eficiencia Directiva | D10: ICPI desagregado por silo y dirección. Evalúa calidad del flujo administrativo. | E10: LOSEP Art.76 + NCI 200-04
A11: 6 | B11: ITAM | C11: Índice de Transparencia Activa Municipal | D11: Calidad y accesibilidad documental en los silos públicos del GAD | E11: LOTAIP Art.7
A12: 7 | B12: ICS | C12: Índice de Congruencia Social | D12: ICPI filtrado para metas sociales y grupos de atención prioritaria | E12: Constitución Art.35
A13: 8 | B13: ISP | C13: Índice de Congruencia del Patronato | D13: Trazabilidad del gasto social delegado. Componente opcional del ICS. | E13: COOTAD Art.249
A14: 9 | B14: ICODS | C14: Índice de Congruencia ODS | D14: Alineación de metas PDOT con Agenda 2030. Incluye subíndice género y generacional. | E14: ODS 16-17 prioritarios
A15: 10 | B15: MOM | C15: Mutación del Objeto de Medición | D15: Gaming del sistema de autoreporte municipal. Tres tipos detectados algorítmicamente. | E15: Campbell 1976 + Hood 2006
A16: 11 | B16: SAT | C16: Señales de Atención Temprana | D16: Cuatro protocolos algorítmicos de detección de anomalías en la cadena de trazabilidad. | E16: COPFP Art.117 + COA Art.196
A17: 12 | B17: CIIN | C17: Cadena de Trazabilidad Intersistémica | D17: Flujo documental con firma digital desde informe mensual de servidor hasta CPCCS. | E17: Constitución Art.18
... A20: 15 | B20: MMP | C20: Motor de Monitoreo Programático | D20: Seguimiento mensual con firma digital por servidor público y director. Cadena de integridad intersistémica. | E20: COPFP Art.115-117
A22: # | B22: Componente | C22: Nombre Completo | D22: Descripción / Valores Permitidos | E22: Referencia
B23: ESTRUCTURA ID CANÓNICO: | C23: XX-T-E-NN | D23: Formato: Sistema (2L) – Tipo (1L) – Enfoque (1L) – Secuencial (2N) | E23: COPFP Art.54; COOTAD Art.295
A24: 1 | B24: AH | C24: Asentamientos Humanos | D24: Infraestructura vial, agua potable, alcantarillado, equipamientos y vivienda. Competencia exclusiva GAD Municipal Art.55 COOTAD. | E24: COOTAD Art.55 lit.d/e
A25: 2 | B25: SC | C25: Socio Cultural | D25: Servicios de salud municipal, protección derechos, cultura y patrimonio, TICs educativas. | E25: COOTAD Art.55 lit.b; COPFP Art.42
A26: 3 | B26: FA | C26: Físico Ambiental | D26: Gestión ambiental, riesgo, desechos sólidos, áreas verdes. Competencia municipal sobre saneamiento. | E26: COOTAD Art.55 lit.c; TULSMA
A27: 4 | B27: PI | C27: Político Institucional | D27: Planificación, talento humano, catastro, participación ciudadana, sostenibilidad financiera. | E27: COPFP Art.41; COOTAD Art.54
A28: 5 | B28: EP | C28: Económico Productivo | D28: Fomento productivo, turismo, artesanías, mipymes. Competencia concurrente. | E28: COOTAD Art.135; COPCI
A29: 6 | B29: C | C29: Competencia Exclusiva | D29: Obligación constitucional del GAD Municipal. Verificable directamente en sistemas estatales. | E29: COOTAD Art.55; CRE Art.264
A30: 7 | B30: I | C30: Competencia Inversión | D30: Inversión pública territorial. Prioridad presupuestaria de la administración. | E30: COPFP Art.58; COOTAD Art.196
A31: 8 | B31: L | C31: Competencia Concurrente | D31: Competencia compartida con otros niveles de gobierno o sector privado. | E31: COOTAD Art.136; CRE Art.260
A32: 9 | B32: X | C32: Competencia Exclusiva (Enfoque) | D32: La meta pertenece a competencias exclusivas del GAD. Máxima trazabilidad TERRA. | E32: COOTAD Art.55; COPFP Art.41
A33: 10 | B33: N | C33: Necesidades Básicas Insatisfechas | D33: La meta aborda directamente indicadores NBI. Prioridad social COPFP. | E33: COPFP Art.42; Agenda 2030 ODS 1/3/6
A34: 11 | B34: G | C34: Gobernanza e Institucionalidad | D34: La meta fortalece capacidades institucionales, transparencia y rendición de cuentas. | E34: COPFP Art.54; COOTAD Art.3 lit.g
A35: 12 | B35: NN | C35: Secuencial por Sistema | D35: Número ordinal de 2 dígitos dentro del mismo sistema (01, 02, …). Sin semántica adicional. | E35: Convención interna TERRA v2.0
A37: # | B37: ID Canónico | C37: Meta Descriptiva | D37: Sistema / Competencia | E37: ODS Primario
A38: 1 | B38: SC-I-N-01 | C38: Salud Municipal: pob. atendida 57,401→84,041 | D38: Socio Cultural / Inversión / NBI | E38: ODS 3, 1, 10
A39: 2 | B39: SC-L-N-02 | C39: TICs y educativo: 19,265→23,265 beneficiarios | D39: Socio Cultural / Concurrente / NBI | E39: ODS 4, 10
A40: 3 | B40: AH-I-X-01 | C40: Vialidad: 43.8km CUP + 57.22km rurales | D40: As. Humanos / Inversión / Exclusiva | E40: ODS 9, 11
A41: 4 | B41: AH-I-X-02 | C41: Señalización e IVU: 10.94→17.32 m²/hab | D41: As. Humanos / Inversión / Exclusiva | E41: ODS 11
A42: 5 | B42: AH-I-X-03 | C42: Equipamientos: canchas, parques, plazas, terminal | D42: As. Humanos / Inversión / Exclusiva | E42: ODS 11, 3, 4
A43: 6 | B43: AH-I-N-01 | C43: Vivienda interés social: 50 VIS hasta 2027 | D43: As. Humanos / Inversión / NBI | E43: ODS 1, 11
A44: 7 | B44: SC-L-G-01 | C44: Cultura y patrimonio: inventario 100%; 10,000 asist. | D44: Socio Cultural / Concurrente / Gobernanza | E44: ODS 4, 11
A45: 8 | B45: AH-I-X-04 | C45: Tránsito: señaliz. 10,000m²; 8 semáforos; 20k rev. | D45: As. Humanos / Inversión / Exclusiva | E45: ODS 11, 3
A46: 9 | B46: PI-I-G-01 | C46: Modernización admin.: automotor + tecnología | D46: Pol. Institucional / Inversión / Gobernanza | E46: ODS 16
A47: 10 | B47: AH-C-X-01 | C47: Agua potable: cobertura 39.25%→42.38% | D47: As. Humanos / Exclusiva / Exclusiva | E47: ODS 6, 3, 11
A48: 11 | B48: AH-C-X-02 | C48: Alcantarillado: 19.77%→24.32%; PTAR 0%→75% | D48: As. Humanos / Exclusiva / Exclusiva | E48: ODS 6, 3, 11
A49: 12 | B49: SC-I-N-03 | C49: Grupos prioritarios: 943→1,649 atenciones (+15%/año) | D49: Socio Cultural / Inversión / NBI | E49: ODS 1, 3, 5, 10
... A57: 20 | B57: EP-L-X-01 | C57: Turismo: 2,700→4,300 visitantes/año; 22 eventos | D57: Econ. Productivo / Concurrente / Exclusiva | E57: ODS 8, 11

Sheet H03_S1_ELECTORAL_CNE
A1: 🏛️ TERRA SIAP-ICPI v2.0 | QUADRUM | B1: ⬅️ ÍNDICE GENERAL | C1: ="ICPI: "&TEXT(H12_MOTOR_ICPI_CANÓNICO!B28,"0,0")&"%" -> ICPI: 72,9% | D1: H03 — S1 CNE | E1: =TEXT(TODAY(),"DD/MM/YYYY") -> 05/04/2026
A2: S1 — SILO ELECTORAL (CNE) — ÍNDICE DE FIDELIDAD ELECTORAL (IFE)
A3: Plan de Trabajo CNE → promesas verificables · Origen absoluto del IFE | Código de la Democracia + LOPC Art.88 | NOTA: IFE es verificador complementario — base del ecosistema es H04
A5: ID_Promesa | B5: Eje_Estratégico | C5: Descripción_Promesa | D5: ID_Meta_PDOT_Vinculada | E5: Score_IFE | F5: Tipo_Vinculación | G5: Justificación_Técnica
A6: EC-001 | B6: Económico | C6: Convertir a Montecristi en destino turístico nacional/internacional; rutas gastronómicas, ecoturísticas, eventos culturales | D6: EP-L-X-01 | E6: 1 | F6: Directa | G6: PDOT-020 (EP-02) recoge íntegramente la meta turística: 2,700→4,300 visitantes/año y 10→22 eventos, presupuesto $350k codificado
A7: EC-002 | B7: Económico | C7: Fomento al sector artesanal, MIPYMES y emprendedores; programa Ka-Larte es por Ti; Cuna de Emprendedores | D7: EP-L-N-01 | E7: 1 | F7: Directa | G7: PDOT-019 (EP-01) recoge el programa artesanal y mipymes con indicador de beneficiarios y presupuesto $230k codificado
A8: EC-003 | B8: Económico | C8: Gestión para repotenciar y ordenar el mercado municipal | D8: PI-I-G-01 | E8: 0.75 | F8: Directa | G8: AH-04 (PDOT-009) incluye 'Gestión para el desarrollo del Mercado de Montecristi' como proyecto estratégico; sin presupuesto exclusivo segregado
A9: EC-004 | B9: Económico | C9: Impulsar desarrollo turístico Playa San José e Isla de la Plata; manglar; Paseo Lúdico | D9: EP-L-X-01 | E9: 0.5 | F9: Parcial | G9: Parcialmente recogida en EP-02; Manglar y Paseo Lúdico aparecen como subproyectos sin indicador cuantitativo propio
A10: EC-005 | B10: Económico | C10: Generación de ordenanzas para exoneración de tributos a nuevas empresas; alianzas sector privado para atracción de inversión | D10: — | E10: 0 | F10: Sin vínculo | G10: No existe meta en el PDOT 2023-2027 con indicador de ordenanzas tributarias ni atracción de inversión privada directa
A11: IN-001 | B11: Institucional | C11: Elaborar PDOT 2023 con ODS; planificación territorial 30 años; Plan Bicentenario | D11: PI-I-G-02 | E11: 1 | F11: Directa | G11: PDOT-017 (PI-05) recoge explícitamente cumplimiento PDOT/PUGS 0%→80% y 37 trámites en línea; el Plan Bicentenario fue elaborado y aprobado
A12: IN-002 | B12: Institucional | C12: Actualización catastral urbana y rural; base de datos grupos vulnerables; registro y delimitación comunal | D12: AH-C-X-02 | E12: 1 | F12: Directa | G12: PDOT-011 (PI-04) — catastro urbano-rural 19.52%→80%, 12 procesos sistematizados, 37 trámites en línea. Registro comunal como subactividad
A13: IN-003 | B13: Institucional | C13: Transformación digital del GAD; plataforma digital de trámites; gobierno electrónico abierto; mejora equipos informáticos | D13: AH-C-X-02 | E13: 0.75 | F13: Directa | G13: Transformación digital incluida en PI-04 como componente (37 trámites en línea); no tiene meta exclusiva de gobierno digital con indicador propio
A14: IN-004 | B14: Institucional | C14: Acceso a información pública (LOTAIP); rendición de cuentas transparente; convenios interinstitucionales nacionales e internacionales | D14: PI-L-G-01 | E14: 1 | F14: Directa | G14: PDOT-018 (PI-07) + PDOT-017 (PI-05) recogen participación ciudadana, rendición de cuentas y 4 instancias participativas efectivas (COPFP Art.115)
A15: IN-005 | B15: Institucional | C15: Seguridad ciudadana: alarmas comunitarias, habilitación UPC Aníbal San Andrés y Colorado, cuarteles bomberos en zonas estratégicas | D15: PI-I-G-01 | E15: 0.5 | F15: Parcial | G15: AH-04 incluye 'Gestión para la Construcción de la Estación Bomberil Parroquia Colorado'; alarmas comunitarias y UPC sin meta ni indicador en PDOT
A16: IN-006 | B16: Institucional | C16: Creación y fortalecimiento de marca ciudad Montecristi; posicionamiento nacional como referente de transformación | D16: — | E16: 0 | F16: Sin vínculo | G16: Sin meta verificable en PDOT: la 'marca ciudad' no tiene indicador cuantificable ni presupuesto exclusivo auditables en ningún silo TERRA
A17: SC-001 | B17: Social | C17: Construcción Centro de Salud Tipo C; construcción Centro Geriátrico; Plan Nacer Aquí; Concejo de Salud Montecristi | D17: AH-I-X-03 | E17: 1 | F17: Directa | G17: PDOT-005 (AH-04) incluye 'Gestión para obtención Centro de Salud tipo C' y SC-01 incluye 'Gestión para Centro Geriátrico Montecristi' como proyectos estratégicos
... A30: TE-005 | B30: Territorial | C30: Construcción camal municipal para faenamiento de carne fresca de calidad; control sanitario y ambiental | D30: — | E30: 0 | F30: Sin vínculo | G30: No existe meta ni proyecto en el PDOT 2023-2027 que contemple el camal municipal con indicador cuantificable ni presupuesto codificado
A31: ■ CÁLCULO IFE — FUENTE Única DEL SISTEMA | B31: ="El GAD convirtió el "&TEXT(B34,"0.0")&"% de sus promesas electorales en metas estratégicas del PDOT." -> El GAD convirtió el 77% de sus promesas electorales en metas estratégicas del PDOT.
A32: IFE_Numerador | B32: =SUM(E6:E30) -> 19.25 | C32: [Suma de scores IFE de las 25 promesas]
A33: IFE_Total_Promesas | B33: =H01_PARÁMETROS!B16 -> 25 | C33: [Lee de H01_PARÁMETROS!B16 = 25]
A34: ★ IFE_GLOBAL ★ [FUENTE Única DEL IFE] | B34: =B32/B33*100 -> 77 | C34: [★★★ CELDA MAESTRA IFE — H16 y H28 referencian única y exclusivamente esta celda ★★★]
A35: Clasificación_IFE | B35: =IF(B34>=85,"✅ Alta Fidelidad Electoral",IF(B34>=60,"⚠️ Fidelidad Moderada",IF(B34>=40,"U0001f7e0 Erosión del Compromiso","U0001f534 Ruptura del Mandato Democrático"))) -> ⚠️ Fidelidad Moderada

Sheet H04_S2_PLANIFICACIÓN_PDOT
A1: 🏛️ TERRA SIAP-ICPI v2.0 | QUADRUM | B1: ⬅️ ÍNDICE GENERAL | C1: ="ICPI: "&TEXT(H12_MOTOR_ICPI_CANÓNICO!B28,"0,0")&"%" -> ICPI: 72,9% | D1: H04 — S2 PDOT | E1: =TEXT(TODAY(),"DD/MM/YYYY") -> 05/04/2026
A2: S2 — SILO PLANIFICACIÓN ESTRATÉGICA (PDOT) — BASE ABSOLUTA DEL ECOSISTEMA TERRA
A3: PDOT quinquenal aprobado mediante ordenanza · 20 metas · Base inmutable | COOTAD Art.295 + COPFP Arts.41-42 | NOTA: Esta hoja nunca se modifica una vez cargada
A5: ID_Meta | B5: Descripción | C5: Eje_Estratégico | D5: Competencia_GAD | E5: R_i_raw | F5: Presup_PDOT_Total | G5: Presup_Anual | H5: P_i | I5: ODS_Cluster | J5: ODS_Específico | K5: Bono_Equidad | L5: R_i_final | M5: Fuente_Financiamiento | N5: Meta_Cuantitativa | O5: Unidad_Medida_ORIGINAL ⚠️INMUTABLE | P5: Línea_Base | Q5: Indicador_PDOT | R5: Dirección_Responsable | S5: Página_PDOT | T5: Vinculación_IFE
A6: SC-I-N-01 | B6: Agua potable: cobertura 39.25%→42.38%; calidad 100% INEN 1108; infraestructura BUENA 22.74%→41.64% | C6: Territorial | D6: Exclusiva_Crítica | E6: 1.5 | F6: 46904874 | G6: 11726219 | H6: =G6/SUM($G$6:$G$25) -> 0.28912002 | I6: Infraestructura | J6: 6,3,11 | K6: =IF(ISNUMBER(SEARCH("13",J6)),H01_PARÁMETROS!$B$36,IF(ISNUMBER(SEARCH("5",J6)),H01_PARÁMETROS!$B$37,1)) -> 1 | L6: {=(E6*K6)/SUMPRODUCT(MAX($E$6:$E$25*$K$6:$K$25))} -> 0.86956522 | M6: Recursos propios + BDE + MIDUVI | N6: 42.38 | O6: % cobertura agua potable | P6: 39.25 | Q6: Porcentaje de cobertura de agua potable cantonal al 42.38% hasta 2027 | R6: Patronato Municipal | S6: 363 | T6: =IF(COUNTIF(H03_S1_ELECTORAL_CNE!D:D,A6)>0,"✅ Vinculada CNE","⚠️ Sin vínculo electoral") -> ✅ Vinculada CNE
A7: SC-L-N-02 | B7: Gestión del talento humano municipal: desempeño 80%→90%; plan capacitación 90% anual | C7: Institucional | D7: Exclusiva_Importante | E7: 1 | F7: 52776878 | G7: 13194220 | H7: =G7/SUM($G$6:$G$25) -> 0.32531485 | I7: Gobernanza | J7: 16 | K7: =IF(ISNUMBER(SEARCH("13",J7)),H01_PARÁMETROS!$B$36,IF(ISNUMBER(SEARCH("5",J7)),H01_PARÁMETROS!$B$37,1)) -> 1 | L7: {=(E7*K7)/SUMPRODUCT(MAX($E$6:$E$25*$K$6:$K$25))} -> 0.57971014 | M7: Recursos propios GAD | N7: 90 | O7: % nivel desempeño personal | P7: 80 | Q7: Porcentaje de cumplimiento del nivel de desempeño institucional al 90% hasta 2027 | R7: Dirección TIC | S7: 367 | T7: =IF(COUNTIF(H03_S1_ELECTORAL_CNE!D:D,A7)>0,"✅ Vinculada CNE","⚠️ Sin vínculo electoral") -> ✅ Vinculada CNE
A8: AH-I-X-01 | B8: Sostenibilidad financiera: autonomía 43.35%→45.30%; gestión cobros y coactivas | C8: Institucional | D8: Exclusiva_Importante | E8: 1 | F8: 20205706 | G8: 5051427 | H8: =G8/SUM($G$6:$G$25) -> 0.12454728 | I8: Gobernanza | J8: 16,17 | K8: =IF(ISNUMBER(SEARCH("13",J8)),H01_PARÁMETROS!$B$36,IF(ISNUMBER(SEARCH("5",J8)),H01_PARÁMETROS!$B$37,1)) -> 1 | L8: {=(E8*K8)/SUMPRODUCT(MAX($E$6:$E$25*$K$6:$K$25))} -> 0.57971014 | M8: Recursos propios GAD | N8: 45.3 | O8: % autonomía financiera | P8: 43.35 | Q8: Porcentaje de autonomía financiera (ingresos propios / ingresos totales - financiamiento) al 45.30% hasta 2027 | R8: Dirección de Obras Públicas | S8: 367 | T8: =IF(COUNTIF(H03_S1_ELECTORAL_CNE!D:D,A8)>0,"✅ Vinculada CNE","⚠️ Sin vínculo electoral") -> ✅ Vinculada CNE
A9: AH-I-X-02 | B9: Vialidad cantonal: mantenimiento 43.8 km vías CUP + 57.22 km rurales; 23.77 km tratamiento medio | C9: Territorial | D9: Exclusiva_Crítica | E9: 1.5 | F9: 10917761 | G9: 2729440 | H9: =G9/SUM($G$6:$G$25) -> 0.067296693 | I9: Infraestructura | J9: 9,11 | K9: =IF(ISNUMBER(SEARCH("13",J9)),H01_PARÁMETROS!$B$36,IF(ISNUMBER(SEARCH("5",J9)),H01_PARÁMETROS!$B$37,1)) -> 1 | L9: {=(E9*K9)/SUMPRODUCT(MAX($E$6:$E$25*$K$6:$K$25))} -> 0.86956522 | M9: Recursos propios + BDE | N9: 130.21 | O9: Km vías mantenidas CUP acumulado | P9: 86.41 | Q9: Kilómetros de mantenimiento de vías en el CUP incrementados a 130.21 km hasta 2027 | R9: Dirección de Obras Públicas | S9: 364 | T9: =IF(COUNTIF(H03_S1_ELECTORAL_CNE!D:D,A9)>0,"✅ Vinculada CNE","⚠️ Sin vínculo electoral") -> ⚠️ Sin vínculo electoral
A10: AH-I-X-03 | B10: Salud integral municipal: población atendida 57,401→84,041 personas (+10% anual) | C10: Social | D10: Complementaria | E10: 0.5 | F10: 5882644 | G10: 1470661 | H10: =G10/SUM($G$6:$G$25) -> 0.036260413 | I10: Inclusion | J10: 3,1,10 | K10: =IF(ISNUMBER(SEARCH("13",J10)),H01_PARÁMETROS!$B$36,IF(ISNUMBER(SEARCH("5",J10)),H01_PARÁMETROS!$B$37,1)) -> 1 | L10: {=(E10*K10)/SUMPRODUCT(MAX($E$6:$E$25*$K$6:$K$25))} -> 0.28985507 | M10: Recursos propios + MSP | N10: 84041 | O10: Personas atendidas salud municipal | P10: 57401 | Q10: Número de personas atendidas en grupos de edades y por discapacidad en servicios de salud municipal | R10: Dirección de Obras Públicas | S10: 365 | T10: =IF(COUNTIF(H03_S1_ELECTORAL_CNE!D:D,A10)>0,"✅ Vinculada CNE","⚠️ Sin vínculo electoral") -> ✅ Vinculada CNE
A11: AH-I-N-01 | B11: Gestión integral desechos sólidos: 20,118→23,086 Tn/año; relleno sanitario; capacidad disposición 0%→20% | C11: Ambiental | D11: Exclusiva_Crítica | E11: 1.5 | F11: 5750745 | G11: 1437686 | H11: =G11/SUM($G$6:$G$25) -> 0.035447386 | I11: Infraestructura | J11: 11,13,3 | K11: =IF(ISNUMBER(SEARCH("13",J11)),H01_PARÁMETROS!$B$36,IF(ISNUMBER(SEARCH("5",J11)),H01_PARÁMETROS!$B$37,1)) -> 1.15 | L11: {=(E11*K11)/SUMPRODUCT(MAX($E$6:$E$25*$K$6:$K$25))} -> 1 | M11: Recursos propios GAD | N11: 23086.94 | O11: Toneladas de desechos gestionadas/año | P11: 20118.96 | Q11: Toneladas de desechos sólidos gestionadas anualmente hasta 23,086.94 Tn/año al 2027 | R11: EP Montehogar | S11: 362 | T11: =IF(COUNTIF(H03_S1_ELECTORAL_CNE!D:D,A11)>0,"✅ Vinculada CNE","⚠️ Sin vínculo electoral") -> ✅ Vinculada CNE
A12: SC-L-G-01 | B12: Alcantarillado sanitario: cobertura 19.77%→24.32%; PTAR 0%→75%; estaciones bombeo 36%→72% | C12: Territorial | D12: Exclusiva_Crítica | E12: 1.5 | F12: 1269859 | G12: 317465 | H12: =G12/SUM($G$6:$G$25) -> 0.0078273729 | I12: Infraestructura | J12: 6,3,11 | K12: =IF(ISNUMBER(SEARCH("13",J12)),H01_PARÁMETROS!$B$36,IF(ISNUMBER(SEARCH("5",J12)),H01_PARÁMETROS!$B$37,1)) -> 1 | L12: {=(E12*K12)/SUMPRODUCT(MAX($E$6:$E$25*$K$6:$K$25))} -> 0.86956522 | M12: Recursos propios + BDE | N12: 24.32 | O12: % cobertura alcantarillado sanitario | P12: 19.77 | Q12: Porcentaje de cobertura de red pública de alcantarillado sanitario al 24.32% hasta 2027 | R12: Dirección de Cultura y Deporte | S12: 363 | T12: =IF(COUNTIF(H03_S1_ELECTORAL_CNE!D:D,A12)>0,"✅ Vinculada CNE","⚠️ Sin vínculo electoral") -> ⚠️ Sin vínculo electoral
A13: AH-I-X-04 | B13: Modernización recursos administrativos: parque automotor, tecnología e infraestructura municipal | C13: Institucional | D13: Exclusiva_Importante | E13: 1 | F13: 3765021 | G13: 941255 | H13: =G13/SUM($G$6:$G$25) -> 0.023207452 | I13: Gobernanza | J13: 16 | K13: =IF(ISNUMBER(SEARCH("13",J13)),H01_PARÁMETROS!$B$36,IF(ISNUMBER(SEARCH("5",J13)),H01_PARÁMETROS!$B$37,1)) -> 1 | L13: {=(E13*K13)/SUMPRODUCT(MAX($E$6:$E$25*$K$6:$K$25))} -> 0.57971014 | M13: Recursos propios GAD | N13: 1 | O13: Parque automotor y tecnología renovados | P13: 0 | Q13: Optimización y modernización de gestión de recursos administrativos municipales ejecutada | R13: Dirección de Obras Públicas | S13: 367 | T13: =IF(COUNTIF(H03_S1_ELECTORAL_CNE!D:D,A13)>0,"✅ Vinculada CNE","⚠️ Sin vínculo electoral") -> ✅ Vinculada CNE
A14: PI-I-G-01 | B14: Equipamientos públicos: terminal terrestre, mercado, estación bomberil, centro salud tipo C, mantenimiento espacios recreativos | C14: Territorial | D14: Exclusiva_Importante | E14: 1 | F14: 2588556 | G14: 647139 | H14: =G14/SUM($G$6:$G$25) -> 0.015955769 | I14: Infraestructura | J14: 11,3,4 | K14: =IF(ISNUMBER(SEARCH("13",J14)),H01_PARÁMETROS!$B$36,IF(ISNUMBER(SEARCH("5",J14)),H01_PARÁMETROS!$B$37,1)) -> 1 | L14: {=(E14*K14)/SUMPRODUCT(MAX($E$6:$E$25*$K$6:$K$25))} -> 0.57971014 | M14: Recursos propios GAD | N14: 10.73 | O14: m² / hab índice equipamiento urbano CUP | P14: 9.96 | Q14: Índice de equipamiento urbano en el Centro Urbano Principal incrementado a 10.73 m²/hab hasta 2027 | R14: Dirección Administrativa | S14: 364 | T14: =IF(COUNTIF(H03_S1_ELECTORAL_CNE!D:D,A14)>0,"✅ Vinculada CNE","⚠️ Sin vínculo electoral") -> ✅ Vinculada CNE
A15: AH-C-X-01 | B15: Protección derechos sociales: atenciones grupos prioritarios 943→1,649 (+15%/año); CDI; adultos mayores; violencia de género | C15: Social | D15: Complementaria | E15: 0.5 | F15: 1755066 | G15: 438767 | H15: =G15/SUM($G$6:$G$25) -> 0.010818178 | I15: Inclusion | J15: 1,3,5,10 | K15: =IF(ISNUMBER(SEARCH("13",J15)),H01_PARÁMETROS!$B$36,IF(ISNUMBER(SEARCH("5",J15)),H01_PARÁMETROS!$B$37,1)) -> 1.15 | L15: {=(E15*K15)/SUMPRODUCT(MAX($E$6:$E$25*$K$6:$K$25))} -> 0.33333333 | M15: Recursos propios + Patronato | N15: 1649 | O15: Atenciones en programas grupos prioritarios | P15: 943 | Q15: Número de atenciones en programas para grupos de atención prioritaria incrementado a 1,649 hasta 2027 | R15: Dirección de Agua y Saneamiento | S15: 366 | T15: =IF(COUNTIF(H03_S1_ELECTORAL_CNE!D:D,A15)>0,"✅ Vinculada CNE","⚠️ Sin vínculo electoral") -> ✅ Vinculada CNE
A16: AH-C-X-02 | B16: Sistema información territorial: catastro urbano-rural 19.52%→80%; 12 procesos sistematizados; 37 trámites en línea | C16: Institucional | D16: Exclusiva_Importante | E16: 1 | F16: 1819567 | G16: 454892 | H16: =G16/SUM($G$6:$G$25) -> 0.011215754 | I16: Gobernanza | J16: 11,16 | K16: =IF(ISNUMBER(SEARCH("13",J16)),H01_PARÁMETROS!$B$36,IF(ISNUMBER(SEARCH("5",J16)),H01_PARÁMETROS!$B$37,1)) -> 1 | L16: {=(E16*K16)/SUMPRODUCT(MAX($E$6:$E$25*$K$6:$K$25))} -> 0.57971014 | M16: Recursos propios GAD | N16: 80 | O16: % levantamiento SIL catastro urbano-rural | P16: 19.52 | Q16: Porcentaje del sistema de información local (catastro urbano-rural) incrementado al 80% hasta 2027 | R16: Dirección de Agua y Saneamiento | S16: 367 | T16: =IF(COUNTIF(H03_S1_ELECTORAL_CNE!D:D,A16)>0,"✅ Vinculada CNE","⚠️ Sin vínculo electoral") -> ✅ Vinculada CNE
A17: SC-I-N-03 | B17: Participación ciudadana: 50→100 Unidades Territoriales participativas; 2→4 instancias efectivas (COPFP Art.115) | C17: Institucional | D17: Exclusiva_Importante | E17: 1 | F17: 137900 | G17: 34475 | H17: =G17/SUM($G$6:$G$25) -> 0.0008500108 | I17: Gobernanza | J17: 16,17 | K17: =IF(ISNUMBER(SEARCH("13",J17)),H01_PARÁMETROS!$B$36,IF(ISNUMBER(SEARCH("5",J17)),H01_PARÁMETROS!$B$37,1)) -> 1 | L17: {=(E17*K17)/SUMPRODUCT(MAX($E$6:$E$25*$K$6:$K$25))} -> 0.57971014 | M17: Recursos propios GAD | N17: 100 | O17: Unidades Territoriales participativas activas | P17: 50 | Q17: Número de Unidades Territoriales participativas incrementado a 100 hasta 2027 | R17: Patronato Municipal | S17: 368 | T17: =IF(COUNTIF(H03_S1_ELECTORAL_CNE!D:D,A17)>0,"✅ Vinculada CNE","⚠️ Sin vínculo electoral") -> ⚠️ Sin vínculo electoral
A18: FA-I-X-01 | B18: Gestión del riesgo: reducir 10% infraestructura susceptible (3,655→2,398 unidades); alerta temprana climática | C18: Ambiental | D18: Exclusiva_Importante | E18: 1 | F18: 950000 | G18: 237500 | H18: =G18/SUM($G$6:$G$25) -> 0.005855767 | I18: Infraestructura | J18: 11,13 | K18: =IF(ISNUMBER(SEARCH("13",J18)),H01_PARÁMETROS!$B$36,IF(ISNUMBER(SEARCH("5",J18)),H01_PARÁMETROS!$B$37,1)) -> 1.15 | L18: {=(E18*K18)/SUMPRODUCT(MAX($E$6:$E$25*$K$6:$K$25))} -> 0.66666667 | M18: Recursos propios GAD | N18: 2398.05 | O18: Unidades infraestructura susceptible (meta reducción) | P18: 3655 | Q18: Número de infraestructura susceptible a riesgos reducida al 10% hasta 2027 | R18: Dirección Ambiental | S18: 362 | T18: =IF(COUNTIF(H03_S1_ELECTORAL_CNE!D:D,A18)>0,"✅ Vinculada CNE","⚠️ Sin vínculo electoral") -> ⚠️ Sin vínculo electoral
A19: FA-C-X-01 | B19: Áreas verdes y parques: IVU 10.94→17.32 m²/hab; parques inter-barriales; recuperación manglar perfil costero | C19: Ambiental | D19: Exclusiva_Importante | E19: 1 | F19: 709999 | G19: 177500 | H19: =G19/SUM($G$6:$G$25) -> 0.0043764153 | I19: Infraestructura | J19: 11,13,15 | K19: =IF(ISNUMBER(SEARCH("13",J19)),H01_PARÁMETROS!$B$36,IF(ISNUMBER(SEARCH("5",J19)),H01_PARÁMETROS!$B$37,1)) -> 1.15 | L19: {=(E19*K19)/SUMPRODUCT(MAX($E$6:$E$25*$K$6:$K$25))} -> 0.66666667 | M19: Recursos propios GAD | N19: 17.32 | O19: m²/hab índice verde urbano | P19: 10.94 | Q19: Índice verde urbano consolidado y áreas recreativas incrementado a 17.32 m²/hab hasta 2027 | R19: EP Aseo Montecristi | S19: 362 | T19: =IF(COUNTIF(H03_S1_ELECTORAL_CNE!D:D,A19)>0,"✅ Vinculada CNE","⚠️ Sin vínculo electoral") -> ✅ Vinculada CNE
A20: FA-I-X-02 | B20: Índice equipamiento urbano CUP 9.96→10.73 m²/hab; recolección desechos 91.95%→97.95%; 77.83→81.07 km/día barrido | C20: Territorial | D20: Exclusiva_Importante | E20: 1 | F20: 5001963 | G20: 1250491 | H20: =G20/SUM($G$6:$G$25) -> 0.030831932 | I20: Infraestructura | J20: 11 | K20: =IF(ISNUMBER(SEARCH("13",J20)),H01_PARÁMETROS!$B$36,IF(ISNUMBER(SEARCH("5",J20)),H01_PARÁMETROS!$B$37,1)) -> 1 | L20: {=(E20*K20)/SUMPRODUCT(MAX($E$6:$E$25*$K$6:$K$25))} -> 0.57971014 | M20: Recursos propios GAD | N20: 97.95 | O20: % cobertura recolección desechos | P20: 91.95 | Q20: Porcentaje de cobertura de recolección de desechos incrementado al 97.95% hasta 2027 | R20: Dirección Ambiental | S20: 365 | T20: =IF(COUNTIF(H03_S1_ELECTORAL_CNE!D:D,A20)>0,"✅ Vinculada CNE","⚠️ Sin vínculo electoral") -> ✅ Vinculada CNE
A21: FA-L-N-01 | B21: Inventario patrimonial 100% al 2026; 8,000→10,000 participantes eventos culturales; Museo del Sombrero | C21: Social | D21: Exclusiva_Importante | E21: 1 | F21: 498449 | G21: 124612 | H21: =G21/SUM($G$6:$G$25) -> 0.0030724161 | I21: Inclusion | J21: 4,11 | K21: =IF(ISNUMBER(SEARCH("13",J21)),H01_PARÁMETROS!$B$36,IF(ISNUMBER(SEARCH("5",J21)),H01_PARÁMETROS!$B$37,1)) -> 1 | L21: {=(E21*K21)/SUMPRODUCT(MAX($E$6:$E$25*$K$6:$K$25))} -> 0.57971014 | M21: Recursos propios GAD | N21: 10000 | O21: Participantes anuales en eventos culturales | P21: 8000 | Q21: Número de participantes en eventos culturales incrementado a 10,000 hasta 2027 | R21: Dirección Ambiental | S21: 366 | T21: =IF(COUNTIF(H03_S1_ELECTORAL_CNE!D:D,A21)>0,"✅ Vinculada CNE","⚠️ Sin vínculo electoral") -> ✅ Vinculada CNE
A22: PI-I-G-02 | B22: Cumplimiento PDOT/PUGS 0%→80%; SIL 19.52%→80%; 37 trámites digitales implementados | C22: Institucional | D22: Exclusiva_Importante | E22: 1 | F22: 472973 | G22: 118243 | H22: =G22/SUM($G$6:$G$25) -> 0.002915383 | I22: Gobernanza | J22: 16,17 | K22: =IF(ISNUMBER(SEARCH("13",J22)),H01_PARÁMETROS!$B$36,IF(ISNUMBER(SEARCH("5",J22)),H01_PARÁMETROS!$B$37,1)) -> 1 | L22: {=(E22*K22)/SUMPRODUCT(MAX($E$6:$E$25*$K$6:$K$25))} -> 0.57971014 | M22: Recursos propios GAD | N22: 80 | O22: % cumplimiento PDOT/PUGS | P22: 0 | Q22: Porcentaje de proyectos del PDOT/PUGS ejecutados incrementado al 80% hasta 2027 | R22: Dirección Planificación | S22: 367 | T22: =IF(COUNTIF(H03_S1_ELECTORAL_CNE!D:D,A22)>0,"✅ Vinculada CNE","⚠️ Sin vínculo electoral") -> ✅ Vinculada CNE
A23: PI-L-G-01 | B23: Señalización vial 0→10,000 m²; 0→8 semáforos; revisiones técnicas 4,000→20,000; educación vial 40 instituciones | C23: Territorial | D23: Exclusiva_Importante | E23: 1 | F23: 270900 | G23: 67725 | H23: =G23/SUM($G$6:$G$25) -> 0.0016698182 | I23: Infraestructura | J23: 11,3 | K23: =IF(ISNUMBER(SEARCH("13",J23)),H01_PARÁMETROS!$B$36,IF(ISNUMBER(SEARCH("5",J23)),H01_PARÁMETROS!$B$37,1)) -> 1 | L23: {=(E23*K23)/SUMPRODUCT(MAX($E$6:$E$25*$K$6:$K$25))} -> 0.57971014 | M23: Recursos propios GAD | N23: 20000 | O23: Revisiones técnicas vehiculares anuales | P23: 4000 | Q23: Número de revisiones técnicas vehiculares incrementado a 20,000 hasta 2027 | R23: Dirección Planificación | S23: 364 | T23: =IF(COUNTIF(H03_S1_ELECTORAL_CNE!D:D,A23)>0,"✅ Vinculada CNE","⚠️ Sin vínculo electoral") -> ✅ Vinculada CNE
A24: EP-L-N-01 | B24: Vivienda de interés social: 50 VIS/VIP hasta 2027; reducción déficit habitacional cualitativo | C24: Territorial | D24: Exclusiva_Importante | E24: 1 | F24: 324000 | G24: 81000 | H24: =G24/SUM($G$6:$G$25) -> 0.0019971247 | I24: Infraestructura | J24: 1,11 | K24: =IF(ISNUMBER(SEARCH("13",J24)),H01_PARÁMETROS!$B$36,IF(ISNUMBER(SEARCH("5",J24)),H01_PARÁMETROS!$B$37,1)) -> 1 | L24: {=(E24*K24)/SUMPRODUCT(MAX($E$6:$E$25*$K$6:$K$25))} -> 0.57971014 | M24: Recursos propios + MIDUVI | N24: 50 | O24: Viviendas de interés social ofertadas | P24: 0 | Q24: Número de viviendas de interés social ofertadas acumuladas: 50 hasta 2027 | R24: Dirección Económica | S24: 365 | T24: =IF(COUNTIF(H03_S1_ELECTORAL_CNE!D:D,A24)>0,"✅ Vinculada CNE","⚠️ Sin vínculo electoral") -> ✅ Vinculada CNE
A25: EP-L-X-01 | B25: Fortalecimiento productivo: beneficiarios artesanos, mipymes, emprendedores, huertos comunitarios y cadenas de valor | C25: Económico | D25: Complementaria | E25: 0.5 | F25: 230363 | G25: 57591 | H25: =G25/SUM($G$6:$G$25) -> 0.0014199557 | I25: Gobernanza | J25: 1,8,10 | K25: =IF(ISNUMBER(SEARCH("13",J25)),H01_PARÁMETROS!$B$36,IF(ISNUMBER(SEARCH("5",J25)),H01_PARÁMETROS!$B$37,1)) -> 1 | L25: {=(E25*K25)/SUMPRODUCT(MAX($E$6:$E$25*$K$6:$K$25))} -> 0.28985507 | M25: Recursos propios GAD | N25: 500 | O25: Beneficiarios programas fortalecimiento productivo | P25: 0 | Q25: Número de beneficiarios de programas de formación y fortalecimiento productivo anuales | R25: Dirección Turismo | S25: 440 | T25: =IF(COUNTIF(H03_S1_ELECTORAL_CNE!D:D,A25)>0,"✅ Vinculada CNE","⚠️ Sin vínculo electoral") -> ✅ Vinculada CNE

Sheet H05_S3_OPERATIVO_POA
A1: 🏛️ TERRA SIAP-ICPI v2.0 | QUADRUM | B1: ⬅️ ÍNDICE GENERAL | C1: ="ICPI: "&TEXT(H12_MOTOR_ICPI_CANÓNICO!B28,"0,0")&"%" -> ICPI: 72,9% | D1: H05 — S3 POA | E1: =TEXT(TODAY(),"DD/MM/YYYY") -> 05/04/2026
A2: S3 — SILO OPERATIVO (POA)
A3: Plan Operativo Anual con metas desagregadas, cronograma de ejecución y responsables. Operacionaliza el PDOT en acciones ejecutables dentro del año fiscal.
A4: Fundamentación: COPFP Art.9 + COOTAD Art.234
A6: ID_Meta | B6: Descripción_Meta | C6: Dirección_Responsable | D6: Meta_Cuantitativa | E6: Unidad_Medida | F6: Presup_Anual_2024 | G6: ENE_Plan_% | H6: ENE_Ejec_% | I6: FEB_Plan_% | J6: FEB_Ejec_% | K6: MAR_Plan_% | L6: MAR_Ejec_% | M6: ABR_Plan_% | N6: ABR_Ejec_% | O6: MAY_Plan_% | P6: MAY_Ejec_% | Q6: JUN_Plan_% | R6: JUN_Ejec_% | S6: JUL_Plan_% | T6: JUL_Ejec_% | U6: AGO_Plan_% | V6: AGO_Ejec_% | W6: SEP_Plan_% | X6: SEP_Ejec_% | Y6: OCT_Plan_% | Z6: OCT_Ejec_% | AA6: NOV_Plan_% | AB6: NOV_Ejec_% | AC6: DIC_Plan_% | AD6: DIC_Ejec_% | AE6: Avance_Acum_Real | AF6: Semáforo_POA | AG6: Alerta_Inversión
A7: =H04_S2_PLANIFICACIÓN_PDOT!A6 -> SC-I-N-01 | B7: =H04_S2_PLANIFICACIÓN_PDOT!B6 -> Agua potable: cobertura 39.25%→42.38%; calidad 100% INEN 1108; infraestructura BUENA 22.74%→41.64% | C7: =H04_S2_PLANIFICACIÓN_PDOT!R6 -> Patronato Municipal | D7: =H04_S2_PLANIFICACIÓN_PDOT!N6 -> 42.38 | E7: =H04_S2_PLANIFICACIÓN_PDOT!O6 -> % cobertura agua potable | F7: =H04_S2_PLANIFICACIÓN_PDOT!G6 -> 11726219 | G7: 5 | H7: 0 | I7: 10 | J7: 0 | K7: 15 | L7: 0 | M7: 25 | N7: 0 | O7: 35 | P7: 0 | Q7: 45 | R7: 0 | S7: 55 | T7: 0 | U7: 65 | V7: 0 | W7: 75 | X7: 0 | Y7: 85 | Z7: 0 | AA7: 92 | AB7: 0 | AC7: 100 | AD7: 0 | AE7: =AVERAGE(H7,J7,L7,N7,P7,R7,T7,V7,X7,Z7,AB7,AD7) -> 0 | AF7: =IF(AC7=0,"⏸️",IF(AE7/AC7>=0.9,"🟢",IF(AE7/AC7>=0.7,"🟡","🔴"))) -> 🔴 | AG7: =IF(F7>0,"✅ Con presupuesto inversión","⚠️ SIN PRESUPUESTO — verificar clasificación") -> ✅ Con presupuesto inversión
A8: =H04_S2_PLANIFICACIÓN_PDOT!A7 -> SC-L-N-02 | B8: =H04_S2_PLANIFICACIÓN_PDOT!B7 -> Gestión del talento humano municipal: desempeño 80%→90%; plan capacitación 90% anual | C8: =H04_S2_PLANIFICACIÓN_PDOT!R7 -> Dirección TIC | D8: =H04_S2_PLANIFICACIÓN_PDOT!N7 -> 90 | E8: =H04_S2_PLANIFICACIÓN_PDOT!O7 -> % nivel desempeño personal | F8: =H04_S2_PLANIFICACIÓN_PDOT!G7 -> 13194220 | G8: 0 | H8: 0 | I8: 0 | J8: 0 | K8: 0 | L8: 0 | M8: 17 | N8: 0 | O8: 33 | P8: 0 | Q8: 50 | R8: 0 | S8: 67 | T8: 0 | U8: 83 | V8: 0 | W8: 100 | X8: 0 | Y8: 100 | Z8: 0 | AA8: 100 | AB8: 0 | AC8: 100 | AD8: 0 | AE8: =AVERAGE(H8,J8,L8,N8,P8,R8,T8,V8,X8,Z8,AB8,AD8) -> 0 | AF8: =IF(AC8=0,"⏸️",IF(AE8/AC8>=0.9,"🟢",IF(AE8/AC8>=0.7,"🟡","🔴"))) -> 🔴 | AG8: =IF(F8>0,"✅ Con presupuesto inversión","⚠️ SIN PRESUPUESTO — verificar clasificación") -> ✅ Con presupuesto inversión
A9: =H04_S2_PLANIFICACIÓN_PDOT!A8 -> AH-I-X-01 | B9: =H04_S2_PLANIFICACIÓN_PDOT!B8 -> Sostenibilidad financiera: autonomía 43.35%→45.30%; gestión cobros y coactivas | C9: =H04_S2_PLANIFICACIÓN_PDOT!R8 -> Dirección de Obras Públicas | D9: =H04_S2_PLANIFICACIÓN_PDOT!N8 -> 45.3 | E9: =H04_S2_PLANIFICACIÓN_PDOT!O8 -> % autonomía financiera | F9: =H04_S2_PLANIFICACIÓN_PDOT!G8 -> 5051427 | G9: 0 | H9: 0 | I9: 0 | J9: 0 | K9: 0 | L9: 0 | M9: 11 | N9: 0 | O9: 22 | P9: 0 | Q9: 33 | R9: 0 | S9: 44 | T9: 0 | U9: 56 | V9: 0 | W9: 67 | X9: 0 | Y9: 78 | Z9: 0 | AA9: 89 | AB9: 0 | AC9: 100 | AD9: 0 | AE9: =AVERAGE(H9,J9,L9,N9,P9,R9,T9,V9,X9,Z9,AB9,AD9) -> 0 | AF9: =IF(AC9=0,"⏸️",IF(AE9/AC9>=0.9,"🟢",IF(AE9/AC9>=0.7,"🟡","🔴"))) -> 🔴 | AG9: =IF(F9>0,"✅ Con presupuesto inversión","⚠️ SIN PRESUPUESTO — verificar clasificación") -> ✅ Con presupuesto inversión
A10: =H04_S2_PLANIFICACIÓN_PDOT!A9 -> AH-I-X-02 | B10: =H04_S2_PLANIFICACIÓN_PDOT!B9 -> Vialidad cantonal: mantenimiento 43.8 km vías CUP + 57.22 km rurales; 23.77 km tratamiento medio | C10: =H04_S2_PLANIFICACIÓN_PDOT!R9 -> Dirección de Obras Públicas | D10: =H04_S2_PLANIFICACIÓN_PDOT!N9 -> 130.21 | E10: =H04_S2_PLANIFICACIÓN_PDOT!O9 -> Km vías mantenidas CUP acumulado | F10: =H04_S2_PLANIFICACIÓN_PDOT!G9 -> 2729440 | G10: 0 | H10: 0 | I10: 0 | J10: 0 | K10: 0 | L10: 0 | M10: 0 | N10: 0 | O10: 0 | P10: 0 | Q10: 0 | R10: 0 | S10: 0 | T10: 0 | U10: 0 | V10: 0 | W10: 0 | X10: 0 | Y10: 0 | Z10: 0 | AA10: 0 | AB10: 0 | AC10: 0 | AD10: 0 | AE10: =AVERAGE(H10,J10,L10,N10,P10,R10,T10,V10,X10,Z10,AB10,AD10) -> 0 | AF10: =IF(AC10=0,"⏸️",IF(AE10/AC10>=0.9,"🟢",IF(AE10/AC10>=0.7,"🟡","🔴"))) -> ⏸️ | AG10: =IF(F10>0,"✅ Con presupuesto inversión","⚠️ SIN PRESUPUESTO — verificar clasificación") -> ✅ Con presupuesto inversión
A11: =H04_S2_PLANIFICACIÓN_PDOT!A10 -> AH-I-X-03 | B11: =H04_S2_PLANIFICACIÓN_PDOT!B10 -> Salud integral municipal: población atendida 57,401→84,041 personas (+10% anual) | C11: =H04_S2_PLANIFICACIÓN_PDOT!R10 -> Dirección de Obras Públicas | D11: =H04_S2_PLANIFICACIÓN_PDOT!N10 -> 84041 | E11: =H04_S2_PLANIFICACIÓN_PDOT!O10 -> Personas atendidas salud municipal | F11: =H04_S2_PLANIFICACIÓN_PDOT!G10 -> 1470661 | G11: 0 | H11: 0 | I11: 0 | J11: 0 | K11: 0 | L11: 0 | M11: 17 | N11: 0 | O11: 33 | P11: 0 | Q11: 50 | R11: 0 | S11: 67 | T11: 0 | U11: 83 | V11: 0 | W11: 100 | X11: 0 | Y11: 100 | Z11: 0 | AA11: 100 | AB11: 0 | AC11: 100 | AD11: 0 | AE11: =AVERAGE(H11,J11,L11,N11,P11,R11,T11,V11,X11,Z11,AB11,AD11) -> 0 | AF11: =IF(AC11=0,"⏸️",IF(AE11/AC11>=0.9,"🟢",IF(AE11/AC11>=0.7,"🟡","🔴"))) -> 🔴 | AG11: =IF(F11>0,"✅ Con presupuesto inversión","⚠️ SIN PRESUPUESTO — verificar clasificación") -> ✅ Con presupuesto inversión
A12: =H04_S2_PLANIFICACIÓN_PDOT!A11 -> AH-I-N-01 | B12: =H04_S2_PLANIFICACIÓN_PDOT!B11 -> Gestión integral desechos sólidos: 20,118→23,086 Tn/año; relleno sanitario; capacidad disposición 0%→20% | C12: =H04_S2_PLANIFICACIÓN_PDOT!R11 -> EP Montehogar | D12: =H04_S2_PLANIFICACIÓN_PDOT!N11 -> 23086.94 | E12: =H04_S2_PLANIFICACIÓN_PDOT!O11 -> Toneladas de desechos gestionadas/año | F12: =H04_S2_PLANIFICACIÓN_PDOT!G11 -> 1437686 | G12: 17 | H12: 0 | I12: 33 | J12: 0 | K12: 50 | L12: 0 | M12: 67 | N12: 0 | O12: 83 | P12: 0 | Q12: 100 | R12: 0 | S12: 100 | T12: 0 | U12: 100 | V12: 0 | W12: 100 | X12: 0 | Y12: 100 | Z12: 0 | AA12: 100 | AB12: 0 | AC12: 100 | AD12: 0 | AE12: =AVERAGE(H12,J12,L12,N12,P12,R12,T12,V12,X12,Z12,AB12,AD12) -> 0 | AF12: =IF(AC12=0,"⏸️",IF(AE12/AC12>=0.9,"🟢",IF(AE12/AC12>=0.7,"🟡","🔴"))) -> 🔴 | AG12: =IF(F12>0,"✅ Con presupuesto inversión","⚠️ SIN PRESUPUESTO — verificar clasificación") -> ✅ Con presupuesto inversión
A13: =H04_S2_PLANIFICACIÓN_PDOT!A12 -> SC-L-G-01 | B13: =H04_S2_PLANIFICACIÓN_PDOT!B12 -> Alcantarillado sanitario: cobertura 19.77%→24.32%; PTAR 0%→75%; estaciones bombeo 36%→72% | C13: =H04_S2_PLANIFICACIÓN_PDOT!R12 -> Dirección de Cultura y Deporte | D13: =H04_S2_PLANIFICACIÓN_PDOT!N12 -> 24.32 | E13: =H04_S2_PLANIFICACIÓN_PDOT!O12 -> % cobertura alcantarillado sanitario | F13: =H04_S2_PLANIFICACIÓN_PDOT!G12 -> 317465 | G13: 5 | H13: 0 | I13: 10 | J13: 0 | K13: 15 | L13: 0 | M13: 25 | N13: 0 | O13: 35 | P13: 0 | Q13: 45 | R13: 0 | S13: 55 | T13: 0 | U13: 65 | V13: 0 | W13: 75 | X13: 0 | Y13: 85 | Z13: 0 | AA13: 92 | AB13: 0 | AC13: 100 | AD13: 0 | AE13: =AVERAGE(H13,J13,L13,N13,P13,R13,T13,V13,X13,Z13,AB13,AD13) -> 0 | AF13: =IF(AC13=0,"⏸️",IF(AE13/AC13>=0.9,"🟢",IF(AE13/AC13>=0.7,"🟡","🔴"))) -> 🔴 | AG13: =IF(F13>0,"✅ Con presupuesto inversión","⚠️ SIN PRESUPUESTO — verificar clasificación") -> ✅ Con presupuesto inversión
A14: =H04_S2_PLANIFICACIÓN_PDOT!A13 -> AH-I-X-04 | B14: =H04_S2_PLANIFICACIÓN_PDOT!B13 -> Modernización recursos administrativos: parque automotor, tecnología e infraestructura municipal | C14: =H04_S2_PLANIFICACIÓN_PDOT!R13 -> Dirección de Obras Públicas | D14: =H04_S2_PLANIFICACIÓN_PDOT!N13 -> 1 | E14: =H04_S2_PLANIFICACIÓN_PDOT!O13 -> Parque automotor y tecnología renovados | F14: =H04_S2_PLANIFICACIÓN_PDOT!G13 -> 941255 | G14: 5 | H14: 0 | I14: 15 | J14: 0 | K14: 25 | L14: 0 | M14: 37 | N14: 0 | O14: 48 | P14: 0 | Q14: 60 | R14: 0 | S14: 72 | T14: 0 | U14: 84 | V14: 0 | W14: 100 | X14: 0 | Y14: 100 | Z14: 0 | AA14: 100 | AB14: 0 | AC14: 100 | AD14: 0 | AE14: =AVERAGE(H14,J14,L14,N14,P14,R14,T14,V14,X14,Z14,AB14,AD14) -> 0 | AF14: =IF(AC14=0,"⏸️",IF(AE14/AC14>=0.9,"🟢",IF(AE14/AC14>=0.7,"🟡","🔴"))) -> 🔴 | AG14: =IF(F14>0,"✅ Con presupuesto inversión","⚠️ SIN PRESUPUESTO — verificar clasificación") -> ✅ Con presupuesto inversión
A15: =H04_S2_PLANIFICACIÓN_PDOT!A14 -> PI-I-G-01 | B15: =H04_S2_PLANIFICACIÓN_PDOT!B14 -> Equipamientos públicos: terminal terrestre, mercado, estación bomberil, centro salud tipo C, mantenimiento espacios recreativos | C15: =H04_S2_PLANIFICACIÓN_PDOT!R14 -> Dirección Administrativa | D15: =H04_S2_PLANIFICACIÓN_PDOT!N14 -> 10.73 | E15: =H04_S2_PLANIFICACIÓN_PDOT!O14 -> m² / hab índice equipamiento urbano CUP | F15: =H04_S2_PLANIFICACIÓN_PDOT!G14 -> 647139 | G15: 5 | H15: 0 | I15: 10 | J15: 0 | K15: 15 | L15: 0 | M15: 25 | N15: 0 | O15: 35 | P15: 0 | Q15: 45 | R15: 0 | S15: 55 | T15: 0 | U15: 65 | V15: 0 | W15: 75 | X15: 0 | Y15: 85 | Z15: 0 | AA15: 92 | AB15: 0 | AC15: 100 | AD15: 0 | AE15: =AVERAGE(H15,J15,L15,N15,P15,R15,T15,V15,X15,Z15,AB15,AD15) -> 0 | AF15: =IF(AC15=0,"⏸️",IF(AE15/AC15>=0.9,"🟢",IF(AE15/AC15>=0.7,"🟡","🔴"))) -> 🔴 | AG15: =IF(F15>0,"✅ Con presupuesto inversión","⚠️ SIN PRESUPUESTO — verificar clasificación") -> ✅ Con presupuesto inversión
A16: =H04_S2_PLANIFICACIÓN_PDOT!A15 -> AH-C-X-01 | B16: =H04_S2_PLANIFICACIÓN_PDOT!B15 -> Protección derechos sociales: atenciones grupos prioritarios 943→1,649 (+15%/año); CDI; adultos mayores; violencia de género | C16: =H04_S2_PLANIFICACIÓN_PDOT!R15 -> Dirección de Agua y Saneamiento | D16: =H04_S2_PLANIFICACIÓN_PDOT!N15 -> 1649 | E16: =H04_S2_PLANIFICACIÓN_PDOT!O15 -> Atenciones en programas grupos prioritarios | F16: =H04_S2_PLANIFICACIÓN_PDOT!G15 -> 438767 | G16: 5 | H16: 0 | I16: 10 | J16: 0 | K16: 15 | L16: 0 | M16: 25 | N16: 0 | O16: 35 | P16: 0 | Q16: 45 | R16: 0 | S16: 55 | T16: 0 | U16: 65 | V16: 0 | W16: 75 | X16: 0 | Y16: 85 | Z16: 0 | AA16: 92 | AB16: 0 | AC16: 100 | AD16: 0 | AE16: =AVERAGE(H16,J16,L16,N16,P16,R16,T16,V16,X16,Z16,AB16,AD16) -> 0 | AF16: =IF(AC16=0,"⏸️",IF(AE16/AC16>=0.9,"🟢",IF(AE16/AC16>=0.7,"🟡","🔴"))) -> 🔴 | AG16: =IF(F16>0,"✅ Con presupuesto inversión","⚠️ SIN PRESUPUESTO — verificar clasificación") -> ✅ Con presupuesto inversión
A17: =H04_S2_PLANIFICACIÓN_PDOT!A16 -> AH-C-X-02 | B17: =H04_S2_PLANIFICACIÓN_PDOT!B16 -> Sistema información territorial: catastro urbano-rural 19.52%→80%; 12 procesos sistematizados; 37 trámites en línea | C17: =H04_S2_PLANIFICACIÓN_PDOT!R16 -> Dirección de Agua y Saneamiento | D17: =H04_S2_PLANIFICACIÓN_PDOT!N16 -> 80 | E17: =H04_S2_PLANIFICACIÓN_PDOT!O16 -> % levantamiento SIL catastro urbano-rural | F17: =H04_S2_PLANIFICACIÓN_PDOT!G16 -> 454892 | G17: 5 | H17: 0 | I17: 15 | J17: 0 | K17: 25 | L17: 0 | M17: 37 | N17: 0 | O17: 48 | P17: 0 | Q17: 60 | R17: 0 | S17: 72 | T17: 0 | U17: 84 | V17: 0 | W17: 100 | X17: 0 | Y17: 100 | Z17: 0 | AA17: 100 | AB17: 0 | AC17: 100 | AD17: 0 | AE17: =AVERAGE(H17,J17,L17,N17,P17,R17,T17,V17,X17,Z17,AB17,AD17) -> 0 | AF17: =IF(AC17=0,"⏸️",IF(AE17/AC17>=0.9,"🟢",IF(AE17/AC17>=0.7,"🟡","🔴"))) -> 🔴 | AG17: =IF(F17>0,"✅ Con presupuesto inversión","⚠️ SIN PRESUPUESTO — verificar clasificación") -> ✅ Con presupuesto inversión
A18: =H04_S2_PLANIFICACIÓN_PDOT!A17 -> SC-I-N-03 | B18: =H04_S2_PLANIFICACIÓN_PDOT!B17 -> Participación ciudadana: 50→100 Unidades Territoriales participativas; 2→4 instancias efectivas (COPFP Art.115) | C18: =H04_S2_PLANIFICACIÓN_PDOT!R17 -> Patronato Municipal | D18: =H04_S2_PLANIFICACIÓN_PDOT!N17 -> 100 | E18: =H04_S2_PLANIFICACIÓN_PDOT!O17 -> Unidades Territoriales participativas activas | F18: =H04_S2_PLANIFICACIÓN_PDOT!G17 -> 34475 | G18: 5 | H18: 0 | I18: 10 | J18: 0 | K18: 15 | L18: 0 | M18: 25 | N18: 0 | O18: 35 | P18: 0 | Q18: 45 | R18: 0 | S18: 55 | T18: 0 | U18: 65 | V18: 0 | W18: 75 | X18: 0 | Y18: 85 | Z18: 0 | AA18: 92 | AB18: 0 | AC18: 100 | AD18: 0 | AE18: =AVERAGE(H18,J18,L18,N18,P18,R18,T18,V18,X18,Z18,AB18,AD18) -> 0 | AF18: =IF(AC18=0,"⏸️",IF(AE18/AC18>=0.9,"🟢",IF(AE18/AC18>=0.7,"🟡","🔴"))) -> 🔴 | AG18: =IF(F18>0,"✅ Con presupuesto inversión","⚠️ SIN PRESUPUESTO — verificar clasificación") -> ✅ Con presupuesto inversión
... A26: =H04_S2_PLANIFICACIÓN_PDOT!A25 -> EP-L-X-01 | B26: =H04_S2_PLANIFICACIÓN_PDOT!B25 -> Fortalecimiento productivo: beneficiarios artesanos, mipymes, emprendedores, huertos comunitarios y cadenas de valor | C26: =H04_S2_PLANIFICACIÓN_PDOT!R25 -> Dirección Turismo | D26: =H04_S2_PLANIFICACIÓN_PDOT!N25 -> 500 | E26: =H04_S2_PLANIFICACIÓN_PDOT!O25 -> Beneficiarios programas fortalecimiento productivo | F26: =H04_S2_PLANIFICACIÓN_PDOT!G25 -> 57591 | G26: 5 | H26: 0 | I26: 10 | J26: 0 | K26: 15 | L26: 0 | M26: 25 | N26: 0 | O26: 35 | P26: 0 | Q26: 45 | R26: 0 | S26: 55 | T26: 0 | U26: 65 | V26: 0 | W26: 75 | X26: 0 | Y26: 85 | Z26: 0 | AA26: 92 | AB26: 0 | AC26: 100 | AD26: 0 | AE26: =AVERAGE(H26,J26,L26,N26,P26,R26,T26,V26,X26,Z26,AB26,AD26) -> 0 | AF26: =IF(AC26=0,"⏸️",IF(AE26/AC26>=0.9,"🟢",IF(AE26/AC26>=0.7,"🟡","🔴"))) -> 🔴 | AG26: =IF(F26>0,"✅ Con presupuesto inversión","⚠️ SIN PRESUPUESTO — verificar clasificación") -> ✅ Con presupuesto inversión

Sheet H06_S4_CONTRATACIÓN_SERCOP
A1: 🏛️ TERRA SIAP-ICPI v2.0 | QUADRUM | B1: ⬅️ ÍNDICE GENERAL | C1: ="ICPI: "&TEXT(H12_MOTOR_ICPI_CANÓNICO!B28,"0,0")&"%" -> ICPI: 72,9% | D1: H06 — S4 SERCOP | E1: =TEXT(TODAY(),"DD/MM/YYYY") -> 05/04/2026
A2: S4 — SILO CONTRATACIÓN PÚBLICA (SERCOP)
A3: Procesos contractuales publicados en el portal del SERCOP. Materializa las metas POA en compromisos contractuales verificables.
A4: Fundamentación: LOSNCP Art.22 + Art.73
A6: ID_Meta | B6: Descripción_Meta | C6: ID_Proceso_SERCOP | D6: Monto_Adjudicado | E6: Proveedor_RUC | F6: Estado_Proceso | G6: URL_SERCOP | H6: V_SERCOP | I6: Alerta_Sobreprecio
A7: =H04_S2_PLANIFICACIÓN_PDOT!A6 -> SC-I-N-01 | B7: =H04_S2_PLANIFICACIÓN_PDOT!B6 -> Agua potable: cobertura 39.25%→42.38%; calidad 100% INEN 1108; infraestructura BUENA 22.74%→41.64% | C7: PAC-2024-068/087/088/134 | D7: 45000 | E7: [Por adjudicar — PAC publicado] | F7: Adjudicado | G7: https://www.compraspublicas.gob.ec/ProcesoContratacion/compras/PC/buscarProceso.cpe?sg=PAC2024GADMC | H7: =IF(AND(C7<>"",F7="Adjudicado"),1,IF(C7<>"",0.5,0)) -> 1 | I7: =IF(AND(D7>0,D7>H04_S2_PLANIFICACIÓN_PDOT!G6),"⚠️ Monto supera planificación PDOT","✅ OK") -> ✅ OK
A8: =H04_S2_PLANIFICACIÓN_PDOT!A7 -> SC-L-N-02 | B8: =H04_S2_PLANIFICACIÓN_PDOT!B7 -> Gestión del talento humano municipal: desempeño 80%→90%; plan capacitación 90% anual | C8: PAC-2024-052/085 | D8: 8900 | E8: [Por adjudicar — PAC publicado] | F8: Adjudicado | G8: https://www.compraspublicas.gob.ec/ProcesoContratacion/compras/PC/buscarProceso.cpe?sg=PAC2024GADMC | H8: =IF(AND(C8<>"",F8="Adjudicado"),1,IF(C8<>"",0.5,0)) -> 1 | I8: =IF(AND(D8>0,D8>H04_S2_PLANIFICACIÓN_PDOT!G7),"⚠️ Monto supera planificación PDOT","✅ OK") -> ✅ OK
A9: =H04_S2_PLANIFICACIÓN_PDOT!A8 -> AH-I-X-01 | B9: =H04_S2_PLANIFICACIÓN_PDOT!B8 -> Sostenibilidad financiera: autonomía 43.35%→45.30%; gestión cobros y coactivas | C9: PAC-2024-027/028/033/034/039/048/062/095/098/100/164 | D9: 2206556 | E9: [Múltiples proveedores — procesos en ejecución] | F9: Adjudicado | G9: https://www.compraspublicas.gob.ec/ProcesoContratacion/compras/PC/buscarProceso.cpe?sg=PAC2024GADMC | H9: =IF(AND(C9<>"",F9="Adjudicado"),1,IF(C9<>"",0.5,0)) -> 1 | I9: =IF(AND(D9>0,D9>H04_S2_PLANIFICACIÓN_PDOT!G8),"⚠️ Monto supera planificación PDOT","✅ OK") -> ✅ OK
A10: =H04_S2_PLANIFICACIÓN_PDOT!A9 -> AH-I-X-02 | B10: =H04_S2_PLANIFICACIÓN_PDOT!B9 -> Vialidad cantonal: mantenimiento 43.8 km vías CUP + 57.22 km rurales; 23.77 km tratamiento medio | D10: 0 | H10: =IF(AND(C10<>"",F10="Adjudicado"),1,IF(C10<>"",0.5,0)) -> 0 | I10: =IF(AND(D10>0,D10>H04_S2_PLANIFICACIÓN_PDOT!G9),"⚠️ Monto supera planificación PDOT","✅ OK") -> ✅ OK
A11: =H04_S2_PLANIFICACIÓN_PDOT!A10 -> AH-I-X-03 | B11: =H04_S2_PLANIFICACIÓN_PDOT!B10 -> Salud integral municipal: población atendida 57,401→84,041 personas (+10% anual) | C11: PAC-2024-001/013/029/035/036/037/038/040/041/042/049/101/115/116 | D11: 675840 | E11: [Múltiples proveedores — procesos en ejecución] | F11: Adjudicado | G11: https://www.compraspublicas.gob.ec/ProcesoContratacion/compras/PC/buscarProceso.cpe?sg=PAC2024GADMC | H11: =IF(AND(C11<>"",F11="Adjudicado"),1,IF(C11<>"",0.5,0)) -> 1 | I11: =IF(AND(D11>0,D11>H04_S2_PLANIFICACIÓN_PDOT!G10),"⚠️ Monto supera planificación PDOT","✅ OK") -> ✅ OK
A12: =H04_S2_PLANIFICACIÓN_PDOT!A11 -> AH-I-N-01 | B12: =H04_S2_PLANIFICACIÓN_PDOT!B11 -> Gestión integral desechos sólidos: 20,118→23,086 Tn/año; relleno sanitario; capacidad disposición 0%→20% | C12: DEA-MONTEHOGAR-2024 | D12: 0 | E12: EP Montehogar — RUC adscrito | F12: DEA | G12: https://www.compraspublicas.gob.ec/ProcesoContratacion/compras/PC/buscarProceso.cpe?sg=PAC2024GADMC | H12: =IF(AND(C12<>"",F12="Adjudicado"),1,IF(C12<>"",0.5,0)) -> 0.5 | I12: =IF(AND(D12>0,D12>H04_S2_PLANIFICACIÓN_PDOT!G11),"⚠️ Monto supera planificación PDOT","✅ OK") -> ✅ OK
A13: =H04_S2_PLANIFICACIÓN_PDOT!A12 -> SC-L-G-01 | B13: =H04_S2_PLANIFICACIÓN_PDOT!B12 -> Alcantarillado sanitario: cobertura 19.77%→24.32%; PTAR 0%→75%; estaciones bombeo 36%→72% | C13: PAC-2024-125/147/156/157/159 | D13: 299271 | E13: [SPD — múltiples proveedores] | F13: En_proceso | G13: https://www.compraspublicas.gob.ec/ProcesoContratacion/compras/PC/buscarProceso.cpe?sg=PAC2024GADMC | H13: =IF(AND(C13<>"",F13="Adjudicado"),1,IF(C13<>"",0.5,0)) -> 0.5 | I13: =IF(AND(D13>0,D13>H04_S2_PLANIFICACIÓN_PDOT!G12),"⚠️ Monto supera planificación PDOT","✅ OK") -> ✅ OK
A14: =H04_S2_PLANIFICACIÓN_PDOT!A13 -> AH-I-X-04 | B14: =H04_S2_PLANIFICACIÓN_PDOT!B13 -> Modernización recursos administrativos: parque automotor, tecnología e infraestructura municipal | C14: PAC-2024-008/051/058/060/061/065/095/098/109/118/119 | D14: 422356 | E14: [Múltiples proveedores — procesos en ejecución] | F14: Adjudicado | G14: https://www.compraspublicas.gob.ec/ProcesoContratacion/compras/PC/buscarProceso.cpe?sg=PAC2024GADMC | H14: =IF(AND(C14<>"",F14="Adjudicado"),1,IF(C14<>"",0.5,0)) -> 1 | I14: =IF(AND(D14>0,D14>H04_S2_PLANIFICACIÓN_PDOT!G13),"⚠️ Monto supera planificación PDOT","✅ OK") -> ✅ OK
A15: =H04_S2_PLANIFICACIÓN_PDOT!A14 -> PI-I-G-01 | B15: =H04_S2_PLANIFICACIÓN_PDOT!B14 -> Equipamientos públicos: terminal terrestre, mercado, estación bomberil, centro salud tipo C, mantenimiento espacios recreativos | C15: PAC-2024-003/005/006/007/009/014/021/022/024/047/072/073/075/076/089/097/102/103/104/105/106/107/108/117/139/155/165/166 | D15: 2183216 | E15: [Múltiples proveedores — procesos en ejecución] | F15: Adjudicado | G15: https://www.compraspublicas.gob.ec/ProcesoContratacion/compras/PC/buscarProceso.cpe?sg=PAC2024GADMC | H15: =IF(AND(C15<>"",F15="Adjudicado"),1,IF(C15<>"",0.5,0)) -> 1 | I15: =IF(AND(D15>0,D15>H04_S2_PLANIFICACIÓN_PDOT!G14),"⚠️ Monto supera planificación PDOT","✅ OK") -> ⚠️ Monto supera planificación PDOT
A16: =H04_S2_PLANIFICACIÓN_PDOT!A15 -> AH-C-X-01 | B16: =H04_S2_PLANIFICACIÓN_PDOT!B15 -> Protección derechos sociales: atenciones grupos prioritarios 943→1,649 (+15%/año); CDI; adultos mayores; violencia de género | C16: PAC-2024-010/019/045/059/064/091/099/128/129/130/149/153 | D16: 558105 | E16: [Múltiples proveedores — procesos en ejecución] | F16: Adjudicado | G16: https://www.compraspublicas.gob.ec/ProcesoContratacion/compras/PC/buscarProceso.cpe?sg=PAC2024GADMC | H16: =IF(AND(C16<>"",F16="Adjudicado"),1,IF(C16<>"",0.5,0)) -> 1 | I16: =IF(AND(D16>0,D16>H04_S2_PLANIFICACIÓN_PDOT!G15),"⚠️ Monto supera planificación PDOT","✅ OK") -> ⚠️ Monto supera planificación PDOT
A17: =H04_S2_PLANIFICACIÓN_PDOT!A16 -> AH-C-X-02 | B17: =H04_S2_PLANIFICACIÓN_PDOT!B16 -> Sistema información territorial: catastro urbano-rural 19.52%→80%; 12 procesos sistematizados; 37 trámites en línea | C17: PAC-2024-030/043/044/063/067/111/150 | D17: 625859 | E17: [Múltiples proveedores — procesos en ejecución] | F17: Adjudicado | G17: https://www.compraspublicas.gob.ec/ProcesoContratacion/compras/PC/buscarProceso.cpe?sg=PAC2024GADMC | H17: =IF(AND(C17<>"",F17="Adjudicado"),1,IF(C17<>"",0.5,0)) -> 1 | I17: =IF(AND(D17>0,D17>H04_S2_PLANIFICACIÓN_PDOT!G16),"⚠️ Monto supera planificación PDOT","✅ OK") -> ⚠️ Monto supera planificación PDOT
A18: =H04_S2_PLANIFICACIÓN_PDOT!A17 -> SC-I-N-03 | B18: =H04_S2_PLANIFICACIÓN_PDOT!B17 -> Participación ciudadana: 50→100 Unidades Territoriales participativas; 2→4 instancias efectivas (COPFP Art.115) | C18: PAC-2024-079/081/083/084/124/135/141 | D18: 37000 | E18: [SPD — múltiples proveedores] | F18: En_proceso | G18: https://www.compraspublicas.gob.ec/ProcesoContratacion/compras/PC/buscarProceso.cpe?sg=PAC2024GADMC | H18: =IF(AND(C18<>"",F18="Adjudicado"),1,IF(C18<>"",0.5,0)) -> 0.5 | I18: =IF(AND(D18>0,D18>H04_S2_PLANIFICACIÓN_PDOT!G17),"⚠️ Monto supera planificación PDOT","✅ OK") -> ⚠️ Monto supera planificación PDOT
A19: =H04_S2_PLANIFICACIÓN_PDOT!A18 -> FA-I-X-01 | B19: =H04_S2_PLANIFICACIÓN_PDOT!B18 -> Gestión del riesgo: reducir 10% infraestructura susceptible (3,655→2,398 unidades); alerta temprana climática | C19: PAC-2024-018/053 | D19: 78500 | E19: [Por adjudicar — PAC publicado] | F19: Adjudicado | G19: https://www.compraspublicas.gob.ec/ProcesoContratacion/compras/PC/buscarProceso.cpe?sg=PAC2024GADMC | H19: =IF(AND(C19<>"",F19="Adjudicado"),1,IF(C19<>"",0.5,0)) -> 1 | I19: =IF(AND(D19>0,D19>H04_S2_PLANIFICACIÓN_PDOT!G18),"⚠️ Monto supera planificación PDOT","✅ OK") -> ✅ OK
A20: =H04_S2_PLANIFICACIÓN_PDOT!A19 -> FA-C-X-01 | B20: =H04_S2_PLANIFICACIÓN_PDOT!B19 -> Áreas verdes y parques: IVU 10.94→17.32 m²/hab; parques inter-barriales; recuperación manglar perfil costero | C20: DEA-ASEO-EP-2024 | D20: 5000 | E20: EP Aseo Montecristi — RUC adscrito | F20: DEA | G20: https://www.compraspublicas.gob.ec/ProcesoContratacion/compras/PC/buscarProceso.cpe?sg=PAC2024GADMC | H20: =IF(AND(C20<>"",F20="Adjudicado"),1,IF(C20<>"",0.5,0)) -> 0.5 | I20: =IF(AND(D20>0,D20>H04_S2_PLANIFICACIÓN_PDOT!G19),"⚠️ Monto supera planificación PDOT","✅ OK") -> ✅ OK
A21: =H04_S2_PLANIFICACIÓN_PDOT!A20 -> FA-I-X-02 | B21: =H04_S2_PLANIFICACIÓN_PDOT!B20 -> Índice equipamiento urbano CUP 9.96→10.73 m²/hab; recolección desechos 91.95%→97.95%; 77.83→81.07 km/día barrido | C21: PAC-2024-013/046/055/110/131 | D21: 37600 | E21: [Por adjudicar — PAC publicado] | F21: Adjudicado | G21: https://www.compraspublicas.gob.ec/ProcesoContratacion/compras/PC/buscarProceso.cpe?sg=PAC2024GADMC | H21: =IF(AND(C21<>"",F21="Adjudicado"),1,IF(C21<>"",0.5,0)) -> 1 | I21: =IF(AND(D21>0,D21>H04_S2_PLANIFICACIÓN_PDOT!G20),"⚠️ Monto supera planificación PDOT","✅ OK") -> ✅ OK
A22: =H04_S2_PLANIFICACIÓN_PDOT!A21 -> FA-L-N-01 | B22: =H04_S2_PLANIFICACIÓN_PDOT!B21 -> Inventario patrimonial 100% al 2026; 8,000→10,000 participantes eventos culturales; Museo del Sombrero | C22: PAC-2024-122 | D22: 5000 | E22: [SPD — proveedor único] | F22: En_proceso | G22: https://www.compraspublicas.gob.ec/ProcesoContratacion/compras/PC/buscarProceso.cpe?sg=PAC2024GADMC | H22: =IF(AND(C22<>"",F22="Adjudicado"),1,IF(C22<>"",0.5,0)) -> 0.5 | I22: =IF(AND(D22>0,D22>H04_S2_PLANIFICACIÓN_PDOT!G21),"⚠️ Monto supera planificación PDOT","✅ OK") -> ✅ OK
... A26: =H04_S2_PLANIFICACIÓN_PDOT!A25 -> EP-L-X-01 | B26: =H04_S2_PLANIFICACIÓN_PDOT!B25 -> Fortalecimiento productivo: beneficiarios artesanos, mipymes, emprendedores, huertos comunitarios y cadenas de valor | C26: PAC-2024-120/121 | D26: 163400 | E26: [Por adjudicar — PAC publicado] | F26: Adjudicado | G26: https://www.compraspublicas.gob.ec/ProcesoContratacion/compras/PC/buscarProceso.cpe?sg=PAC2024GADMC | H26: =IF(AND(C26<>"",F26="Adjudicado"),1,IF(C26<>"",0.5,0)) -> 1 | I26: =IF(AND(D26>0,D26>H04_S2_PLANIFICACIÓN_PDOT!G25),"⚠️ Monto supera planificación PDOT","✅ OK") -> ⚠️ Monto supera planificación PDOT

Sheet H07_S5_FINANCIERO_eSIGEF
A1: ⚠️ SIMULACIÓN TÉCNICA — CÉDULA 2024: Datos simulados a partir del PAC 2024 oficial y POA 2024 del GAD Montecristi. Portal eSIGEF no es de acceso público. Actualizar con cédula real cuando el GAD autorice el acceso. Metodología: tasas de ejecución basadas en estándares GADs similares Ecuador. Ref. Memorandum 0511-CNVC-DF-GADMCM-2026 | B1: ⬅️ ÍNDICE GENERAL | C1: ="ICPI: "&TEXT(H12_MOTOR_ICPI_CANÓNICO!B28,"0,0")&"%" -> ICPI: 72,9% | D1: H07 — S5 eSIGEF | E1: =TEXT(TODAY(),"DD/MM/YYYY") -> 05/04/2026
A2: S5 — SILO FINANCIERO (eSIGEF/MEF)
A3: Ejecución presupuestaria con devengado certificado en el sistema nacional del MEF. Registra el momento en que el bien o servicio es efectivamente recibido.
A4: Fundamentación: COPFP Arts.115-117 + Acuerdo 067 MEF
A6: ID_Meta | B6: Descripción_Meta | C6: Partida_Presupuestaria | D6: Grupo_Presup | E6: Codificado | F6: Devengado | G6: T_i (Tasa Ejec.) | H6: V_eSIGEF | I6: Flag_SAT_IV
A7: =H04_S2_PLANIFICACIÓN_PDOT!A6 -> SC-I-N-01 | B7: =H04_S2_PLANIFICACIÓN_PDOT!B6 -> Agua potable: cobertura 39.25%→42.38%; calidad 100% INEN 1108; infraestructura BUENA 22.74%→41.64% | C7: 73.08 | D7: 73 | E7: 45000 | F7: =E7*0.95 -> 42750 | G7: =IF(E7>0,F7/E7,0) -> 0.95 | H7: =IF(F7>0,1,IF(E7>0,0.5,0)) -> 1 | I7: =IF(AND(OR(D7=71,D7=73,D7=78),F7>0,H01_PARÁMETROS!B34="SÍ"),"⚠️ SAT-IV — Meta social en período restricción fiscal","✅ OK") -> ✅ OK
A8: =H04_S2_PLANIFICACIÓN_PDOT!A7 -> SC-L-N-02 | B8: =H04_S2_PLANIFICACIÓN_PDOT!B7 -> Gestión del talento humano municipal: desempeño 80%→90%; plan capacitación 90% anual | C8: 53.08 | D8: 53 | E8: 8900 | F8: =E8*0.85 -> 7565 | G8: =IF(E8>0,F8/E8,0) -> 0.85 | H8: =IF(F8>0,1,IF(E8>0,0.5,0)) -> 1 | I8: =IF(AND(OR(D8=71,D8=73,D8=78),F8>0,H01_PARÁMETROS!B34="SÍ"),"⚠️ SAT-IV — Meta social en período restricción fiscal","✅ OK") -> ✅ OK
A9: =H04_S2_PLANIFICACIÓN_PDOT!A8 -> AH-I-X-01 | B9: =H04_S2_PLANIFICACIÓN_PDOT!B8 -> Sostenibilidad financiera: autonomía 43.35%→45.30%; gestión cobros y coactivas | C9: 75.01 | D9: 75 | E9: 2206556 | F9: =E9*0.72 -> 1588720.3 | G9: =IF(E9>0,F9/E9,0) -> 0.72 | H9: =IF(F9>0,1,IF(E9>0,0.5,0)) -> 1 | I9: =IF(AND(OR(D9=71,D9=73,D9=78),F9>0,H01_PARÁMETROS!B34="SÍ"),"⚠️ SAT-IV — Meta social en período restricción fiscal","✅ OK") -> ✅ OK
A10: =H04_S2_PLANIFICACIÓN_PDOT!A9 -> AH-I-X-02 | B10: =H04_S2_PLANIFICACIÓN_PDOT!B9 -> Vialidad cantonal: mantenimiento 43.8 km vías CUP + 57.22 km rurales; 23.77 km tratamiento medio | E10: 0 | F10: 0 | G10: =IF(E10>0,F10/E10,0) -> 0 | H10: =IF(F10>0,1,IF(E10>0,0.5,0)) -> 0 | I10: =IF(AND(OR(D10=71,D10=73,D10=78),F10>0,H01_PARÁMETROS!B34="SÍ"),"⚠️ SAT-IV — Meta social en período restricción fiscal","✅ OK") -> ✅ OK
A11: =H04_S2_PLANIFICACIÓN_PDOT!A10 -> AH-I-X-03 | B11: =H04_S2_PLANIFICACIÓN_PDOT!B10 -> Salud integral municipal: población atendida 57,401→84,041 personas (+10% anual) | C11: 75.01 | D11: 75 | E11: 675840 | F11: =E11*0.72 -> 486604.8 | G11: =IF(E11>0,F11/E11,0) -> 0.72 | H11: =IF(F11>0,1,IF(E11>0,0.5,0)) -> 1 | I11: =IF(AND(OR(D11=71,D11=73,D11=78),F11>0,H01_PARÁMETROS!B34="SÍ"),"⚠️ SAT-IV — Meta social en período restricción fiscal","✅ OK") -> ✅ OK
A12: =H04_S2_PLANIFICACIÓN_PDOT!A11 -> AH-I-N-01 | B12: =H04_S2_PLANIFICACIÓN_PDOT!B11 -> Gestión integral desechos sólidos: 20,118→23,086 Tn/año; relleno sanitario; capacidad disposición 0%→20% | C12: 78.01 | D12: 78 | E12: 50400 | F12: =E12*0.8 -> 40320 | G12: =IF(E12>0,F12/E12,0) -> 0.8 | H12: =IF(F12>0,1,IF(E12>0,0.5,0)) -> 1 | I12: =IF(AND(OR(D12=71,D12=73,D12=78),F12>0,H01_PARÁMETROS!B34="SÍ"),"⚠️ SAT-IV — Meta social en período restricción fiscal","✅ OK") -> ✅ OK
A13: =H04_S2_PLANIFICACIÓN_PDOT!A12 -> SC-L-G-01 | B13: =H04_S2_PLANIFICACIÓN_PDOT!B12 -> Alcantarillado sanitario: cobertura 19.77%→24.32%; PTAR 0%→75%; estaciones bombeo 36%→72% | C13: 73.08 | D13: 73 | E13: 299271 | F13: =E13*0.85 -> 254380.35 | G13: =IF(E13>0,F13/E13,0) -> 0.85 | H13: =IF(F13>0,1,IF(E13>0,0.5,0)) -> 1 | I13: =IF(AND(OR(D13=71,D13=73,D13=78),F13>0,H01_PARÁMETROS!B34="SÍ"),"⚠️ SAT-IV — Meta social en período restricción fiscal","✅ OK") -> ✅ OK
A14: =H04_S2_PLANIFICACIÓN_PDOT!A13 -> AH-I-X-04 | B14: =H04_S2_PLANIFICACIÓN_PDOT!B13 -> Modernización recursos administrativos: parque automotor, tecnología e infraestructura municipal | C14: 75.01 | D14: 75 | E14: 422356 | F14: =E14*0.72 -> 304096.32 | G14: =IF(E14>0,F14/E14,0) -> 0.72 | H14: =IF(F14>0,1,IF(E14>0,0.5,0)) -> 1 | I14: =IF(AND(OR(D14=71,D14=73,D14=78),F14>0,H01_PARÁMETROS!B34="SÍ"),"⚠️ SAT-IV — Meta social en período restricción fiscal","✅ OK") -> ✅ OK
A15: =H04_S2_PLANIFICACIÓN_PDOT!A14 -> PI-I-G-01 | B15: =H04_S2_PLANIFICACIÓN_PDOT!B14 -> Equipamientos públicos: terminal terrestre, mercado, estación bomberil, centro salud tipo C, mantenimiento espacios recreativos | C15: 84.01 | D15: 84 | E15: 2183216 | F15: =E15*0.85 -> 1855733.6 | G15: =IF(E15>0,F15/E15,0) -> 0.85 | H15: =IF(F15>0,1,IF(E15>0,0.5,0)) -> 1 | I15: =IF(AND(OR(D15=71,D15=73,D15=78),F15>0,H01_PARÁMETROS!B34="SÍ"),"⚠️ SAT-IV — Meta social en período restricción fiscal","✅ OK") -> ✅ OK
A16: =H04_S2_PLANIFICACIÓN_PDOT!A15 -> AH-C-X-01 | B16: =H04_S2_PLANIFICACIÓN_PDOT!B15 -> Protección derechos sociales: atenciones grupos prioritarios 943→1,649 (+15%/año); CDI; adultos mayores; violencia de género | C16: 75.01 | D16: 75 | E16: 558105 | F16: =E16*0.72 -> 401835.6 | G16: =IF(E16>0,F16/E16,0) -> 0.72 | H16: =IF(F16>0,1,IF(E16>0,0.5,0)) -> 1 | I16: =IF(AND(OR(D16=71,D16=73,D16=78),F16>0,H01_PARÁMETROS!B34="SÍ"),"⚠️ SAT-IV — Meta social en período restricción fiscal","✅ OK") -> ✅ OK
A17: =H04_S2_PLANIFICACIÓN_PDOT!A16 -> AH-C-X-02 | B17: =H04_S2_PLANIFICACIÓN_PDOT!B16 -> Sistema información territorial: catastro urbano-rural 19.52%→80%; 12 procesos sistematizados; 37 trámites en línea | C17: 75.01 | D17: 75 | E17: 625859 | F17: =E17*0.72 -> 450618.48 | G17: =IF(E17>0,F17/E17,0) -> 0.72 | H17: =IF(F17>0,1,IF(E17>0,0.5,0)) -> 1 | I17: =IF(AND(OR(D17=71,D17=73,D17=78),F17>0,H01_PARÁMETROS!B34="SÍ"),"⚠️ SAT-IV — Meta social en período restricción fiscal","✅ OK") -> ✅ OK
A18: =H04_S2_PLANIFICACIÓN_PDOT!A17 -> SC-I-N-03 | B18: =H04_S2_PLANIFICACIÓN_PDOT!B17 -> Participación ciudadana: 50→100 Unidades Territoriales participativas; 2→4 instancias efectivas (COPFP Art.115) | C18: 71.06 | D18: 71 | E18: 37000 | F18: =E18*0.95 -> 35150 | G18: =IF(E18>0,F18/E18,0) -> 0.95 | H18: =IF(F18>0,1,IF(E18>0,0.5,0)) -> 1 | I18: =IF(AND(OR(D18=71,D18=73,D18=78),F18>0,H01_PARÁMETROS!B34="SÍ"),"⚠️ SAT-IV — Meta social en período restricción fiscal","✅ OK") -> ✅ OK
A19: =H04_S2_PLANIFICACIÓN_PDOT!A18 -> FA-I-X-01 | B19: =H04_S2_PLANIFICACIÓN_PDOT!B18 -> Gestión del riesgo: reducir 10% infraestructura susceptible (3,655→2,398 unidades); alerta temprana climática | C19: 75.01 | D19: 75 | E19: 78500 | F19: =E19*0.65 -> 51025 | G19: =IF(E19>0,F19/E19,0) -> 0.65 | H19: =IF(F19>0,1,IF(E19>0,0.5,0)) -> 1 | I19: =IF(AND(OR(D19=71,D19=73,D19=78),F19>0,H01_PARÁMETROS!B34="SÍ"),"⚠️ SAT-IV — Meta social en período restricción fiscal","✅ OK") -> ✅ OK
A20: =H04_S2_PLANIFICACIÓN_PDOT!A19 -> FA-C-X-01 | B20: =H04_S2_PLANIFICACIÓN_PDOT!B19 -> Áreas verdes y parques: IVU 10.94→17.32 m²/hab; parques inter-barriales; recuperación manglar perfil costero | C20: 78.01 | D20: 78 | E20: 5000 | F20: =E20*0.8 -> 4000 | G20: =IF(E20>0,F20/E20,0) -> 0.8 | H20: =IF(F20>0,1,IF(E20>0,0.5,0)) -> 1 | I20: =IF(AND(OR(D20=71,D20=73,D20=78),F20>0,H01_PARÁMETROS!B34="SÍ"),"⚠️ SAT-IV — Meta social en período restricción fiscal","✅ OK") -> ✅ OK
A21: =H04_S2_PLANIFICACIÓN_PDOT!A20 -> FA-I-X-02 | B21: =H04_S2_PLANIFICACIÓN_PDOT!B20 -> Índice equipamiento urbano CUP 9.96→10.73 m²/hab; recolección desechos 91.95%→97.95%; 77.83→81.07 km/día barrido | C21: 73.08 | D21: 73 | E21: 37600 | F21: =E21*0.85 -> 31960 | G21: =IF(E21>0,F21/E21,0) -> 0.85 | H21: =IF(F21>0,1,IF(E21>0,0.5,0)) -> 1 | I21: =IF(AND(OR(D21=71,D21=73,D21=78),F21>0,H01_PARÁMETROS!B34="SÍ"),"⚠️ SAT-IV — Meta social en período restricción fiscal","✅ OK") -> ✅ OK
A22: =H04_S2_PLANIFICACIÓN_PDOT!A21 -> FA-L-N-01 | B22: =H04_S2_PLANIFICACIÓN_PDOT!B21 -> Inventario patrimonial 100% al 2026; 8,000→10,000 participantes eventos culturales; Museo del Sombrero | C22: 71.06 | D22: 71 | E22: 5000 | F22: =E22*0.95 -> 4750 | G22: =IF(E22>0,F22/E22,0) -> 0.95 | H22: =IF(F22>0,1,IF(E22>0,0.5,0)) -> 1 | I22: =IF(AND(OR(D22=71,D22=73,D22=78),F22>0,H01_PARÁMETROS!B34="SÍ"),"⚠️ SAT-IV — Meta social en período restricción fiscal","✅ OK") -> ✅ OK
A23: =H04_S2_PLANIFICACIÓN_PDOT!A22 -> PI-I-G-02 | B23: =H04_S2_PLANIFICACIÓN_PDOT!B22 -> Cumplimiento PDOT/PUGS 0%→80%; SIL 19.52%→80%; 37 trámites digitales implementados | C23: 84.01 | D23: 84 | E23: 422100 | F23: =E23*0.85 -> 358785 | G23: =IF(E23>0,F23/E23,0) -> 0.85 | H23: =IF(F23>0,1,IF(E23>0,0.5,0)) -> 1 | I23: =IF(AND(OR(D23=71,D23=73,D23=78),F23>0,H01_PARÁMETROS!B34="SÍ"),"⚠️ SAT-IV — Meta social en período restricción fiscal","✅ OK") -> ✅ OK
A24: =H04_S2_PLANIFICACIÓN_PDOT!A23 -> PI-L-G-01 | B24: =H04_S2_PLANIFICACIÓN_PDOT!B23 -> Señalización vial 0→10,000 m²; 0→8 semáforos; revisiones técnicas 4,000→20,000; educación vial 40 instituciones | C24: 71.06 | D24: 71 | E24: 20222 | F24: =E24*0.95 -> 19210.9 | G24: =IF(E24>0,F24/E24,0) -> 0.95 | H24: =IF(F24>0,1,IF(E24>0,0.5,0)) -> 1 | I24: =IF(AND(OR(D24=71,D24=73,D24=78),F24>0,H01_PARÁMETROS!B34="SÍ"),"⚠️ SAT-IV — Meta social en período restricción fiscal","✅ OK") -> ✅ OK
A25: =H04_S2_PLANIFICACIÓN_PDOT!A24 -> EP-L-N-01 | B25: =H04_S2_PLANIFICACIÓN_PDOT!B24 -> Vivienda de interés social: 50 VIS/VIP hasta 2027; reducción déficit habitacional cualitativo | C25: 71.06 | D25: 71 | E25: 30600 | F25: =E25*0.95 -> 29070 | G25: =IF(E25>0,F25/E25,0) -> 0.95 | H25: =IF(F25>0,1,IF(E25>0,0.5,0)) -> 1 | I25: =IF(AND(OR(D25=71,D25=73,D25=78),F25>0,H01_PARÁMETROS!B34="SÍ"),"⚠️ SAT-IV — Meta social en período restricción fiscal","✅ OK") -> ✅ OK
A26: =H04_S2_PLANIFICACIÓN_PDOT!A25 -> EP-L-X-01 | B26: =H04_S2_PLANIFICACIÓN_PDOT!B25 -> Fortalecimiento productivo: beneficiarios artesanos, mipymes, emprendedores, huertos comunitarios y cadenas de valor | C26: 73.08 | D26: 73 | E26: 163400 | F26: =E26*0.85 -> 138890 | G26: =IF(E26>0,F26/E26,0) -> 0.85 | H26: =IF(F26>0,1,IF(E26>0,0.5,0)) -> 1 | I26: =IF(AND(OR(D26=71,D26=73,D26=78),F26>0,H01_PARÁMETROS!B34="SÍ"),"⚠️ SAT-IV — Meta social en período restricción fiscal","✅ OK") -> ✅ OK
A27: TOTALES | E27: =SUM(E7:E26) -> 7874925 | F27: =SUM(F7:F26) -> 6105465.4 | G27: =IF(E27>0,F27/E27,0) -> 0.77530457
A28: T_i_Promedio_Global | B28: =AVERAGE(G7:G26) -> 0.785

Sheet H08_S6_AUTOREPORTE_SIGAD
A1: 🏛️ TERRA SIAP-ICPI v2.0 | QUADRUM | B1: ⬅️ ÍNDICE GENERAL | C1: ="ICPI: "&TEXT(H12_MOTOR_ICPI_CANÓNICO!B28,"0,0")&"%" -> ICPI: 72,9% | D1: H08 — S6 SIGAD | E1: =TEXT(TODAY(),"DD/MM/YYYY") -> 05/04/2026
A2: S6 — SILO AUTOREPORTE (SIGAD/SNP)
A3: Índice de Cumplimiento de Metas reportado a la Secretaría Nacional de Planificación. Métrica oficial de evaluación de gestión — objeto de contraste con el ICPI verificado.
A4: Fundamentación: COPFP Art.9 + COOTAD Art.295 | NUNCA usar 'SENPLADES' — fue suprimida en 2019
A6: ID_Meta | B6: Descripción_Meta | C6: Pct_Avance_Reportado_SIGAD | D6: Unidad_Medida_Reportada | E6: Fecha_Ultimo_Reporte | F6: V_SIGAD | G6: Alerta_Unidad_MOM_III
A7: =H04_S2_PLANIFICACIÓN_PDOT!A6 -> SC-I-N-01 | B7: =H04_S2_PLANIFICACIÓN_PDOT!B6 -> Agua potable: cobertura 39.25%→42.38%; calidad 100% INEN 1108; infraestructura BUENA 22.74%→41.64% | C7: 100 | D7: =H04_S2_PLANIFICACIÓN_PDOT!O6 -> % cobertura agua potable | E7: 31/12/2024 | F7: =IF(C7<>"",1,0) -> 1 | G7: =IF(D7<>H04_S2_PLANIFICACIÓN_PDOT!O6,"⚠️ CAMBIO DE UNIDAD — Posible MOM-III","✅ Unidad consistente con PDOT") -> ✅ Unidad consistente con PDOT
A8: =H04_S2_PLANIFICACIÓN_PDOT!A7 -> SC-L-N-02 | B8: =H04_S2_PLANIFICACIÓN_PDOT!B7 -> Gestión del talento humano municipal: desempeño 80%→90%; plan capacitación 90% anual | C8: 100 | D8: =H04_S2_PLANIFICACIÓN_PDOT!O7 -> % nivel desempeño personal | E8: 31/12/2024 | F8: =IF(C8<>"",1,0) -> 1 | G8: =IF(D8<>H04_S2_PLANIFICACIÓN_PDOT!O7,"⚠️ CAMBIO DE UNIDAD — Posible MOM-III","✅ Unidad consistente con PDOT") -> ✅ Unidad consistente con PDOT
A9: =H04_S2_PLANIFICACIÓN_PDOT!A8 -> AH-I-X-01 | B9: =H04_S2_PLANIFICACIÓN_PDOT!B8 -> Sostenibilidad financiera: autonomía 43.35%→45.30%; gestión cobros y coactivas | C9: 100 | D9: =H04_S2_PLANIFICACIÓN_PDOT!O8 -> % autonomía financiera | E9: 31/12/2024 | F9: =IF(C9<>"",1,0) -> 1 | G9: =IF(D9<>H04_S2_PLANIFICACIÓN_PDOT!O8,"⚠️ CAMBIO DE UNIDAD — Posible MOM-III","✅ Unidad consistente con PDOT") -> ✅ Unidad consistente con PDOT
A10: =H04_S2_PLANIFICACIÓN_PDOT!A9 -> AH-I-X-02 | B10: =H04_S2_PLANIFICACIÓN_PDOT!B9 -> Vialidad cantonal: mantenimiento 43.8 km vías CUP + 57.22 km rurales; 23.77 km tratamiento medio | C10: 100 | D10: =H04_S2_PLANIFICACIÓN_PDOT!O9 -> Km vías mantenidas CUP acumulado | E10: 31/12/2024 | F10: =IF(C10<>"",1,0) -> 1 | G10: =IF(D10<>H04_S2_PLANIFICACIÓN_PDOT!O9,"⚠️ CAMBIO DE UNIDAD — Posible MOM-III","✅ Unidad consistente con PDOT") -> ✅ Unidad consistente con PDOT
A11: =H04_S2_PLANIFICACIÓN_PDOT!A10 -> AH-I-X-03 | B11: =H04_S2_PLANIFICACIÓN_PDOT!B10 -> Salud integral municipal: población atendida 57,401→84,041 personas (+10% anual) | C11: 100 | D11: =H04_S2_PLANIFICACIÓN_PDOT!O10 -> Personas atendidas salud municipal | E11: 31/12/2024 | F11: =IF(C11<>"",1,0) -> 1 | G11: =IF(D11<>H04_S2_PLANIFICACIÓN_PDOT!O10,"⚠️ CAMBIO DE UNIDAD — Posible MOM-III","✅ Unidad consistente con PDOT") -> ✅ Unidad consistente con PDOT
A12: =H04_S2_PLANIFICACIÓN_PDOT!A11 -> AH-I-N-01 | B12: =H04_S2_PLANIFICACIÓN_PDOT!B11 -> Gestión integral desechos sólidos: 20,118→23,086 Tn/año; relleno sanitario; capacidad disposición 0%→20% | C12: 100 | D12: =H04_S2_PLANIFICACIÓN_PDOT!O11 -> Toneladas de desechos gestionadas/año | E12: 31/12/2024 | F12: =IF(C12<>"",1,0) -> 1 | G12: =IF(D12<>H04_S2_PLANIFICACIÓN_PDOT!O11,"⚠️ CAMBIO DE UNIDAD — Posible MOM-III","✅ Unidad consistente con PDOT") -> ✅ Unidad consistente con PDOT
A13: =H04_S2_PLANIFICACIÓN_PDOT!A12 -> SC-L-G-01 | B13: =H04_S2_PLANIFICACIÓN_PDOT!B12 -> Alcantarillado sanitario: cobertura 19.77%→24.32%; PTAR 0%→75%; estaciones bombeo 36%→72% | C13: 100 | D13: =H04_S2_PLANIFICACIÓN_PDOT!O12 -> % cobertura alcantarillado sanitario | E13: 31/12/2024 | F13: =IF(C13<>"",1,0) -> 1 | G13: =IF(D13<>H04_S2_PLANIFICACIÓN_PDOT!O12,"⚠️ CAMBIO DE UNIDAD — Posible MOM-III","✅ Unidad consistente con PDOT") -> ✅ Unidad consistente con PDOT
A14: =H04_S2_PLANIFICACIÓN_PDOT!A13 -> AH-I-X-04 | B14: =H04_S2_PLANIFICACIÓN_PDOT!B13 -> Modernización recursos administrativos: parque automotor, tecnología e infraestructura municipal | C14: 100 | D14: =H04_S2_PLANIFICACIÓN_PDOT!O13 -> Parque automotor y tecnología renovados | E14: 31/12/2024 | F14: =IF(C14<>"",1,0) -> 1 | G14: =IF(D14<>H04_S2_PLANIFICACIÓN_PDOT!O13,"⚠️ CAMBIO DE UNIDAD — Posible MOM-III","✅ Unidad consistente con PDOT") -> ✅ Unidad consistente con PDOT
A15: =H04_S2_PLANIFICACIÓN_PDOT!A14 -> PI-I-G-01 | B15: =H04_S2_PLANIFICACIÓN_PDOT!B14 -> Equipamientos públicos: terminal terrestre, mercado, estación bomberil, centro salud tipo C, mantenimiento espacios recreativos | C15: 100 | D15: =H04_S2_PLANIFICACIÓN_PDOT!O14 -> m² / hab índice equipamiento urbano CUP | E15: 31/12/2024 | F15: =IF(C15<>"",1,0) -> 1 | G15: =IF(D15<>H04_S2_PLANIFICACIÓN_PDOT!O14,"⚠️ CAMBIO DE UNIDAD — Posible MOM-III","✅ Unidad consistente con PDOT") -> ✅ Unidad consistente con PDOT
A16: =H04_S2_PLANIFICACIÓN_PDOT!A15 -> AH-C-X-01 | B16: =H04_S2_PLANIFICACIÓN_PDOT!B15 -> Protección derechos sociales: atenciones grupos prioritarios 943→1,649 (+15%/año); CDI; adultos mayores; violencia de género | C16: 100 | D16: =H04_S2_PLANIFICACIÓN_PDOT!O15 -> Atenciones en programas grupos prioritarios | E16: 31/12/2024 | F16: =IF(C16<>"",1,0) -> 1 | G16: =IF(D16<>H04_S2_PLANIFICACIÓN_PDOT!O15,"⚠️ CAMBIO DE UNIDAD — Posible MOM-III","✅ Unidad consistente con PDOT") -> ✅ Unidad consistente con PDOT
A17: =H04_S2_PLANIFICACIÓN_PDOT!A16 -> AH-C-X-02 | B17: =H04_S2_PLANIFICACIÓN_PDOT!B16 -> Sistema información territorial: catastro urbano-rural 19.52%→80%; 12 procesos sistematizados; 37 trámites en línea | C17: 100 | D17: =H04_S2_PLANIFICACIÓN_PDOT!O16 -> % levantamiento SIL catastro urbano-rural | E17: 31/12/2024 | F17: =IF(C17<>"",1,0) -> 1 | G17: =IF(D17<>H04_S2_PLANIFICACIÓN_PDOT!O16,"⚠️ CAMBIO DE UNIDAD — Posible MOM-III","✅ Unidad consistente con PDOT") -> ✅ Unidad consistente con PDOT
A18: =H04_S2_PLANIFICACIÓN_PDOT!A17 -> SC-I-N-03 | B18: =H04_S2_PLANIFICACIÓN_PDOT!B17 -> Participación ciudadana: 50→100 Unidades Territoriales participativas; 2→4 instancias efectivas (COPFP Art.115) | C18: 100 | D18: =H04_S2_PLANIFICACIÓN_PDOT!O17 -> Unidades Territoriales participativas activas | E18: 31/12/2024 | F18: =IF(C18<>"",1,0) -> 1 | G18: =IF(D18<>H04_S2_PLANIFICACIÓN_PDOT!O17,"⚠️ CAMBIO DE UNIDAD — Posible MOM-III","✅ Unidad consistente con PDOT") -> ✅ Unidad consistente con PDOT
... A26: =H04_S2_PLANIFICACIÓN_PDOT!A25 -> EP-L-X-01 | B26: =H04_S2_PLANIFICACIÓN_PDOT!B25 -> Fortalecimiento productivo: beneficiarios artesanos, mipymes, emprendedores, huertos comunitarios y cadenas de valor | C26: 100 | D26: =H04_S2_PLANIFICACIÓN_PDOT!O25 -> Beneficiarios programas fortalecimiento productivo | E26: 31/12/2024 | F26: =IF(C26<>"",1,0) -> 1 | G26: =IF(D26<>H04_S2_PLANIFICACIÓN_PDOT!O25,"⚠️ CAMBIO DE UNIDAD — Posible MOM-III","✅ Unidad consistente con PDOT") -> ✅ Unidad consistente con PDOT
A27: ICM_Global_SIGAD | C27: 100 | D27: ← ICM Oficial SIGAD (referenciado por SAT-I)
A28: Total_Metas_Reportadas | C28: 20

Sheet H09_S7_TRANSPARENCIA_LOTAIP
A1: ⚠️ SIMULACIÓN TÉCNICA: Datos simulados basados en estándares de transparencia de GADs costa ecuatoriana. Portal LOTAIP verificado manualmente de forma parcial. Actualizar con verificación sistemática del portal www.montecristi.gob.ec | B1: ⬅️ ÍNDICE GENERAL | C1: ="ICPI: "&TEXT(H12_MOTOR_ICPI_CANÓNICO!B28,"0,0")&"%" -> ICPI: 72,9% | D1: H09 — S7 LOTAIP | E1: =TEXT(TODAY(),"DD/MM/YYYY") -> 05/04/2026
A2: S7 — SILO TRANSPARENCIA ACTIVA (LOTAIP)
A3: Documentos contractuales, actas y evidencia publicados en el portal institucional del GAD. Si el documento no está en URL pública, algorítmicamente no existe.
A4: Fundamentación: LOTAIP Art.7 + Constitución Art.18
A6: ID_Meta | B6: Descripción_Meta | C6: Literal_LOTAIP | D6: Tipo_Documento | E6: URL_Portal_GAD | F6: Fecha_Publicacion | G6: Accesible | H6: V_LOTAIP
A7: =H04_S2_PLANIFICACIÓN_PDOT!A6 -> SC-I-N-01 | B7: =H04_S2_PLANIFICACIÓN_PDOT!B6 -> Agua potable: cobertura 39.25%→42.38%; calidad 100% INEN 1108; infraestructura BUENA 22.74%→41.64% | C7: k | D7: Acta adjudicación | E7: https://montecristi.gob.ec/transparencia/k/pdot001 | F7: 31/12/2024 | G7: SÍ | H7: 0.5
A8: =H04_S2_PLANIFICACIÓN_PDOT!A7 -> SC-L-N-02 | B8: =H04_S2_PLANIFICACIÓN_PDOT!B7 -> Gestión del talento humano municipal: desempeño 80%→90%; plan capacitación 90% anual | C8: k | D8: Contrato MIPYMES | E8: https://montecristi.gob.ec/transparencia/k/pdot002 | F8: 31/12/2024 | G8: SÍ | H8: 0.5
A9: =H04_S2_PLANIFICACIÓN_PDOT!A8 -> AH-I-X-01 | B9: =H04_S2_PLANIFICACIÓN_PDOT!B8 -> Sostenibilidad financiera: autonomía 43.35%→45.30%; gestión cobros y coactivas | C9: a4 | D9: Informe obras | E9: https://montecristi.gob.ec/transparencia/a4/pdot003 | F9: 31/12/2024 | G9: SÍ | H9: 1
A10: =H04_S2_PLANIFICACIÓN_PDOT!A9 -> AH-I-X-02 | B10: =H04_S2_PLANIFICACIÓN_PDOT!B9 -> Vialidad cantonal: mantenimiento 43.8 km vías CUP + 57.22 km rurales; 23.77 km tratamiento medio | C10: k | D10: Acta feria | E10: https://montecristi.gob.ec/transparencia/k/pdot004 | F10: 31/12/2024 | G10: SÍ | H10: 0
A11: =H04_S2_PLANIFICACIÓN_PDOT!A10 -> AH-I-X-03 | B11: =H04_S2_PLANIFICACIÓN_PDOT!B10 -> Salud integral municipal: población atendida 57,401→84,041 personas (+10% anual) | C11: a1 | D11: Plataforma digital | E11: https://montecristi.gob.ec/transparencia/a1/pdot005 | F11: 31/12/2024 | G11: SÍ | H11: 1
A12: =H04_S2_PLANIFICACIÓN_PDOT!A11 -> AH-I-N-01 | B12: =H04_S2_PLANIFICACIÓN_PDOT!B11 -> Gestión integral desechos sólidos: 20,118→23,086 Tn/año; relleno sanitario; capacidad disposición 0%→20% | C12: m | D12: Informe salud | E12: https://montecristi.gob.ec/transparencia/m/pdot006 | F12: 31/12/2024 | G12: SÍ | H12: 0
A13: =H04_S2_PLANIFICACIÓN_PDOT!A12 -> SC-L-G-01 | B13: =H04_S2_PLANIFICACIÓN_PDOT!B12 -> Alcantarillado sanitario: cobertura 19.77%→24.32%; PTAR 0%→75%; estaciones bombeo 36%→72% | C13: m | D13: Convenio MINEDUC | E13: https://montecristi.gob.ec/transparencia/m/pdot007 | F13: 31/12/2024 | G13: SÍ | H13: 0.5
A14: =H04_S2_PLANIFICACIÓN_PDOT!A13 -> AH-I-X-04 | B14: =H04_S2_PLANIFICACIÓN_PDOT!B13 -> Modernización recursos administrativos: parque automotor, tecnología e infraestructura municipal | C14: k | D14: Acta guarderìa | E14: https://montecristi.gob.ec/transparencia/k/pdot008 | F14: 31/12/2024 | G14: SÍ | H14: 1
A15: =H04_S2_PLANIFICACIÓN_PDOT!A14 -> PI-I-G-01 | B15: =H04_S2_PLANIFICACIÓN_PDOT!B14 -> Equipamientos públicos: terminal terrestre, mercado, estación bomberil, centro salud tipo C, mantenimiento espacios recreativos | C15: a4 | D15: Acta recepción vías | E15: https://montecristi.gob.ec/transparencia/a4/pdot009 | F15: 31/12/2024 | G15: SÍ | H15: 1
A16: =H04_S2_PLANIFICACIÓN_PDOT!A15 -> AH-C-X-01 | B16: =H04_S2_PLANIFICACIÓN_PDOT!B15 -> Protección derechos sociales: atenciones grupos prioritarios 943→1,649 (+15%/año); CDI; adultos mayores; violencia de género | C16: a4 | D16: Acta agua potable | E16: https://montecristi.gob.ec/transparencia/a4/pdot010 | F16: 31/12/2024 | G16: SÍ | H16: 1
A17: =H04_S2_PLANIFICACIÓN_PDOT!A16 -> AH-C-X-02 | B17: =H04_S2_PLANIFICACIÓN_PDOT!B16 -> Sistema información territorial: catastro urbano-rural 19.52%→80%; 12 procesos sistematizados; 37 trámites en línea | C17: a4 | D17: Acta alcantarillado | E17: https://montecristi.gob.ec/transparencia/a4/pdot011 | F17: 31/12/2024 | G17: SÍ | H17: 1
A18: =H04_S2_PLANIFICACIÓN_PDOT!A17 -> SC-I-N-03 | B18: =H04_S2_PLANIFICACIÓN_PDOT!B17 -> Participación ciudadana: 50→100 Unidades Territoriales participativas; 2→4 instancias efectivas (COPFP Art.115) | C18: m | D18: Informe brigadas | F18: 31/12/2024 | G18: NO | H18: 0.5
A19: =H04_S2_PLANIFICACIÓN_PDOT!A18 -> FA-I-X-01 | B19: =H04_S2_PLANIFICACIÓN_PDOT!B18 -> Gestión del riesgo: reducir 10% infraestructura susceptible (3,655→2,398 unidades); alerta temprana climática | C19: k | D19: Acta reforestación | E19: https://montecristi.gob.ec/transparencia/k/pdot013 | F19: 31/12/2024 | G19: SÍ | H19: 1
A20: =H04_S2_PLANIFICACIÓN_PDOT!A19 -> FA-C-X-01 | B20: =H04_S2_PLANIFICACIÓN_PDOT!B19 -> Áreas verdes y parques: IVU 10.94→17.32 m²/hab; parques inter-barriales; recuperación manglar perfil costero | C20: a4 | D20: Informe residuos | E20: https://montecristi.gob.ec/transparencia/a4/pdot014 | F20: 31/12/2024 | G20: SÍ | H20: 1
A21: =H04_S2_PLANIFICACIÓN_PDOT!A20 -> FA-I-X-02 | B21: =H04_S2_PLANIFICACIÓN_PDOT!B20 -> Índice equipamiento urbano CUP 9.96→10.73 m²/hab; recolección desechos 91.95%→97.95%; 77.83→81.07 km/día barrido | C21: m | D21: Informe cuencas | F21: 31/12/2024 | G21: NO | H21: 1
A22: =H04_S2_PLANIFICACIÓN_PDOT!A21 -> FA-L-N-01 | B22: =H04_S2_PLANIFICACIÓN_PDOT!B21 -> Inventario patrimonial 100% al 2026; 8,000→10,000 participantes eventos culturales; Museo del Sombrero | C22: a1 | D22: Informe TIC | E22: https://montecristi.gob.ec/transparencia/a1/pdot016 | F22: 31/12/2024 | G22: SÍ | H22: 0.5
A23: =H04_S2_PLANIFICACIÓN_PDOT!A22 -> PI-I-G-02 | B23: =H04_S2_PLANIFICACIÓN_PDOT!B22 -> Cumplimiento PDOT/PUGS 0%→80%; SIL 19.52%→80%; 37 trámites digitales implementados | C23: k | D23: Informe SERCOP | E23: https://montecristi.gob.ec/transparencia/k/pdot017 | F23: 31/12/2024 | G23: SÍ | H23: 1
A24: =H04_S2_PLANIFICACIÓN_PDOT!A23 -> PI-L-G-01 | B24: =H04_S2_PLANIFICACIÓN_PDOT!B23 -> Señalización vial 0→10,000 m²; 0→8 semáforos; revisiones técnicas 4,000→20,000; educación vial 40 instituciones | C24: m | D24: Informe adulto mayor | E24: https://montecristi.gob.ec/transparencia/m/pdot018 | F24: 31/12/2024 | G24: SÍ | H24: 0.5
A25: =H04_S2_PLANIFICACIÓN_PDOT!A24 -> EP-L-N-01 | B25: =H04_S2_PLANIFICACIÓN_PDOT!B24 -> Vivienda de interés social: 50 VIS/VIP hasta 2027; reducción déficit habitacional cualitativo | C25: a1 | D25: Informe rendición | E25: https://montecristi.gob.ec/transparencia/a1/pdot019 | F25: 31/12/2024 | G25: SÍ | H25: 0.5
A26: =H04_S2_PLANIFICACIÓN_PDOT!A25 -> EP-L-X-01 | B26: =H04_S2_PLANIFICACIÓN_PDOT!B25 -> Fortalecimiento productivo: beneficiarios artesanos, mipymes, emprendedores, huertos comunitarios y cadenas de valor | C26: k | D26: Acta infraestructura | E26: https://montecristi.gob.ec/transparencia/k/pdot020 | F26: 31/12/2024 | G26: SÍ | H26: 0.5
A28: ITAM_Base | B28: =AVERAGE(H7:H26)*100 -> 70 | C28: ← Este valor es referenciado por H18_ITAM

Sheet H10_S8_PARTICIPACIÓN_CPCCS
A1: ✅ DATOS REALES: Informe Rendición de Cuentas N°22844, GAD Montecristi, período 2024. Alcalde: Luis Jonathan Toro Largacha. Deliberación pública: 11/07/2025. Asistentes: 261. Lugar: Comuna Toalla Grande. | B1: ⬅️ ÍNDICE GENERAL | C1: ICPI: 58,8% | D1: H10 — S8 CPCCS | E1: 46146
A2: S8 — SILO PARTICIPACIÓN CIUDADANA (CPCCS)
A3: Informe de rendición de cuentas anual ante el CPCCS. Fuente: PDF Informe RDC 2024 GAD Montecristi — Nro. 22844. Revisión: 15 páginas. Porcentajes declarados por meta: NO REPORTADOS en el documento (narración de acciones sin % por meta).
A4: Fundamentación: LOPC Art.88 + Constitución Art.204 | MECANISMOS CONFIRMADOS: Asamblea Local SÍ | Audiencia Pública SÍ | Consejo Planificación Local SÍ | Cabildo Popular NO
A6: ID_Meta | B6: Descripción_Meta | C6: Mencionada_Rendición | D6: Pct_Declarado_Alcalde | E6: Evidencia_Citada | F6: Observaciones_Asamblea | G6: V_CPCCS | H6: Alerta_Demagogia
A7: SC-I-N-01 | B7: Agua potable: cobertura 39.25%→42.38%; calidad 100% INEN 1108; infraestructura BUENA 22.74%→41.64% | C7: SÍ | D7: N/D — no declarado % | E7: SÍ — 2438m tubería instalada; acueducto CAF $28M aprobado 29/12/2024; convenios Rocafuerte, Portoviejo, Jaramijó | F7: Avanzar agua potable Isabel Muentes; ampliación Com. Eloy Alfaro; soluciones reparto periódico agua | G7: 1 | H7: ✅ Sin alerta — T_i=0.95, D no declarado
A8: SC-L-N-02 | B8: Gestión del talento humano municipal: desempeño 80%→90%; plan capacitación 90% anual | C8: PARCIAL | D8: N/D — no declarado % | E8: SÍ — capacitaciones AME, fortalecimiento servidores públicos gestión/transparencia | F8: Sin observaciones ciudadanas específicas a esta meta | G8: 0.5 | H8: ✅ Sin alerta — T_i=0.85, D no declarado
A9: AH-I-X-01 | B9: Sostenibilidad financiera: autonomía 43.35%→45.30%; gestión cobros y coactivas | C9: SÍ | D9: N/D — no declarado % | E9: SÍ — 6 ordenanzas tributarias sancionadas/Registro Oficial; convenio dación pago bonos MEF; URLs verificables | F9: Ciudadano señaló mala atención en pago predios hace 8 meses (retroalimentación negativa) | G9: 1 | H9: ✅ Sin alerta — T_i=0.72, D no declarado
A10: AH-I-X-02 | B10: Vialidad cantonal: mantenimiento 43.8 km vías CUP + 57.22 km rurales; 23.77 km tratamiento medio | C10: SÍ | D10: N/D — no declarado % | E10: PARCIAL — Narrativa de 90km reconformación y maquinaria precontractual; maquinaria aún SIN ENTREGA (espera anticipo al cierre 2024) | F10: Arreglo de vías y escombros múltiples comunidades; arreglo vía Com. Eloy Alfaro | G10: 0.5 | H10: ⚠️ ALERTA EJECUCIÓN CERO — T_i=0.00 — maquinaria no entregada al 31/12/2024. Discurso narrativo alto vs ejecución financiera NULA
A11: AH-I-X-03 | B11: Salud integral municipal: población atendida 57,401→84,041 personas (+10% anual) | C11: SÍ | D11: N/D — no declarado % | E11: SÍ — 3743 usuarios brigadas médicas; 500+ beneficiados violencia género; 320 talleres aux.enfermería ULEAM; 200 Club Diabéticos; gestión Centro Salud Tipo C y B | F11: Buscar mejoras en todos los centros de salud | G11: 1 | H11: ✅ Sin alerta — T_i=0.72, D no declarado
A12: AH-I-N-01 | B12: Gestión integral desechos sólidos: 20,118→23,086 Tn/año; relleno sanitario; capacidad disposición 0%→20% | C12: SÍ | D12: N/D — no declarado % | E12: SÍ — 6 vehículos recolectores adquiridos; alquiler vehículos transición; estudio cierre técnico botadero; postulación BDE crédito PTAR | F12: Controlar recolección basura; cumplir horario Pepa de Huso; más contenedores; ducto cajón aguas residuales; chancheras mal olor | G12: 1 | H12: ✅ Sin alerta — T_i=0.80, D no declarado
A13: SC-L-G-01 | B13: Alcantarillado sanitario: cobertura 19.77%→24.32%; PTAR 0%→75%; estaciones bombeo 36%→72% | C13: SÍ | D13: N/D — no declarado % | E13: SÍ — Fase I alcantarillado Parroquia Gral. Eloy Alfaro rediseño 21/05/2024; PTAR cerramiento estudio; AASS y AAPP cabecera cantonal — estudios definitivos | F13: Ampliación alcantarillado/agua potable Isabel Muentes Cielito Lindo; rehabilitación alcantarillado Com. Eloy Alfaro | G13: 1 | H13: ✅ Sin alerta — T_i=0.85, D no declarado
A14: AH-I-X-04 | B14: Modernización recursos administrativos: parque automotor, tecnología e infraestructura municipal | C14: PARCIAL | D14: N/D — no declarado % | E14: PARCIAL — Digitalización trámites mencionada; Plan de Comunicación 2024; tecnología TIC implícita | F14: Sin observaciones ciudadanas directas | G14: 0.5 | H14: ✅ Sin alerta — T_i=0.72, D no declarado
A15: PI-I-G-01 | B15: Equipamientos públicos: terminal terrestre, mercado, estación bomberil, centro salud tipo C, mantenimiento espacios recreativos | C15: SÍ | D15: N/D — no declarado % | E15: SÍ — Parque La Huella; Mercado Municipal readecuado; cuartel bomberos estudio suelo; 57 espacios públicos recuperados; 5 puntos wifi; 15 alarmas comunitarias | F15: Gestionar senderos y miradores turísticos; mantenimiento alumbrado público calle Chimborazo | G15: 1 | H15: ✅ Sin alerta — T_i=0.85, D no declarado
A16: AH-C-X-01 | B16: Protección derechos sociales: atenciones grupos prioritarios 943→1,649 (+15%/año); CDI; adultos mayores; violencia de género | C16: SÍ | D16: N/D — no declarado % | E16: SÍ — AVSI/CCPD movilidad humana; Patronato 3743 usuarios; Fundación Adelanto Comunitario 500+ charlas género; Club Diabéticos 200 beneficiados; Lactario/Biblioteca Patronato | F16: Sin observaciones ciudadanas específicas directas | G16: 1 | H16: ✅ Sin alerta — T_i=0.72, D no declarado
A17: AH-C-X-02 | B17: Sistema información territorial: catastro urbano-rural 19.52%→80%; 12 procesos sistematizados; 37 trámites en línea | C17: PARCIAL | D17: N/D — no declarado % | E17: PARCIAL — Digitalización trámites municipales mencionada; catastro no cuantificado explícitamente en el informe | F17: Socialización cambios de domicilios en toda la extensión territorial (demanda ciudadana) | G17: 0.5 | H17: ✅ Sin alerta — T_i=0.72, D no declarado
A18: SC-I-N-03 | B18: Participación ciudadana: 50→100 Unidades Territoriales participativas; 2→4 instancias efectivas (COPFP Art.115) | C18: SÍ | D18: N/D — no declarado % | E18: SÍ — 87 personas talleres CPCCS; 16 clubes jóvenes 350 beneficiarios; Asamblea Local SÍ; Audiencia Pública SÍ; CPL SÍ; Presupuesto participativo 2023 | F18: Felicitaciones al alcalde por mejoramiento recolección. Ordenanza protección dirigentes barriales solicitada | G18: 1 | H18: ✅ Sin alerta — T_i=0.95, D no declarado
... A26: EP-L-X-01 | B26: Fortalecimiento productivo: beneficiarios artesanos, mipymes, emprendedores, huertos comunitarios y cadenas de valor | C26: SÍ | D26: N/D — no declarado % | E26: SÍ — 20 personas agricultura orgánica UELAM; 350 jóvenes 16 clubes Plan Internacional; 3000 usuarios Manta Bachiller; Mercado Municipal reorganizado; borrador ordenanza incentivos inversión | F26: Turismo comunitario Sitio Secal; proyecto apicultura; siembra comunitaria; senderos y miradores turísticos | G26: 1 | H26: ✅ Sin alerta — T_i=0.85, D no declarado

Sheet H11_S9_AGENDA_GLOBAL_ODS
A1: 🏛️ TERRA SIAP-ICPI v2.0 | QUADRUM | B1: ⬅️ ÍNDICE GENERAL | C1: ="ICPI: "&TEXT(H12_MOTOR_ICPI_CANÓNICO!B28,"0,0")&"%" -> ICPI: 72,9% | D1: H11 — S9 ODS | E1: =TEXT(TODAY(),"DD/MM/YYYY") -> 05/04/2026
A2: S9 — SILO AGENDA GLOBAL (ODS/BILATERALES)
A3: Alineación de metas PDOT con Agenda 2030. Puente entre gestión local y estándares de reportabilidad ante CAF, BID y BM.
A4: PND vigente: 'Ecuador No Se Detiene' 2025-2029 (Resolución CNP 0012-2025). 96 de 98 metas alineadas con Agenda 2030.
A6: ▌ SECCIÓN A — 3 CLÚSTERES ODS
A7: Clúster | B7: ODS | C7: N°_Metas_PDOT | D7: ICPI_Cluster (pendiente H12) | E7: Semáforo
A8: 🏛️ Gobernanza | B8: ODS 16-17 | C8: =COUNTIF(H04_S2_PLANIFICACIÓN_PDOT!I6:I25,"Gobernanza") -> 7 | D8: {=IFERROR(SUMPRODUCT((H04_S2_PLANIFICACIÓN_PDOT!I6:I25="Gobernanza")*H12_MOTOR_ICPI_CANÓNICO!H6:H25)/SUMPRODUCT((H04_S2_PLANIFICACIÓN_PDOT!I6:I25="Gobernanza")*H12_MOTOR_ICPI_CANÓNICO!I6:I25)*100,0)} -> 75.735167 | E8: =IF(D8>=90,"🔵 Excelencia en Gobernanza",IF(D8>=70,"🟢 Gestión por Mandato",IF(D8>=40,"🟡 Transición Crítica",IF(D8>=20,"🟠 Gestión por Ocurrencia","🔴 Ruptura Sistémica")))) -> 🟢 Gestión por Mandato
A9: 🏗️ Infraestructura | B9: ODS 6-9-11-13 | C9: =COUNTIF(H04_S2_PLANIFICACIÓN_PDOT!I6:I25,"Infraestructura") -> 10 | D9: {=IFERROR(SUMPRODUCT((H04_S2_PLANIFICACIÓN_PDOT!I6:I25="Infraestructura")*H12_MOTOR_ICPI_CANÓNICO!H6:H25)/SUMPRODUCT((H04_S2_PLANIFICACIÓN_PDOT!I6:I25="Infraestructura")*H12_MOTOR_ICPI_CANÓNICO!I6:I25)*100,0)} -> 71.274659 | E9: =IF(D9>=90,"🔵 Excelencia en Gobernanza",IF(D9>=70,"🟢 Gestión por Mandato",IF(D9>=40,"🟡 Transición Crítica",IF(D9>=20,"🟠 Gestión por Ocurrencia","🔴 Ruptura Sistémica")))) -> 🟢 Gestión por Mandato
A10: 🤝 Inclusión Social | B10: ODS 1-3-4-5-10 | C10: =COUNTIF(H04_S2_PLANIFICACIÓN_PDOT!I6:I25,"Inclusion") -> 3 | D10: {=IFERROR(SUMPRODUCT((H04_S2_PLANIFICACIÓN_PDOT!I6:I25="Inclusion")*H12_MOTOR_ICPI_CANÓNICO!H6:H25)/SUMPRODUCT((H04_S2_PLANIFICACIÓN_PDOT!I6:I25="Inclusion")*H12_MOTOR_ICPI_CANÓNICO!I6:I25)*100,0)} -> 63.510333 | E10: =IF(D10>=90,"🔵 Excelencia en Gobernanza",IF(D10>=70,"🟢 Gestión por Mandato",IF(D10>=40,"🟡 Transición Crítica",IF(D10>=20,"🟠 Gestión por Ocurrencia","🔴 Ruptura Sistémica")))) -> 🟡 Transición Crítica
A13: ▌ SECCIÓN B — ENFOQUE GÉNERO Y GENERACIONAL
A14: ♀️🌍 Metas con enfoque especial
A15: Total_Metas_Género_ODS5 | B15: =COUNTIF(H04_S2_PLANIFICACIÓN_PDOT!J6:J25,"*5*") -> 2 | C15: ← Metas con ODS 5 (Igualdad de género)
A16: Total_Metas_Clima_ODS13 | B16: =COUNTIF(H04_S2_PLANIFICACIÓN_PDOT!J6:J25,"*13*") -> 3 | C16: ← Metas con ODS 13 (Acción por el clima)
A18: ID_Meta | B18: Descripción | C18: ODS_Primario | D18: Enfoque
A19: PDOT-008 | B19: Guardería comunitaria | C19: ODS 5 | D19: Género
A20: PDOT-018 | B20: Adulto mayor | C20: ODS 10 | D20: Generacional
A21: PDOT-012 | B21: Salud móvil | C21: ODS 3 | D21: Género/Generacional
A22: PDOT-007 | B22: Educación rural | C22: ODS 4 | D22: Generacional
A23: PDOT-006 | B23: Salud rural | C23: ODS 3 | D23: Generacional
A25: ▌ SECCIÓN C — ARGUMENTOS PARA FINANCIADORES INTERNACIONALES
A26: CAF — Texto automático: | B26: ="ICPI Gobernanza: "&TEXT(D8,"0.0")&"% — Certifica base institucional elegible para financiamiento CAF bajo marco Gobernanza Anticipatoria ODS 16-17." -> ICPI Gobernanza: 76% — Certifica base institucional elegible para financiamiento CAF bajo marco Gobernanza Anticipatoria ODS 16-17.
A27: BID/BM — Texto automático: | B27: ="ICPI Inclusión: "&TEXT(D10,"0.0")&"% — Evidencia que inversión en grupos vulnerables requiere fortalecimiento de trazabilidad. Argumento BID Social." -> ICPI Inclusión: 64% — Evidencia que inversión en grupos vulnerables requiere fortalecimiento de trazabilidad. Argumento BID Social.
A28: ✅ Celdas D7, D8, D9 actualizadas con referencias reales a H12_MOTOR_ICPI_CANÓNICO

Sheet H12_MOTOR_ICPI_CANÓNICO
A1: 🏛️ TERRA SIAP-ICPI v2.0 | QUADRUM | B1: ⬅️ ÍNDICE GENERAL | C1: ="ICPI: "&TEXT(B28,"0,0")&"%" -> ICPI: 72,9% | D1: H12 — ★ MOTOR | E1: =TEXT(TODAY(),"DD/MM/YYYY") -> 05/04/2026
A2: ★ MOTOR ICPI CANÓNICO — TERRA v2.0 — FUENTE ÚNICA DEL ICPI GLOBAL
A3: ICPI = [Σ(Pi×Ri×Vi×Ei×Ti×Ci) / Σ(Pi×Ri)] × 100 | ★★★ B30 ES LA FUENTE ÚNICA — NINGUNA OTRA HOJA CALCULA EL ICPI ★★★ | R_i incorpora bono discriminación positiva desde H04
A4: E_i: 1.0=autónomo | 0.9=compartido | 0.75=difuso | C_i: 1.0=proceso único limpio | 0.9=compartido | 0.75=difuso o ambiguo [Ingresar manualmente según Estatuto Orgánico]
A5: ID_Meta | B5: P_i (Peso Fin.) | C5: R_i (con bono) | D5: V_i (Producto lógico silos) | E5: E_i (Autonomía orgánica) | F5: T_i (Devengado real) | G5: C_i (Calidad proceso) | H5: Numerador_i (Pi×Ri×Vi×Ei×Ti×Ci) | I5: Denominador_i (Pi×Ri) | J5: ICPI_Meta_i | K5: Nivel_AVEP
A6: SC-I-N-01 | B6: =H04_S2_PLANIFICACIÓN_PDOT!H6 -> 0.28912002 | C6: =H04_S2_PLANIFICACIÓN_PDOT!L6 -> 0.86956522 | D6: =IF(AND(H06_S4_CONTRATACIÓN_SERCOP!H7>0,H07_S5_FINANCIERO_eSIGEF!H7>0,H09_S7_TRANSPARENCIA_LOTAIP!H7>0,H10_S8_PARTICIPACIÓN_CPCCS!G7>0),1,IF(H06_S4_CONTRATACIÓN_SERCOP!H7+H07_S5_FINANCIERO_eSIGEF!H7+H09_S7_TRANSPARENCIA_LOTAIP!H7+H10_S8_PARTICIPACIÓN_CPCCS!G7>=2,0.5,0)) -> 1 | E6: 1 | F6: =H07_S5_FINANCIERO_eSIGEF!G7 -> 0.95 | G6: 1 | H6: =B6*C6*D6*E6*F6*G6 -> 0.23883828 | I6: =B6*C6 -> 0.25140872 | J6: =IF(I6>0,(H6/I6)*100,0) -> 95 | K6: =IF(J6>=90,"🔵 Excelencia",IF(J6>=70,"🟢 Por Mandato",IF(J6>=40,"🟡 Transición",IF(J6>=20,"🟠 Por Ocurrencia","🔴 Ruptura")))) -> 🔵 Excelencia
A7: SC-L-N-02 | B7: =H04_S2_PLANIFICACIÓN_PDOT!H7 -> 0.32531485 | C7: =H04_S2_PLANIFICACIÓN_PDOT!L7 -> 0.57971014 | D7: =IF(AND(H06_S4_CONTRATACIÓN_SERCOP!H8>0,H07_S5_FINANCIERO_eSIGEF!H8>0,H09_S7_TRANSPARENCIA_LOTAIP!H8>0,H10_S8_PARTICIPACIÓN_CPCCS!G8>0),1,IF(H06_S4_CONTRATACIÓN_SERCOP!H8+H07_S5_FINANCIERO_eSIGEF!H8+H09_S7_TRANSPARENCIA_LOTAIP!H8+H10_S8_PARTICIPACIÓN_CPCCS!G8>=2,0.5,0)) -> 1 | E7: 1 | F7: =H07_S5_FINANCIERO_eSIGEF!G8 -> 0.85 | G7: 1 | H7: =B7*C7*D7*E7*F7*G7 -> 0.16030007 | I7: =B7*C7 -> 0.18858832 | J7: =IF(I7>0,(H7/I7)*100,0) -> 85 | K7: =IF(J7>=90,"🔵 Excelencia",IF(J7>=70,"🟢 Por Mandato",IF(J7>=40,"🟡 Transición",IF(J7>=20,"🟠 Por Ocurrencia","🔴 Ruptura")))) -> 🟢 Por Mandato
A8: AH-I-X-01 | B8: =H04_S2_PLANIFICACIÓN_PDOT!H8 -> 0.12454728 | C8: =H04_S2_PLANIFICACIÓN_PDOT!L8 -> 0.57971014 | D8: =IF(AND(H06_S4_CONTRATACIÓN_SERCOP!H9>0,H07_S5_FINANCIERO_eSIGEF!H9>0,H09_S7_TRANSPARENCIA_LOTAIP!H9>0,H10_S8_PARTICIPACIÓN_CPCCS!G9>0),1,IF(H06_S4_CONTRATACIÓN_SERCOP!H9+H07_S5_FINANCIERO_eSIGEF!H9+H09_S7_TRANSPARENCIA_LOTAIP!H9+H10_S8_PARTICIPACIÓN_CPCCS!G9>=2,0.5,0)) -> 1 | E8: 0.9 | F8: =H07_S5_FINANCIERO_eSIGEF!G9 -> 0.72 | G8: 0.9 | H8: =B8*C8*D8*E8*F8*G8 -> 0.042107811 | I8: =B8*C8 -> 0.072201323 | J8: =IF(I8>0,(H8/I8)*100,0) -> 58.32 | K8: =IF(J8>=90,"🔵 Excelencia",IF(J8>=70,"🟢 Por Mandato",IF(J8>=40,"🟡 Transición",IF(J8>=20,"🟠 Por Ocurrencia","🔴 Ruptura")))) -> 🟡 Transición
A9: AH-I-X-02 | B9: =H04_S2_PLANIFICACIÓN_PDOT!H9 -> 0.067296693 | C9: =H04_S2_PLANIFICACIÓN_PDOT!L9 -> 0.86956522 | D9: =IF(AND(H06_S4_CONTRATACIÓN_SERCOP!H10>0,H07_S5_FINANCIERO_eSIGEF!H10>0,H09_S7_TRANSPARENCIA_LOTAIP!H10>0,H10_S8_PARTICIPACIÓN_CPCCS!G10>0),1,IF(H06_S4_CONTRATACIÓN_SERCOP!H10+H07_S5_FINANCIERO_eSIGEF!H10+H09_S7_TRANSPARENCIA_LOTAIP!H10+H10_S8_PARTICIPACIÓN_CPCCS!G10>=2,0.5,0)) -> 0 | E9: 1 | F9: =H07_S5_FINANCIERO_eSIGEF!G10 -> 0 | G9: 1 | H9: =B9*C9*D9*E9*F9*G9 -> 0 | I9: =B9*C9 -> 0.058518863 | J9: =IF(I9>0,(H9/I9)*100,0) -> 0 | K9: =IF(J9>=90,"🔵 Excelencia",IF(J9>=70,"🟢 Por Mandato",IF(J9>=40,"🟡 Transición",IF(J9>=20,"🟠 Por Ocurrencia","🔴 Ruptura")))) -> 🔴 Ruptura
A10: AH-I-X-03 | B10: =H04_S2_PLANIFICACIÓN_PDOT!H10 -> 0.036260413 | C10: =H04_S2_PLANIFICACIÓN_PDOT!L10 -> 0.28985507 | D10: =IF(AND(H06_S4_CONTRATACIÓN_SERCOP!H11>0,H07_S5_FINANCIERO_eSIGEF!H11>0,H09_S7_TRANSPARENCIA_LOTAIP!H11>0,H10_S8_PARTICIPACIÓN_CPCCS!G11>0),1,IF(H06_S4_CONTRATACIÓN_SERCOP!H11+H07_S5_FINANCIERO_eSIGEF!H11+H09_S7_TRANSPARENCIA_LOTAIP!H11+H10_S8_PARTICIPACIÓN_CPCCS!G11>=2,0.5,0)) -> 1 | E10: 0.9 | F10: =H07_S5_FINANCIERO_eSIGEF!G11 -> 0.72 | G10: 0.9 | H10: =B10*C10*D10*E10*F10*G10 -> 0.0061295863 | I10: =B10*C10 -> 0.010510265 | J10: =IF(I10>0,(H10/I10)*100,0) -> 58.32 | K10: =IF(J10>=90,"🔵 Excelencia",IF(J10>=70,"🟢 Por Mandato",IF(J10>=40,"🟡 Transición",IF(J10>=20,"🟠 Por Ocurrencia","🔴 Ruptura")))) -> 🟡 Transición
A11: AH-I-N-01 | B11: =H04_S2_PLANIFICACIÓN_PDOT!H11 -> 0.035447386 | C11: =H04_S2_PLANIFICACIÓN_PDOT!L11 -> 1 | D11: =IF(AND(H06_S4_CONTRATACIÓN_SERCOP!H12>0,H07_S5_FINANCIERO_eSIGEF!H12>0,H09_S7_TRANSPARENCIA_LOTAIP!H12>0,H10_S8_PARTICIPACIÓN_CPCCS!G12>0),1,IF(H06_S4_CONTRATACIÓN_SERCOP!H12+H07_S5_FINANCIERO_eSIGEF!H12+H09_S7_TRANSPARENCIA_LOTAIP!H12+H10_S8_PARTICIPACIÓN_CPCCS!G12>=2,0.5,0)) -> 0.5 | E11: 0.75 | F11: =H07_S5_FINANCIERO_eSIGEF!G12 -> 0.8 | G11: 0.75 | H11: =B11*C11*D11*E11*F11*G11 -> 0.0079756619 | I11: =B11*C11 -> 0.035447386 | J11: =IF(I11>0,(H11/I11)*100,0) -> 22.5 | K11: =IF(J11>=90,"🔵 Excelencia",IF(J11>=70,"🟢 Por Mandato",IF(J11>=40,"🟡 Transición",IF(J11>=20,"🟠 Por Ocurrencia","🔴 Ruptura")))) -> 🟠 Por Ocurrencia
A12: SC-L-G-01 | B12: =H04_S2_PLANIFICACIÓN_PDOT!H12 -> 0.0078273729 | C12: =H04_S2_PLANIFICACIÓN_PDOT!L12 -> 0.86956522 | D12: =IF(AND(H06_S4_CONTRATACIÓN_SERCOP!H13>0,H07_S5_FINANCIERO_eSIGEF!H13>0,H09_S7_TRANSPARENCIA_LOTAIP!H13>0,H10_S8_PARTICIPACIÓN_CPCCS!G13>0),1,IF(H06_S4_CONTRATACIÓN_SERCOP!H13+H07_S5_FINANCIERO_eSIGEF!H13+H09_S7_TRANSPARENCIA_LOTAIP!H13+H10_S8_PARTICIPACIÓN_CPCCS!G13>=2,0.5,0)) -> 1 | E12: 0.75 | F12: =H07_S5_FINANCIERO_eSIGEF!G13 -> 0.85 | G12: 0.75 | H12: =B12*C12*D12*E12*F12*G12 -> 0.0032543154 | I12: =B12*C12 -> 0.0068064112 | J12: =IF(I12>0,(H12/I12)*100,0) -> 47.8125 | K12: =IF(J12>=90,"🔵 Excelencia",IF(J12>=70,"🟢 Por Mandato",IF(J12>=40,"🟡 Transición",IF(J12>=20,"🟠 Por Ocurrencia","🔴 Ruptura")))) -> 🟡 Transición
A13: AH-I-X-04 | B13: =H04_S2_PLANIFICACIÓN_PDOT!H13 -> 0.023207452 | C13: =H04_S2_PLANIFICACIÓN_PDOT!L13 -> 0.57971014 | D13: =IF(AND(H06_S4_CONTRATACIÓN_SERCOP!H14>0,H07_S5_FINANCIERO_eSIGEF!H14>0,H09_S7_TRANSPARENCIA_LOTAIP!H14>0,H10_S8_PARTICIPACIÓN_CPCCS!G14>0),1,IF(H06_S4_CONTRATACIÓN_SERCOP!H14+H07_S5_FINANCIERO_eSIGEF!H14+H09_S7_TRANSPARENCIA_LOTAIP!H14+H10_S8_PARTICIPACIÓN_CPCCS!G14>=2,0.5,0)) -> 1 | E13: 0.75 | F13: =H07_S5_FINANCIERO_eSIGEF!G14 -> 0.72 | G13: 0.75 | H13: =B13*C13*D13*E13*F13*G13 -> 0.0054487062 | I13: =B13*C13 -> 0.013453596 | J13: =IF(I13>0,(H13/I13)*100,0) -> 40.5 | K13: =IF(J13>=90,"🔵 Excelencia",IF(J13>=70,"🟢 Por Mandato",IF(J13>=40,"🟡 Transición",IF(J13>=20,"🟠 Por Ocurrencia","🔴 Ruptura")))) -> 🟡 Transición
A14: PI-I-G-01 | B14: =H04_S2_PLANIFICACIÓN_PDOT!H14 -> 0.015955769 | C14: =H04_S2_PLANIFICACIÓN_PDOT!L14 -> 0.57971014 | D14: =IF(AND(H06_S4_CONTRATACIÓN_SERCOP!H15>0,H07_S5_FINANCIERO_eSIGEF!H15>0,H09_S7_TRANSPARENCIA_LOTAIP!H15>0,H10_S8_PARTICIPACIÓN_CPCCS!G15>0),1,IF(H06_S4_CONTRATACIÓN_SERCOP!H15+H07_S5_FINANCIERO_eSIGEF!H15+H09_S7_TRANSPARENCIA_LOTAIP!H15+H10_S8_PARTICIPACIÓN_CPCCS!G15>=2,0.5,0)) -> 1 | E14: 1 | F14: =H07_S5_FINANCIERO_eSIGEF!G15 -> 0.85 | G14: 1 | H14: =B14*C14*D14*E14*F14*G14 -> 0.0078622631 | I14: =B14*C14 -> 0.0092497213 | J14: =IF(I14>0,(H14/I14)*100,0) -> 85 | K14: =IF(J14>=90,"🔵 Excelencia",IF(J14>=70,"🟢 Por Mandato",IF(J14>=40,"🟡 Transición",IF(J14>=20,"🟠 Por Ocurrencia","🔴 Ruptura")))) -> 🟢 Por Mandato
A15: AH-C-X-01 | B15: =H04_S2_PLANIFICACIÓN_PDOT!H15 -> 0.010818178 | C15: =H04_S2_PLANIFICACIÓN_PDOT!L15 -> 0.33333333 | D15: =IF(AND(H06_S4_CONTRATACIÓN_SERCOP!H16>0,H07_S5_FINANCIERO_eSIGEF!H16>0,H09_S7_TRANSPARENCIA_LOTAIP!H16>0,H10_S8_PARTICIPACIÓN_CPCCS!G16>0),1,IF(H06_S4_CONTRATACIÓN_SERCOP!H16+H07_S5_FINANCIERO_eSIGEF!H16+H09_S7_TRANSPARENCIA_LOTAIP!H16+H10_S8_PARTICIPACIÓN_CPCCS!G16>=2,0.5,0)) -> 1 | E15: 1 | F15: =H07_S5_FINANCIERO_eSIGEF!G16 -> 0.72 | G15: 1 | H15: =B15*C15*D15*E15*F15*G15 -> 0.0025963627 | I15: =B15*C15 -> 0.0036060594 | J15: =IF(I15>0,(H15/I15)*100,0) -> 72 | K15: =IF(J15>=90,"🔵 Excelencia",IF(J15>=70,"🟢 Por Mandato",IF(J15>=40,"🟡 Transición",IF(J15>=20,"🟠 Por Ocurrencia","🔴 Ruptura")))) -> 🟢 Por Mandato
A16: AH-C-X-02 | B16: =H04_S2_PLANIFICACIÓN_PDOT!H16 -> 0.011215754 | C16: =H04_S2_PLANIFICACIÓN_PDOT!L16 -> 0.57971014 | D16: =IF(AND(H06_S4_CONTRATACIÓN_SERCOP!H17>0,H07_S5_FINANCIERO_eSIGEF!H17>0,H09_S7_TRANSPARENCIA_LOTAIP!H17>0,H10_S8_PARTICIPACIÓN_CPCCS!G17>0),1,IF(H06_S4_CONTRATACIÓN_SERCOP!H17+H07_S5_FINANCIERO_eSIGEF!H17+H09_S7_TRANSPARENCIA_LOTAIP!H17+H10_S8_PARTICIPACIÓN_CPCCS!G17>=2,0.5,0)) -> 1 | E16: 1 | F16: =H07_S5_FINANCIERO_eSIGEF!G17 -> 0.72 | G16: 1 | H16: =B16*C16*D16*E16*F16*G16 -> 0.0046813581 | I16: =B16*C16 -> 0.0065018863 | J16: =IF(I16>0,(H16/I16)*100,0) -> 72 | K16: =IF(J16>=90,"🔵 Excelencia",IF(J16>=70,"🟢 Por Mandato",IF(J16>=40,"🟡 Transición",IF(J16>=20,"🟠 Por Ocurrencia","🔴 Ruptura")))) -> 🟢 Por Mandato
A17: SC-I-N-03 | B17: =H04_S2_PLANIFICACIÓN_PDOT!H17 -> 0.0008500108 | C17: =H04_S2_PLANIFICACIÓN_PDOT!L17 -> 0.57971014 | D17: =IF(AND(H06_S4_CONTRATACIÓN_SERCOP!H18>0,H07_S5_FINANCIERO_eSIGEF!H18>0,H09_S7_TRANSPARENCIA_LOTAIP!H18>0,H10_S8_PARTICIPACIÓN_CPCCS!G18>0),1,IF(H06_S4_CONTRATACIÓN_SERCOP!H18+H07_S5_FINANCIERO_eSIGEF!H18+H09_S7_TRANSPARENCIA_LOTAIP!H18+H10_S8_PARTICIPACIÓN_CPCCS!G18>=2,0.5,0)) -> 1 | E17: 0.75 | F17: =H07_S5_FINANCIERO_eSIGEF!G18 -> 0.95 | G17: 0.75 | H17: =B17*C17*D17*E17*F17*G17 -> 0.00026331856 | I17: =B17*C17 -> 0.00049275989 | J17: =IF(I17>0,(H17/I17)*100,0) -> 53.4375 | K17: =IF(J17>=90,"🔵 Excelencia",IF(J17>=70,"🟢 Por Mandato",IF(J17>=40,"🟡 Transición",IF(J17>=20,"🟠 Por Ocurrencia","🔴 Ruptura")))) -> 🟡 Transición
... A25: EP-L-X-01 | B25: =H04_S2_PLANIFICACIÓN_PDOT!H25 -> 0.0014199557 | C25: =H04_S2_PLANIFICACIÓN_PDOT!L25 -> 0.28985507 | D25: =IF(AND(H06_S4_CONTRATACIÓN_SERCOP!H26>0,H07_S5_FINANCIERO_eSIGEF!H26>0,H09_S7_TRANSPARENCIA_LOTAIP!H26>0,H10_S8_PARTICIPACIÓN_CPCCS!G26>0),1,IF(H06_S4_CONTRATACIÓN_SERCOP!H26+H07_S5_FINANCIERO_eSIGEF!H26+H09_S7_TRANSPARENCIA_LOTAIP!H26+H10_S8_PARTICIPACIÓN_CPCCS!G26>=2,0.5,0)) -> 1 | E25: 1 | F25: =H07_S5_FINANCIERO_eSIGEF!G26 -> 0.85 | G25: 1 | H25: =B25*C25*D25*E25*F25*G25 -> 0.00034984415 | I25: =B25*C25 -> 0.00041158136 | J25: =IF(I25>0,(H25/I25)*100,0) -> 85 | K25: =IF(J25>=90,"🔵 Excelencia",IF(J25>=70,"🟢 Por Mandato",IF(J25>=40,"🟡 Transición",IF(J25>=20,"🟠 Por Ocurrencia","🔴 Ruptura")))) -> 🟢 Por Mandato
A26: ICPI_Numerador_Global | B26: =SUM(H6:H25) -> 0.50140941
A27: ICPI_Denominador_Global | B27: =SUM(I6:I25) -> 0.68748888
A28: ★★★ ICPI_GLOBAL_SISTEMA ★★★ | B28: =(B26/B27)*100 -> 72.933457 | C28: ← FUENTE ÚNICA ICPI. Todas las hojas referencian SOLO esta celda. NUNCA recalculan.
A29: Clasificación_AVEP | B29: =IF(B28>=90,"🔵 Excelencia en Gobernanza",IF(B28>=70,"🟢 Gestión por Mandato",IF(B28>=40,"🟡 Transición Crítica",IF(B28>=20,"🟠 Gestión por Ocurrencia","🔴 Ruptura Sistémica")))) -> 🟢 Gestión por Mandato | C29: ← CELDA MAESTRA ICPI. H15, H16, H17, H18, H19, H20, H28, H36 solo referencian esta celda.
A30: ICM_Oficial (SIGAD) | B30: =H01_PARÁMETROS!B12*100 -> 100
A31: Brecha_ICM_ICPI | B31: =B30-B28 -> 27.066543
A32: Interpretación_Brecha | B32: =IF(B31>30,"⚠️ Brecha crítica — MOM-I posible",IF(B31>15,"⚠️ Brecha moderada — vigilar","✅ Brecha aceptable")) -> ⚠️ Brecha moderada — vigilar

Sheet H13_VARIABLES_Vi
A1: 🏛️ TERRA SIAP-ICPI v2.0 | QUADRUM | B1: ⬅️ ÍNDICE GENERAL | C1: ="ICPI: "&TEXT(H12_MOTOR_ICPI_CANÓNICO!B28,"0,0")&"%" -> ICPI: 72,9% | D1: H13 — VARIABLES Vi | E1: =TEXT(TODAY(),"DD/MM/YYYY") -> 05/04/2026
A2: H13 — VARIABLES Vi — VERIFICACIÓN INTERSISTÉMICA
A3: Los 5 componentes que forman el producto lógico V_i en H12. Cada uno verifica evidencia independiente en un silo diferente.
A4: REGLA MAESTRA: Si todos ≥1 → V_i=1.0 | Si suma ≥2 → V_i=0.5 | Si suma <2 → V_i=0.0
A6: Silo | B6: V_Componente | C6: Criterio V=1.0 | D6: Criterio V=0.5 | E6: Criterio V=0.0 | F6: Fuente de Datos | G6: Fundamentación Legal
A7: S3 — POA | B7: V_POA | C7: Proyecto incluido en POA con cronograma mensual y presupuesto asignado | D7: POA registrado sin cronograma completo o sin presupuesto | E7: Proyecto sin POA o sin registro en S3 | F7: H05_S3_OPERATIVO_POA | G7: COPFP Art.9 + COOTAD Art.234
A8: S4 — SERCOP | B8: V_SERCOP | C8: Proceso adjudicado publicado en portal SERCOP | D8: Proceso registrado en SERCOP pero no adjudicado (en proceso) | E8: Sin proceso SERCOP registrado | F8: H06_S4_CONTRATACIÓN_SERCOP | G8: LOSNCP Art.22 + Art.73
A9: S5 — eSIGEF | B9: V_eSIGEF | C9: Devengado certificado > 0 en sistema MEF | D9: Codificado > 0 pero sin devengado registrado | E9: Sin registro presupuestario en eSIGEF | F9: H07_S5_FINANCIERO_eSIGEF | G9: COPFP Arts.115-117 + Acuerdo 067 MEF
A10: S7 — LOTAIP | B10: V_LOTAIP | C10: Documento en URL pública del GAD y accesible | D10: URL registrada pero no accesible o sin evidencia completa | E10: Sin URL pública — algorítmicamente no existe | F10: H09_S7_TRANSPARENCIA_LOTAIP | G10: LOTAIP Art.7 + Constitución Art.18
A11: S8 — CPCCS | B11: V_CPCCS | C11: Mencionada en rendición con evidencia citada ante CPCCS | D11: Mencionada en rendición sin evidencia documental | E11: No mencionada en acto de rendición de cuentas | F11: H10_S8_PARTICIPACIÓN_CPCCS | G11: LOPC Art.88 + Constitución Art.204
A13: ▌ FÓRMULA DEL PRODUCTO LÓGICO V_i (implementada en H12 columna D)
A14: =SI(Y(V1=1,V2=1,V3=1,V4=1),1.0, SI(SUMA(V1+V2+V3+V4)>=2,0.5,0.0))
A15: NOTA: V_POA (S3) no entra en el producto lógico del motor H12 — S3 es la programación, los verificadores son S4/S5/S7/S8.

Sheet H14_PONDERADORES
A1: 🏛️ TERRA SIAP-ICPI v2.0 | QUADRUM | B1: ⬅️ ÍNDICE GENERAL | C1: ="ICPI: "&TEXT(H12_MOTOR_ICPI_CANÓNICO!B28,"0,0")&"%" -> ICPI: 72,9% | D1: H14 — PONDERADORES | E1: =TEXT(TODAY(),"DD/MM/YYYY") -> 05/04/2026
A2: H14 — PONDERADORES Pi y Ri — JUSTIFICACIÓN METODOLÓGICA
A3: P_i = Peso financiero normalizado (Presupuesto_Anual / Total). Suma = 1.0000. R_i_raw: 1.5=Exclusiva Crítica | 1.0=Exclusiva Importante | 0.5=Complementaria
A4: Escala R_i_raw: 1.5=agua/alcantarillado/desechos | 1.0=vialidad/salud/educación | 0.5=cultura/deporte/turismo. R_i_final incorpora bono ODS 5 y ODS 13 (×1.15 desde H01).
A6: ID_Meta | B6: Descripción | C6: Competencia_GAD | D6: R_i_raw | E6: Bono_Equidad | F6: R_i_final | G6: P_i | H6: Justificación R_i | I6: Justificación P_i
A7: =H04_S2_PLANIFICACIÓN_PDOT!A6 -> SC-I-N-01 | B7: =H04_S2_PLANIFICACIÓN_PDOT!B6 -> Agua potable: cobertura 39.25%→42.38%; calidad 100% INEN 1108; infraestructura BUENA 22.74%→41.64% | C7: =H04_S2_PLANIFICACIÓN_PDOT!D6 -> Exclusiva_Crítica | D7: =H04_S2_PLANIFICACIÓN_PDOT!E6 -> 1.5 | E7: =H04_S2_PLANIFICACIÓN_PDOT!K6 -> 1 | F7: =H04_S2_PLANIFICACIÓN_PDOT!L6 -> 0.86956522 | G7: =H04_S2_PLANIFICACIÓN_PDOT!H6 -> 0.28912002 | H7: Competencia complementaria — fomento productivo no exclusivo del GAD | I7: Peso proporcional al presupuesto anual 2024 / total presupuesto anual del PDOT
A8: =H04_S2_PLANIFICACIÓN_PDOT!A7 -> SC-L-N-02 | B8: =H04_S2_PLANIFICACIÓN_PDOT!B7 -> Gestión del talento humano municipal: desempeño 80%→90%; plan capacitación 90% anual | C8: =H04_S2_PLANIFICACIÓN_PDOT!D7 -> Exclusiva_Importante | D8: =H04_S2_PLANIFICACIÓN_PDOT!E7 -> 1 | E8: =H04_S2_PLANIFICACIÓN_PDOT!K7 -> 1 | F8: =H04_S2_PLANIFICACIÓN_PDOT!L7 -> 0.57971014 | G8: =H04_S2_PLANIFICACIÓN_PDOT!H7 -> 0.32531485 | H8: Competencia complementaria — apoyo económico delegado | I8: Peso proporcional al presupuesto anual 2024 / total presupuesto anual del PDOT
A9: =H04_S2_PLANIFICACIÓN_PDOT!A8 -> AH-I-X-01 | B9: =H04_S2_PLANIFICACIÓN_PDOT!B8 -> Sostenibilidad financiera: autonomía 43.35%→45.30%; gestión cobros y coactivas | C9: =H04_S2_PLANIFICACIÓN_PDOT!D8 -> Exclusiva_Importante | D9: =H04_S2_PLANIFICACIÓN_PDOT!E8 -> 1 | E9: =H04_S2_PLANIFICACIÓN_PDOT!K8 -> 1 | F9: =H04_S2_PLANIFICACIÓN_PDOT!L8 -> 0.57971014 | G9: =H04_S2_PLANIFICACIÓN_PDOT!H8 -> 0.12454728 | H9: Competencia exclusiva importante — infraestructura de servicios municipales | I9: Mayor peso por presupuesto significativo de rehabilitación de mercado
A10: =H04_S2_PLANIFICACIÓN_PDOT!A9 -> AH-I-X-02 | B10: =H04_S2_PLANIFICACIÓN_PDOT!B9 -> Vialidad cantonal: mantenimiento 43.8 km vías CUP + 57.22 km rurales; 23.77 km tratamiento medio | C10: =H04_S2_PLANIFICACIÓN_PDOT!D9 -> Exclusiva_Crítica | D10: =H04_S2_PLANIFICACIÓN_PDOT!E9 -> 1.5 | E10: =H04_S2_PLANIFICACIÓN_PDOT!K9 -> 1 | F10: =H04_S2_PLANIFICACIÓN_PDOT!L9 -> 0.86956522 | G10: =H04_S2_PLANIFICACIÓN_PDOT!H9 -> 0.067296693 | H10: Competencia complementaria — ferias y desarrollo productivo | I10: Peso moderado acorde a presupuesto de ferias
A11: =H04_S2_PLANIFICACIÓN_PDOT!A10 -> AH-I-X-03 | B11: =H04_S2_PLANIFICACIÓN_PDOT!B10 -> Salud integral municipal: población atendida 57,401→84,041 personas (+10% anual) | C11: =H04_S2_PLANIFICACIÓN_PDOT!D10 -> Complementaria | D11: =H04_S2_PLANIFICACIÓN_PDOT!E10 -> 0.5 | E11: =H04_S2_PLANIFICACIÓN_PDOT!K10 -> 1 | F11: =H04_S2_PLANIFICACIÓN_PDOT!L10 -> 0.28985507 | G11: =H04_S2_PLANIFICACIÓN_PDOT!H10 -> 0.036260413 | H11: Competencia exclusiva importante — digitalización de servicios municipales | I11: Peso moderado por inversión en plataforma digital
A12: =H04_S2_PLANIFICACIÓN_PDOT!A11 -> AH-I-N-01 | B12: =H04_S2_PLANIFICACIÓN_PDOT!B11 -> Gestión integral desechos sólidos: 20,118→23,086 Tn/año; relleno sanitario; capacidad disposición 0%→20% | C12: =H04_S2_PLANIFICACIÓN_PDOT!D11 -> Exclusiva_Crítica | D12: =H04_S2_PLANIFICACIÓN_PDOT!E11 -> 1.5 | E12: =H04_S2_PLANIFICACIÓN_PDOT!K11 -> 1.15 | F12: =H04_S2_PLANIFICACIÓN_PDOT!L11 -> 1 | G12: =H04_S2_PLANIFICACIÓN_PDOT!H11 -> 0.035447386 | H12: Competencia complementaria — salud compartida con MSP | I12: Peso proporcional con componente MSP
A13: =H04_S2_PLANIFICACIÓN_PDOT!A12 -> SC-L-G-01 | B13: =H04_S2_PLANIFICACIÓN_PDOT!B12 -> Alcantarillado sanitario: cobertura 19.77%→24.32%; PTAR 0%→75%; estaciones bombeo 36%→72% | C13: =H04_S2_PLANIFICACIÓN_PDOT!D12 -> Exclusiva_Crítica | D13: =H04_S2_PLANIFICACIÓN_PDOT!E12 -> 1.5 | E13: =H04_S2_PLANIFICACIÓN_PDOT!K12 -> 1 | F13: =H04_S2_PLANIFICACIÓN_PDOT!L12 -> 0.86956522 | G13: =H04_S2_PLANIFICACIÓN_PDOT!H12 -> 0.0078273729 | H13: Competencia complementaria — educación compartida con MINEDUC | I13: Peso proporcional con componente MINEDUC
A14: =H04_S2_PLANIFICACIÓN_PDOT!A13 -> AH-I-X-04 | B14: =H04_S2_PLANIFICACIÓN_PDOT!B13 -> Modernización recursos administrativos: parque automotor, tecnología e infraestructura municipal | C14: =H04_S2_PLANIFICACIÓN_PDOT!D13 -> Exclusiva_Importante | D14: =H04_S2_PLANIFICACIÓN_PDOT!E13 -> 1 | E14: =H04_S2_PLANIFICACIÓN_PDOT!K13 -> 1 | F14: =H04_S2_PLANIFICACIÓN_PDOT!L13 -> 0.57971014 | G14: =H04_S2_PLANIFICACIÓN_PDOT!H13 -> 0.023207452 | H14: Competencia complementaria — género/social delegado (bono ODS 5 ×1.15) | I14: Peso menor por delegación parcial al Patronato
A15: =H04_S2_PLANIFICACIÓN_PDOT!A14 -> PI-I-G-01 | B15: =H04_S2_PLANIFICACIÓN_PDOT!B14 -> Equipamientos públicos: terminal terrestre, mercado, estación bomberil, centro salud tipo C, mantenimiento espacios recreativos | C15: =H04_S2_PLANIFICACIÓN_PDOT!D14 -> Exclusiva_Importante | D15: =H04_S2_PLANIFICACIÓN_PDOT!E14 -> 1 | E15: =H04_S2_PLANIFICACIÓN_PDOT!K14 -> 1 | F15: =H04_S2_PLANIFICACIÓN_PDOT!L14 -> 0.57971014 | G15: =H04_S2_PLANIFICACIÓN_PDOT!H14 -> 0.015955769 | H15: Competencia exclusiva crítica — vialidad urbana y rural del cantón | I15: Alto peso por inversión vial 200K — competencia exclusiva crítica
A16: =H04_S2_PLANIFICACIÓN_PDOT!A15 -> AH-C-X-01 | B16: =H04_S2_PLANIFICACIÓN_PDOT!B15 -> Protección derechos sociales: atenciones grupos prioritarios 943→1,649 (+15%/año); CDI; adultos mayores; violencia de género | C16: =H04_S2_PLANIFICACIÓN_PDOT!D15 -> Complementaria | D16: =H04_S2_PLANIFICACIÓN_PDOT!E15 -> 0.5 | E16: =H04_S2_PLANIFICACIÓN_PDOT!K15 -> 1.15 | F16: =H04_S2_PLANIFICACIÓN_PDOT!L15 -> 0.33333333 | G16: =H04_S2_PLANIFICACIÓN_PDOT!H15 -> 0.010818178 | H16: Competencia exclusiva crítica — agua potable bajo COOTAD Art.264 | I16: Mayor peso presupuestario — agua potable 300K prioridad constitucional
A17: =H04_S2_PLANIFICACIÓN_PDOT!A16 -> AH-C-X-02 | B17: =H04_S2_PLANIFICACIÓN_PDOT!B16 -> Sistema información territorial: catastro urbano-rural 19.52%→80%; 12 procesos sistematizados; 37 trámites en línea | C17: =H04_S2_PLANIFICACIÓN_PDOT!D16 -> Exclusiva_Importante | D17: =H04_S2_PLANIFICACIÓN_PDOT!E16 -> 1 | E17: =H04_S2_PLANIFICACIÓN_PDOT!K16 -> 1 | F17: =H04_S2_PLANIFICACIÓN_PDOT!L16 -> 0.57971014 | G17: =H04_S2_PLANIFICACIÓN_PDOT!H16 -> 0.011215754 | H17: Competencia exclusiva crítica — saneamiento bajo COOTAD Art.264 | I17: Alto peso — alcantarillado 237.5K competencia exclusiva
A18: =H04_S2_PLANIFICACIÓN_PDOT!A17 -> SC-I-N-03 | B18: =H04_S2_PLANIFICACIÓN_PDOT!B17 -> Participación ciudadana: 50→100 Unidades Territoriales participativas; 2→4 instancias efectivas (COPFP Art.115) | C18: =H04_S2_PLANIFICACIÓN_PDOT!D17 -> Exclusiva_Importante | D18: =H04_S2_PLANIFICACIÓN_PDOT!E17 -> 1 | E18: =H04_S2_PLANIFICACIÓN_PDOT!K17 -> 1 | F18: =H04_S2_PLANIFICACIÓN_PDOT!L17 -> 0.57971014 | G18: =H04_S2_PLANIFICACIÓN_PDOT!H17 -> 0.0008500108 | H18: Competencia complementaria — salud móvil con MSP (bono ODS 5 ×1.15) | I18: Peso reducido — brigadas de bajo costo unitario
... A26: =H04_S2_PLANIFICACIÓN_PDOT!A25 -> EP-L-X-01 | B26: =H04_S2_PLANIFICACIÓN_PDOT!B25 -> Fortalecimiento productivo: beneficiarios artesanos, mipymes, emprendedores, huertos comunitarios y cadenas de valor | C26: =H04_S2_PLANIFICACIÓN_PDOT!D25 -> Complementaria | D26: =H04_S2_PLANIFICACIÓN_PDOT!E25 -> 0.5 | E26: =H04_S2_PLANIFICACIÓN_PDOT!K25 -> 1 | F26: =H04_S2_PLANIFICACIÓN_PDOT!L25 -> 0.28985507 | G26: =H04_S2_PLANIFICACIÓN_PDOT!H25 -> 0.0014199557 | H26: Competencia complementaria — cultura y deporte no exclusivo | I26: Peso proporcional — cultura y deporte 50K
A27: TOTALES / VERIFICACIÓN | G27: =SUM(G7:G26) -> 1 | H27: ← Suma P_i debe ser = 1.0000

Sheet H15_ICPI_GLOBAL
A1: 🏛️ TERRA SIAP-ICPI v2.0 | QUADRUM | B1: ⬅️ ÍNDICE GENERAL | C1: ="ICPI: "&TEXT(H12_MOTOR_ICPI_CANÓNICO!B28,"0,0")&"%" -> ICPI: 72,9% | D1: H15 — ICPI GLOBAL | E1: =TEXT(TODAY(),"DD/MM/YYYY") -> 05/04/2026
A2: H15 — ICPI GLOBAL — ÍNDICE NUCLEAR
A3: NIVEL 3 — Solo referencia H12. NUNCA recalcula el ICPI. Fuente: H12_MOTOR_ICPI_CANÓNICO!B29
A5: ▌ PANEL MAESTRO ICPI
A6: ICPI_Global (%) | B6: =H12_MOTOR_ICPI_CANÓNICO!B28 -> 72.933457 | C6: ← Fuente única: H12!B29. Esta hoja NO recalcula el ICPI.
A7: Clasificación_AVEP | B7: =H12_MOTOR_ICPI_CANÓNICO!B29 -> 🟢 Gestión por Mandato
A8: ICM_Oficial (SIGAD) | B8: =H12_MOTOR_ICPI_CANÓNICO!B30 -> 100
A9: Brecha_ICM_ICPI | B9: =H12_MOTOR_ICPI_CANÓNICO!B31 -> 27.066543
A10: Interpretación_Brecha | B10: =H12_MOTOR_ICPI_CANÓNICO!B32 -> ⚠️ Brecha moderada — vigilar
A12: ▌ ICPI POR META (20 metas)
A13: ID_Meta | B13: Descripción | C13: ICPI_Meta_i (%) | D13: Nivel_AVEP | E13: P_i | F13: R_i_final
A14: =H12_MOTOR_ICPI_CANÓNICO!A6 -> SC-I-N-01 | B14: =H04_S2_PLANIFICACIÓN_PDOT!B6 -> Agua potable: cobertura 39.25%→42.38%; calidad 100% INEN 1108; infraestructura BUENA 22.74%→41.64% | C14: =H12_MOTOR_ICPI_CANÓNICO!J6 -> 95 | D14: =H12_MOTOR_ICPI_CANÓNICO!K6 -> 🔵 Excelencia | E14: =H12_MOTOR_ICPI_CANÓNICO!B6 -> 0.28912002 | F14: =H12_MOTOR_ICPI_CANÓNICO!C6 -> 0.86956522
A15: =H12_MOTOR_ICPI_CANÓNICO!A7 -> SC-L-N-02 | B15: =H04_S2_PLANIFICACIÓN_PDOT!B7 -> Gestión del talento humano municipal: desempeño 80%→90%; plan capacitación 90% anual | C15: =H12_MOTOR_ICPI_CANÓNICO!J7 -> 85 | D15: =H12_MOTOR_ICPI_CANÓNICO!K7 -> 🟢 Por Mandato | E15: =H12_MOTOR_ICPI_CANÓNICO!B7 -> 0.32531485 | F15: =H12_MOTOR_ICPI_CANÓNICO!C7 -> 0.57971014
A16: =H12_MOTOR_ICPI_CANÓNICO!A8 -> AH-I-X-01 | B16: =H04_S2_PLANIFICACIÓN_PDOT!B8 -> Sostenibilidad financiera: autonomía 43.35%→45.30%; gestión cobros y coactivas | C16: =H12_MOTOR_ICPI_CANÓNICO!J8 -> 58.32 | D16: =H12_MOTOR_ICPI_CANÓNICO!K8 -> 🟡 Transición | E16: =H12_MOTOR_ICPI_CANÓNICO!B8 -> 0.12454728 | F16: =H12_MOTOR_ICPI_CANÓNICO!C8 -> 0.57971014
A17: =H12_MOTOR_ICPI_CANÓNICO!A9 -> AH-I-X-02 | B17: =H04_S2_PLANIFICACIÓN_PDOT!B9 -> Vialidad cantonal: mantenimiento 43.8 km vías CUP + 57.22 km rurales; 23.77 km tratamiento medio | C17: =H12_MOTOR_ICPI_CANÓNICO!J9 -> 0 | D17: =H12_MOTOR_ICPI_CANÓNICO!K9 -> 🔴 Ruptura | E17: =H12_MOTOR_ICPI_CANÓNICO!B9 -> 0.067296693 | F17: =H12_MOTOR_ICPI_CANÓNICO!C9 -> 0.86956522
A18: =H12_MOTOR_ICPI_CANÓNICO!A10 -> AH-I-X-03 | B18: =H04_S2_PLANIFICACIÓN_PDOT!B10 -> Salud integral municipal: población atendida 57,401→84,041 personas (+10% anual) | C18: =H12_MOTOR_ICPI_CANÓNICO!J10 -> 58.32 | D18: =H12_MOTOR_ICPI_CANÓNICO!K10 -> 🟡 Transición | E18: =H12_MOTOR_ICPI_CANÓNICO!B10 -> 0.036260413 | F18: =H12_MOTOR_ICPI_CANÓNICO!C10 -> 0.28985507
A19: =H12_MOTOR_ICPI_CANÓNICO!A11 -> AH-I-N-01 | B19: =H04_S2_PLANIFICACIÓN_PDOT!B11 -> Gestión integral desechos sólidos: 20,118→23,086 Tn/año; relleno sanitario; capacidad disposición 0%→20% | C19: =H12_MOTOR_ICPI_CANÓNICO!J11 -> 22.5 | D19: =H12_MOTOR_ICPI_CANÓNICO!K11 -> 🟠 Por Ocurrencia | E19: =H12_MOTOR_ICPI_CANÓNICO!B11 -> 0.035447386 | F19: =H12_MOTOR_ICPI_CANÓNICO!C11 -> 1
A20: =H12_MOTOR_ICPI_CANÓNICO!A12 -> SC-L-G-01 | B20: =H04_S2_PLANIFICACIÓN_PDOT!B12 -> Alcantarillado sanitario: cobertura 19.77%→24.32%; PTAR 0%→75%; estaciones bombeo 36%→72% | C20: =H12_MOTOR_ICPI_CANÓNICO!J12 -> 47.8125 | D20: =H12_MOTOR_ICPI_CANÓNICO!K12 -> 🟡 Transición | E20: =H12_MOTOR_ICPI_CANÓNICO!B12 -> 0.0078273729 | F20: =H12_MOTOR_ICPI_CANÓNICO!C12 -> 0.86956522
A21: =H12_MOTOR_ICPI_CANÓNICO!A13 -> AH-I-X-04 | B21: =H04_S2_PLANIFICACIÓN_PDOT!B13 -> Modernización recursos administrativos: parque automotor, tecnología e infraestructura municipal | C21: =H12_MOTOR_ICPI_CANÓNICO!J13 -> 40.5 | D21: =H12_MOTOR_ICPI_CANÓNICO!K13 -> 🟡 Transición | E21: =H12_MOTOR_ICPI_CANÓNICO!B13 -> 0.023207452 | F21: =H12_MOTOR_ICPI_CANÓNICO!C13 -> 0.57971014
A22: =H12_MOTOR_ICPI_CANÓNICO!A14 -> PI-I-G-01 | B22: =H04_S2_PLANIFICACIÓN_PDOT!B14 -> Equipamientos públicos: terminal terrestre, mercado, estación bomberil, centro salud tipo C, mantenimiento espacios recreativos | C22: =H12_MOTOR_ICPI_CANÓNICO!J14 -> 85 | D22: =H12_MOTOR_ICPI_CANÓNICO!K14 -> 🟢 Por Mandato | E22: =H12_MOTOR_ICPI_CANÓNICO!B14 -> 0.015955769 | F22: =H12_MOTOR_ICPI_CANÓNICO!C14 -> 0.57971014
A23: =H12_MOTOR_ICPI_CANÓNICO!A15 -> AH-C-X-01 | B23: =H04_S2_PLANIFICACIÓN_PDOT!B15 -> Protección derechos sociales: atenciones grupos prioritarios 943→1,649 (+15%/año); CDI; adultos mayores; violencia de género | C23: =H12_MOTOR_ICPI_CANÓNICO!J15 -> 72 | D23: =H12_MOTOR_ICPI_CANÓNICO!K15 -> 🟢 Por Mandato | E23: =H12_MOTOR_ICPI_CANÓNICO!B15 -> 0.010818178 | F23: =H12_MOTOR_ICPI_CANÓNICO!C15 -> 0.33333333
A24: =H12_MOTOR_ICPI_CANÓNICO!A16 -> AH-C-X-02 | B24: =H04_S2_PLANIFICACIÓN_PDOT!B16 -> Sistema información territorial: catastro urbano-rural 19.52%→80%; 12 procesos sistematizados; 37 trámites en línea | C24: =H12_MOTOR_ICPI_CANÓNICO!J16 -> 72 | D24: =H12_MOTOR_ICPI_CANÓNICO!K16 -> 🟢 Por Mandato | E24: =H12_MOTOR_ICPI_CANÓNICO!B16 -> 0.011215754 | F24: =H12_MOTOR_ICPI_CANÓNICO!C16 -> 0.57971014
A25: =H12_MOTOR_ICPI_CANÓNICO!A17 -> SC-I-N-03 | B25: =H04_S2_PLANIFICACIÓN_PDOT!B17 -> Participación ciudadana: 50→100 Unidades Territoriales participativas; 2→4 instancias efectivas (COPFP Art.115) | C25: =H12_MOTOR_ICPI_CANÓNICO!J17 -> 53.4375 | D25: =H12_MOTOR_ICPI_CANÓNICO!K17 -> 🟡 Transición | E25: =H12_MOTOR_ICPI_CANÓNICO!B17 -> 0.0008500108 | F25: =H12_MOTOR_ICPI_CANÓNICO!C17 -> 0.57971014
... A33: =H12_MOTOR_ICPI_CANÓNICO!A25 -> EP-L-X-01 | B33: =H04_S2_PLANIFICACIÓN_PDOT!B25 -> Fortalecimiento productivo: beneficiarios artesanos, mipymes, emprendedores, huertos comunitarios y cadenas de valor | C33: =H12_MOTOR_ICPI_CANÓNICO!J25 -> 85 | D33: =H12_MOTOR_ICPI_CANÓNICO!K25 -> 🟢 Por Mandato | E33: =H12_MOTOR_ICPI_CANÓNICO!B25 -> 0.0014199557 | F33: =H12_MOTOR_ICPI_CANÓNICO!C25 -> 0.28985507

Sheet H16_IFE
A1: 🏛️ TERRA SIAP-ICPI v2.0 | QUADRUM | B1: ⬅️ ÍNDICE GENERAL | C1: ="ICPI: "&TEXT(H12_MOTOR_ICPI_CANÓNICO!B28,"0,0")&"%" -> ICPI: 72,9% | D1: H16 — IFE | E1: =TEXT(TODAY(),"DD/MM/YYYY") -> 05/04/2026
A2: H16 — IFE — ÍNDICE DE FIDELIDAD ELECTORAL
A3: NIVEL 3 — Verificador complementario. Solo referencia H03!B30. El motor del ecosistema es el PDOT, no el CNE.
A4: NOTA: IFE es verificador complementario. La base del ecosistema es el PDOT (S2). El CNE es el origen democrático de los compromisos.
A6: ▌ PANEL IFE
A7: IFE_Global (%) | B7: =H03_S1_ELECTORAL_CNE!B34 -> 77 | C7: ← Fuente única: H03!B34 (IFE_GLOBAL). Esta hoja NO recalcula el IFE.
A8: Clasificación_IFE | B8: =H03_S1_ELECTORAL_CNE!B35 -> ⚠️ Fidelidad Moderada
A9: Interpretación | B9: ="El GAD convirtió el "&TEXT(H03_S1_ELECTORAL_CNE!B34,"0.0")&"% de sus promesas electorales en metas estratégicas del PDOT." -> El GAD convirtió el 77% de sus promesas electorales en metas estratégicas del PDOT.
A11: ▌ 20 PROMESAS CNE — DETALLE IFE
A12: ID_Promesa | B12: Eje | C12: Descripción | D12: ID_Meta_PDOT | E12: Score_IFE | F12: Tipo_Vinculación
A13: =H03_S1_ELECTORAL_CNE!A5 -> ID_Promesa | B13: =H03_S1_ELECTORAL_CNE!B5 -> Eje_Estratégico | C13: =H03_S1_ELECTORAL_CNE!C5 -> Descripción_Promesa | D13: =H03_S1_ELECTORAL_CNE!D5 -> ID_Meta_PDOT_Vinculada | E13: =H03_S1_ELECTORAL_CNE!E5 -> Score_IFE | F13: =H03_S1_ELECTORAL_CNE!F5 -> Tipo_Vinculación
A14: =H03_S1_ELECTORAL_CNE!A6 -> EC-001 | B14: =H03_S1_ELECTORAL_CNE!B6 -> Económico | C14: =H03_S1_ELECTORAL_CNE!C6 -> Convertir a Montecristi en destino turístico nacional/internacional; rutas gastronómicas, ecoturísticas, eventos culturales | D14: =H03_S1_ELECTORAL_CNE!D6 -> EP-L-X-01 | E14: =H03_S1_ELECTORAL_CNE!E6 -> 1 | F14: =H03_S1_ELECTORAL_CNE!F6 -> Directa
A15: =H03_S1_ELECTORAL_CNE!A7 -> EC-002 | B15: =H03_S1_ELECTORAL_CNE!B7 -> Económico | C15: =H03_S1_ELECTORAL_CNE!C7 -> Fomento al sector artesanal, MIPYMES y emprendedores; programa Ka-Larte es por Ti; Cuna de Emprendedores | D15: =H03_S1_ELECTORAL_CNE!D7 -> EP-L-N-01 | E15: =H03_S1_ELECTORAL_CNE!E7 -> 1 | F15: =H03_S1_ELECTORAL_CNE!F7 -> Directa
A16: =H03_S1_ELECTORAL_CNE!A8 -> EC-003 | B16: =H03_S1_ELECTORAL_CNE!B8 -> Económico | C16: =H03_S1_ELECTORAL_CNE!C8 -> Gestión para repotenciar y ordenar el mercado municipal | D16: =H03_S1_ELECTORAL_CNE!D8 -> PI-I-G-01 | E16: =H03_S1_ELECTORAL_CNE!E8 -> 0.75 | F16: =H03_S1_ELECTORAL_CNE!F8 -> Directa
A17: =H03_S1_ELECTORAL_CNE!A9 -> EC-004 | B17: =H03_S1_ELECTORAL_CNE!B9 -> Económico | C17: =H03_S1_ELECTORAL_CNE!C9 -> Impulsar desarrollo turístico Playa San José e Isla de la Plata; manglar; Paseo Lúdico | D17: =H03_S1_ELECTORAL_CNE!D9 -> EP-L-X-01 | E17: =H03_S1_ELECTORAL_CNE!E9 -> 0.5 | F17: =H03_S1_ELECTORAL_CNE!F9 -> Parcial
A18: =H03_S1_ELECTORAL_CNE!A10 -> EC-005 | B18: =H03_S1_ELECTORAL_CNE!B10 -> Económico | C18: =H03_S1_ELECTORAL_CNE!C10 -> Generación de ordenanzas para exoneración de tributos a nuevas empresas; alianzas sector privado para atracción de inversión | D18: =H03_S1_ELECTORAL_CNE!D10 -> — | E18: =H03_S1_ELECTORAL_CNE!E10 -> 0 | F18: =H03_S1_ELECTORAL_CNE!F10 -> Sin vínculo
A19: =H03_S1_ELECTORAL_CNE!A11 -> IN-001 | B19: =H03_S1_ELECTORAL_CNE!B11 -> Institucional | C19: =H03_S1_ELECTORAL_CNE!C11 -> Elaborar PDOT 2023 con ODS; planificación territorial 30 años; Plan Bicentenario | D19: =H03_S1_ELECTORAL_CNE!D11 -> PI-I-G-02 | E19: =H03_S1_ELECTORAL_CNE!E11 -> 1 | F19: =H03_S1_ELECTORAL_CNE!F11 -> Directa
A20: =H03_S1_ELECTORAL_CNE!A12 -> IN-002 | B20: =H03_S1_ELECTORAL_CNE!B12 -> Institucional | C20: =H03_S1_ELECTORAL_CNE!C12 -> Actualización catastral urbana y rural; base de datos grupos vulnerables; registro y delimitación comunal | D20: =H03_S1_ELECTORAL_CNE!D12 -> AH-C-X-02 | E20: =H03_S1_ELECTORAL_CNE!E12 -> 1 | F20: =H03_S1_ELECTORAL_CNE!F12 -> Directa
A21: =H03_S1_ELECTORAL_CNE!A13 -> IN-003 | B21: =H03_S1_ELECTORAL_CNE!B13 -> Institucional | C21: =H03_S1_ELECTORAL_CNE!C13 -> Transformación digital del GAD; plataforma digital de trámites; gobierno electrónico abierto; mejora equipos informáticos | D21: =H03_S1_ELECTORAL_CNE!D13 -> AH-C-X-02 | E21: =H03_S1_ELECTORAL_CNE!E13 -> 0.75 | F21: =H03_S1_ELECTORAL_CNE!F13 -> Directa
A22: =H03_S1_ELECTORAL_CNE!A14 -> IN-004 | B22: =H03_S1_ELECTORAL_CNE!B14 -> Institucional | C22: =H03_S1_ELECTORAL_CNE!C14 -> Acceso a información pública (LOTAIP); rendición de cuentas transparente; convenios interinstitucionales nacionales e internacionales | D22: =H03_S1_ELECTORAL_CNE!D14 -> PI-L-G-01 | E22: =H03_S1_ELECTORAL_CNE!E14 -> 1 | F22: =H03_S1_ELECTORAL_CNE!F14 -> Directa
A23: =H03_S1_ELECTORAL_CNE!A15 -> IN-005 | B23: =H03_S1_ELECTORAL_CNE!B15 -> Institucional | C23: =H03_S1_ELECTORAL_CNE!C15 -> Seguridad ciudadana: alarmas comunitarias, habilitación UPC Aníbal San Andrés y Colorado, cuarteles bomberos en zonas estratégicas | D23: =H03_S1_ELECTORAL_CNE!D15 -> PI-I-G-01 | E23: =H03_S1_ELECTORAL_CNE!E15 -> 0.5 | F23: =H03_S1_ELECTORAL_CNE!F15 -> Parcial
A24: =H03_S1_ELECTORAL_CNE!A16 -> IN-006 | B24: =H03_S1_ELECTORAL_CNE!B16 -> Institucional | C24: =H03_S1_ELECTORAL_CNE!C16 -> Creación y fortalecimiento de marca ciudad Montecristi; posicionamiento nacional como referente de transformación | D24: =H03_S1_ELECTORAL_CNE!D16 -> — | E24: =H03_S1_ELECTORAL_CNE!E16 -> 0 | F24: =H03_S1_ELECTORAL_CNE!F16 -> Sin vínculo
... A32: =H03_S1_ELECTORAL_CNE!A24 -> AM-002 | B32: =H03_S1_ELECTORAL_CNE!B24 -> Ambiental | C32: =H03_S1_ELECTORAL_CNE!C24 -> Planificación y desarrollo de áreas verdes; arborización urbana y rural; protección cerro Montecristi y biodiversidad | D32: =H03_S1_ELECTORAL_CNE!D24 -> FA-I-X-02 | E32: =H03_S1_ELECTORAL_CNE!E24 -> 1 | F32: =H03_S1_ELECTORAL_CNE!F24 -> Directa

Sheet H17_IED
A1: 🏛️ TERRA SIAP-ICPI v2.0 | QUADRUM | B1: ⬅️ ÍNDICE GENERAL | C1: ="ICPI: "&TEXT(H12_MOTOR_ICPI_CANÓNICO!B28,"0,0")&"%" -> ICPI: 72,9% | D1: H17 — IED | E1: =TEXT(TODAY(),"DD/MM/YYYY") -> 05/04/2026
A2: H17 — IED — ÍNDICE DE EFICIENCIA DIRECTIVA POR DIRECCIÓN MUNICIPAL
A3: ICPI desagregado por clúster/dirección · SUMPRODUCT filtrado sobre H12 · No recalcula | LOSEP Art.76 + NCI 200-04 | Escala: ≥95% Excelente · ≥85% Muy Bueno · ≥75% Satisfactorio · ≥60% Regular
A5: ▌ IED POR CLÚSTER ODS
A6: Clúster_ODS | B6: N°_Metas | C6: IED_% | D6: Semáforo_AVEP | E6: Nivel_LOSEP
A7: 🏛️ Gobernanza | B7: =COUNTIF(H04_S2_PLANIFICACIÓN_PDOT!I6:I25,"Gobernanza") -> 7 | C7: {=IFERROR(SUMPRODUCT((H04_S2_PLANIFICACIÓN_PDOT!I6:I25="Gobernanza")*H12_MOTOR_ICPI_CANÓNICO!H6:H25)/SUMPRODUCT((H04_S2_PLANIFICACIÓN_PDOT!I6:I25="Gobernanza")*H12_MOTOR_ICPI_CANÓNICO!I6:I25)*100,0)} -> 75.735167 | D7: =IF(C7>=90,"🔵 Excelencia en Gobernanza",IF(C7>=70,"🟢 Gestión por Mandato",IF(C7>=40,"🟡 Transición Crítica",IF(C7>=20,"🟠 Gestión por Ocurrencia","🔴 Ruptura Sistémica")))) -> 🟢 Gestión por Mandato | E7: =IF(C7>=95,"⭐ Excelente",IF(C7>=85,"✅ Muy Bueno",IF(C7>=75,"✔️ Satisfactorio",IF(C7>=60,"🟡 Regular","🔴 Insuficiente")))) -> ✔️ Satisfactorio
A8: 🏗️ Infraestructura | B8: =COUNTIF(H04_S2_PLANIFICACIÓN_PDOT!I6:I25,"Infraestructura") -> 10 | C8: {=IFERROR(SUMPRODUCT((H04_S2_PLANIFICACIÓN_PDOT!I6:I25="Infraestructura")*H12_MOTOR_ICPI_CANÓNICO!H6:H25)/SUMPRODUCT((H04_S2_PLANIFICACIÓN_PDOT!I6:I25="Infraestructura")*H12_MOTOR_ICPI_CANÓNICO!I6:I25)*100,0)} -> 71.274659 | D8: =IF(C8>=90,"🔵 Excelencia en Gobernanza",IF(C8>=70,"🟢 Gestión por Mandato",IF(C8>=40,"🟡 Transición Crítica",IF(C8>=20,"🟠 Gestión por Ocurrencia","🔴 Ruptura Sistémica")))) -> 🟢 Gestión por Mandato | E8: =IF(C8>=95,"⭐ Excelente",IF(C8>=85,"✅ Muy Bueno",IF(C8>=75,"✔️ Satisfactorio",IF(C8>=60,"🟡 Regular","🔴 Insuficiente")))) -> 🟡 Regular
A9: 🤝 Inclusión Social | B9: =COUNTIF(H04_S2_PLANIFICACIÓN_PDOT!I6:I25,"Inclusion") -> 3 | C9: {=IFERROR(SUMPRODUCT((H04_S2_PLANIFICACIÓN_PDOT!I6:I25="Inclusion")*H12_MOTOR_ICPI_CANÓNICO!H6:H25)/SUMPRODUCT((H04_S2_PLANIFICACIÓN_PDOT!I6:I25="Inclusion")*H12_MOTOR_ICPI_CANÓNICO!I6:I25)*100,0)} -> 63.510333 | D9: =IF(C9>=90,"🔵 Excelencia en Gobernanza",IF(C9>=70,"🟢 Gestión por Mandato",IF(C9>=40,"🟡 Transición Crítica",IF(C9>=20,"🟠 Gestión por Ocurrencia","🔴 Ruptura Sistémica")))) -> 🟡 Transición Crítica | E9: =IF(C9>=95,"⭐ Excelente",IF(C9>=85,"✅ Muy Bueno",IF(C9>=75,"✔️ Satisfactorio",IF(C9>=60,"🟡 Regular","🔴 Insuficiente")))) -> 🟡 Regular
A12: ▌ IED POR DIRECCIÓN MUNICIPAL
A13: Dirección | B13: N°_Metas | C13: IED_% | D13: Semáforo_AVEP | E13: Nivel_LOSEP | F13: Metas_en_Riesgo
A14: Dirección Económica | B14: =COUNTIF(H04_S2_PLANIFICACIÓN_PDOT!R6:R25,"Dirección Económica") -> 1 | C14: {=IFERROR(SUMPRODUCT((H04_S2_PLANIFICACIÓN_PDOT!R6:R25="Dirección Económica")*H12_MOTOR_ICPI_CANÓNICO!H6:H25)/SUMPRODUCT((H04_S2_PLANIFICACIÓN_PDOT!R6:R25="Dirección Económica")*H12_MOTOR_ICPI_CANÓNICO!I6:I25)*100,0)} -> 95 | D14: =IF(C14>=90,"🔵 Excelencia en Gobernanza",IF(C14>=70,"🟢 Gestión por Mandato",IF(C14>=40,"🟡 Transición Crítica",IF(C14>=20,"🟠 Gestión por Ocurrencia","🔴 Ruptura Sistémica")))) -> 🔵 Excelencia en Gobernanza | E14: =IF(C14>=95,"⭐ Excelente",IF(C14>=85,"✅ Muy Bueno",IF(C14>=75,"✔️ Satisfactorio",IF(C14>=60,"🟡 Regular","🔴 Insuficiente")))) -> ⭐ Excelente | F14: {=SUMPRODUCT((H04_S2_PLANIFICACIÓN_PDOT!R6:R25="Dirección Económica")*( H12_MOTOR_ICPI_CANÓNICO!J6:J25<40))} -> 0
A15: Dirección de Obras Públicas | B15: =COUNTIF(H04_S2_PLANIFICACIÓN_PDOT!R6:R25,"Dirección de Obras Públicas") -> 4 | C15: {=IFERROR(SUMPRODUCT((H04_S2_PLANIFICACIÓN_PDOT!R6:R25="Dirección de Obras Públicas")*H12_MOTOR_ICPI_CANÓNICO!H6:H25)/SUMPRODUCT((H04_S2_PLANIFICACIÓN_PDOT!R6:R25="Dirección de Obras Públicas")*H12_MOTOR_ICPI_CANÓNICO!I6:I25)*100,0)} -> 34.706943 | D15: =IF(C15>=90,"🔵 Excelencia en Gobernanza",IF(C15>=70,"🟢 Gestión por Mandato",IF(C15>=40,"🟡 Transición Crítica",IF(C15>=20,"🟠 Gestión por Ocurrencia","🔴 Ruptura Sistémica")))) -> 🟠 Gestión por Ocurrencia | E15: =IF(C15>=95,"⭐ Excelente",IF(C15>=85,"✅ Muy Bueno",IF(C15>=75,"✔️ Satisfactorio",IF(C15>=60,"🟡 Regular","🔴 Insuficiente")))) -> 🔴 Insuficiente | F15: {=SUMPRODUCT((H04_S2_PLANIFICACIÓN_PDOT!R6:R25="Dirección de Obras Públicas")*( H12_MOTOR_ICPI_CANÓNICO!J6:J25<40))} -> 1
A16: Dirección TIC | B16: =COUNTIF(H04_S2_PLANIFICACIÓN_PDOT!R6:R25,"Dirección TIC") -> 1 | C16: {=IFERROR(SUMPRODUCT((H04_S2_PLANIFICACIÓN_PDOT!R6:R25="Dirección TIC")*H12_MOTOR_ICPI_CANÓNICO!H6:H25)/SUMPRODUCT((H04_S2_PLANIFICACIÓN_PDOT!R6:R25="Dirección TIC")*H12_MOTOR_ICPI_CANÓNICO!I6:I25)*100,0)} -> 85 | D16: =IF(C16>=90,"🔵 Excelencia en Gobernanza",IF(C16>=70,"🟢 Gestión por Mandato",IF(C16>=40,"🟡 Transición Crítica",IF(C16>=20,"🟠 Gestión por Ocurrencia","🔴 Ruptura Sistémica")))) -> 🟢 Gestión por Mandato | E16: =IF(C16>=95,"⭐ Excelente",IF(C16>=85,"✅ Muy Bueno",IF(C16>=75,"✔️ Satisfactorio",IF(C16>=60,"🟡 Regular","🔴 Insuficiente")))) -> ✅ Muy Bueno | F16: {=SUMPRODUCT((H04_S2_PLANIFICACIÓN_PDOT!R6:R25="Dirección TIC")*( H12_MOTOR_ICPI_CANÓNICO!J6:J25<40))} -> 0
A17: Dirección de Salud | B17: =COUNTIF(H04_S2_PLANIFICACIÓN_PDOT!R6:R25,"Dirección de Salud") -> 0 | C17: {=IFERROR(SUMPRODUCT((H04_S2_PLANIFICACIÓN_PDOT!R6:R25="Dirección de Salud")*H12_MOTOR_ICPI_CANÓNICO!H6:H25)/SUMPRODUCT((H04_S2_PLANIFICACIÓN_PDOT!R6:R25="Dirección de Salud")*H12_MOTOR_ICPI_CANÓNICO!I6:I25)*100,0)} -> 0 | D17: =IF(C17>=90,"🔵 Excelencia en Gobernanza",IF(C17>=70,"🟢 Gestión por Mandato",IF(C17>=40,"🟡 Transición Crítica",IF(C17>=20,"🟠 Gestión por Ocurrencia","🔴 Ruptura Sistémica")))) -> 🔴 Ruptura Sistémica | E17: =IF(C17>=95,"⭐ Excelente",IF(C17>=85,"✅ Muy Bueno",IF(C17>=75,"✔️ Satisfactorio",IF(C17>=60,"🟡 Regular","🔴 Insuficiente")))) -> 🔴 Insuficiente | F17: {=SUMPRODUCT((H04_S2_PLANIFICACIÓN_PDOT!R6:R25="Dirección de Salud")*( H12_MOTOR_ICPI_CANÓNICO!J6:J25<40))} -> 0
A18: Dirección de Educación | B18: =COUNTIF(H04_S2_PLANIFICACIÓN_PDOT!R6:R25,"Dirección de Educación") -> 0 | C18: {=IFERROR(SUMPRODUCT((H04_S2_PLANIFICACIÓN_PDOT!R6:R25="Dirección de Educación")*H12_MOTOR_ICPI_CANÓNICO!H6:H25)/SUMPRODUCT((H04_S2_PLANIFICACIÓN_PDOT!R6:R25="Dirección de Educación")*H12_MOTOR_ICPI_CANÓNICO!I6:I25)*100,0)} -> 0 | D18: =IF(C18>=90,"🔵 Excelencia en Gobernanza",IF(C18>=70,"🟢 Gestión por Mandato",IF(C18>=40,"🟡 Transición Crítica",IF(C18>=20,"🟠 Gestión por Ocurrencia","🔴 Ruptura Sistémica")))) -> 🔴 Ruptura Sistémica | E18: =IF(C18>=95,"⭐ Excelente",IF(C18>=85,"✅ Muy Bueno",IF(C18>=75,"✔️ Satisfactorio",IF(C18>=60,"🟡 Regular","🔴 Insuficiente")))) -> 🔴 Insuficiente | F18: {=SUMPRODUCT((H04_S2_PLANIFICACIÓN_PDOT!R6:R25="Dirección de Educación")*( H12_MOTOR_ICPI_CANÓNICO!J6:J25<40))} -> 0
A19: Patronato Municipal | B19: =COUNTIF(H04_S2_PLANIFICACIÓN_PDOT!R6:R25,"Patronato Municipal") -> 2 | C19: {=IFERROR(SUMPRODUCT((H04_S2_PLANIFICACIÓN_PDOT!R6:R25="Patronato Municipal")*H12_MOTOR_ICPI_CANÓNICO!H6:H25)/SUMPRODUCT((H04_S2_PLANIFICACIÓN_PDOT!R6:R25="Patronato Municipal")*H12_MOTOR_ICPI_CANÓNICO!I6:I25)*100,0)} -> 94.918697 | D19: =IF(C19>=90,"🔵 Excelencia en Gobernanza",IF(C19>=70,"🟢 Gestión por Mandato",IF(C19>=40,"🟡 Transición Crítica",IF(C19>=20,"🟠 Gestión por Ocurrencia","🔴 Ruptura Sistémica")))) -> 🔵 Excelencia en Gobernanza | E19: =IF(C19>=95,"⭐ Excelente",IF(C19>=85,"✅ Muy Bueno",IF(C19>=75,"✔️ Satisfactorio",IF(C19>=60,"🟡 Regular","🔴 Insuficiente")))) -> ✅ Muy Bueno | F19: {=SUMPRODUCT((H04_S2_PLANIFICACIÓN_PDOT!R6:R25="Patronato Municipal")*( H12_MOTOR_ICPI_CANÓNICO!J6:J25<40))} -> 0
A20: Dirección Ambiental | B20: =COUNTIF(H04_S2_PLANIFICACIÓN_PDOT!R6:R25,"Dirección Ambiental") -> 3 | C20: {=IFERROR(SUMPRODUCT((H04_S2_PLANIFICACIÓN_PDOT!R6:R25="Dirección Ambiental")*H12_MOTOR_ICPI_CANÓNICO!H6:H25)/SUMPRODUCT((H04_S2_PLANIFICACIÓN_PDOT!R6:R25="Dirección Ambiental")*H12_MOTOR_ICPI_CANÓNICO!I6:I25)*100,0)} -> 68.824412 | D20: =IF(C20>=90,"🔵 Excelencia en Gobernanza",IF(C20>=70,"🟢 Gestión por Mandato",IF(C20>=40,"🟡 Transición Crítica",IF(C20>=20,"🟠 Gestión por Ocurrencia","🔴 Ruptura Sistémica")))) -> 🟡 Transición Crítica | E20: =IF(C20>=95,"⭐ Excelente",IF(C20>=85,"✅ Muy Bueno",IF(C20>=75,"✔️ Satisfactorio",IF(C20>=60,"🟡 Regular","🔴 Insuficiente")))) -> 🟡 Regular | F20: {=SUMPRODUCT((H04_S2_PLANIFICACIÓN_PDOT!R6:R25="Dirección Ambiental")*( H12_MOTOR_ICPI_CANÓNICO!J6:J25<40))} -> 0
A21: Dirección Administrativa | B21: =COUNTIF(H04_S2_PLANIFICACIÓN_PDOT!R6:R25,"Dirección Administrativa") -> 1 | C21: {=IFERROR(SUMPRODUCT((H04_S2_PLANIFICACIÓN_PDOT!R6:R25="Dirección Administrativa")*H12_MOTOR_ICPI_CANÓNICO!H6:H25)/SUMPRODUCT((H04_S2_PLANIFICACIÓN_PDOT!R6:R25="Dirección Administrativa")*H12_MOTOR_ICPI_CANÓNICO!I6:I25)*100,0)} -> 85 | D21: =IF(C21>=90,"🔵 Excelencia en Gobernanza",IF(C21>=70,"🟢 Gestión por Mandato",IF(C21>=40,"🟡 Transición Crítica",IF(C21>=20,"🟠 Gestión por Ocurrencia","🔴 Ruptura Sistémica")))) -> 🟢 Gestión por Mandato | E21: =IF(C21>=95,"⭐ Excelente",IF(C21>=85,"✅ Muy Bueno",IF(C21>=75,"✔️ Satisfactorio",IF(C21>=60,"🟡 Regular","🔴 Insuficiente")))) -> ✅ Muy Bueno | F21: {=SUMPRODUCT((H04_S2_PLANIFICACIÓN_PDOT!R6:R25="Dirección Administrativa")*( H12_MOTOR_ICPI_CANÓNICO!J6:J25<40))} -> 0
A22: Secretaría General | B22: =COUNTIF(H04_S2_PLANIFICACIÓN_PDOT!R6:R25,"Secretaría General") -> 0 | C22: {=IFERROR(SUMPRODUCT((H04_S2_PLANIFICACIÓN_PDOT!R6:R25="Secretaría General")*H12_MOTOR_ICPI_CANÓNICO!H6:H25)/SUMPRODUCT((H04_S2_PLANIFICACIÓN_PDOT!R6:R25="Secretaría General")*H12_MOTOR_ICPI_CANÓNICO!I6:I25)*100,0)} -> 0 | D22: =IF(C22>=90,"🔵 Excelencia en Gobernanza",IF(C22>=70,"🟢 Gestión por Mandato",IF(C22>=40,"🟡 Transición Crítica",IF(C22>=20,"🟠 Gestión por Ocurrencia","🔴 Ruptura Sistémica")))) -> 🔴 Ruptura Sistémica | E22: =IF(C22>=95,"⭐ Excelente",IF(C22>=85,"✅ Muy Bueno",IF(C22>=75,"✔️ Satisfactorio",IF(C22>=60,"🟡 Regular","🔴 Insuficiente")))) -> 🔴 Insuficiente | F22: {=SUMPRODUCT((H04_S2_PLANIFICACIÓN_PDOT!R6:R25="Secretaría General")*( H12_MOTOR_ICPI_CANÓNICO!J6:J25<40))} -> 0
A23: Dirección de Cultura y Deporte | B23: =COUNTIF(H04_S2_PLANIFICACIÓN_PDOT!R6:R25,"Dirección de Cultura y Deporte") -> 1 | C23: {=IFERROR(SUMPRODUCT((H04_S2_PLANIFICACIÓN_PDOT!R6:R25="Dirección de Cultura y Deporte")*H12_MOTOR_ICPI_CANÓNICO!H6:H25)/SUMPRODUCT((H04_S2_PLANIFICACIÓN_PDOT!R6:R25="Dirección de Cultura y Deporte")*H12_MOTOR_ICPI_CANÓNICO!I6:I25)*100,0)} -> 47.8125 | D23: =IF(C23>=90,"🔵 Excelencia en Gobernanza",IF(C23>=70,"🟢 Gestión por Mandato",IF(C23>=40,"🟡 Transición Crítica",IF(C23>=20,"🟠 Gestión por Ocurrencia","🔴 Ruptura Sistémica")))) -> 🟡 Transición Crítica | E23: =IF(C23>=95,"⭐ Excelente",IF(C23>=85,"✅ Muy Bueno",IF(C23>=75,"✔️ Satisfactorio",IF(C23>=60,"🟡 Regular","🔴 Insuficiente")))) -> 🔴 Insuficiente | F23: {=SUMPRODUCT((H04_S2_PLANIFICACIÓN_PDOT!R6:R25="Dirección de Cultura y Deporte")*( H12_MOTOR_ICPI_CANÓNICO!J6:J25<40))} -> 0
A24: Dirección de Agua y Saneamiento | B24: =COUNTIF(H04_S2_PLANIFICACIÓN_PDOT!R6:R25,"Dirección de Agua y Saneamiento") -> 2 | C24: {=IFERROR(SUMPRODUCT((H04_S2_PLANIFICACIÓN_PDOT!R6:R25="Dirección de Agua y Saneamiento")*H12_MOTOR_ICPI_CANÓNICO!H6:H25)/SUMPRODUCT((H04_S2_PLANIFICACIÓN_PDOT!R6:R25="Dirección de Agua y Saneamiento")*H12_MOTOR_ICPI_CANÓNICO!I6:I25)*100,0)} -> 72 | D24: =IF(C24>=90,"🔵 Excelencia en Gobernanza",IF(C24>=70,"🟢 Gestión por Mandato",IF(C24>=40,"🟡 Transición Crítica",IF(C24>=20,"🟠 Gestión por Ocurrencia","🔴 Ruptura Sistémica")))) -> 🟢 Gestión por Mandato | E24: =IF(C24>=95,"⭐ Excelente",IF(C24>=85,"✅ Muy Bueno",IF(C24>=75,"✔️ Satisfactorio",IF(C24>=60,"🟡 Regular","🔴 Insuficiente")))) -> 🟡 Regular | F24: {=SUMPRODUCT((H04_S2_PLANIFICACIÓN_PDOT!R6:R25="Dirección de Agua y Saneamiento")*( H12_MOTOR_ICPI_CANÓNICO!J6:J25<40))} -> 0
A26: IED_Promedio_Global | B26: =IFERROR(AVERAGE(C14:C24),0) -> 53.023868 | C26: ← Referenciado por H28 y H29

Sheet H18_ITAM
A1: 🏛️ TERRA SIAP-ICPI v2.0 | QUADRUM | B1: ⬅️ ÍNDICE GENERAL | C1: ="ICPI: "&TEXT(H12_MOTOR_ICPI_CANÓNICO!B28,"0,0")&"%" -> ICPI: 72,9% | D1: H18 — ITAM | E1: =TEXT(TODAY(),"DD/MM/YYYY") -> 05/04/2026
A2: H18 — ITAM — ÍNDICE DE TRANSPARENCIA ACTIVA MUNICIPAL
A3: NIVEL 3 — Calidad y accesibilidad documental. Solo referencia H09!B27 (ITAM_Base). Fundamentación: LOTAIP Art.7 + Constitución Art.18
A5: ▌ PANEL ITAM
A6: ITAM_Global (%) | B6: =H09_S7_TRANSPARENCIA_LOTAIP!B28 -> 70 | C6: ← Fuente única: H09!B27. Esta hoja NO recalcula el ITAM.
A7: Clasificación_ITAM | B7: =IF(B6>=85,"✅ Alta Transparencia — LOTAIP cumplida",IF(B6>=60,"⚠️ Transparencia Media — revisar literales",IF(B6>=40,"🟠 Transparencia Baja — incumplimiento parcial","🔴 Opacidad institucional — incumplimiento grave"))) -> ⚠️ Transparencia Media — revisar literales
A8: Metas con URL pública | B8: =COUNTIF(H09_S7_TRANSPARENCIA_LOTAIP!G7:G26,"SÍ") -> 18
A9: Metas sin URL pública | B9: =COUNTIF(H09_S7_TRANSPARENCIA_LOTAIP!G7:G26,"NO") -> 2
A11: ▌ DESGLOSE POR LITERAL LOTAIP
A12: Literal_LOTAIP | B12: N°_Documentos | C12: Accesibles | D12: V_LOTAIP_Prom
A13: a1 | B13: =COUNTIF(H09_S7_TRANSPARENCIA_LOTAIP!C7:C26,"a1") -> 3 | C13: =COUNTIFS(H09_S7_TRANSPARENCIA_LOTAIP!C7:C26,"a1",H09_S7_TRANSPARENCIA_LOTAIP!G7:G26,"SÍ") -> 3 | D13: =IFERROR(AVERAGEIF(H09_S7_TRANSPARENCIA_LOTAIP!C7:C26,"a1",H09_S7_TRANSPARENCIA_LOTAIP!H7:H26),0) -> 0.66666667
A14: a4 | B14: =COUNTIF(H09_S7_TRANSPARENCIA_LOTAIP!C7:C26,"a4") -> 5 | C14: =COUNTIFS(H09_S7_TRANSPARENCIA_LOTAIP!C7:C26,"a4",H09_S7_TRANSPARENCIA_LOTAIP!G7:G26,"SÍ") -> 5 | D14: =IFERROR(AVERAGEIF(H09_S7_TRANSPARENCIA_LOTAIP!C7:C26,"a4",H09_S7_TRANSPARENCIA_LOTAIP!H7:H26),0) -> 1
A15: k | B15: =COUNTIF(H09_S7_TRANSPARENCIA_LOTAIP!C7:C26,"k") -> 7 | C15: =COUNTIFS(H09_S7_TRANSPARENCIA_LOTAIP!C7:C26,"k",H09_S7_TRANSPARENCIA_LOTAIP!G7:G26,"SÍ") -> 7 | D15: =IFERROR(AVERAGEIF(H09_S7_TRANSPARENCIA_LOTAIP!C7:C26,"k",H09_S7_TRANSPARENCIA_LOTAIP!H7:H26),0) -> 0.64285714
A16: m | B16: =COUNTIF(H09_S7_TRANSPARENCIA_LOTAIP!C7:C26,"m") -> 5 | C16: =COUNTIFS(H09_S7_TRANSPARENCIA_LOTAIP!C7:C26,"m",H09_S7_TRANSPARENCIA_LOTAIP!G7:G26,"SÍ") -> 3 | D16: =IFERROR(AVERAGEIF(H09_S7_TRANSPARENCIA_LOTAIP!C7:C26,"m",H09_S7_TRANSPARENCIA_LOTAIP!H7:H26),0) -> 0.5
A17: otro | B17: =COUNTIF(H09_S7_TRANSPARENCIA_LOTAIP!C7:C26,"otro") -> 0 | C17: =COUNTIFS(H09_S7_TRANSPARENCIA_LOTAIP!C7:C26,"otro",H09_S7_TRANSPARENCIA_LOTAIP!G7:G26,"SÍ") -> 0 | D17: =IFERROR(AVERAGEIF(H09_S7_TRANSPARENCIA_LOTAIP!C7:C26,"otro",H09_S7_TRANSPARENCIA_LOTAIP!H7:H26),0) -> 0
A20: ▌ DETALLE POR META
A21: ID_Meta | B21: Literal | C21: URL_Portal_GAD | D21: Accesible | E21: V_LOTAIP
A22: =H09_S7_TRANSPARENCIA_LOTAIP!A7 -> SC-I-N-01 | B22: =H09_S7_TRANSPARENCIA_LOTAIP!C7 -> k | C22: =H09_S7_TRANSPARENCIA_LOTAIP!E7 -> https://montecristi.gob.ec/transparencia/k/pdot001 | D22: =H09_S7_TRANSPARENCIA_LOTAIP!G7 -> SÍ | E22: =H09_S7_TRANSPARENCIA_LOTAIP!H7 -> 0.5
A23: =H09_S7_TRANSPARENCIA_LOTAIP!A8 -> SC-L-N-02 | B23: =H09_S7_TRANSPARENCIA_LOTAIP!C8 -> k | C23: =H09_S7_TRANSPARENCIA_LOTAIP!E8 -> https://montecristi.gob.ec/transparencia/k/pdot002 | D23: =H09_S7_TRANSPARENCIA_LOTAIP!G8 -> SÍ | E23: =H09_S7_TRANSPARENCIA_LOTAIP!H8 -> 0.5
A24: =H09_S7_TRANSPARENCIA_LOTAIP!A9 -> AH-I-X-01 | B24: =H09_S7_TRANSPARENCIA_LOTAIP!C9 -> a4 | C24: =H09_S7_TRANSPARENCIA_LOTAIP!E9 -> https://montecristi.gob.ec/transparencia/a4/pdot003 | D24: =H09_S7_TRANSPARENCIA_LOTAIP!G9 -> SÍ | E24: =H09_S7_TRANSPARENCIA_LOTAIP!H9 -> 1
A25: =H09_S7_TRANSPARENCIA_LOTAIP!A10 -> AH-I-X-02 | B25: =H09_S7_TRANSPARENCIA_LOTAIP!C10 -> k | C25: =H09_S7_TRANSPARENCIA_LOTAIP!E10 -> https://montecristi.gob.ec/transparencia/k/pdot004 | D25: =H09_S7_TRANSPARENCIA_LOTAIP!G10 -> SÍ | E25: =H09_S7_TRANSPARENCIA_LOTAIP!H10 -> 0
A26: =H09_S7_TRANSPARENCIA_LOTAIP!A11 -> AH-I-X-03 | B26: =H09_S7_TRANSPARENCIA_LOTAIP!C11 -> a1 | C26: =H09_S7_TRANSPARENCIA_LOTAIP!E11 -> https://montecristi.gob.ec/transparencia/a1/pdot005 | D26: =H09_S7_TRANSPARENCIA_LOTAIP!G11 -> SÍ | E26: =H09_S7_TRANSPARENCIA_LOTAIP!H11 -> 1
A27: =H09_S7_TRANSPARENCIA_LOTAIP!A12 -> AH-I-N-01 | B27: =H09_S7_TRANSPARENCIA_LOTAIP!C12 -> m | C27: =H09_S7_TRANSPARENCIA_LOTAIP!E12 -> https://montecristi.gob.ec/transparencia/m/pdot006 | D27: =H09_S7_TRANSPARENCIA_LOTAIP!G12 -> SÍ | E27: =H09_S7_TRANSPARENCIA_LOTAIP!H12 -> 0
A28: =H09_S7_TRANSPARENCIA_LOTAIP!A13 -> SC-L-G-01 | B28: =H09_S7_TRANSPARENCIA_LOTAIP!C13 -> m | C28: =H09_S7_TRANSPARENCIA_LOTAIP!E13 -> https://montecristi.gob.ec/transparencia/m/pdot007 | D28: =H09_S7_TRANSPARENCIA_LOTAIP!G13 -> SÍ | E28: =H09_S7_TRANSPARENCIA_LOTAIP!H13 -> 0.5
A29: =H09_S7_TRANSPARENCIA_LOTAIP!A14 -> AH-I-X-04 | B29: =H09_S7_TRANSPARENCIA_LOTAIP!C14 -> k | C29: =H09_S7_TRANSPARENCIA_LOTAIP!E14 -> https://montecristi.gob.ec/transparencia/k/pdot008 | D29: =H09_S7_TRANSPARENCIA_LOTAIP!G14 -> SÍ | E29: =H09_S7_TRANSPARENCIA_LOTAIP!H14 -> 1
A30: =H09_S7_TRANSPARENCIA_LOTAIP!A15 -> PI-I-G-01 | B30: =H09_S7_TRANSPARENCIA_LOTAIP!C15 -> a4 | C30: =H09_S7_TRANSPARENCIA_LOTAIP!E15 -> https://montecristi.gob.ec/transparencia/a4/pdot009 | D30: =H09_S7_TRANSPARENCIA_LOTAIP!G15 -> SÍ | E30: =H09_S7_TRANSPARENCIA_LOTAIP!H15 -> 1
A31: =H09_S7_TRANSPARENCIA_LOTAIP!A16 -> AH-C-X-01 | B31: =H09_S7_TRANSPARENCIA_LOTAIP!C16 -> a4 | C31: =H09_S7_TRANSPARENCIA_LOTAIP!E16 -> https://montecristi.gob.ec/transparencia/a4/pdot010 | D31: =H09_S7_TRANSPARENCIA_LOTAIP!G16 -> SÍ | E31: =H09_S7_TRANSPARENCIA_LOTAIP!H16 -> 1
A32: =H09_S7_TRANSPARENCIA_LOTAIP!A17 -> AH-C-X-02 | B32: =H09_S7_TRANSPARENCIA_LOTAIP!C17 -> a4 | C32: =H09_S7_TRANSPARENCIA_LOTAIP!E17 -> https://montecristi.gob.ec/transparencia/a4/pdot011 | D32: =H09_S7_TRANSPARENCIA_LOTAIP!G17 -> SÍ | E32: =H09_S7_TRANSPARENCIA_LOTAIP!H17 -> 1
A33: =H09_S7_TRANSPARENCIA_LOTAIP!A18 -> SC-I-N-03 | B33: =H09_S7_TRANSPARENCIA_LOTAIP!C18 -> m | C33: =H09_S7_TRANSPARENCIA_LOTAIP!E18 -> 0 | D33: =H09_S7_TRANSPARENCIA_LOTAIP!G18 -> NO | E33: =H09_S7_TRANSPARENCIA_LOTAIP!H18 -> 0.5
... A41: =H09_S7_TRANSPARENCIA_LOTAIP!A26 -> EP-L-X-01 | B41: =H09_S7_TRANSPARENCIA_LOTAIP!C26 -> k | C41: =H09_S7_TRANSPARENCIA_LOTAIP!E26 -> https://montecristi.gob.ec/transparencia/k/pdot020 | D41: =H09_S7_TRANSPARENCIA_LOTAIP!G26 -> SÍ | E41: =H09_S7_TRANSPARENCIA_LOTAIP!H26 -> 0.5

Sheet H19_ICS_ISP
A1: 🏛️ TERRA SIAP-ICPI v2.0 | QUADRUM | B1: ⬅️ ÍNDICE GENERAL | C1: ="ICPI: "&TEXT(H12_MOTOR_ICPI_CANÓNICO!B28,"0,0")&"%" -> ICPI: 72,9% | D1: H19 — ICS+ISP | E1: =TEXT(TODAY(),"DD/MM/YYYY") -> 05/04/2026
A2: H19 — ICS+ISP — CONGRUENCIA SOCIAL Y PATRONATO
A3: ICS: ICPI filtrado para metas ODS Cluster=Inclusion. ISP: Trazabilidad del gasto social delegado (Patronato). Fundamentación: Constitución Art.35 + COOTAD Art.249
A5: ▌ ICS — ÍNDICE DE CONGRUENCIA SOCIAL
A6: ICS_Global (%) | B6: {=IFERROR(SUMPRODUCT((H04_S2_PLANIFICACIÓN_PDOT!I6:I25="Inclusion")*H12_MOTOR_ICPI_CANÓNICO!H6:H25)/SUMPRODUCT((H04_S2_PLANIFICACIÓN_PDOT!I6:I25="Inclusion")*H12_MOTOR_ICPI_CANÓNICO!I6:I25)*100,0)} -> 63.510333
A7: Clasificación_ICS | B7: =IF(B6>=90,"🔵 Excelencia en Gobernanza",IF(B6>=70,"🟢 Gestión por Mandato",IF(B6>=40,"🟡 Transición Crítica",IF(B6>=20,"🟠 Gestión por Ocurrencia","🔴 Ruptura Sistémica")))) -> 🟡 Transición Crítica
A8: N°_Metas_Sociales | B8: =COUNTIF(H04_S2_PLANIFICACIÓN_PDOT!I6:I25,"Inclusion") -> 3
A10: ▌ ISP — ÍNDICE DE CONGRUENCIA DEL PATRONATO (Componente opcional)
A11: Presupuesto_Ejecutado_Patronato [ingresar manualmente] | B11: 0
A12: Presupuesto_Patronato_10%_COOTAD | B12: =H01_PARÁMETROS!B29 -> 2668914.7
A13: ISP_Patronato (%) | B13: =IF(B11>0,B11/B12*100,"N/A — Sin Patronato") -> N/A — Sin Patronato
A14: SSC_Compuesto | B14: =IF(B13="N/A — Sin Patronato",B6,B6*0.7+B13*0.3) -> 63.510333 | C14: ← SSC = ICS×0.70 + ISP×0.30 si Patronato activo | = ICS si sin Patronato
A16: ▌ METAS SOCIALES (ODS_Cluster = Inclusion)
A17: ID_Meta | B17: Descripción | C17: ODS_Específico | D17: ICPI_Meta_i (%) | E17: Nivel_AVEP
A18: =H12_MOTOR_ICPI_CANÓNICO!A11 -> AH-I-N-01 | B18: =H04_S2_PLANIFICACIÓN_PDOT!B11 -> Gestión integral desechos sólidos: 20,118→23,086 Tn/año; relleno sanitario; capacidad disposición 0%→20% | C18: =H04_S2_PLANIFICACIÓN_PDOT!J11 -> 11,13,3 | D18: =H12_MOTOR_ICPI_CANÓNICO!J11 -> 22.5 | E18: =H12_MOTOR_ICPI_CANÓNICO!K11 -> 🟠 Por Ocurrencia
A19: =H12_MOTOR_ICPI_CANÓNICO!A12 -> SC-L-G-01 | B19: =H04_S2_PLANIFICACIÓN_PDOT!B12 -> Alcantarillado sanitario: cobertura 19.77%→24.32%; PTAR 0%→75%; estaciones bombeo 36%→72% | C19: =H04_S2_PLANIFICACIÓN_PDOT!J12 -> 6,3,11 | D19: =H12_MOTOR_ICPI_CANÓNICO!J12 -> 47.8125 | E19: =H12_MOTOR_ICPI_CANÓNICO!K12 -> 🟡 Transición
A20: =H12_MOTOR_ICPI_CANÓNICO!A13 -> AH-I-X-04 | B20: =H04_S2_PLANIFICACIÓN_PDOT!B13 -> Modernización recursos administrativos: parque automotor, tecnología e infraestructura municipal | C20: =H04_S2_PLANIFICACIÓN_PDOT!J13 -> 16 | D20: =H12_MOTOR_ICPI_CANÓNICO!J13 -> 40.5 | E20: =H12_MOTOR_ICPI_CANÓNICO!K13 -> 🟡 Transición
A21: =H12_MOTOR_ICPI_CANÓNICO!A17 -> SC-I-N-03 | B21: =H04_S2_PLANIFICACIÓN_PDOT!B17 -> Participación ciudadana: 50→100 Unidades Territoriales participativas; 2→4 instancias efectivas (COPFP Art.115) | C21: =H04_S2_PLANIFICACIÓN_PDOT!J17 -> 16,17 | D21: =H12_MOTOR_ICPI_CANÓNICO!J17 -> 53.4375 | E21: =H12_MOTOR_ICPI_CANÓNICO!K17 -> 🟡 Transición
A22: =H12_MOTOR_ICPI_CANÓNICO!A23 -> PI-L-G-01 | B22: =H04_S2_PLANIFICACIÓN_PDOT!B23 -> Señalización vial 0→10,000 m²; 0→8 semáforos; revisiones técnicas 4,000→20,000; educación vial 40 instituciones | C22: =H04_S2_PLANIFICACIÓN_PDOT!J23 -> 11,3 | D22: =H12_MOTOR_ICPI_CANÓNICO!J23 -> 53.4375 | E22: =H12_MOTOR_ICPI_CANÓNICO!K23 -> 🟡 Transición
A23: =H12_MOTOR_ICPI_CANÓNICO!A25 -> EP-L-X-01 | B23: =H04_S2_PLANIFICACIÓN_PDOT!B25 -> Fortalecimiento productivo: beneficiarios artesanos, mipymes, emprendedores, huertos comunitarios y cadenas de valor | C23: =H04_S2_PLANIFICACIÓN_PDOT!J25 -> 1,8,10 | D23: =H12_MOTOR_ICPI_CANÓNICO!J25 -> 85 | E23: =H12_MOTOR_ICPI_CANÓNICO!K25 -> 🟢 Por Mandato

Sheet H20_ICODS
A1: 🏛️ TERRA SIAP-ICPI v2.0 | QUADRUM | B1: ⬅️ ÍNDICE GENERAL | C1: ="ICPI: "&TEXT(H12_MOTOR_ICPI_CANÓNICO!B28,"0,0")&"%" -> ICPI: 72,9% | D1: H20 — ICODS | E1: =TEXT(TODAY(),"DD/MM/YYYY") -> 05/04/2026
A2: H20 — ICODS — ÍNDICE DE CONGRUENCIA ODS
A3: Alineación de metas PDOT con Agenda 2030. Lee de H11_S9 y H12. Pasaporte internacional de TERRA para CAF, BID y BM.
A4: PND vigente: 'Ecuador No Se Detiene' 2025-2029 (Resolución CNP 0012-2025). 96 de 98 metas alineadas con Agenda 2030.
A6: ▌ ICODS POR CLÚSTER
A7: Clúster | B7: ODS | C7: N°_Metas | D7: ICPI_Cluster (%) | E7: Semáforo_AVEP
A8: Gobernanza | B8: ODS 16-17 | C8: =H11_S9_AGENDA_GLOBAL_ODS!C8 -> 7 | D8: =H11_S9_AGENDA_GLOBAL_ODS!D8 -> 75.735167 | E8: =H11_S9_AGENDA_GLOBAL_ODS!E8 -> 🟢 Gestión por Mandato
A9: Infraestructura | B9: ODS 6-9-11-13 | C9: =H11_S9_AGENDA_GLOBAL_ODS!C9 -> 10 | D9: =H11_S9_AGENDA_GLOBAL_ODS!D9 -> 71.274659 | E9: =H11_S9_AGENDA_GLOBAL_ODS!E9 -> 🟢 Gestión por Mandato
A10: Inclusión Social | B10: ODS 1-3-4-5-10 | C10: =H11_S9_AGENDA_GLOBAL_ODS!C10 -> 3 | D10: =H11_S9_AGENDA_GLOBAL_ODS!D10 -> 63.510333 | E10: =H11_S9_AGENDA_GLOBAL_ODS!E10 -> 🟡 Transición Crítica
A12: ▌ SUBÍNDICE GÉNERO (ODS 5)
A13: N°_Metas_ODS5 | B13: =H11_S9_AGENDA_GLOBAL_ODS!B15 -> 2
A14: ICPI_Género (%) | B14: {=IFERROR(SUMPRODUCT(ISNUMBER(SEARCH("5",H04_S2_PLANIFICACIÓN_PDOT!J6:J25))*H12_MOTOR_ICPI_CANÓNICO!H6:H25)/SUMPRODUCT(ISNUMBER(SEARCH("5",H04_S2_PLANIFICACIÓN_PDOT!J6:J25))*H12_MOTOR_ICPI_CANÓNICO!I6:I25)*100,0)} -> 75.577876
A15: Clasificación_Género | B15: =IF(B14>=90,"🔵 Excelencia",IF(B14>=70,"🟢 Por Mandato",IF(B14>=40,"🟡 Transición",IF(B14>=20,"🟠 Por Ocurrencia","🔴 Ruptura")))) -> 🟢 Por Mandato
A17: ▌ SUBÍNDICE GENERACIONAL (ODS 3, 4, 10)
A18: ICPI_Generacional (%) | B18: {=IFERROR(SUMPRODUCT((ISNUMBER(SEARCH("3",H04_S2_PLANIFICACIÓN_PDOT!J6:J25))+ISNUMBER(SEARCH("4",H04_S2_PLANIFICACIÓN_PDOT!J6:J25))+ISNUMBER(SEARCH("10",H04_S2_PLANIFICACIÓN_PDOT!J6:J25))>0)*H12_MOTOR_ICPI_CANÓNICO!H6:H25)/SUMPRODUCT((ISNUMBER(SEARCH("3",H04_S2_PLANIFICACIÓN_PDOT!J6:J25))+ISNUMBER(SEARCH("4",H04_S2_PLANIFICACIÓN_PDOT!J6:J25))+ISNUMBER(SEARCH("10",H04_S2_PLANIFICACIÓN_PDOT!J6:J25))>0)*H12_MOTOR_ICPI_CANÓNICO!I6:I25)*100,0)} -> 83.717668
A19: Clasificación_Generacional | B19: =IF(B18>=90,"🔵 Excelencia",IF(B18>=70,"🟢 Por Mandato",IF(B18>=40,"🟡 Transición",IF(B18>=20,"🟠 Por Ocurrencia","🔴 Ruptura")))) -> 🟢 Por Mandato
A21: ▌ SUBÍNDICE CLIMA (ODS 13)
A22: N°_Metas_ODS13 | B22: =H11_S9_AGENDA_GLOBAL_ODS!B16 -> 3
A23: ICPI_Clima (%) | B23: {=IFERROR(SUMPRODUCT(ISNUMBER(SEARCH("13",H04_S2_PLANIFICACIÓN_PDOT!J6:J25))*H12_MOTOR_ICPI_CANÓNICO!H6:H25)/SUMPRODUCT(ISNUMBER(SEARCH("13",H04_S2_PLANIFICACIÓN_PDOT!J6:J25))*H12_MOTOR_ICPI_CANÓNICO!I6:I25)*100,0)} -> 30.394136
A25: ▌ ARGUMENTOS BILATERALES AUTOMÁTICOS
A26: CAF (Gobernanza ODS 16-17): | B26: =H11_S9_AGENDA_GLOBAL_ODS!B26 -> ICPI Gobernanza: 76% — Certifica base institucional elegible para financiamiento CAF bajo marco Gobernanza Anticipatoria ODS 16-17.
A27: BID/BM (Inclusión Social): | B27: =H11_S9_AGENDA_GLOBAL_ODS!B27 -> ICPI Inclusión: 64% — Evidencia que inversión en grupos vulnerables requiere fortalecimiento de trazabilidad. Argumento BID Social.
A28: Género ODS 5: | B28: ="ICPI Género: "&TEXT(B14,"0.0")&"% — "&B15&". "&TEXT(B13,"0")&" metas con enfoque ODS 5 verificadas en 9 silos. Bono discriminación positiva 1.15 activo (H01!B37)." -> ICPI Género: 76% — 🟢 Por Mandato. 2 metas con enfoque ODS 5 verificadas en 9 silos. Bono discriminación positiva 1.15 activo (H01!B37).
A29: PND Ecuador: | B29: Alineado con 'Ecuador No Se Detiene 2025-2029' (Res. CNP 0012-2025). 96/98 metas nacionales vinculadas Agenda 2030.

Sheet H21_SAT-I
A1: 🏛️ TERRA SIAP-ICPI v2.0 | QUADRUM | B1: ⬅️ ÍNDICE GENERAL | C1: ="ICPI: "&TEXT(H12_MOTOR_ICPI_CANÓNICO!B28,"0,0")&"%" -> ICPI: 72,9% | D1: H21 — SAT-I | E1: =TEXT(TODAY(),"DD/MM/YYYY") -> 05/04/2026
A2: H21 — SAT-I — FRAGMENTACIÓN SELECTIVA
A3: SEÑAL DE ATENCIÓN TEMPRANA I: Auto-reporte muy alto sobre universo reducido de metas. Fundamentación: COPFP Art.54
A4: Condición: ICM_SIGAD >= Umbral_ICM (H01!B41) Y metas_reportadas/20 <= Umbral_Universo (H01!B42)
A6: ▌ PARÁMETROS DE DETECCIÓN (leídos de H01)
A7: SAT_I_Umbral_ICM | B7: =H01_PARÁMETROS!B41 -> 0.8 | C7: ICM reportado >= este valor activa la condición 1
A8: SAT_I_Umbral_Universo | B8: =H01_PARÁMETROS!B42 -> 0.1 | C8: Pct metas reportadas/total <= este valor activa condición 2
A9: ICM_Global_SIGAD (actual) | B9: =H08_S6_AUTOREPORTE_SIGAD!C27 -> 100 | C9: ICM promedio reportado al SNP
A10: Pct_Metas_Reportadas (actual) | B10: =H08_S6_AUTOREPORTE_SIGAD!C28/20 -> 1 | C10: Proporción de metas con reporte
A12: ▌ ESTADO SAT-I
A13: Estado: | B13: =IF(AND(H08_S6_AUTOREPORTE_SIGAD!C27>=H01_PARÁMETROS!B41,H08_S6_AUTOREPORTE_SIGAD!C28/20<=H01_PARÁMETROS!B42),"⚠️ SAT-I ACTIVA — Fragmentación Selectiva","✅ Sin señal SAT-I") -> ✅ Sin señal SAT-I
A15: ▌ EVIDENCIA AUTOMÁTICA
A16: ICM reportado: | B16: =H08_S6_AUTOREPORTE_SIGAD!C27 -> 100
A17: Metas reportadas: | B17: =H08_S6_AUTOREPORTE_SIGAD!C28 -> 20
A18: Total metas universo: | B18: =20 -> 20
A19: Presupuesto excluido estimado: | B19: =IFERROR((20-H08_S6_AUTOREPORTE_SIGAD!C28)/20*H01_PARÁMETROS!B28,0) -> 0
A21: ▌ DICTAMEN
A22: Dictamen: | B22: Alta calificación sobre universo reducido. Posible omisión selectiva de metas con bajo cumplimiento. Ref: COPFP Art.54
A24: Estado_SAT_I (alias para H28): | B24: =B13 -> ✅ Sin señal SAT-I

Sheet H22_SAT-II
A1: 🏛️ TERRA SIAP-ICPI v2.0 | QUADRUM | B1: ⬅️ ÍNDICE GENERAL | C1: ="ICPI: "&TEXT(H12_MOTOR_ICPI_CANÓNICO!B28,"0,0")&"%" -> ICPI: 72,9% | D1: H22 — SAT-II | E1: =TEXT(TODAY(),"DD/MM/YYYY") -> 05/04/2026
A2: H22 — SAT-II — SUSTITUCIÓN ESTRATÉGICA
A3: SEÑAL DE ATENCIÓN TEMPRANA II: Cambio de unidad de medida sin ordenanza formal de reforma al PDOT.
A4: Condición: Existe al menos 1 meta con alerta MOM-III en H08 col G (Unidad_Medida_Reportada ≠ Unidad_Medida_ORIGINAL PDOT)
A6: ▌ PARÁMETROS DE DETECCIÓN
A7: Metas con cambio de unidad detectado: | B7: =COUNTIF(H08_S6_AUTOREPORTE_SIGAD!G7:G26,"⚠️*") -> 0 | C7: ← Conteo de alertas MOM-III en H08 col G
A9: ▌ ESTADO SAT-II
A10: Estado: | B10: =IF(COUNTIF(H08_S6_AUTOREPORTE_SIGAD!G7:G26,"⚠️*")>0,"⚠️ SAT-II ACTIVA — Sustitución Estratégica","✅ Sin señal SAT-II") -> ✅ Sin señal SAT-II
A12: ▌ METAS CON CAMBIO DE UNIDAD DETECTADO
A13: ID_Meta | B13: Unidad_PDOT_Original | C13: Unidad_Reportada_SIGAD | D13: Alerta_MOM_III
A14: =H08_S6_AUTOREPORTE_SIGAD!A7 -> SC-I-N-01 | B14: =H04_S2_PLANIFICACIÓN_PDOT!O6 -> % cobertura agua potable | C14: =H08_S6_AUTOREPORTE_SIGAD!D7 -> % cobertura agua potable | D14: =H08_S6_AUTOREPORTE_SIGAD!G7 -> ✅ Unidad consistente con PDOT
A15: =H08_S6_AUTOREPORTE_SIGAD!A8 -> SC-L-N-02 | B15: =H04_S2_PLANIFICACIÓN_PDOT!O7 -> % nivel desempeño personal | C15: =H08_S6_AUTOREPORTE_SIGAD!D8 -> % nivel desempeño personal | D15: =H08_S6_AUTOREPORTE_SIGAD!G8 -> ✅ Unidad consistente con PDOT
A16: =H08_S6_AUTOREPORTE_SIGAD!A9 -> AH-I-X-01 | B16: =H04_S2_PLANIFICACIÓN_PDOT!O8 -> % autonomía financiera | C16: =H08_S6_AUTOREPORTE_SIGAD!D9 -> % autonomía financiera | D16: =H08_S6_AUTOREPORTE_SIGAD!G9 -> ✅ Unidad consistente con PDOT
A17: =H08_S6_AUTOREPORTE_SIGAD!A10 -> AH-I-X-02 | B17: =H04_S2_PLANIFICACIÓN_PDOT!O9 -> Km vías mantenidas CUP acumulado | C17: =H08_S6_AUTOREPORTE_SIGAD!D10 -> Km vías mantenidas CUP acumulado | D17: =H08_S6_AUTOREPORTE_SIGAD!G10 -> ✅ Unidad consistente con PDOT
A18: =H08_S6_AUTOREPORTE_SIGAD!A11 -> AH-I-X-03 | B18: =H04_S2_PLANIFICACIÓN_PDOT!O10 -> Personas atendidas salud municipal | C18: =H08_S6_AUTOREPORTE_SIGAD!D11 -> Personas atendidas salud municipal | D18: =H08_S6_AUTOREPORTE_SIGAD!G11 -> ✅ Unidad consistente con PDOT
A19: =H08_S6_AUTOREPORTE_SIGAD!A12 -> AH-I-N-01 | B19: =H04_S2_PLANIFICACIÓN_PDOT!O11 -> Toneladas de desechos gestionadas/año | C19: =H08_S6_AUTOREPORTE_SIGAD!D12 -> Toneladas de desechos gestionadas/año | D19: =H08_S6_AUTOREPORTE_SIGAD!G12 -> ✅ Unidad consistente con PDOT
A20: =H08_S6_AUTOREPORTE_SIGAD!A13 -> SC-L-G-01 | B20: =H04_S2_PLANIFICACIÓN_PDOT!O12 -> % cobertura alcantarillado sanitario | C20: =H08_S6_AUTOREPORTE_SIGAD!D13 -> % cobertura alcantarillado sanitario | D20: =H08_S6_AUTOREPORTE_SIGAD!G13 -> ✅ Unidad consistente con PDOT
A21: =H08_S6_AUTOREPORTE_SIGAD!A14 -> AH-I-X-04 | B21: =H04_S2_PLANIFICACIÓN_PDOT!O13 -> Parque automotor y tecnología renovados | C21: =H08_S6_AUTOREPORTE_SIGAD!D14 -> Parque automotor y tecnología renovados | D21: =H08_S6_AUTOREPORTE_SIGAD!G14 -> ✅ Unidad consistente con PDOT
A22: =H08_S6_AUTOREPORTE_SIGAD!A15 -> PI-I-G-01 | B22: =H04_S2_PLANIFICACIÓN_PDOT!O14 -> m² / hab índice equipamiento urbano CUP | C22: =H08_S6_AUTOREPORTE_SIGAD!D15 -> m² / hab índice equipamiento urbano CUP | D22: =H08_S6_AUTOREPORTE_SIGAD!G15 -> ✅ Unidad consistente con PDOT
A23: =H08_S6_AUTOREPORTE_SIGAD!A16 -> AH-C-X-01 | B23: =H04_S2_PLANIFICACIÓN_PDOT!O15 -> Atenciones en programas grupos prioritarios | C23: =H08_S6_AUTOREPORTE_SIGAD!D16 -> Atenciones en programas grupos prioritarios | D23: =H08_S6_AUTOREPORTE_SIGAD!G16 -> ✅ Unidad consistente con PDOT
A24: =H08_S6_AUTOREPORTE_SIGAD!A17 -> AH-C-X-02 | B24: =H04_S2_PLANIFICACIÓN_PDOT!O16 -> % levantamiento SIL catastro urbano-rural | C24: =H08_S6_AUTOREPORTE_SIGAD!D17 -> % levantamiento SIL catastro urbano-rural | D24: =H08_S6_AUTOREPORTE_SIGAD!G17 -> ✅ Unidad consistente con PDOT
A25: =H08_S6_AUTOREPORTE_SIGAD!A18 -> SC-I-N-03 | B25: =H04_S2_PLANIFICACIÓN_PDOT!O17 -> Unidades Territoriales participativas activas | C25: =H08_S6_AUTOREPORTE_SIGAD!D18 -> Unidades Territoriales participativas activas | D25: =H08_S6_AUTOREPORTE_SIGAD!G18 -> ✅ Unidad consistente con PDOT
... A33: =H08_S6_AUTOREPORTE_SIGAD!A26 -> EP-L-X-01 | B33: =H04_S2_PLANIFICACIÓN_PDOT!O25 -> Beneficiarios programas fortalecimiento productivo | C33: =H08_S6_AUTOREPORTE_SIGAD!D26 -> Beneficiarios programas fortalecimiento productivo | D33: =H08_S6_AUTOREPORTE_SIGAD!G26 -> ✅ Unidad consistente con PDOT
A35: ▌ DICTAMEN
A36: Dictamen: | B36: Cambio de unidad de medida sin reforma formal del PDOT constituye mutación del objeto de medición (MOM-II). Requiere ordenanza municipal de reforma o reverting a unidad original. Ref: Campbell 1976 + Hood 2006.
A38: Estado_SAT_II (alias para H28): | B38: =B10 -> ✅ Sin señal SAT-II

Sheet H23_SAT-III
A1: 🏛️ TERRA SIAP-ICPI v2.0 | QUADRUM | B1: ⬅️ ÍNDICE GENERAL | C1: ="ICPI: "&TEXT(H12_MOTOR_ICPI_CANÓNICO!B28,"0,0")&"%" -> ICPI: 72,9% | D1: H23 — SAT-III | E1: =TEXT(TODAY(),"DD/MM/YYYY") -> 05/04/2026
A2: H23 — SAT-III — INFLACIÓN DE UNIDADES
A3: SEÑAL DE ATENCIÓN TEMPRANA III: Cumplimiento reportado >500% con devengado <10% del codificado y cambio de unidad de medida.
A4: Condición TRIPLE: ICM_SIGAD > Umbral_Cumpl (500%) Y T_i_promedio < Umbral_Deveng (10%) Y cambio de unidad detectado (SAT-II activa)
A6: ▌ PARÁMETROS DE DETECCIÓN (leídos de H01)
A7: SAT_III_Umbral_Cumpl (500%) | B7: =H01_PARÁMETROS!B44 -> 5 | C7: ICM_SIGAD debe superar este múltiplo
A8: SAT_III_Umbral_Deveng (10%) | B8: =H01_PARÁMETROS!B45 -> 0.1 | C8: T_i promedio debe estar por debajo de este valor
A9: ICM_Global_SIGAD (actual) | B9: =H08_S6_AUTOREPORTE_SIGAD!C27 -> 100 | C9: ICM reportado — verificar contra umbral
A10: T_i_Promedio_Global (actual) | B10: =H07_S5_FINANCIERO_eSIGEF!B28 -> 0.785 | C10: Tasa devengado promedio
A11: Metas con cambio de unidad: | B11: =COUNTIF(H08_S6_AUTOREPORTE_SIGAD!G7:G26,"⚠️*") -> 0 | C11: Conteo alertas MOM
A13: ▌ ESTADO SAT-III
A14: Estado: | B14: =IF(AND(H08_S6_AUTOREPORTE_SIGAD!C27>H01_PARÁMETROS!B44,H07_S5_FINANCIERO_eSIGEF!B28<H01_PARÁMETROS!B45,COUNTIF(H08_S6_AUTOREPORTE_SIGAD!G7:G26,"⚠️*")>0),"⚠️ SAT-III ACTIVA — Inflación de Unidades","✅ Sin señal SAT-III") -> ✅ Sin señal SAT-III
A16: ▌ DIAGNÓSTICO DE CONDICIONES
A17: Condición 1 — ICM > 500%: | B17: =IF(H08_S6_AUTOREPORTE_SIGAD!C27>H01_PARÁMETROS!B44,"🔴 ACTIVA","✅ No activada") -> 🔴 ACTIVA
A18: Condición 2 — T_i < 10%: | B18: =IF(H07_S5_FINANCIERO_eSIGEF!B28<H01_PARÁMETROS!B45,"🔴 ACTIVA","✅ No activada") -> ✅ No activada
A19: Condición 3 — Cambio unidad: | B19: =IF(COUNTIF(H08_S6_AUTOREPORTE_SIGAD!G7:G26,"⚠️*")>0,"🔴 ACTIVA","✅ No activada") -> ✅ No activada
A21: ▌ DICTAMEN
A22: Dictamen: | B22: Cumplimiento reportado masivo con ejecución financiera mínima y cambio de unidad. Patrón típico de gaming del sistema de autoreporte (MOM tipo III). Requiere auditoría de la Contraloría General. Ref: Campbell 1976 + Hood 2006 + COPFP Art.117.
A24: Estado_SAT_III (alias para H28): | B24: =B14 -> ✅ Sin señal SAT-III

Sheet H24_SAT-IV
A1: 🏛️ TERRA SIAP-ICPI v2.0 | QUADRUM | B1: ⬅️ ÍNDICE GENERAL | C1: ="ICPI: "&TEXT(H12_MOTOR_ICPI_CANÓNICO!B28,"0,0")&"%" -> ICPI: 72,9% | D1: H24 — SAT-IV | E1: =TEXT(TODAY(),"DD/MM/YYYY") -> 05/04/2026
A2: H24 — SAT-IV — TENSIÓN NORMATIVA PROGRAMÁTICA
A3: SEÑAL DE ATENCIÓN TEMPRANA IV: Meta social ejecutada con grupos presupuestarios 71/73/78 en período de restricción fiscal COOTAD 2026.
A4: ★ SAT-IV ES MALEABLE ★ Si la Corte Constitucional deroga la reforma COOTAD, actualizar H01_PARÁMETROS!B31 con la nueva fecha. La señal se desactiva automáticamente.
A6: ▌ PARÁMETROS DE CONTROL NORMATIVO (leídos de H01)
A7: SAT_IV_Activa (H01!B34): | B7: =H01_PARÁMETROS!B34 -> NO | C7: SÍ si Fecha_Corte >= Fecha_Vigencia_Regla_Fiscal
A8: Fecha_Vigencia_Regla_Fiscal: | B8: =H01_PARÁMETROS!B31 -> 2026-06-01T05:00:00.000Z | C8: Actualizar si reforma es derogada
A9: Fecha_Corte: | B9: =H01_PARÁMETROS!B13 -> 2024-12-31T05:00:00.000Z | C9: Fecha de evaluación actual
A10: Metas afectadas (grupos 71/73/78): | B10: =COUNTIF(H07_S5_FINANCIERO_eSIGEF!I7:I26,"⚠️*") -> 0 | C10: Flag_SAT_IV en H07 col I
A12: ▌ ESTADO SAT-IV
A13: Estado: | B13: =IF(H01_PARÁMETROS!B34="SÍ",IF(COUNTIF(H07_S5_FINANCIERO_eSIGEF!I7:I26,"⚠️*")>0,"⚠️ SAT-IV ACTIVA — Tensión Normativa Programática [Reforma COOTAD 2026]","✅ Sin metas afectadas [reforma vigente]"),"✅ SAT-IV no aplica — Reforma no vigente o derogada por Corte Constitucional") -> ✅ SAT-IV no aplica — Reforma no vigente o derogada por Corte Constitucional
A15: ▌ INSTRUCCIÓN DE MALEABILIDAD
A16: Para desactivar SAT-IV: | B16: 1. Ir a H01_PARÁMETROS!B31. Actualizar Fecha_Vigencia_Regla_Fiscal a una fecha posterior al año fiscal actual.
A17: Resultado automático: | B17: H01!B34 calculará 'NO'. Esta celda B12 mostrará '✅ SAT-IV no aplica'. Ningún otro cambio requerido en el sistema.
A19: ▌ METAS CON GRUPOS PRESUPUESTARIOS 71 / 73 / 78
A20: ID_Meta | B20: Grupo_Presup | C20: Devengado | D20: T_i | E20: Flag_SAT_IV
A21: =H07_S5_FINANCIERO_eSIGEF!A7 -> SC-I-N-01 | B21: =H07_S5_FINANCIERO_eSIGEF!D7 -> 73 | C21: =H07_S5_FINANCIERO_eSIGEF!F7 -> 42750 | D21: =H07_S5_FINANCIERO_eSIGEF!G7 -> 0.95 | E21: =H07_S5_FINANCIERO_eSIGEF!I7 -> ✅ OK
A22: =H07_S5_FINANCIERO_eSIGEF!A8 -> SC-L-N-02 | B22: =H07_S5_FINANCIERO_eSIGEF!D8 -> 53 | C22: =H07_S5_FINANCIERO_eSIGEF!F8 -> 7565 | D22: =H07_S5_FINANCIERO_eSIGEF!G8 -> 0.85 | E22: =H07_S5_FINANCIERO_eSIGEF!I8 -> ✅ OK
A23: =H07_S5_FINANCIERO_eSIGEF!A9 -> AH-I-X-01 | B23: =H07_S5_FINANCIERO_eSIGEF!D9 -> 75 | C23: =H07_S5_FINANCIERO_eSIGEF!F9 -> 1588720.3 | D23: =H07_S5_FINANCIERO_eSIGEF!G9 -> 0.72 | E23: =H07_S5_FINANCIERO_eSIGEF!I9 -> ✅ OK
A24: =H07_S5_FINANCIERO_eSIGEF!A10 -> AH-I-X-02 | B24: =H07_S5_FINANCIERO_eSIGEF!D10 -> 0 | C24: =H07_S5_FINANCIERO_eSIGEF!F10 -> 0 | D24: =H07_S5_FINANCIERO_eSIGEF!G10 -> 0 | E24: =H07_S5_FINANCIERO_eSIGEF!I10 -> ✅ OK
A25: =H07_S5_FINANCIERO_eSIGEF!A11 -> AH-I-X-03 | B25: =H07_S5_FINANCIERO_eSIGEF!D11 -> 75 | C25: =H07_S5_FINANCIERO_eSIGEF!F11 -> 486604.8 | D25: =H07_S5_FINANCIERO_eSIGEF!G11 -> 0.72 | E25: =H07_S5_FINANCIERO_eSIGEF!I11 -> ✅ OK
A26: =H07_S5_FINANCIERO_eSIGEF!A12 -> AH-I-N-01 | B26: =H07_S5_FINANCIERO_eSIGEF!D12 -> 78 | C26: =H07_S5_FINANCIERO_eSIGEF!F12 -> 40320 | D26: =H07_S5_FINANCIERO_eSIGEF!G12 -> 0.8 | E26: =H07_S5_FINANCIERO_eSIGEF!I12 -> ✅ OK
A27: =H07_S5_FINANCIERO_eSIGEF!A13 -> SC-L-G-01 | B27: =H07_S5_FINANCIERO_eSIGEF!D13 -> 73 | C27: =H07_S5_FINANCIERO_eSIGEF!F13 -> 254380.35 | D27: =H07_S5_FINANCIERO_eSIGEF!G13 -> 0.85 | E27: =H07_S5_FINANCIERO_eSIGEF!I13 -> ✅ OK
A28: =H07_S5_FINANCIERO_eSIGEF!A14 -> AH-I-X-04 | B28: =H07_S5_FINANCIERO_eSIGEF!D14 -> 75 | C28: =H07_S5_FINANCIERO_eSIGEF!F14 -> 304096.32 | D28: =H07_S5_FINANCIERO_eSIGEF!G14 -> 0.72 | E28: =H07_S5_FINANCIERO_eSIGEF!I14 -> ✅ OK
A29: =H07_S5_FINANCIERO_eSIGEF!A15 -> PI-I-G-01 | B29: =H07_S5_FINANCIERO_eSIGEF!D15 -> 84 | C29: =H07_S5_FINANCIERO_eSIGEF!F15 -> 1855733.6 | D29: =H07_S5_FINANCIERO_eSIGEF!G15 -> 0.85 | E29: =H07_S5_FINANCIERO_eSIGEF!I15 -> ✅ OK
A30: =H07_S5_FINANCIERO_eSIGEF!A16 -> AH-C-X-01 | B30: =H07_S5_FINANCIERO_eSIGEF!D16 -> 75 | C30: =H07_S5_FINANCIERO_eSIGEF!F16 -> 401835.6 | D30: =H07_S5_FINANCIERO_eSIGEF!G16 -> 0.72 | E30: =H07_S5_FINANCIERO_eSIGEF!I16 -> ✅ OK
A31: =H07_S5_FINANCIERO_eSIGEF!A17 -> AH-C-X-02 | B31: =H07_S5_FINANCIERO_eSIGEF!D17 -> 75 | C31: =H07_S5_FINANCIERO_eSIGEF!F17 -> 450618.48 | D31: =H07_S5_FINANCIERO_eSIGEF!G17 -> 0.72 | E31: =H07_S5_FINANCIERO_eSIGEF!I17 -> ✅ OK
A32: =H07_S5_FINANCIERO_eSIGEF!A18 -> SC-I-N-03 | B32: =H07_S5_FINANCIERO_eSIGEF!D18 -> 71 | C32: =H07_S5_FINANCIERO_eSIGEF!F18 -> 35150 | D32: =H07_S5_FINANCIERO_eSIGEF!G18 -> 0.95 | E32: =H07_S5_FINANCIERO_eSIGEF!I18 -> ✅ OK
... A40: =H07_S5_FINANCIERO_eSIGEF!A26 -> EP-L-X-01 | B40: =H07_S5_FINANCIERO_eSIGEF!D26 -> 73 | C40: =H07_S5_FINANCIERO_eSIGEF!F26 -> 138890 | D40: =H07_S5_FINANCIERO_eSIGEF!G26 -> 0.85 | E40: =H07_S5_FINANCIERO_eSIGEF!I26 -> ✅ OK
A42: ▌ DICTAMEN (si SAT-IV activa)
A43: Dictamen: | B43: Metas con grupos presupuestarios 71/73/78 ejecutadas en período de restricción fiscal. El GAD priorizó compromisos PDOT sobre regla fiscal. Documentar justificación técnica mediante ordenanza municipal para blindaje jurídico institucional.
A45: Estado_SAT_IV (alias para H28): | B45: =B13 -> ✅ SAT-IV no aplica — Reforma no vigente o derogada por Corte Constitucional

Sheet H25_MMP_MENSUAL
A1: 🏛️ TERRA SIAP-ICPI v2.0 | QUADRUM | B1: ⬅️ ÍNDICE GENERAL | C1: ="ICPI: "&TEXT(H12_MOTOR_ICPI_CANÓNICO!B28,"0,0")&"%" -> ICPI: 72,9% | D1: H25 — MMP MENSUAL | E1: =TEXT(TODAY(),"DD/MM/YYYY") -> 05/04/2026
A2: H25 — MOTOR DE MONITOREO PROGRAMÁTICO (MMP) — NIVEL MENSUAL
A3: Seguimiento mensual operativo · cadena de responsabilidad documentada | Nivel 1 MMP | NOTA: Informe mensual firmado digitalmente constituye evidencia de gestión ante Contraloría
A5: ID_Meta | B5: Descripción_Meta | C5: Dirección_Responsable | D5: Meta_Anual | E5: Unidad_Medida | F5: Presupuesto_Codificado | G5: Pi_Meta | H5: ENE_Plan% | I5: ENE_Ejec% | J5: ENE_Dev_$ | K5: ENE_Sem | L5: ENE_Hash | M5: FEB_Plan% | N5: FEB_Ejec% | O5: FEB_Dev_$ | P5: FEB_Sem | Q5: FEB_Hash | R5: MAR_Plan% | S5: MAR_Ejec% | T5: MAR_Dev_$ | U5: MAR_Sem | V5: MAR_Hash | W5: ABR_Plan% | X5: ABR_Ejec% | Y5: ABR_Dev_$ | Z5: ABR_Sem | AA5: ABR_Hash | AB5: MAY_Plan% | AC5: MAY_Ejec% | AD5: MAY_Dev_$ | AE5: MAY_Sem | AF5: MAY_Hash | AG5: JUN_Plan% | AH5: JUN_Ejec% | AI5: JUN_Dev_$ | AJ5: JUN_Sem | AK5: JUN_Hash | AL5: JUL_Plan% | AM5: JUL_Ejec% | AN5: JUL_Dev_$ | AO5: JUL_Sem | AP5: JUL_Hash | AQ5: AGO_Plan% | AR5: AGO_Ejec% | AS5: AGO_Dev_$ | AT5: AGO_Sem | AU5: AGO_Hash | AV5: SEP_Plan% | AW5: SEP_Ejec% | AX5: SEP_Dev_$ | AY5: SEP_Sem | AZ5: SEP_Hash | BA5: OCT_Plan% | BB5: OCT_Ejec% | BC5: OCT_Dev_$ | BD5: OCT_Sem | BE5: OCT_Hash | BF5: NOV_Plan% | BG5: NOV_Ejec% | BH5: NOV_Dev_$ | BI5: NOV_Sem | BJ5: NOV_Hash | BK5: DIC_Plan% | BL5: DIC_Ejec% | BM5: DIC_Dev_$ | BN5: DIC_Sem | BO5: DIC_Hash | BP5: Proyección_Cierre_% | BQ5: AVEP_Proyectado | BR5: SAT_Activa | BS5: Brecha_Financiamiento | BT5: Inf_Director_Estado | BU5: Fecha_Firma_Digital | BV5: Hash_Informe_Director
A6: =H04_S2_PLANIFICACIÓN_PDOT!A6 -> SC-I-N-01 | B6: =H04_S2_PLANIFICACIÓN_PDOT!B6 -> Agua potable: cobertura 39.25%→42.38%; calidad 100% INEN 1108; infraestructura BUENA 22.74%→41.64% | C6: =H04_S2_PLANIFICACIÓN_PDOT!R6 -> Patronato Municipal | D6: =H04_S2_PLANIFICACIÓN_PDOT!N6 -> 42.38 | E6: =H04_S2_PLANIFICACIÓN_PDOT!O6 -> % cobertura agua potable | F6: =H04_S2_PLANIFICACIÓN_PDOT!G6 -> 11726219 | G6: =H04_S2_PLANIFICACIÓN_PDOT!H6 -> 0.28912002 | H6: 5 | I6: 0 | J6: 0 | K6: =IF(H6=0,"⏸️",IF(I6/H6>=0.9,"🟢",IF(I6/H6>=0.7,"🟡","🔴"))) -> 🔴 | L6: [SHA-256 pendiente] | M6: 10 | N6: 0 | O6: 0 | P6: =IF(M6=0,"⏸️",IF(N6/M6>=0.9,"🟢",IF(N6/M6>=0.7,"🟡","🔴"))) -> 🔴 | Q6: [SHA-256 pendiente] | R6: 15 | S6: 0 | T6: 0 | U6: =IF(R6=0,"⏸️",IF(S6/R6>=0.9,"🟢",IF(S6/R6>=0.7,"🟡","🔴"))) -> 🔴 | V6: [SHA-256 pendiente] | W6: 25 | X6: 0 | Y6: 0 | Z6: =IF(W6=0,"⏸️",IF(X6/W6>=0.9,"🟢",IF(X6/W6>=0.7,"🟡","🔴"))) -> 🔴 | AA6: [SHA-256 pendiente] | AB6: 35 | AC6: 0 | AD6: 0 | AE6: =IF(AB6=0,"⏸️",IF(AC6/AB6>=0.9,"🟢",IF(AC6/AB6>=0.7,"🟡","🔴"))) -> 🔴 | AF6: [SHA-256 pendiente] | AG6: 45 | AH6: 0 | AI6: 0 | AJ6: =IF(AG6=0,"⏸️",IF(AH6/AG6>=0.9,"🟢",IF(AH6/AG6>=0.7,"🟡","🔴"))) -> 🔴 | AK6: [SHA-256 pendiente] | AL6: 55 | AM6: 0 | AN6: 0 | AO6: =IF(AL6=0,"⏸️",IF(AM6/AL6>=0.9,"🟢",IF(AM6/AL6>=0.7,"🟡","🔴"))) -> 🔴 | AP6: [SHA-256 pendiente] | AQ6: 65 | AR6: 0 | AS6: 0 | AT6: =IF(AQ6=0,"⏸️",IF(AR6/AQ6>=0.9,"🟢",IF(AR6/AQ6>=0.7,"🟡","🔴"))) -> 🔴 | AU6: [SHA-256 pendiente] | AV6: 75 | AW6: 0 | AX6: 0 | AY6: =IF(AV6=0,"⏸️",IF(AW6/AV6>=0.9,"🟢",IF(AW6/AV6>=0.7,"🟡","🔴"))) -> 🔴 | AZ6: [SHA-256 pendiente] | BA6: 85 | BB6: 0 | BC6: 0 | BD6: =IF(BA6=0,"⏸️",IF(BB6/BA6>=0.9,"🟢",IF(BB6/BA6>=0.7,"🟡","🔴"))) -> 🔴 | BE6: [SHA-256 pendiente] | BF6: 92 | BG6: 0 | BH6: 0 | BI6: =IF(BF6=0,"⏸️",IF(BG6/BF6>=0.9,"🟢",IF(BG6/BF6>=0.7,"🟡","🔴"))) -> 🔴 | BJ6: [SHA-256 pendiente] | BK6: 100 | BL6: 0 | BM6: 0 | BN6: =IF(BK6=0,"⏸️",IF(BL6/BK6>=0.9,"🟢",IF(BL6/BK6>=0.7,"🟡","🔴"))) -> 🔴 | BO6: [SHA-256 pendiente] | BP6: =IFERROR(AVERAGE(I6,N6,S6,X6,AC6,AH6,AM6,AR6,AW6,BB6,BG6,BL6),"N/D") -> 0 | BQ6: =IF(ISNUMBER(BP6),IF(BP6>=90,"🔵 Excelencia en Gobernanza",IF(BP6>=70,"🟢 Gestión por Mandato",IF(BP6>=40,"🟡 Transición Crítica",IF(BP6>=20,"🟠 Gestión por Ocurrencia","🔴 Ruptura Sistémica")))),"Sin datos") -> 🔴 Ruptura Sistémica | BR6: =IF(BQ6="🔴 Ruptura Sistémica","⚠️ Revisar — riesgo incumplimiento","✅ En seguimiento") -> ⚠️ Revisar — riesgo incumplimiento | BS6: =IF(IFERROR(SUM(J6,O6,T6,Y6,AD6,AI6,AN6,AS6,AX6,BC6,BH6,BM6),0)/F6<H01_PARÁMETROS!$B$46,"🚨 ELEGIBLE COOPERACIÓN EXTERNA","✅ Financiamiento suficiente") -> 🚨 ELEGIBLE COOPERACIÓN EXTERNA | BT6: Pendiente | BV6: [SHA-256 director pendiente]
A7: =H04_S2_PLANIFICACIÓN_PDOT!A7 -> SC-L-N-02 | B7: =H04_S2_PLANIFICACIÓN_PDOT!B7 -> Gestión del talento humano municipal: desempeño 80%→90%; plan capacitación 90% anual | C7: =H04_S2_PLANIFICACIÓN_PDOT!R7 -> Dirección TIC | D7: =H04_S2_PLANIFICACIÓN_PDOT!N7 -> 90 | E7: =H04_S2_PLANIFICACIÓN_PDOT!O7 -> % nivel desempeño personal | F7: =H04_S2_PLANIFICACIÓN_PDOT!G7 -> 13194220 | G7: =H04_S2_PLANIFICACIÓN_PDOT!H7 -> 0.32531485 | H7: 5 | I7: 0 | J7: 0 | K7: =IF(H7=0,"⏸️",IF(I7/H7>=0.9,"🟢",IF(I7/H7>=0.7,"🟡","🔴"))) -> 🔴 | L7: [SHA-256 pendiente] | M7: 10 | N7: 0 | O7: 0 | P7: =IF(M7=0,"⏸️",IF(N7/M7>=0.9,"🟢",IF(N7/M7>=0.7,"🟡","🔴"))) -> 🔴 | Q7: [SHA-256 pendiente] | R7: 15 | S7: 0 | T7: 0 | U7: =IF(R7=0,"⏸️",IF(S7/R7>=0.9,"🟢",IF(S7/R7>=0.7,"🟡","🔴"))) -> 🔴 | V7: [SHA-256 pendiente] | W7: 25 | X7: 0 | Y7: 0 | Z7: =IF(W7=0,"⏸️",IF(X7/W7>=0.9,"🟢",IF(X7/W7>=0.7,"🟡","🔴"))) -> 🔴 | AA7: [SHA-256 pendiente] | AB7: 35 | AC7: 0 | AD7: 0 | AE7: =IF(AB7=0,"⏸️",IF(AC7/AB7>=0.9,"🟢",IF(AC7/AB7>=0.7,"🟡","🔴"))) -> 🔴 | AF7: [SHA-256 pendiente] | AG7: 45 | AH7: 0 | AI7: 0 | AJ7: =IF(AG7=0,"⏸️",IF(AH7/AG7>=0.9,"🟢",IF(AH7/AG7>=0.7,"🟡","🔴"))) -> 🔴 | AK7: [SHA-256 pendiente] | AL7: 55 | AM7: 0 | AN7: 0 | AO7: =IF(AL7=0,"⏸️",IF(AM7/AL7>=0.9,"🟢",IF(AM7/AL7>=0.7,"🟡","🔴"))) -> 🔴 | AP7: [SHA-256 pendiente] | AQ7: 65 | AR7: 0 | AS7: 0 | AT7: =IF(AQ7=0,"⏸️",IF(AR7/AQ7>=0.9,"🟢",IF(AR7/AQ7>=0.7,"🟡","🔴"))) -> 🔴 | AU7: [SHA-256 pendiente] | AV7: 75 | AW7: 0 | AX7: 0 | AY7: =IF(AV7=0,"⏸️",IF(AW7/AV7>=0.9,"🟢",IF(AW7/AV7>=0.7,"🟡","🔴"))) -> 🔴 | AZ7: [SHA-256 pendiente] | BA7: 85 | BB7: 0 | BC7: 0 | BD7: =IF(BA7=0,"⏸️",IF(BB7/BA7>=0.9,"🟢",IF(BB7/BA7>=0.7,"🟡","🔴"))) -> 🔴 | BE7: [SHA-256 pendiente] | BF7: 92 | BG7: 0 | BH7: 0 | BI7: =IF(BF7=0,"⏸️",IF(BG7/BF7>=0.9,"🟢",IF(BG7/BF7>=0.7,"🟡","🔴"))) -> 🔴 | BJ7: [SHA-256 pendiente] | BK7: 100 | BL7: 0 | BM7: 0 | BN7: =IF(BK7=0,"⏸️",IF(BL7/BK7>=0.9,"🟢",IF(BL7/BK7>=0.7,"🟡","🔴"))) -> 🔴 | BO7: [SHA-256 pendiente] | BP7: =IFERROR(AVERAGE(I7,N7,S7,X7,AC7,AH7,AM7,AR7,AW7,BB7,BG7,BL7),"N/D") -> 0 | BQ7: =IF(ISNUMBER(BP7),IF(BP7>=90,"🔵 Excelencia en Gobernanza",IF(BP7>=70,"🟢 Gestión por Mandato",IF(BP7>=40,"🟡 Transición Crítica",IF(BP7>=20,"🟠 Gestión por Ocurrencia","🔴 Ruptura Sistémica")))),"Sin datos") -> 🔴 Ruptura Sistémica | BR7: =IF(BQ7="🔴 Ruptura Sistémica","⚠️ Revisar — riesgo incumplimiento","✅ En seguimiento") -> ⚠️ Revisar — riesgo incumplimiento | BS7: =IF(IFERROR(SUM(J7,O7,T7,Y7,AD7,AI7,AN7,AS7,AX7,BC7,BH7,BM7),0)/F7<H01_PARÁMETROS!$B$46,"🚨 ELEGIBLE COOPERACIÓN EXTERNA","✅ Financiamiento suficiente") -> 🚨 ELEGIBLE COOPERACIÓN EXTERNA | BT7: Pendiente | BV7: [SHA-256 director pendiente]
A8: =H04_S2_PLANIFICACIÓN_PDOT!A8 -> AH-I-X-01 | B8: =H04_S2_PLANIFICACIÓN_PDOT!B8 -> Sostenibilidad financiera: autonomía 43.35%→45.30%; gestión cobros y coactivas | C8: =H04_S2_PLANIFICACIÓN_PDOT!R8 -> Dirección de Obras Públicas | D8: =H04_S2_PLANIFICACIÓN_PDOT!N8 -> 45.3 | E8: =H04_S2_PLANIFICACIÓN_PDOT!O8 -> % autonomía financiera | F8: =H04_S2_PLANIFICACIÓN_PDOT!G8 -> 5051427 | G8: =H04_S2_PLANIFICACIÓN_PDOT!H8 -> 0.12454728 | H8: 5 | I8: 0 | J8: 0 | K8: =IF(H8=0,"⏸️",IF(I8/H8>=0.9,"🟢",IF(I8/H8>=0.7,"🟡","🔴"))) -> 🔴 | L8: [SHA-256 pendiente] | M8: 10 | N8: 0 | O8: 0 | P8: =IF(M8=0,"⏸️",IF(N8/M8>=0.9,"🟢",IF(N8/M8>=0.7,"🟡","🔴"))) -> 🔴 | Q8: [SHA-256 pendiente] | R8: 15 | S8: 0 | T8: 0 | U8: =IF(R8=0,"⏸️",IF(S8/R8>=0.9,"🟢",IF(S8/R8>=0.7,"🟡","🔴"))) -> 🔴 | V8: [SHA-256 pendiente] | W8: 25 | X8: 0 | Y8: 0 | Z8: =IF(W8=0,"⏸️",IF(X8/W8>=0.9,"🟢",IF(X8/W8>=0.7,"🟡","🔴"))) -> 🔴 | AA8: [SHA-256 pendiente] | AB8: 35 | AC8: 0 | AD8: 0 | AE8: =IF(AB8=0,"⏸️",IF(AC8/AB8>=0.9,"🟢",IF(AC8/AB8>=0.7,"🟡","🔴"))) -> 🔴 | AF8: [SHA-256 pendiente] | AG8: 45 | AH8: 0 | AI8: 0 | AJ8: =IF(AG8=0,"⏸️",IF(AH8/AG8>=0.9,"🟢",IF(AH8/AG8>=0.7,"🟡","🔴"))) -> 🔴 | AK8: [SHA-256 pendiente] | AL8: 55 | AM8: 0 | AN8: 0 | AO8: =IF(AL8=0,"⏸️",IF(AM8/AL8>=0.9,"🟢",IF(AM8/AL8>=0.7,"🟡","🔴"))) -> 🔴 | AP8: [SHA-256 pendiente] | AQ8: 65 | AR8: 0 | AS8: 0 | AT8: =IF(AQ8=0,"⏸️",IF(AR8/AQ8>=0.9,"🟢",IF(AR8/AQ8>=0.7,"🟡","🔴"))) -> 🔴 | AU8: [SHA-256 pendiente] | AV8: 75 | AW8: 0 | AX8: 0 | AY8: =IF(AV8=0,"⏸️",IF(AW8/AV8>=0.9,"🟢",IF(AW8/AV8>=0.7,"🟡","🔴"))) -> 🔴 | AZ8: [SHA-256 pendiente] | BA8: 85 | BB8: 0 | BC8: 0 | BD8: =IF(BA8=0,"⏸️",IF(BB8/BA8>=0.9,"🟢",IF(BB8/BA8>=0.7,"🟡","🔴"))) -> 🔴 | BE8: [SHA-256 pendiente] | BF8: 92 | BG8: 0 | BH8: 0 | BI8: =IF(BF8=0,"⏸️",IF(BG8/BF8>=0.9,"🟢",IF(BG8/BF8>=0.7,"🟡","🔴"))) -> 🔴 | BJ8: [SHA-256 pendiente] | BK8: 100 | BL8: 0 | BM8: 0 | BN8: =IF(BK8=0,"⏸️",IF(BL8/BK8>=0.9,"🟢",IF(BL8/BK8>=0.7,"🟡","🔴"))) -> 🔴 | BO8: [SHA-256 pendiente] | BP8: =IFERROR(AVERAGE(I8,N8,S8,X8,AC8,AH8,AM8,AR8,AW8,BB8,BG8,BL8),"N/D") -> 0 | BQ8: =IF(ISNUMBER(BP8),IF(BP8>=90,"🔵 Excelencia en Gobernanza",IF(BP8>=70,"🟢 Gestión por Mandato",IF(BP8>=40,"🟡 Transición Crítica",IF(BP8>=20,"🟠 Gestión por Ocurrencia","🔴 Ruptura Sistémica")))),"Sin datos") -> 🔴 Ruptura Sistémica | BR8: =IF(BQ8="🔴 Ruptura Sistémica","⚠️ Revisar — riesgo incumplimiento","✅ En seguimiento") -> ⚠️ Revisar — riesgo incumplimiento | BS8: =IF(IFERROR(SUM(J8,O8,T8,Y8,AD8,AI8,AN8,AS8,AX8,BC8,BH8,BM8),0)/F8<H01_PARÁMETROS!$B$46,"🚨 ELEGIBLE COOPERACIÓN EXTERNA","✅ Financiamiento suficiente") -> 🚨 ELEGIBLE COOPERACIÓN EXTERNA | BT8: Pendiente | BV8: [SHA-256 director pendiente]
A9: =H04_S2_PLANIFICACIÓN_PDOT!A9 -> AH-I-X-02 | B9: =H04_S2_PLANIFICACIÓN_PDOT!B9 -> Vialidad cantonal: mantenimiento 43.8 km vías CUP + 57.22 km rurales; 23.77 km tratamiento medio | C9: =H04_S2_PLANIFICACIÓN_PDOT!R9 -> Dirección de Obras Públicas | D9: =H04_S2_PLANIFICACIÓN_PDOT!N9 -> 130.21 | E9: =H04_S2_PLANIFICACIÓN_PDOT!O9 -> Km vías mantenidas CUP acumulado | F9: =H04_S2_PLANIFICACIÓN_PDOT!G9 -> 2729440 | G9: =H04_S2_PLANIFICACIÓN_PDOT!H9 -> 0.067296693 | H9: 5 | I9: 0 | J9: 0 | K9: =IF(H9=0,"⏸️",IF(I9/H9>=0.9,"🟢",IF(I9/H9>=0.7,"🟡","🔴"))) -> 🔴 | L9: [SHA-256 pendiente] | M9: 10 | N9: 0 | O9: 0 | P9: =IF(M9=0,"⏸️",IF(N9/M9>=0.9,"🟢",IF(N9/M9>=0.7,"🟡","🔴"))) -> 🔴 | Q9: [SHA-256 pendiente] | R9: 15 | S9: 0 | T9: 0 | U9: =IF(R9=0,"⏸️",IF(S9/R9>=0.9,"🟢",IF(S9/R9>=0.7,"🟡","🔴"))) -> 🔴 | V9: [SHA-256 pendiente] | W9: 25 | X9: 0 | Y9: 0 | Z9: =IF(W9=0,"⏸️",IF(X9/W9>=0.9,"🟢",IF(X9/W9>=0.7,"🟡","🔴"))) -> 🔴 | AA9: [SHA-256 pendiente] | AB9: 35 | AC9: 0 | AD9: 0 | AE9: =IF(AB9=0,"⏸️",IF(AC9/AB9>=0.9,"🟢",IF(AC9/AB9>=0.7,"🟡","🔴"))) -> 🔴 | AF9: [SHA-256 pendiente] | AG9: 45 | AH9: 0 | AI9: 0 | AJ9: =IF(AG9=0,"⏸️",IF(AH9/AG9>=0.9,"🟢",IF(AH9/AG9>=0.7,"🟡","🔴"))) -> 🔴 | AK9: [SHA-256 pendiente] | AL9: 55 | AM9: 0 | AN9: 0 | AO9: =IF(AL9=0,"⏸️",IF(AM9/AL9>=0.9,"🟢",IF(AM9/AL9>=0.7,"🟡","🔴"))) -> 🔴 | AP9: [SHA-256 pendiente] | AQ9: 65 | AR9: 0 | AS9: 0 | AT9: =IF(AQ9=0,"⏸️",IF(AR9/AQ9>=0.9,"🟢",IF(AR9/AQ9>=0.7,"🟡","🔴"))) -> 🔴 | AU9: [SHA-256 pendiente] | AV9: 75 | AW9: 0 | AX9: 0 | AY9: =IF(AV9=0,"⏸️",IF(AW9/AV9>=0.9,"🟢",IF(AW9/AV9>=0.7,"🟡","🔴"))) -> 🔴 | AZ9: [SHA-256 pendiente] | BA9: 85 | BB9: 0 | BC9: 0 | BD9: =IF(BA9=0,"⏸️",IF(BB9/BA9>=0.9,"🟢",IF(BB9/BA9>=0.7,"🟡","🔴"))) -> 🔴 | BE9: [SHA-256 pendiente] | BF9: 92 | BG9: 0 | BH9: 0 | BI9: =IF(BF9=0,"⏸️",IF(BG9/BF9>=0.9,"🟢",IF(BG9/BF9>=0.7,"🟡","🔴"))) -> 🔴 | BJ9: [SHA-256 pendiente] | BK9: 100 | BL9: 0 | BM9: 0 | BN9: =IF(BK9=0,"⏸️",IF(BL9/BK9>=0.9,"🟢",IF(BL9/BK9>=0.7,"🟡","🔴"))) -> 🔴 | BO9: [SHA-256 pendiente] | BP9: =IFERROR(AVERAGE(I9,N9,S9,X9,AC9,AH9,AM9,AR9,AW9,BB9,BG9,BL9),"N/D") -> 0 | BQ9: =IF(ISNUMBER(BP9),IF(BP9>=90,"🔵 Excelencia en Gobernanza",IF(BP9>=70,"🟢 Gestión por Mandato",IF(BP9>=40,"🟡 Transición Crítica",IF(BP9>=20,"🟠 Gestión por Ocurrencia","🔴 Ruptura Sistémica")))),"Sin datos") -> 🔴 Ruptura Sistémica | BR9: =IF(BQ9="🔴 Ruptura Sistémica","⚠️ Revisar — riesgo incumplimiento","✅ En seguimiento") -> ⚠️ Revisar — riesgo incumplimiento | BS9: =IF(IFERROR(SUM(J9,O9,T9,Y9,AD9,AI9,AN9,AS9,AX9,BC9,BH9,BM9),0)/F9<H01_PARÁMETROS!$B$46,"🚨 ELEGIBLE COOPERACIÓN EXTERNA","✅ Financiamiento suficiente") -> 🚨 ELEGIBLE COOPERACIÓN EXTERNA | BT9: Pendiente | BV9: [SHA-256 director pendiente]
A10: =H04_S2_PLANIFICACIÓN_PDOT!A10 -> AH-I-X-03 | B10: =H04_S2_PLANIFICACIÓN_PDOT!B10 -> Salud integral municipal: población atendida 57,401→84,041 personas (+10% anual) | C10: =H04_S2_PLANIFICACIÓN_PDOT!R10 -> Dirección de Obras Públicas | D10: =H04_S2_PLANIFICACIÓN_PDOT!N10 -> 84041 | E10: =H04_S2_PLANIFICACIÓN_PDOT!O10 -> Personas atendidas salud municipal | F10: =H04_S2_PLANIFICACIÓN_PDOT!G10 -> 1470661 | G10: =H04_S2_PLANIFICACIÓN_PDOT!H10 -> 0.036260413 | H10: 5 | I10: 0 | J10: 0 | K10: =IF(H10=0,"⏸️",IF(I10/H10>=0.9,"🟢",IF(I10/H10>=0.7,"🟡","🔴"))) -> 🔴 | L10: [SHA-256 pendiente] | M10: 10 | N10: 0 | O10: 0 | P10: =IF(M10=0,"⏸️",IF(N10/M10>=0.9,"🟢",IF(N10/M10>=0.7,"🟡","🔴"))) -> 🔴 | Q10: [SHA-256 pendiente] | R10: 15 | S10: 0 | T10: 0 | U10: =IF(R10=0,"⏸️",IF(S10/R10>=0.9,"🟢",IF(S10/R10>=0.7,"🟡","🔴"))) -> 🔴 | V10: [SHA-256 pendiente] | W10: 25 | X10: 0 | Y10: 0 | Z10: =IF(W10=0,"⏸️",IF(X10/W10>=0.9,"🟢",IF(X10/W10>=0.7,"🟡","🔴"))) -> 🔴 | AA10: [SHA-256 pendiente] | AB10: 35 | AC10: 0 | AD10: 0 | AE10: =IF(AB10=0,"⏸️",IF(AC10/AB10>=0.9,"🟢",IF(AC10/AB10>=0.7,"🟡","🔴"))) -> 🔴 | AF10: [SHA-256 pendiente] | AG10: 45 | AH10: 0 | AI10: 0 | AJ10: =IF(AG10=0,"⏸️",IF(AH10/AG10>=0.9,"🟢",IF(AH10/AG10>=0.7,"🟡","🔴"))) -> 🔴 | AK10: [SHA-256 pendiente] | AL10: 55 | AM10: 0 | AN10: 0 | AO10: =IF(AL10=0,"⏸️",IF(AM10/AL10>=0.9,"🟢",IF(AM10/AL10>=0.7,"🟡","🔴"))) -> 🔴 | AP10: [SHA-256 pendiente] | AQ10: 65 | AR10: 0 | AS10: 0 | AT10: =IF(AQ10=0,"⏸️",IF(AR10/AQ10>=0.9,"🟢",IF(AR10/AQ10>=0.7,"🟡","🔴"))) -> 🔴 | AU10: [SHA-256 pendiente] | AV10: 75 | AW10: 0 | AX10: 0 | AY10: =IF(AV10=0,"⏸️",IF(AW10/AV10>=0.9,"🟢",IF(AW10/AV10>=0.7,"🟡","🔴"))) -> 🔴 | AZ10: [SHA-256 pendiente] | BA10: 85 | BB10: 0 | BC10: 0 | BD10: =IF(BA10=0,"⏸️",IF(BB10/BA10>=0.9,"🟢",IF(BB10/BA10>=0.7,"🟡","🔴"))) -> 🔴 | BE10: [SHA-256 pendiente] | BF10: 92 | BG10: 0 | BH10: 0 | BI10: =IF(BF10=0,"⏸️",IF(BG10/BF10>=0.9,"🟢",IF(BG10/BF10>=0.7,"🟡","🔴"))) -> 🔴 | BJ10: [SHA-256 pendiente] | BK10: 100 | BL10: 0 | BM10: 0 | BN10: =IF(BK10=0,"⏸️",IF(BL10/BK10>=0.9,"🟢",IF(BL10/BK10>=0.7,"🟡","🔴"))) -> 🔴 | BO10: [SHA-256 pendiente] | BP10: =IFERROR(AVERAGE(I10,N10,S10,X10,AC10,AH10,AM10,AR10,AW10,BB10,BG10,BL10),"N/D") -> 0 | BQ10: =IF(ISNUMBER(BP10),IF(BP10>=90,"🔵 Excelencia en Gobernanza",IF(BP10>=70,"🟢 Gestión por Mandato",IF(BP10>=40,"🟡 Transición Crítica",IF(BP10>=20,"🟠 Gestión por Ocurrencia","🔴 Ruptura Sistémica")))),"Sin datos") -> 🔴 Ruptura Sistémica | BR10: =IF(BQ10="🔴 Ruptura Sistémica","⚠️ Revisar — riesgo incumplimiento","✅ En seguimiento") -> ⚠️ Revisar — riesgo incumplimiento | BS10: =IF(IFERROR(SUM(J10,O10,T10,Y10,AD10,AI10,AN10,AS10,AX10,BC10,BH10,BM10),0)/F10<H01_PARÁMETROS!$B$46,"🚨 ELEGIBLE COOPERACIÓN EXTERNA","✅ Financiamiento suficiente") -> 🚨 ELEGIBLE COOPERACIÓN EXTERNA | BT10: Pendiente | BV10: [SHA-256 director pendiente]
A11: =H04_S2_PLANIFICACIÓN_PDOT!A11 -> AH-I-N-01 | B11: =H04_S2_PLANIFICACIÓN_PDOT!B11 -> Gestión integral desechos sólidos: 20,118→23,086 Tn/año; relleno sanitario; capacidad disposición 0%→20% | C11: =H04_S2_PLANIFICACIÓN_PDOT!R11 -> EP Montehogar | D11: =H04_S2_PLANIFICACIÓN_PDOT!N11 -> 23086.94 | E11: =H04_S2_PLANIFICACIÓN_PDOT!O11 -> Toneladas de desechos gestionadas/año | F11: =H04_S2_PLANIFICACIÓN_PDOT!G11 -> 1437686 | G11: =H04_S2_PLANIFICACIÓN_PDOT!H11 -> 0.035447386 | H11: 5 | I11: 0 | J11: 0 | K11: =IF(H11=0,"⏸️",IF(I11/H11>=0.9,"🟢",IF(I11/H11>=0.7,"🟡","🔴"))) -> 🔴 | L11: [SHA-256 pendiente] | M11: 10 | N11: 0 | O11: 0 | P11: =IF(M11=0,"⏸️",IF(N11/M11>=0.9,"🟢",IF(N11/M11>=0.7,"🟡","🔴"))) -> 🔴 | Q11: [SHA-256 pendiente] | R11: 15 | S11: 0 | T11: 0 | U11: =IF(R11=0,"⏸️",IF(S11/R11>=0.9,"🟢",IF(S11/R11>=0.7,"🟡","🔴"))) -> 🔴 | V11: [SHA-256 pendiente] | W11: 25 | X11: 0 | Y11: 0 | Z11: =IF(W11=0,"⏸️",IF(X11/W11>=0.9,"🟢",IF(X11/W11>=0.7,"🟡","🔴"))) -> 🔴 | AA11: [SHA-256 pendiente] | AB11: 35 | AC11: 0 | AD11: 0 | AE11: =IF(AB11=0,"⏸️",IF(AC11/AB11>=0.9,"🟢",IF(AC11/AB11>=0.7,"🟡","🔴"))) -> 🔴 | AF11: [SHA-256 pendiente] | AG11: 45 | AH11: 0 | AI11: 0 | AJ11: =IF(AG11=0,"⏸️",IF(AH11/AG11>=0.9,"🟢",IF(AH11/AG11>=0.7,"🟡","🔴"))) -> 🔴 | AK11: [SHA-256 pendiente] | AL11: 55 | AM11: 0 | AN11: 0 | AO11: =IF(AL11=0,"⏸️",IF(AM11/AL11>=0.9,"🟢",IF(AM11/AL11>=0.7,"🟡","🔴"))) -> 🔴 | AP11: [SHA-256 pendiente] | AQ11: 65 | AR11: 0 | AS11: 0 | AT11: =IF(AQ11=0,"⏸️",IF(AR11/AQ11>=0.9,"🟢",IF(AR11/AQ11>=0.7,"🟡","🔴"))) -> 🔴 | AU11: [SHA-256 pendiente] | AV11: 75 | AW11: 0 | AX11: 0 | AY11: =IF(AV11=0,"⏸️",IF(AW11/AV11>=0.9,"🟢",IF(AW11/AV11>=0.7,"🟡","🔴"))) -> 🔴 | AZ11: [SHA-256 pendiente] | BA11: 85 | BB11: 0 | BC11: 0 | BD11: =IF(BA11=0,"⏸️",IF(BB11/BA11>=0.9,"🟢",IF(BB11/BA11>=0.7,"🟡","🔴"))) -> 🔴 | BE11: [SHA-256 pendiente] | BF11: 92 | BG11: 0 | BH11: 0 | BI11: =IF(BF11=0,"⏸️",IF(BG11/BF11>=0.9,"🟢",IF(BG11/BF11>=0.7,"🟡","🔴"))) -> 🔴 | BJ11: [SHA-256 pendiente] | BK11: 100 | BL11: 0 | BM11: 0 | BN11: =IF(BK11=0,"⏸️",IF(BL11/BK11>=0.9,"🟢",IF(BL11/BK11>=0.7,"🟡","🔴"))) -> 🔴 | BO11: [SHA-256 pendiente] | BP11: =IFERROR(AVERAGE(I11,N11,S11,X11,AC11,AH11,AM11,AR11,AW11,BB11,BG11,BL11),"N/D") -> 0 | BQ11: =IF(ISNUMBER(BP11),IF(BP11>=90,"🔵 Excelencia en Gobernanza",IF(BP11>=70,"🟢 Gestión por Mandato",IF(BP11>=40,"🟡 Transición Crítica",IF(BP11>=20,"🟠 Gestión por Ocurrencia","🔴 Ruptura Sistémica")))),"Sin datos") -> 🔴 Ruptura Sistémica | BR11: =IF(BQ11="🔴 Ruptura Sistémica","⚠️ Revisar — riesgo incumplimiento","✅ En seguimiento") -> ⚠️ Revisar — riesgo incumplimiento | BS11: =IF(IFERROR(SUM(J11,O11,T11,Y11,AD11,AI11,AN11,AS11,AX11,BC11,BH11,BM11),0)/F11<H01_PARÁMETROS!$B$46,"🚨 ELEGIBLE COOPERACIÓN EXTERNA","✅ Financiamiento suficiente") -> 🚨 ELEGIBLE COOPERACIÓN EXTERNA | BT11: Pendiente | BV11: [SHA-256 director pendiente]
A12: =H04_S2_PLANIFICACIÓN_PDOT!A12 -> SC-L-G-01 | B12: =H04_S2_PLANIFICACIÓN_PDOT!B12 -> Alcantarillado sanitario: cobertura 19.77%→24.32%; PTAR 0%→75%; estaciones bombeo 36%→72% | C12: =H04_S2_PLANIFICACIÓN_PDOT!R12 -> Dirección de Cultura y Deporte | D12: =H04_S2_PLANIFICACIÓN_PDOT!N12 -> 24.32 | E12: =H04_S2_PLANIFICACIÓN_PDOT!O12 -> % cobertura alcantarillado sanitario | F12: =H04_S2_PLANIFICACIÓN_PDOT!G12 -> 317465 | G12: =H04_S2_PLANIFICACIÓN_PDOT!H12 -> 0.0078273729 | H12: 5 | I12: 0 | J12: 0 | K12: =IF(H12=0,"⏸️",IF(I12/H12>=0.9,"🟢",IF(I12/H12>=0.7,"🟡","🔴"))) -> 🔴 | L12: [SHA-256 pendiente] | M12: 10 | N12: 0 | O12: 0 | P12: =IF(M12=0,"⏸️",IF(N12/M12>=0.9,"🟢",IF(N12/M12>=0.7,"🟡","🔴"))) -> 🔴 | Q12: [SHA-256 pendiente] | R12: 15 | S12: 0 | T12: 0 | U12: =IF(R12=0,"⏸️",IF(S12/R12>=0.9,"🟢",IF(S12/R12>=0.7,"🟡","🔴"))) -> 🔴 | V12: [SHA-256 pendiente] | W12: 25 | X12: 0 | Y12: 0 | Z12: =IF(W12=0,"⏸️",IF(X12/W12>=0.9,"🟢",IF(X12/W12>=0.7,"🟡","🔴"))) -> 🔴 | AA12: [SHA-256 pendiente] | AB12: 35 | AC12: 0 | AD12: 0 | AE12: =IF(AB12=0,"⏸️",IF(AC12/AB12>=0.9,"🟢",IF(AC12/AB12>=0.7,"🟡","🔴"))) -> 🔴 | AF12: [SHA-256 pendiente] | AG12: 45 | AH12: 0 | AI12: 0 | AJ12: =IF(AG12=0,"⏸️",IF(AH12/AG12>=0.9,"🟢",IF(AH12/AG12>=0.7,"🟡","🔴"))) -> 🔴 | AK12: [SHA-256 pendiente] | AL12: 55 | AM12: 0 | AN12: 0 | AO12: =IF(AL12=0,"⏸️",IF(AM12/AL12>=0.9,"🟢",IF(AM12/AL12>=0.7,"🟡","🔴"))) -> 🔴 | AP12: [SHA-256 pendiente] | AQ12: 65 | AR12: 0 | AS12: 0 | AT12: =IF(AQ12=0,"⏸️",IF(AR12/AQ12>=0.9,"🟢",IF(AR12/AQ12>=0.7,"🟡","🔴"))) -> 🔴 | AU12: [SHA-256 pendiente] | AV12: 75 | AW12: 0 | AX12: 0 | AY12: =IF(AV12=0,"⏸️",IF(AW12/AV12>=0.9,"🟢",IF(AW12/AV12>=0.7,"🟡","🔴"))) -> 🔴 | AZ12: [SHA-256 pendiente] | BA12: 85 | BB12: 0 | BC12: 0 | BD12: =IF(BA12=0,"⏸️",IF(BB12/BA12>=0.9,"🟢",IF(BB12/BA12>=0.7,"🟡","🔴"))) -> 🔴 | BE12: [SHA-256 pendiente] | BF12: 92 | BG12: 0 | BH12: 0 | BI12: =IF(BF12=0,"⏸️",IF(BG12/BF12>=0.9,"🟢",IF(BG12/BF12>=0.7,"🟡","🔴"))) -> 🔴 | BJ12: [SHA-256 pendiente] | BK12: 100 | BL12: 0 | BM12: 0 | BN12: =IF(BK12=0,"⏸️",IF(BL12/BK12>=0.9,"🟢",IF(BL12/BK12>=0.7,"🟡","🔴"))) -> 🔴 | BO12: [SHA-256 pendiente] | BP12: =IFERROR(AVERAGE(I12,N12,S12,X12,AC12,AH12,AM12,AR12,AW12,BB12,BG12,BL12),"N/D") -> 0 | BQ12: =IF(ISNUMBER(BP12),IF(BP12>=90,"🔵 Excelencia en Gobernanza",IF(BP12>=70,"🟢 Gestión por Mandato",IF(BP12>=40,"🟡 Transición Crítica",IF(BP12>=20,"🟠 Gestión por Ocurrencia","🔴 Ruptura Sistémica")))),"Sin datos") -> 🔴 Ruptura Sistémica | BR12: =IF(BQ12="🔴 Ruptura Sistémica","⚠️ Revisar — riesgo incumplimiento","✅ En seguimiento") -> ⚠️ Revisar — riesgo incumplimiento | BS12: =IF(IFERROR(SUM(J12,O12,T12,Y12,AD12,AI12,AN12,AS12,AX12,BC12,BH12,BM12),0)/F12<H01_PARÁMETROS!$B$46,"🚨 ELEGIBLE COOPERACIÓN EXTERNA","✅ Financiamiento suficiente") -> 🚨 ELEGIBLE COOPERACIÓN EXTERNA | BT12: Pendiente | BV12: [SHA-256 director pendiente]
A13: =H04_S2_PLANIFICACIÓN_PDOT!A13 -> AH-I-X-04 | B13: =H04_S2_PLANIFICACIÓN_PDOT!B13 -> Modernización recursos administrativos: parque automotor, tecnología e infraestructura municipal | C13: =H04_S2_PLANIFICACIÓN_PDOT!R13 -> Dirección de Obras Públicas | D13: =H04_S2_PLANIFICACIÓN_PDOT!N13 -> 1 | E13: =H04_S2_PLANIFICACIÓN_PDOT!O13 -> Parque automotor y tecnología renovados | F13: =H04_S2_PLANIFICACIÓN_PDOT!G13 -> 941255 | G13: =H04_S2_PLANIFICACIÓN_PDOT!H13 -> 0.023207452 | H13: 5 | I13: 0 | J13: 0 | K13: =IF(H13=0,"⏸️",IF(I13/H13>=0.9,"🟢",IF(I13/H13>=0.7,"🟡","🔴"))) -> 🔴 | L13: [SHA-256 pendiente] | M13: 10 | N13: 0 | O13: 0 | P13: =IF(M13=0,"⏸️",IF(N13/M13>=0.9,"🟢",IF(N13/M13>=0.7,"🟡","🔴"))) -> 🔴 | Q13: [SHA-256 pendiente] | R13: 15 | S13: 0 | T13: 0 | U13: =IF(R13=0,"⏸️",IF(S13/R13>=0.9,"🟢",IF(S13/R13>=0.7,"🟡","🔴"))) -> 🔴 | V13: [SHA-256 pendiente] | W13: 25 | X13: 0 | Y13: 0 | Z13: =IF(W13=0,"⏸️",IF(X13/W13>=0.9,"🟢",IF(X13/W13>=0.7,"🟡","🔴"))) -> 🔴 | AA13: [SHA-256 pendiente] | AB13: 35 | AC13: 0 | AD13: 0 | AE13: =IF(AB13=0,"⏸️",IF(AC13/AB13>=0.9,"🟢",IF(AC13/AB13>=0.7,"🟡","🔴"))) -> 🔴 | AF13: [SHA-256 pendiente] | AG13: 45 | AH13: 0 | AI13: 0 | AJ13: =IF(AG13=0,"⏸️",IF(AH13/AG13>=0.9,"🟢",IF(AH13/AG13>=0.7,"🟡","🔴"))) -> 🔴 | AK13: [SHA-256 pendiente] | AL13: 55 | AM13: 0 | AN13: 0 | AO13: =IF(AL13=0,"⏸️",IF(AM13/AL13>=0.9,"🟢",IF(AM13/AL13>=0.7,"🟡","🔴"))) -> 🔴 | AP13: [SHA-256 pendiente] | AQ13: 65 | AR13: 0 | AS13: 0 | AT13: =IF(AQ13=0,"⏸️",IF(AR13/AQ13>=0.9,"🟢",IF(AR13/AQ13>=0.7,"🟡","🔴"))) -> 🔴 | AU13: [SHA-256 pendiente] | AV13: 75 | AW13: 0 | AX13: 0 | AY13: =IF(AV13=0,"⏸️",IF(AW13/AV13>=0.9,"🟢",IF(AW13/AV13>=0.7,"🟡","🔴"))) -> 🔴 | AZ13: [SHA-256 pendiente] | BA13: 85 | BB13: 0 | BC13: 0 | BD13: =IF(BA13=0,"⏸️",IF(BB13/BA13>=0.9,"🟢",IF(BB13/BA13>=0.7,"🟡","🔴"))) -> 🔴 | BE13: [SHA-256 pendiente] | BF13: 92 | BG13: 0 | BH13: 0 | BI13: =IF(BF13=0,"⏸️",IF(BG13/BF13>=0.9,"🟢",IF(BG13/BF13>=0.7,"🟡","🔴"))) -> 🔴 | BJ13: [SHA-256 pendiente] | BK13: 100 | BL13: 0 | BM13: 0 | BN13: =IF(BK13=0,"⏸️",IF(BL13/BK13>=0.9,"🟢",IF(BL13/BK13>=0.7,"🟡","🔴"))) -> 🔴 | BO13: [SHA-256 pendiente] | BP13: =IFERROR(AVERAGE(I13,N13,S13,X13,AC13,AH13,AM13,AR13,AW13,BB13,BG13,BL13),"N/D") -> 0 | BQ13: =IF(ISNUMBER(BP13),IF(BP13>=90,"🔵 Excelencia en Gobernanza",IF(BP13>=70,"🟢 Gestión por Mandato",IF(BP13>=40,"🟡 Transición Crítica",IF(BP13>=20,"🟠 Gestión por Ocurrencia","🔴 Ruptura Sistémica")))),"Sin datos") -> 🔴 Ruptura Sistémica | BR13: =IF(BQ13="🔴 Ruptura Sistémica","⚠️ Revisar — riesgo incumplimiento","✅ En seguimiento") -> ⚠️ Revisar — riesgo incumplimiento | BS13: =IF(IFERROR(SUM(J13,O13,T13,Y13,AD13,AI13,AN13,AS13,AX13,BC13,BH13,BM13),0)/F13<H01_PARÁMETROS!$B$46,"🚨 ELEGIBLE COOPERACIÓN EXTERNA","✅ Financiamiento suficiente") -> 🚨 ELEGIBLE COOPERACIÓN EXTERNA | BT13: Pendiente | BV13: [SHA-256 director pendiente]
A14: =H04_S2_PLANIFICACIÓN_PDOT!A14 -> PI-I-G-01 | B14: =H04_S2_PLANIFICACIÓN_PDOT!B14 -> Equipamientos públicos: terminal terrestre, mercado, estación bomberil, centro salud tipo C, mantenimiento espacios recreativos | C14: =H04_S2_PLANIFICACIÓN_PDOT!R14 -> Dirección Administrativa | D14: =H04_S2_PLANIFICACIÓN_PDOT!N14 -> 10.73 | E14: =H04_S2_PLANIFICACIÓN_PDOT!O14 -> m² / hab índice equipamiento urbano CUP | F14: =H04_S2_PLANIFICACIÓN_PDOT!G14 -> 647139 | G14: =H04_S2_PLANIFICACIÓN_PDOT!H14 -> 0.015955769 | H14: 5 | I14: 0 | J14: 0 | K14: =IF(H14=0,"⏸️",IF(I14/H14>=0.9,"🟢",IF(I14/H14>=0.7,"🟡","🔴"))) -> 🔴 | L14: [SHA-256 pendiente] | M14: 10 | N14: 0 | O14: 0 | P14: =IF(M14=0,"⏸️",IF(N14/M14>=0.9,"🟢",IF(N14/M14>=0.7,"🟡","🔴"))) -> 🔴 | Q14: [SHA-256 pendiente] | R14: 15 | S14: 0 | T14: 0 | U14: =IF(R14=0,"⏸️",IF(S14/R14>=0.9,"🟢",IF(S14/R14>=0.7,"🟡","🔴"))) -> 🔴 | V14: [SHA-256 pendiente] | W14: 25 | X14: 0 | Y14: 0 | Z14: =IF(W14=0,"⏸️",IF(X14/W14>=0.9,"🟢",IF(X14/W14>=0.7,"🟡","🔴"))) -> 🔴 | AA14: [SHA-256 pendiente] | AB14: 35 | AC14: 0 | AD14: 0 | AE14: =IF(AB14=0,"⏸️",IF(AC14/AB14>=0.9,"🟢",IF(AC14/AB14>=0.7,"🟡","🔴"))) -> 🔴 | AF14: [SHA-256 pendiente] | AG14: 45 | AH14: 0 | AI14: 0 | AJ14: =IF(AG14=0,"⏸️",IF(AH14/AG14>=0.9,"🟢",IF(AH14/AG14>=0.7,"🟡","🔴"))) -> 🔴 | AK14: [SHA-256 pendiente] | AL14: 55 | AM14: 0 | AN14: 0 | AO14: =IF(AL14=0,"⏸️",IF(AM14/AL14>=0.9,"🟢",IF(AM14/AL14>=0.7,"🟡","🔴"))) -> 🔴 | AP14: [SHA-256 pendiente] | AQ14: 65 | AR14: 0 | AS14: 0 | AT14: =IF(AQ14=0,"⏸️",IF(AR14/AQ14>=0.9,"🟢",IF(AR14/AQ14>=0.7,"🟡","🔴"))) -> 🔴 | AU14: [SHA-256 pendiente] | AV14: 75 | AW14: 0 | AX14: 0 | AY14: =IF(AV14=0,"⏸️",IF(AW14/AV14>=0.9,"🟢",IF(AW14/AV14>=0.7,"🟡","🔴"))) -> 🔴 | AZ14: [SHA-256 pendiente] | BA14: 85 | BB14: 0 | BC14: 0 | BD14: =IF(BA14=0,"⏸️",IF(BB14/BA14>=0.9,"🟢",IF(BB14/BA14>=0.7,"🟡","🔴"))) -> 🔴 | BE14: [SHA-256 pendiente] | BF14: 92 | BG14: 0 | BH14: 0 | BI14: =IF(BF14=0,"⏸️",IF(BG14/BF14>=0.9,"🟢",IF(BG14/BF14>=0.7,"🟡","🔴"))) -> 🔴 | BJ14: [SHA-256 pendiente] | BK14: 100 | BL14: 0 | BM14: 0 | BN14: =IF(BK14=0,"⏸️",IF(BL14/BK14>=0.9,"🟢",IF(BL14/BK14>=0.7,"🟡","🔴"))) -> 🔴 | BO14: [SHA-256 pendiente] | BP14: =IFERROR(AVERAGE(I14,N14,S14,X14,AC14,AH14,AM14,AR14,AW14,BB14,BG14,BL14),"N/D") -> 0 | BQ14: =IF(ISNUMBER(BP14),IF(BP14>=90,"🔵 Excelencia en Gobernanza",IF(BP14>=70,"🟢 Gestión por Mandato",IF(BP14>=40,"🟡 Transición Crítica",IF(BP14>=20,"🟠 Gestión por Ocurrencia","🔴 Ruptura Sistémica")))),"Sin datos") -> 🔴 Ruptura Sistémica | BR14: =IF(BQ14="🔴 Ruptura Sistémica","⚠️ Revisar — riesgo incumplimiento","✅ En seguimiento") -> ⚠️ Revisar — riesgo incumplimiento | BS14: =IF(IFERROR(SUM(J14,O14,T14,Y14,AD14,AI14,AN14,AS14,AX14,BC14,BH14,BM14),0)/F14<H01_PARÁMETROS!$B$46,"🚨 ELEGIBLE COOPERACIÓN EXTERNA","✅ Financiamiento suficiente") -> 🚨 ELEGIBLE COOPERACIÓN EXTERNA | BT14: Pendiente | BV14: [SHA-256 director pendiente]
A15: =H04_S2_PLANIFICACIÓN_PDOT!A15 -> AH-C-X-01 | B15: =H04_S2_PLANIFICACIÓN_PDOT!B15 -> Protección derechos sociales: atenciones grupos prioritarios 943→1,649 (+15%/año); CDI; adultos mayores; violencia de género | C15: =H04_S2_PLANIFICACIÓN_PDOT!R15 -> Dirección de Agua y Saneamiento | D15: =H04_S2_PLANIFICACIÓN_PDOT!N15 -> 1649 | E15: =H04_S2_PLANIFICACIÓN_PDOT!O15 -> Atenciones en programas grupos prioritarios | F15: =H04_S2_PLANIFICACIÓN_PDOT!G15 -> 438767 | G15: =H04_S2_PLANIFICACIÓN_PDOT!H15 -> 0.010818178 | H15: 5 | I15: 0 | J15: 0 | K15: =IF(H15=0,"⏸️",IF(I15/H15>=0.9,"🟢",IF(I15/H15>=0.7,"🟡","🔴"))) -> 🔴 | L15: [SHA-256 pendiente] | M15: 10 | N15: 0 | O15: 0 | P15: =IF(M15=0,"⏸️",IF(N15/M15>=0.9,"🟢",IF(N15/M15>=0.7,"🟡","🔴"))) -> 🔴 | Q15: [SHA-256 pendiente] | R15: 15 | S15: 0 | T15: 0 | U15: =IF(R15=0,"⏸️",IF(S15/R15>=0.9,"🟢",IF(S15/R15>=0.7,"🟡","🔴"))) -> 🔴 | V15: [SHA-256 pendiente] | W15: 25 | X15: 0 | Y15: 0 | Z15: =IF(W15=0,"⏸️",IF(X15/W15>=0.9,"🟢",IF(X15/W15>=0.7,"🟡","🔴"))) -> 🔴 | AA15: [SHA-256 pendiente] | AB15: 35 | AC15: 0 | AD15: 0 | AE15: =IF(AB15=0,"⏸️",IF(AC15/AB15>=0.9,"🟢",IF(AC15/AB15>=0.7,"🟡","🔴"))) -> 🔴 | AF15: [SHA-256 pendiente] | AG15: 45 | AH15: 0 | AI15: 0 | AJ15: =IF(AG15=0,"⏸️",IF(AH15/AG15>=0.9,"🟢",IF(AH15/AG15>=0.7,"🟡","🔴"))) -> 🔴 | AK15: [SHA-256 pendiente] | AL15: 55 | AM15: 0 | AN15: 0 | AO15: =IF(AL15=0,"⏸️",IF(AM15/AL15>=0.9,"🟢",IF(AM15/AL15>=0.7,"🟡","🔴"))) -> 🔴 | AP15: [SHA-256 pendiente] | AQ15: 65 | AR15: 0 | AS15: 0 | AT15: =IF(AQ15=0,"⏸️",IF(AR15/AQ15>=0.9,"🟢",IF(AR15/AQ15>=0.7,"🟡","🔴"))) -> 🔴 | AU15: [SHA-256 pendiente] | AV15: 75 | AW15: 0 | AX15: 0 | AY15: =IF(AV15=0,"⏸️",IF(AW15/AV15>=0.9,"🟢",IF(AW15/AV15>=0.7,"🟡","🔴"))) -> 🔴 | AZ15: [SHA-256 pendiente] | BA15: 85 | BB15: 0 | BC15: 0 | BD15: =IF(BA15=0,"⏸️",IF(BB15/BA15>=0.9,"🟢",IF(BB15/BA15>=0.7,"🟡","🔴"))) -> 🔴 | BE15: [SHA-256 pendiente] | BF15: 92 | BG15: 0 | BH15: 0 | BI15: =IF(BF15=0,"⏸️",IF(BG15/BF15>=0.9,"🟢",IF(BG15/BF15>=0.7,"🟡","🔴"))) -> 🔴 | BJ15: [SHA-256 pendiente] | BK15: 100 | BL15: 0 | BM15: 0 | BN15: =IF(BK15=0,"⏸️",IF(BL15/BK15>=0.9,"🟢",IF(BL15/BK15>=0.7,"🟡","🔴"))) -> 🔴 | BO15: [SHA-256 pendiente] | BP15: =IFERROR(AVERAGE(I15,N15,S15,X15,AC15,AH15,AM15,AR15,AW15,BB15,BG15,BL15),"N/D") -> 0 | BQ15: =IF(ISNUMBER(BP15),IF(BP15>=90,"🔵 Excelencia en Gobernanza",IF(BP15>=70,"🟢 Gestión por Mandato",IF(BP15>=40,"🟡 Transición Crítica",IF(BP15>=20,"🟠 Gestión por Ocurrencia","🔴 Ruptura Sistémica")))),"Sin datos") -> 🔴 Ruptura Sistémica | BR15: =IF(BQ15="🔴 Ruptura Sistémica","⚠️ Revisar — riesgo incumplimiento","✅ En seguimiento") -> ⚠️ Revisar — riesgo incumplimiento | BS15: =IF(IFERROR(SUM(J15,O15,T15,Y15,AD15,AI15,AN15,AS15,AX15,BC15,BH15,BM15),0)/F15<H01_PARÁMETROS!$B$46,"🚨 ELEGIBLE COOPERACIÓN EXTERNA","✅ Financiamiento suficiente") -> 🚨 ELEGIBLE COOPERACIÓN EXTERNA | BT15: Pendiente | BV15: [SHA-256 director pendiente]
